Workbook

Sheet 兴趣电商-运营
C1: 岗位绩效责任书
C2: 部门： | D2: 兴趣电商部 | E2: 岗位： | F2: 兴趣电商运营
E3: 姓名：
B4: 编号 | C4: 评价维度 | D4: 指标项目 | E4: 指标权重 | F4: 目标 | G4: 计算公式 | H4: 单位 | I4: 评分标准 | J4: 数据来源 | K4: 评价周期 | L4: 完成结果 | M4: 最终得分
B6: 1 | C6: 组织指标 | D6: 团队GSV营收目标达成率 | E6: 0.3 | F6: 确保所负责渠道退货后营收（GSV）对照预算目标的达成率 | G6: 达成率=实际GSV达成/预算目标GSV达成 | H6: % | I6: 达成率≥100%：按照实际达成取两位小数点计入该项目分，最高150分。 100%＞达成率≥80%，90分 80%＞达成率≥60%，60分 60%＞达成率，0分 | J6: 平台数据 | K6: 核算时间：每月5日完成绩效绩效核算 取值范围：上月整月 | L6: 120 | M6: =$E6*L6 -> 36
B7: 2 | C7: 组织指标 | D7: 团队ROI签收目标达成率 | E7: 0.3 | F7: 确保所负责渠道签收ROI对照预算目标的达成率 | G7: 达成率=实际签收ROI/预算目标签收ROI | H7: % | I7: 达成率≥90%：按照实际达成取两位小数点计入该项目分，最高110分。 90%＞达成率≥85%，85分 85%＞达成率≥80%，80分 80%＞达成率，0分 | J7: 平台数据 | K7: 核算时间：每月5日完成绩效绩效核算 取值范围：上月整月 | L7: 90 | M7: =$E7*L7 -> 27
B8: 3 | C8: 岗位指标 | D8: 店铺运营能力 | E8: 0.2 | H8: / | I8: 0-60分，差：违规频繁，基础问题出错 60-80分，合格：直播节奏稳定，日常工作零失误 80-100分，优秀：研究平台活动，提报跟进及时，主动做好活动规划和执行 | J8: 部门负责人 | K8: 核算时间：每月5日完成绩效绩效核算 取值范围：上月整月 | L8: 100 | M8: =$E8*L8 -> 20
B9: 4 | C9: 岗位指标 | D9: 团队管理及组织能力 | E9: 0.2 | H9: / | I9: 0-60分，差：管理主播、中控均杂乱无章 60-80分，合格：带领主播、中控正常完成工作 80-100分，优秀：有组织、有条理，主播、中控积极性高 | J9: 部门负责人 | K9: 核算时间：每月5日完成绩效绩效核算 取值范围：上月整月 | L9: 100 | M9: =$E9*L9 -> 20
B10: 合计 | E10: =SUM(E6:E9) -> 1 | L10: 100 | M10: =SUM(M6:M9) -> 103
I12: 岗位提成标准说明 | J12: 提成基数 | K12: 0.003
I13: 提成来源 | J13: 得分下限 （包含） | K13: 得分上限 （不包含） | L13: 系数比例 | M13: 提成比例
I14: 运营店铺GSV | J14: 0 | K14: 50 | L14: 0 | M14: =$K$12*L14 -> 0
I15: 运营店铺GSV | J15: 50 | K15: 70 | L15: 0.2 | M15: =$K$12*L15 -> 0.0006
I16: 运营店铺GSV | J16: 70 | K16: 90 | L16: 0.4 | M16: =$K$12*L16 -> 0.0012
I17: 运营店铺GSV | J17: 90 | K17: 100 | L17: 0.6 | M17: =$K$12*L17 -> 0.0018
I18: 运营店铺GSV | J18: 100 | K18: 103 | L18: 1 | M18: =$K$12*L18 -> 0.003
I19: 运营店铺GSV | J19: 103 | K19: 108 | L19: 1.2 | M19: =$K$12*L19 -> 0.0036
I20: 运营店铺GSV | J20: 108 | K20: ♾️ | L20: 1.5 | M20: =$K$12*L20 -> 0.0045

Sheet 兴趣电商-高级主管
C1: 岗位绩效责任书 | O1: 测算用
C2: 部门： | D2: 兴趣电商部 | E2: 岗位： | F2: 兴趣电商运营高级主管 | N2: 目标ROI | O2: 2.65 | P2: 达成 | Q2: =$O$2*Q7/100 -> 2.438 | S2: 达成 | T2: =$O$2*T7/100 -> 2.5175 | V2: 达成 | W2: =$O$2*W7/100 -> 2.385
E3: 姓名：
B4: 编号 | C4: 评价维度 | D4: 指标项目 | E4: 指标权重 | F4: 目标 | G4: 计算公式 | H4: 单位 | I4: 评分标准 | J4: 数据来源 | K4: 评价周期 | L4: 完成结果 | M4: 最终得分
Q5: 达成率 | R5: 得分 | T5: 达成率 | U5: 得分 | W5: 达成率 | X5: 得分
B6: 1 | C6: 组织指标 | D6: 团队GSV营收目标达成率 | E6: 0.3 | F6: 确保所负责渠道退货后营收（GSV）对照预算目标的达成率 | G6: 达成率=实际GSV达成/预算目标GSV达成 | H6: % | I6: 达成率≥100%：按照实际达成取两位小数点计入该项目分，最高150分。 100%＞达成率≥80%，90分 80%＞达成率≥60%，60分 60%＞达成率，0分 | J6: 平台数据 | K6: 核算时间：每月5日完成绩效绩效核算 取值范围：上月整月 | L6: 120 | M6: =E6*L6 -> 36 | P6: GSV 得分 | Q6: 100 | R6: ='兴趣电商-运营'!$E6*Q6 -> 30 | T6: 115 | U6: ='兴趣电商-运营'!$E6*T6 -> 34.5 | W6: 100 | X6: ='兴趣电商-运营'!$E6*W6 -> 30
B7: 2 | C7: 组织指标 | D7: 团队ROI签收目标达成率 | E7: 0.3 | F7: 确保所负责渠道签收ROI对照预算目标的达成率 | G7: 达成率=实际签收ROI/预算目标签收ROI | H7: % | I7: 达成率≥90%：按照实际达成取两位小数点计入该项目分，最高150分。 90%＞达成率≥80%，60分 80%＞达成率，0分 | J7: 平台数据 | K7: 核算时间：每月5日完成绩效绩效核算 取值范围：上月整月 | L7: 100 | M7: =E7*L7 -> 30 | P7: ROI 得分 | Q7: 92 | R7: ='兴趣电商-运营'!$E7*Q7 -> 27.6 | T7: 95 | U7: ='兴趣电商-运营'!$E7*T7 -> 28.5 | W7: 90 | X7: ='兴趣电商-运营'!$E7*W7 -> 27
B8: 3 | C8: 岗位指标 | D8: 跨部门协调 | E8: 0.2 | H8: / | I8: 0-60分（差）：跨部门沟通缺乏主动性，导致业务进展滞后 60-80分（合格）：发生问题时主动与对应部门沟通，解决问题 80-100分（优秀）：做事有预知，保障产品、价格、投放、物料、售后全链路 | J8: 部门负责人 | K8: 核算时间：每月5日完成绩效绩效核算 取值范围：上月整月 | L8: 100 | M8: =E8*L8 -> 20 | Q8: 100 | R8: ='兴趣电商-运营'!$E8*Q8 -> 20 | T8: 100 | U8: ='兴趣电商-运营'!$E8*T8 -> 20 | W8: 100 | X8: ='兴趣电商-运营'!$E8*W8 -> 20
B9: 4 | C9: 个人指标 | D9: 团队管理及组织能力 | E9: 0.2 | H9: / | I9: 0-60分（差）：运营人效低，水平参差不齐，团队稳定性差 60-80分（合格）：统筹各运营小组执行工作零失误 80-100分（优秀）：定期运营技能培训、经验交流、团队高效积极 | J9: 部门负责人 | K9: 核算时间：每月5日完成绩效绩效核算 取值范围：上月整月 | L9: 100 | M9: =E9*L9 -> 20 | Q9: 100 | R9: ='兴趣电商-运营'!$E9*Q9 -> 20 | T9: 100 | U9: ='兴趣电商-运营'!$E9*T9 -> 20 | W9: 100 | X9: ='兴趣电商-运营'!$E9*W9 -> 20
B10: 合计 | E10: =SUM(E6:E9) -> 1 | M10: =SUM(M6:M9) -> 106 | R10: =SUM(R6:R9) -> 97.6 | U10: =SUM(U6:U9) -> 103 | X10: =SUM(X6:X9) -> 97
D12: 考核方式说明 | I12: 岗位提成标准说明 | L12: 提成基数 | M12: 0.003
D13: 负责项目 | E13: 渠道 | F13: 考核方式 | G13: 新项目评价周期 满足任意条件脱离新项目机制考核 | I13: 提成来源 | J13: 得分下限 （包含） | K13: 得分上限 （不包含） | L13: 系数比例 | M13: 提成比例 基数*系数 | Q13: 系数比例 | R13: 提成比例 | T13: 系数比例 | U13: 提成比例 | W13: 系数比例 | X13: 提成比例
D14: 高个子 | E14: 抖音 | F14: 按绩效考核，根据得分取提成系数*固定基数 | I14: 运营店铺GSV | J14: 0 | K14: 50 | L14: 0 | M14: =$K$12*L14 -> 0 | Q14: =LOOKUP(R10,'兴趣电商-高级主管'!$J$14:$J$20,'兴趣电商-高级主管'!$L$14:$L$20) -> 0.8 | R14: =LOOKUP(R10,'兴趣电商-高级主管'!$J$14:$J$20,'兴趣电商-高级主管'!$M$14:$M$20) -> 0 | T14: =LOOKUP(U10,'兴趣电商-高级主管'!$J$14:$J$20,'兴趣电商-高级主管'!$L$14:$L$20) -> 1.2 | U14: =LOOKUP(U10,'兴趣电商-高级主管'!$J$14:$J$20,'兴趣电商-高级主管'!$M$14:$M$20) -> 0 | W14: =LOOKUP(X10,'兴趣电商-高级主管'!$J$14:$J$20,'兴趣电商-高级主管'!$L$14:$L$20) -> 0.8 | X14: =LOOKUP(X10,'兴趣电商-高级主管'!$J$14:$J$20,'兴趣电商-高级主管'!$M$14:$M$20) -> 0
D15: 高个子 | E15: 视频号 | F15: 按新项目机制考核，享受免责提成+达成激励 | G15: 暂定单月GSV达成100万or运营两个月 | I15: 运营店铺GSV | J15: 50 | K15: 70 | L15: 0.2 | M15: =$K$12*L15 -> 0
D16: 少年状元 | E16: 整项目 | F16: 按新项目机制考核，享受免责提成+达成激励 | G16: 暂定单月GSV达成100万or运营两个月 | I16: 运营店铺GSV | J16: 70 | K16: 90 | L16: 0.4 | M16: =$K$12*L16 -> 0
D17: 骨能 | E17: 整项目 | F17: 按新项目机制考核，享受免责提成+达成激励 | G17: 暂定单月GSV达成100万or运营两个月 | I17: 运营店铺GSV | J17: 90 | K17: 100 | L17: 0.8 | M17: =$K$12*L17 -> 0 | N17: *这部分运营和高级主管差0.2，运营系数是0.6和之前一致
I18: 运营店铺GSV | J18: 100 | K18: 103 | L18: 1 | M18: =$K$12*L18 -> 0
D19: *免责提成：新项目免责期内，按照提成基数*0.8作为项目免责提成比例 | I19: 运营店铺GSV | J19: 103 | K19: 108 | L19: 1.2 | M19: =$K$12*L19 -> 0
D20: *新项目达成激励：新项目免责期内，达成免责期期间预算目标，取项目利润3%作为项目激励 | I20: 运营店铺GSV | J20: 108 | K20: ♾️ | L20: 1.5 | M20: =$K$12*L20 -> 0

Sheet 兴趣电商-广告投放
C1: 岗位绩效责任书
C2: 部门： | D2: 兴趣电商部 | E2: 岗位： | F2: 广告投放
E3: 姓名：
B4: 编号 | C4: 评价维度 | D4: 指标项目 | E4: 指标权重 | F4: 目标 | G4: 计算公式 | H4: 单位 | I4: 评分标准 | J4: 数据来源 | K4: 评价周期 | L4: 完成结果 | M4: 最终得分
B6: 1 | C6: 组织指标 | D6: 团队GSV营收目标达成率 | E6: 0.2 | F6: 确保所负责渠道退货后营收（GSV）对照预算目标的达成率 | G6: 达成率=实际GSV达成/预算目标GSV达成 | H6: % | I6: 达成率≥100%：按照实际达成取两位小数点计入该项目分，最高150分。 100%＞达成率≥80%，90分 80%＞达成率≥60%，60分 60%＞达成率，0分 | J6: 平台数据 | K6: 核算时间：每月5日完成绩效绩效核算 取值范围：上月整月 | L6: 100 | M6: =E6*L6 -> 20
B7: 2 | C7: 组织指标 | D7: 团队ROI签收目标达成率 | E7: 0.4 | F7: 确保所负责渠道签收ROI对照预算目标的达成率 | G7: 达成率=实际签收ROI/预算目标签收ROI | H7: % | I7: 达成率≥90%：按照实际达成取两位小数点计入该项目分，最高150分。 90%＞达成率≥80%，60分 90%＞达成率，0分 | J7: 平台数据 | K7: 核算时间：每月5日完成绩效绩效核算 取值范围：上月整月 | L7: 100 | M7: =E7*L7 -> 40
B8: 3 | C8: 岗位指标 | D8: 投中管理 | E8: 0.2 | H8: / | I8: 0-60分（差）：盯盘不及时，广告操作，预算，空耗控制混乱 60-80分（合格）：盯盘及时，按照要求正确操作广告 80-100分（优秀）：根据月度目标，主动规划广告预算 | J8: 部门负责人 | K8: 核算时间：每月5日完成绩效绩效核算 取值范围：上月整月 | L8: 100 | M8: =E8*L8 -> 20
B9: 4 | C9: 岗位指标 | D9: 素材管理 | E9: 0.1 | H9: / | I9: 0-60分（差）：不及时上传新素材，测试节奏缓慢 60-80分（合格）：正常上传素材，及时反馈测试结果 80-100分（优秀）：主动对接素材，沟通素材合规性，制作方向 | J9: 部门负责人 | K9: 核算时间：每月5日完成绩效绩效核算 取值范围：上月整月 | L9: 100 | M9: =E9*L9 -> 10
B10: 5 | C10: 岗位指标 | D10: 投后复盘 | E10: 0.1 | H10: / | I10: 0-60分（差）：问题定位不清晰，放量与ROI控制节奏混乱 60-80分（合格）：针对广告，素材问题及时进行基础调整 80-100分（优秀）：问题分析、优化策略、放量方案逻辑清晰 | J10: 部门负责人 | K10: 核算时间：每月5日完成绩效绩效核算 取值范围：上月整月 | L10: 100 | M10: =E10*L10 -> 10
B11: 合计 | E11: =SUM(E6:E10) -> 1 | L11: 100 | M11: =SUM(M6:M10) -> 100
I15: 岗位提成标准说明
I16: 提成来源 | K16: 得分下限 （包含） | L16: 得分上限 （不包含） | M16: 提成比例
I17: 投放账户广告消耗 | K17: 0 | L17: 60 | M17: 0.001
I18: 投放账户广告消耗 | K18: 60 | L18: 80 | M18: 0.001
I19: 投放账户广告消耗 | K19: 80 | L19: 100 | M19: 0.001
I20: 投放账户广告消耗 | K20: 100 | L20: 150 | M20: 0.001

Sheet 兴趣电商-直播中控
C1: 岗位绩效责任书
C2: 部门： | D2: 兴趣电商部 | E2: 岗位： | F2: 直播中控/运营助理
E3: 姓名：
B4: 编号 | C4: 评价维度 | D4: 指标项目 | E4: 指标权重 | F4: 目标 | G4: 计算公式 | H4: 单位 | I4: 评分标准 | J4: 数据来源 | K4: 评价周期 | L4: 完成结果 | M4: 最终得分
B6: 1 | C6: 组织指标 | D6: 团队GSV营收目标达成率 | E6: 0.1 | F6: 确保所负责渠道营收对照预算目标的达成率 | H6: % | I6: 对照预算目标的达成率： 计算公式： 达成率=实际GSV达成/预算目标GSV达成 评分范围 达成率≥100%：按照实际达成取两位小数点计入该项目分，最高150分。 100%＞达成率≥80%，90分 80%＞达成率≥60%，60分 60%＞达成率，0分 | J6: 平台数据 | K6: 核算时间：每月5日完成绩效绩效核算 取值范围：上月整月 | L6: 100 | M6: =E6*L6 -> 10
B7: 2 | C7: 岗位指标 | D7: 店铺链接管理： 产品链接设置/产品编码编辑 | E7: 0.2 | F7: 链接上架、编码编辑及产品价格需保证及时、准确 | H7: / | I7: 错误次数 = 0 次，得 100 分 错误次数 < 3 次，得 80 分 错误次数 ≥ 3 次，得 0 分 | J7: 部门负责人 | K7: 核算时间：每月5日完成绩效绩效核算 取值范围：上月整月 | L7: 100 | M7: =E7*L7 -> 20
B8: 3 | C8: 岗位指标 | D8: 客户服务与答疑 | E8: 0.2 | F8: 及时回应顾客的各类咨询，提供专业且实用的建议，同时积极引导有购物意向的观众顺利完成购买流程 | H8: / | I8: 回复率达到100%，得100分； 漏回复次数少于3次，得60分； 漏回复次数达到或超过3次，得0分。 | J8: 部门负责人 | K8: 核算时间：每月5日完成绩效绩效核算 取值范围：上月整月 | L8: 100 | M8: =E8*L8 -> 20
B9: 4 | C9: 岗位指标 | D9: 样品管理 | E9: 0.1 | F9: 确保直播间样品，手卡，手机，相机，灯光等工作物料，有序整理 | H9: / | I9: 0-60分（差） 60-80分（合格） 80-100分（优秀） | J9: 部门负责人 | K9: 核算时间：每月5日完成绩效绩效核算 取值范围：上月整月 | L9: 100 | M9: =E9*L9 -> 10
B10: 5 | C10: 个人指标 | D10: 工作态度 | E10: 0.2 | F10: 理解和遵守公司的各项规章制度、服从上级的指示和命令，不在跟播期间做与工作无关的事情 | H10: / | I10: 0-60分（差） 60-80分（合格） 80-100分（优秀） | J10: 部门负责人 | K10: 核算时间：每月5日完成绩效绩效核算 取值范围：上月整月 | L10: 100 | M10: =E10*L10 -> 20
B11: 6 | C11: 个人指标 | D11: 工作能力 | E11: 0.2 | F11: 熟悉操作直播伴侣，巨量百应等工作台，及时调整直播画面问题，出现违规时及时查询反馈具体原因 | H11: / | I11: 0-60分（差） 60-80分（合格） 80-100分（优秀） | J11: 部门负责人 | K11: 核算时间：每月5日完成绩效绩效核算 取值范围：上月整月 | L11: 100 | M11: =E11*L11 -> 20
B12: 合计 | E12: =SUM(E6:E11) -> 1 | M12: =SUM(M6:M11) -> 100
I16: 岗位提成标准说明
I17: 提成来源 | K17: 得分下限 （包含） | L17: 得分上限 （不包含） | M17: 提成比例
I18: 运营店铺GSV | J18: 0 | K18: 60 | L18: 0.1%/中控人数 | M18: 绩效工资*80%
I19: 运营店铺GSV | J19: 60 | K19: 80 | L19: 0.1%/中控人数 | M19: 绩效工资*90%
I20: 运营店铺GSV | J20: 80 | K20: 100 | L20: 0.1%/中控人数 | M20: 绩效工资*100%
I21: 运营店铺GSV | J21: 100 | K21: 150 | L21: 0.1%/中控人数 | M21: 绩效工资*110%

Sheet 兴趣电商-主播
C1: 岗位绩效责任书
C2: 部门： | D2: 兴趣电商部 | E2: 岗位： | F2: 主播
E3: 姓名：
B4: 编号 | C4: 评价维度 | D4: 指标项目 | E4: 指标权重 | F4: 目标 | G4: 计算公式 | H4: 单位 | I4: 评分标准 | J4: 数据来源 | K4: 评价周期 | L4: 完成结果 | M4: 最终得分
B6: 1 | C6: 岗位指标 | D6: 个人直播签收ROI达成 | E6: 0.6 | F6: 确保个人直播时段签收ROI对照预算目标的达成率 | G6: 达成率=实际签收ROI/预算目标签收ROI | H6: % | I6: 达成率≥100%：按照实际达成取两位小数点计入该项目分，最高150分。 100%＞达成率≥80%，90分 80%＞达成率≥60%，60分 60%＞达成率，0分 | J6: 平台数据 | K6: 核算时间：每月5日完成绩效绩效核算 取值范围：上月整月 | L6: 100 | M6: =E6*L6 -> 60
B7: 2 | C7: 岗位指标 | D7: 直播话术持续梳理与迭代 | E7: 0.2 | F7: 有创新意识，主动策划直播活动和话术；能够承担大型活动、承受业绩目标 | H7: / | I7: 0-60分（差） 60-80分（合格） 80-100分（优秀） | J7: 部门负责人 | K7: 核算时间：每月5日完成绩效绩效核算 取值范围：上月整月 | L7: 100 | M7: =E7*L7 -> 20
B8: 3 | C8: 个人指标 | D8: 工作态度 | E8: 0.1 | F8: 理解和遵守公司的各项规章制度、服从上级的指示和命令。充分理解自己的责任和义务，不回避责任 | H8: / | I8: 0-60分（差） 60-80分（合格） 80-100分（优秀） | J8: 部门负责人 | K8: 核算时间：每月5日完成绩效绩效核算 取值范围：上月整月 | L8: 100 | M8: =E8*L8 -> 10
B9: 4 | C9: 个人指标 | D9: 工作能力 | E9: 0.1 | F9: 对上级的命令，下达的计划，布置的工作能及时贯彻执行，及时提出需要的帮忙或支持，保持状态积极饱满 | H9: / | I9: 0-60分（差） 60-80分（合格） 80-100分（优秀） | J9: 部门负责人 | K9: 核算时间：每月5日完成绩效绩效核算 取值范围：上月整月 | L9: 100 | M9: =E9*L9 -> 10
B10: 合计 | E10: =SUM(E6:E9) -> 1 | L10: 100 | M10: =SUM(M6:M9) -> 100
I14: 岗位提成标准说明
I15: 提成来源 | K15: 得分下限 （包含） | L15: 得分上限 （不包含） | M15: 提成比例
I16: 个人直播时段GSV | K16: 0 | L16: 60 | M16: 0.001
I17: 个人直播时段GSV | K17: 60 | L17: 80 | M17: 0.002
I18: 个人直播时段GSV | K18: 80 | L18: 100 | M18: 0.004
I19: 个人直播时段GSV | K19: 100 | L19: 150 | M19: 0.005

Sheet 兴趣电商-客服
C1: 岗位绩效责任书
C2: 部门： | D2: 兴趣电商部 | E2: 岗位： | F2: 电商客服专员
E3: 姓名：
B4: 编号 | C4: 评价维度 | D4: 指标项目 | E4: 指标权重 | F4: 评分标准 | G4: 奖励条件及金额/提成标准 | H4: 处罚条件及金额/评分标准 | I4: 数据来源 | J4: 评价周期 | K4: 完成结果 | L4: 最终得分
B6: 1 | C6: 岗位指标 | D6: 接待响应率 | E6: 0.1 | F6: 1. 平均响应时间百分比（按全平台平均值）； 2. 响应率100%（无漏接咨询） | G6: 全平台响应率＞98%，奖励50元 | H6: 1.全平台月平均响应率＜95%，每低1%扣10元，5分 2.漏接咨询1次扣20元（恶意漏接翻倍），5分 | I6: 平台客服后台数据 | J6: 核算时间：每月5日完成绩效绩效核算 取值范围：上月整月 | K6: 100 | L6: =E6*K6 -> 10
B7: 2 | D7: 售前咨询转化标准 | E7: 0.3 | F7: 进线咨询主动给客户推送产品+产品介绍+下单引导 | G7: 1. 成功引导下单转化＞50%奖励100 2.引导转化＞80%以上奖励200 （拉全平台平均值） | H7: 1.问一答一无做引导扣10元/次，10分 2. 转化率＜10%，扣100元，10分 3.转化率＜20%扣50（拉全平台月平均值），10分 | I7: 平台客服后台数据 | J7: 核算时间：每月5日完成绩效绩效核算 取值范围：上月整月 | K7: 100 | L7: =E7*K7 -> 30
B8: 3 | D8: 售后挽留 | E8: 0.2 | F8: 1.仅退款挽留2. 退货退款挽留 | G8: 1. 已发货仅退款成功挽留奖5元/单 2. 已收货退货退款挽留奖励10元/单（合规挽留，方式不限） | H8: 1. 已发货仅退款申请+退货退款未做挽留机制扣5元/单 ，15分 2.已做挽留机制但不成功不扣钱，5分 | I8: 平台客服后台数据 | J8: 核算时间：每月5日完成绩效绩效核算 取值范围：上月整月 | K8: 100 | L8: =E8*K8 -> 20
B9: 4 | D9: 未付款催付+话术 | E9: 0.2 | F9: 结合AI协助话术对未付款催付及时挽单有效； | G9: 利用有效话术催促未付款订单并有效挽留订单奖5元/单 | H9: 1.下单未付款未及时催付扣5元/次，15分 2.当月催付挽留订单＜10单不扣钱，5分 | I9: 平台客服后台数据 | J9: 核算时间：每月5日完成绩效绩效核算 取值范围：上月整月 | K9: 100 | L9: =E9*K9 -> 20
B10: 5 | D10: 违规词/敏感词/错误回复 | E10: 0.1 | F10: 客服话术上出现违规/敏感词（如：增高，发育，免疫力等）/未按客户问题进行回复，错误答复 | G10: 当月接待聊天记录未出现过一次敏感词，违规词/错误答复，奖励个人50元 | H10: 1.接待过程出现敏感/违规词，未造成影响并及时修改，首次不做处罚，若发现无修改者处罚扣取50元/次 ，3分 2.用词出现违规对店铺造成影响扣200/次并追责，3分 3.接待出现错误答复扣5元/次，4分 | I10: 平台客服后台数据 | J10: 核算时间：每月5日完成绩效绩效核算 取值范围：上月整月 | K10: 100 | L10: =E10*K10 -> 10
D11: 邀请好评 | E11: 0.1 | F11: 合理邀评晒图 | G11: 当月成功邀请客户评价晒图数超过30次，奖励100元，晒图客数＞50次奖励150元 | H11: 1.未主动邀评，5分 2.拉动好评数＜10条扣50元，5分 | I11: 平台客服后台数据 | J11: 核算时间：每月5日完成绩效绩效核算 取值范围：上月整月 | K11: 100 | L11: =E11*K11 -> 10
B12: 合计 | E12: =SUM(E6:E11) -> 1 | K12: 100 | L12: =SUM(L6:L11) -> 100
H16: 岗位提成标准说明
H17: 提成来源 | J17: 得分下限 （包含） | K17: 得分上限 （不包含） | L17: 提成比例
H18: 平台客服后台数据 | L18: 以奖励条件及金额为准
H19: 平台客服后台数据 | L19: 以奖励条件及金额为准
H20: 平台客服后台数据 | L20: 以奖励条件及金额为准
H21: 平台客服后台数据 | L21: 以奖励条件及金额为准

Sheet 制作部-编导
C1: 岗位绩效责任书
C2: 部门： | D2: 制作部 | E2: 岗位： | F2: 编导
E3: 姓名：
B4: 编号 | C4: 评价维度 | D4: 指标项目 | E4: 指标权重 | F4: 目标 | G4: 计算公式 | H4: 单位 | I4: 评分标准 | J4: 数据来源 | K4: 评价周期 | L4: 完成结果 | M4: 最终得分
B6: 1 | C6: 组织指标 | D6: 团队营收目标达成率 | E6: 0.1 | F6: 确保所负责渠道退货后营收（GSV）对照预算目标的达成率 | G6: 达成率=实际GSV达成/预算目标GSV达成 | H6: % | I6: 达成率≥100%：按照实际达成取两位小数点计入该项目分，最高150分。 100%＞达成率≥80%，90分 80%＞达成率≥60%，60分 60%＞达成率，0分 | J6: 云视频管家 | K6: 核算时间：每月5日完成绩效绩效核算 取值范围：上传时间90天内素材的上月整月消耗 | L6: 100 | M6: =E6*L6 -> 10
B7: 2 | C7: 岗位指标 | D7: 团队产出数量 | E7: 0.2 | F7: 当月所带领剪辑团队人均视频产出不低于140个/人，不含机剪 | G7: 人均产出=当月项目组剪辑总产出/项目组人数 | H7: / | I7: 人均产出≥140：按照实际达成取两位小数点计入该项目分，最高120分。 140＞人均产出≥120，80分 120＞人均产出，0分 | J7: 云视频管家 | K7: 核算时间：每月5日完成绩效绩效核算 取值范围：上传时间90天内素材的上月整月消耗 | L7: 100 | M7: =E7*L7 -> 20
B8: 3 | C8: 岗位指标 | D8: 团队产出消耗金额 | E8: 0.3 | F8: 按照个人所带领小组所覆盖项目的整体当月消耗合计，对比目标与达成，计算达成率。 计算范围：成片上传时间90天内。 | G8: 达成率=当月项目组总消耗/项目预算目标消耗值 | H8: % | I8: 达成率≤80%，0分； 80%＜达成率≤100%，计90分； 达成率大于等于100%，按照实际达成取两位小数点计入该项目分，封顶系数1.5。 | J8: 云视频管家 | K8: 核算时间：每月5日完成绩效绩效核算 取值范围：上传时间90天内素材的上月整月消耗 | L8: 100 | M8: =E8*L8 -> 30
B9: 4 | C9: 个人指标 | D9: 工作能力 | E9: 0.15 | F9: 根据目标制定季度 / 月度内容规划与选题方向，研究行业竞品内容动态、平台算法规则与热门趋势，输出可落地的内容打法，建立公司内容资产库，确保所有内容调性统一、卖点准确 | H9: / | I9: 0-60分（差） 60-80分（合格） 80-100分（优秀） | J9: 部门负责人 | K9: 核算时间：每月5日完成绩效绩效核算 取值范围：上传时间90天内素材的上月整月消耗 | L9: 100 | M9: =E9*L9 -> 15
B10: 5 | C10: 个人指标 | D10: 投后复盘 | E10: 0.15 | F10: 跟踪所有内容的发布数据（播放量、完播率、点赞率、转化率等），每周 / 每月组织内容复盘会，分析数据表现，总结成功经验与失败教训，根据数据反馈持续优化内容策略与创作方向，提升内容 ROI | H10: % | I10: 0-60分（差） 60-80分（合格） 80-100分（优秀） | J10: 部门负责人 | K10: 核算时间：每月5日完成绩效绩效核算 取值范围：上传时间90天内素材的上月整月消耗 | L10: 100 | M10: =E10*L10 -> 15
B11: 6 | C11: 个人指标 | D11: 团队管理及组织能力 | E11: 0.1 | F11: 负责摄像、剪辑团队的日常管理、绩效考核与技能培训，建立清晰的工作流程与标准，提高团队整体工作效率，关注团队成员工作状态，及时解决工作中出现的问题 | H11: / | I11: 0-60分（差） 60-80分（合格） 80-100分（优秀） | J11: 部门负责人 | K11: 核算时间：每月5日完成绩效绩效核算 取值范围：上传时间90天内素材的上月整月消耗 | L11: 100 | M11: =E11*L11 -> 10
B12: 合计 | E12: =SUM(E6:E11) -> 1 | L12: 100 | M12: =SUM(M6:M11) -> 100
F16: 爆款激励说明 | I16: 岗位提成标准说明
F17: 说明项 | G17: 明细 | I17: 提成来源 | K17: 得分下限 （包含） | L17: 得分上限 （不包含） | M17: 提成比例
F18: 爆款定义 | G18: 近90天内上传素材单视频消耗超50万 | I18: 个人上传素材广告消耗 | K18: 0 | L18: 60 | M18: 0
F19: 激励金额 | G19: 除消耗提成外，额外一次性奖励1500元/片 | I19: 个人上传素材广告消耗 | K19: 60 | L19: 80 | M19: 0.001
I20: 个人上传素材广告消耗 | K20: 80 | L20: 100 | M20: 0.003
I21: 个人上传素材广告消耗 | K21: 100 | L21: 150 | M21: 0.0045

Sheet 制作部-视频剪辑
C1: 岗位绩效责任书
C2: 部门： | D2: 制作部 | E2: 岗位： | F2: 视频剪辑师
E3: 姓名：
B4: 编号 | C4: 评价维度 | D4: 指标项目 | E4: 指标权重 | F4: 目标 | G4: 计算公式 | H4: 单位 | I4: 评分标准 | J4: 数据来源 | K4: 评价周期 | L4: 完成结果 | M4: 最终得分
B6: 1 | C6: 组织指标 | D6: 团队营收目标达成率 | E6: 0.1 | F6: 确保所负责渠道退货后营收（GSV）对照预算目标的达成率 | G6: 达成率=实际GSV达成/预算目标GSV达成 | H6: % | I6: 达成率≥100%：按照实际达成取两位小数点计入该项目分，最高150分。 100%＞达成率≥80%，90分 80%＞达成率≥60%，60分 60%＞达成率，0分 | J6: 云视频管家 | K6: 核算时间：每月5日完成绩效绩效核算 取值范围：上传时间90天内素材的上月整月消耗 | L6: 100 | M6: =E6*L6 -> 10
B7: 2 | C7: 岗位指标 | D7: 个人成片数量 | E7: 0.2 | F7: 当月个人产出不低于150条成片视频，不含机剪视频 | G7: 达成率=个人产出总数/150 | H7: % | I7: 达成率≤80%，0分； 80%＜达成率≤100%，计80分； 达成率≥100%，按照实际达成取两位小数点计入该项目分，封顶系数1.2。 | J7: 云视频管家 | K7: 核算时间：每月5日完成绩效绩效核算 取值范围：上传时间90天内素材的上月整月消耗 | L7: 100 | M7: =E7*L7 -> 20
B8: 3 | C8: 岗位指标 | D8: 个人成片消耗金额 | E8: 0.3 | F8: 按照“不低于当月项目组总消耗金额的个人均额的90%”的方式计算达成率。 计算范围：成片上传时间90天内。 豁免规则：运行不足90天的新项目得分默认为100分同时不参与计算。 | G8: 个人贡献率公式=个人消耗达成金额/（当月项目总消耗/项目组剪辑人数*0.9） | H8: % | I8: 达成率≤80%，0分； 80%＜达成率≤100%，计90分； 达成率≥100%，按照实际达成取两位小数点计入该项目分，封顶系数1.5。 | J8: 云视频管家 | K8: 核算时间：每月5日完成绩效绩效核算 取值范围：上传时间90天内素材的上月整月消耗 | L8: 100 | M8: =E8*L8 -> 30
B9: 4 | C9: 个人指标 | D9: 工作能力 | E9: 0.2 | F9: 1.根据内容主管提供的工单与脚本，完成视频制作工作，持续提升视频观感； 2.根据内容主管的修改意见，及时调整剪辑内容，直到成片审核通过。 | H9: / | I9: 出现与目标相悖的情况（如文本错误等），单次扣除5分 | J9: 直属内容主管/编导 | K9: 核算时间：每月5日完成绩效绩效核算 取值范围：上传时间90天内素材的上月整月消耗 | L9: 100 | M9: =E9*L9 -> 20
B10: 5 | C10: 个人指标 | D10: 素材管理 | E10: 0.2 | F10: 1.负责个人上传成片的文件管理与工程备份，维护分类、归档、以及标签管理工作； 2.根据不同平台的要求，输出相应格式、分辨率与码率的视频文件。 | H10: / | I10: 出现与目标相悖的情况（如标签、命名混乱等），单次扣除5分 | J10: 直属内容主管/编导 | K10: 核算时间：每月5日完成绩效绩效核算 取值范围：上传时间90天内素材的上月整月消耗 | L10: 100 | M10: =E10*L10 -> 20
B11: 合计 | E11: =SUM(E6:E10) -> 1 | L11: 100 | M11: =SUM(M6:M10) -> 100
F15: 爆款激励说明 | I15: 岗位提成标准说明
F16: 说明项 | G16: 明细 | I16: 提成来源 | K16: 得分下限 （包含） | L16: 得分上限 （不包含） | M16: 提成比例
F17: 爆款定义 | G17: 近90天内上传素材单视频消耗超50万 | I17: 个人上传素材广告消耗 | K17: 0 | L17: 60 | M17: 0
F18: 激励金额 | G18: 除消耗提成外，额外一次性奖励1500元/片 | I18: 个人上传素材广告消耗 | K18: 60 | L18: 80 | M18: 0.001
I19: 个人上传素材广告消耗 | K19: 80 | L19: 100 | M19: 0.003
I20: 个人上传素材广告消耗 | K20: 100 | L20: 150 | M20: 0.0045
B21: 、

Sheet 制作部-摄影师
C1: 岗位绩效责任书
C2: 部门： | D2: 制作部 | E2: 岗位： | F2: 摄影师
E3: 姓名：
B4: 编号 | C4: 评价维度 | D4: 指标项目 | E4: 指标权重 | F4: 目标 | G4: 计算公式 | H4: 单位 | I4: 评分标准 | J4: 数据来源 | K4: 评价周期 | L4: 完成结果 | M4: 最终得分
B6: 1 | C6: 组织指标 | D6: 团队营收目标达成率 | E6: 0.1 | F6: 确保所负责渠道退货后营收（GSV）对照预算目标的达成率 | G6: 达成率=实际GSV达成/预算目标GSV达成 | H6: % | I6: 达成率≥100%：按照实际达成取两位小数点计入该项目分，最高150分。 100%＞达成率≥80%，90分 80%＞达成率≥60%，60分 60%＞达成率，0分 | J6: 云视频管家 | K6: 核算时间：每月5日完成绩效绩效核算 取值范围：上传时间90天内素材的上月整月消耗 | L6: 100 | M6: =E6*L6 -> 10
B7: 2 | C7: 岗位指标 | D7: 个人素材数量 | E7: 0.5 | F7: 当月个人产出完成全部任务工单中的素材实拍/AI生成数量 | G7: 达成率=个人发布工单数/工单任务数 | H7: % | I7: 达成率≤100%，0分； 达成率≥100%，100分。 | J7: 云视频管家 | K7: 核算时间：每月5日完成绩效绩效核算 取值范围：上传时间90天内素材的上月整月消耗 | L7: 100 | M7: =E7*L7 -> 50
B8: 3 | C8: 岗位指标 | D8: 工作能力 | E8: 0.2 | F8: 1.根据内容主管提供的脚本，制定详细的拍摄计划与镜头清单； 2.熟练操作单反、微单、摄像机、稳定器、无人机等各类摄像设备，精通布光技巧； 3.能够根据不同场景与产品特点搭建合适的灯光环境，独立完成产品特写、场景展示、人物采访等各类镜头的拍摄工作； 4.把控拍摄节奏，在规定时间内完成所有拍摄任务，确保素材质量达标 | H8: / | I8: 出现与目标相悖的情况，单次扣除5分 | J8: 直属内容主管/编导 | K8: 核算时间：每月5日完成绩效绩效核算 取值范围：上传时间90天内素材的上月整月消耗 | L8: 100 | M8: =E8*L8 -> 20
B9: 4 | C9: 个人指标 | D9: 职业素养 | E9: 0.1 | F9: 1.拍摄前与内容主管、运营充分沟通，明确拍摄需求与注意事项； 2.拍摄过程中积极配合内容主管的现场指导，及时调整拍摄方案； 3.协助内容主管完成场地勘景、道具准备、演员调度等工作； 4.拍摄结束后协助整理拍摄场地，归还借用物品。 | H9: / | I9: 出现与目标相悖的情况，单次扣除5分 | J9: 直属内容主管/编导 | K9: 核算时间：每月5日完成绩效绩效核算 取值范围：上传时间90天内素材的上月整月消耗 | L9: 100 | M9: =E9*L9 -> 10
B10: 5 | C10: 个人指标 | D10: 工作态度 | E10: 0.1 | F10: 1.拍摄完成后 24 小时内完成素材的导出、备份与分类归档； 2.按照公司统一的命名规则对素材进行命名，确保素材可快速检索； 3.定期整理素材库，删除无用素材，释放存储空间； 4.向剪辑师提供清晰、完整的素材，标注关键镜头位置 | H10: / | I10: 出现与目标相悖的情况，单次扣除5分 | J10: 直属内容主管/编导 | K10: 核算时间：每月5日完成绩效绩效核算 取值范围：上传时间90天内素材的上月整月消耗 | L10: 100 | M10: =E10*L10 -> 10
B11: 合计 | E11: =SUM(E6:E10) -> 1 | L11: 100 | M11: =SUM(M6:M10) -> 100
I15: 岗位提成标准说明
I16: 提成来源 | K16: 得分下限 （包含） | L16: 得分上限 （不包含） | M16: 提成比例
I17: 个人拍摄素材消耗 | K17: 0 | L17: 60 | M17: 0
I18: 个人拍摄素材消耗 | K18: 60 | L18: 80 | M18: 0.001
I19: 个人拍摄素材消耗 | K19: 80 | L19: 100 | M19: 0.0015
I20: 个人拍摄素材消耗 | K20: 100 | L20: 150 | M20: 0.002
