Workbook

Sheet 目录及说明
A1: 羊喜市中期预算模型 V60 目录及说明
A3: 版本 | B3: V60 渠道二维汇总、汇总损益费用链路与目录重建
A4: 表格逻辑 | B4: https://jv8fym591u8.feishu.cn/docx/YzETdWRa3oLB9rxM8i7ccsNAnfg?from=from_copylink
A5: 输出规则 | B5: 目录、总表、说明、假设、测算、辅助、参考；各工作表均可通过目录跳转。
A6: 本版重点 | B6: 统一全表字体为等线；渠道费用明细按科目名称映射，渠道总贡献与汇总损益表口径一致。
A7: 校验单位 | B7: 金额单位均为万元；测算与总表的1-6月列保留分组隐藏规则。
A8: 序号 | B8: 工作表 | C8: 类型 | D8: 计算角色 | E8: 定义/用途 | F8: 跳转 | G8: 显示状态 | H8: 备注
A9: 1 | B9: 目录及说明 | C9: 目录 | D9: 导航 | E9: 模型导航、版本与维护规则 | F9: =HYPERLINK("#'目录及说明'!A1","当前") -> 当前 | G9: 显示 | H9: 当前工作表
A10: 2 | B10: 总表-汇总损益表 | C10: 总表 | D10: 汇总 | E10: 公司合并损益、其他业务收入与净利润 | F10: =HYPERLINK("#'总表-汇总损益表'!A1","打开") -> 打开 | G10: 显示 | H10: 集团口径总览
A11: 3 | B11: 总表-渠道二维汇总 | C11: 总表 | D11: 汇总 | E11: 渠道收入、成本、费用及贡献横向对比 | F11: =HYPERLINK("#'总表-渠道二维汇总'!A1","打开") -> 打开 | G11: 显示 | H11: 仅展示渠道及渠道总贡献
A12: 4 | B12: 费用科目说明 | C12: 说明 | D12: 说明 | E12: 预算费用科目与财报科目映射说明 | F12: =HYPERLINK("#'费用科目说明'!A1","打开") -> 打开 | G12: 显示 | H12: 不参与计算，建议保留审计说明
A13: 5 | B13: 假设-财务口径 | C13: 假设/输入 | D13: 驱动 | E13: 税率、返利及整体经营财务假设 | F13: =HYPERLINK("#'假设-财务口径'!A1","打开") -> 打开 | G13: 显示 | H13: 直接参与整体经营及所得税计算
A14: 6 | B14: 假设-人工成本固定额 | C14: 假设/输入 | D14: 驱动 | E14: 各渠道固定薪资及奖金规则 | F14: =HYPERLINK("#'假设-人工成本固定额'!A1","打开") -> 打开 | G14: 隐藏 | H14: 驱动渠道人工成本
A15: 7 | B15: 假设-产品价值链定价 | C15: 假设/输入 | D15: 驱动 | E15: 集团采购、内部拿货及产品定价假设 | F15: =HYPERLINK("#'假设-产品价值链定价'!A1","打开") -> 打开 | G15: 隐藏 | H15: 驱动整体经营剪刀差测算
A16: 8 | B16: 假设-成本与任务量 | C16: 假设/输入 | D16: 驱动 | E16: 产品采购成本与SALEIN任务分解 | F16: =HYPERLINK("#'假设-成本与任务量'!A1","打开") -> 打开 | G16: 显示 | H16: 驱动产品成本与任务目标
A17: 9 | B17: 参考值-平台主推SKU占比 | C17: 参考 | D17: 引用源 | E17: 平台主推SKU结构及成交占比 | F17: =HYPERLINK("#'参考值-平台主推SKU占比'!A1","打开") -> 打开 | G17: 隐藏 | H17: 驱动平台主推机制
A18: 10 | B18: 假设-平台主推机制 | C18: 假设/输入 | D18: 驱动 | E18: 渠道机制、到手价及主品成本结构 | F18: =HYPERLINK("#'假设-平台主推机制'!A1","打开") -> 打开 | G18: 隐藏 | H18: 驱动渠道收入与产品成本
A19: 11 | B19: 假设-目标渠道分解 | C19: 假设/输入 | D19: 驱动 | E19: 渠道SALEIN任务与月度目标 | F19: =HYPERLINK("#'假设-目标渠道分解'!A1","打开") -> 打开 | G19: 显示 | H19: 驱动渠道滚动目标
A20: 12 | B20: 参考值-平台费用率分析 | C20: 参考 | D20: 引用源 | E20: 财务口径平台1-12月实际费用与收入数据 | F20: =HYPERLINK("#'参考值-平台费用率分析'!A1","打开") -> 打开 | G20: 隐藏 | H20: 销售费用率与实际达成取数源
A21: 13 | B21: 假设-销售费用率 | C21: 假设/输入 | D21: 驱动 | E21: 渠道月度费用率、历史参考及运营调整 | F21: =HYPERLINK("#'假设-销售费用率'!A1","打开") -> 打开 | G21: 显示 | H21: 驱动渠道销售费用
A22: 14 | B22: 假设-ROI月度滚动 | C22: 假设/输入 | D22: 驱动 | E22: 广告投流ROI月度假设 | F22: =HYPERLINK("#'假设-ROI月度滚动'!A1","打开") -> 打开 | G22: 显示 | H22: 驱动ROI相关费用
A23: 15 | B23: 测算-高个子抖音 | C23: 测算 | D23: 计算 | E23: 抖音渠道收入、成本、费用与贡献利润 | F23: =HYPERLINK("#'测算-高个子抖音'!A1","打开") -> 打开 | G23: 显示 | H23: 渠道测算
A24: 16 | B24: 测算-高个子视频号 | C24: 测算 | D24: 计算 | E24: 视频号渠道收入、成本、费用与贡献利润 | F24: =HYPERLINK("#'测算-高个子视频号'!A1","打开") -> 打开 | G24: 显示 | H24: 渠道测算
A25: 17 | B25: 测算-天猫淘宝 | C25: 测算 | D25: 计算 | E25: 天猫淘宝渠道收入、成本、费用与贡献利润 | F25: =HYPERLINK("#'测算-天猫淘宝'!A1","打开") -> 打开 | G25: 显示 | H25: 渠道测算
A26: 18 | B26: 测算-拼多多 | C26: 测算 | D26: 计算 | E26: 拼多多渠道收入、成本、费用与贡献利润 | F26: =HYPERLINK("#'测算-拼多多'!A1","打开") -> 打开 | G26: 显示 | H26: 渠道测算
A27: 19 | B27: 测算-京东POP | C27: 测算 | D27: 计算 | E27: 京东POP渠道收入、成本、费用与贡献利润 | F27: =HYPERLINK("#'测算-京东POP'!A1","打开") -> 打开 | G27: 显示 | H27: 渠道测算
A28: 20 | B28: 测算-京东自营 | C28: 测算 | D28: 计算 | E28: 京东自营B2B供货、费用与贡献利润 | F28: =HYPERLINK("#'测算-京东自营'!A1","打开") -> 打开 | G28: 显示 | H28: 渠道测算
A29: 21 | B29: 测算-达播 | C29: 测算 | D29: 计算 | E29: 达播渠道收入、成本、费用与贡献利润 | F29: =HYPERLINK("#'测算-达播'!A1","打开") -> 打开 | G29: 显示 | H29: 渠道测算
A30: 22 | B30: 测算-私域 | C30: 测算 | D30: 计算 | E30: 私域渠道独立业务测算 | F30: =HYPERLINK("#'测算-私域'!A1","打开") -> 打开 | G30: 显示 | H30: 业务部门薪资奖金按其测算口径
A31: 23 | B31: 测算-外部分销 | C31: 测算 | D31: 计算 | E31: 外部分销收入、成本、返佣与物流费用 | F31: =HYPERLINK("#'测算-外部分销'!A1","打开") -> 打开 | G31: 显示 | H31: 渠道测算
A32: 24 | B32: 测算-整体经营 | C32: 测算 | D32: 计算 | E32: 集团内部供货价差、返利及公司公共费用 | F32: =HYPERLINK("#'测算-整体经营'!A1","打开") -> 打开 | G32: 显示 | H32: 整体经营损益
A33: 25 | B33: 辅助-汇总损益长表 | C33: 辅助 | D33: 汇总辅助 | E33: 各渠道与整体经营的纵向汇总底表 | F33: =HYPERLINK("#'辅助-汇总损益长表'!A1","打开") -> 打开 | G33: 隐藏 | H33: 直接参与总表计算，不可删除
A34: 26 | B34: 辅助-机制测算 | C34: 辅助 | D34: 计算辅助 | E34: 平台机制的收入、主品成本及SKU拆分 | F34: =HYPERLINK("#'辅助-机制测算'!A1","打开") -> 打开 | G34: 隐藏 | H34: 直接参与渠道测算，不可删除

Sheet 总表-汇总损益表
A1: 返回目录
B2: 公司层面汇总损益（万元）
D6: 科目明细 | E6: 说明 | F6: 驱动 | H6: 2026-01 | I6: 2026-02 | J6: 2026-03 | K6: 2026-04 | L6: 2026-05 | M6: 2026-06 | N6: 2026-07 | O6: 2026-08 | P6: 2026-09 | Q6: 2026-10 | R6: 2026-11 | S6: 2026-12 | U6: 全年合计 | V6: 中期合计
B7: 主营业务收入 | F7: 来自各渠道测算表 | H7: =SUMIFS('辅助-汇总损益长表'!$C$2:$C$242,'辅助-汇总损益长表'!$A$2:$A$242,"主营业务收入",'辅助-汇总损益长表'!$B$2:$B$242,H$6)-SUMIFS('辅助-汇总损益长表'!$M$2:$M$242,'辅助-汇总损益长表'!$A$2:$A$242,"主营业务收入",'辅助-汇总损益长表'!$B$2:$B$242,H$6) -> 1096.5403 | I7: =SUMIFS('辅助-汇总损益长表'!$C$2:$C$242,'辅助-汇总损益长表'!$A$2:$A$242,"主营业务收入",'辅助-汇总损益长表'!$B$2:$B$242,I$6)-SUMIFS('辅助-汇总损益长表'!$M$2:$M$242,'辅助-汇总损益长表'!$A$2:$A$242,"主营业务收入",'辅助-汇总损益长表'!$B$2:$B$242,I$6) -> 664.95961 | J7: =SUMIFS('辅助-汇总损益长表'!$C$2:$C$242,'辅助-汇总损益长表'!$A$2:$A$242,"主营业务收入",'辅助-汇总损益长表'!$B$2:$B$242,J$6)-SUMIFS('辅助-汇总损益长表'!$M$2:$M$242,'辅助-汇总损益长表'!$A$2:$A$242,"主营业务收入",'辅助-汇总损益长表'!$B$2:$B$242,J$6) -> 1012.2948 | K7: =SUMIFS('辅助-汇总损益长表'!$C$2:$C$242,'辅助-汇总损益长表'!$A$2:$A$242,"主营业务收入",'辅助-汇总损益长表'!$B$2:$B$242,K$6)-SUMIFS('辅助-汇总损益长表'!$M$2:$M$242,'辅助-汇总损益长表'!$A$2:$A$242,"主营业务收入",'辅助-汇总损益长表'!$B$2:$B$242,K$6) -> 977.84975 | L7: =SUMIFS('辅助-汇总损益长表'!$C$2:$C$242,'辅助-汇总损益长表'!$A$2:$A$242,"主营业务收入",'辅助-汇总损益长表'!$B$2:$B$242,L$6)-SUMIFS('辅助-汇总损益长表'!$M$2:$M$242,'辅助-汇总损益长表'!$A$2:$A$242,"主营业务收入",'辅助-汇总损益长表'!$B$2:$B$242,L$6) -> 1218.1032 | M7: =SUMIFS('辅助-汇总损益长表'!$C$2:$C$242,'辅助-汇总损益长表'!$A$2:$A$242,"主营业务收入",'辅助-汇总损益长表'!$B$2:$B$242,M$6)-SUMIFS('辅助-汇总损益长表'!$M$2:$M$242,'辅助-汇总损益长表'!$A$2:$A$242,"主营业务收入",'辅助-汇总损益长表'!$B$2:$B$242,M$6) -> 1240.5906 | N7: =SUMIFS('辅助-汇总损益长表'!$C$2:$C$242,'辅助-汇总损益长表'!$A$2:$A$242,"主营业务收入",'辅助-汇总损益长表'!$B$2:$B$242,N$6)-SUMIFS('辅助-汇总损益长表'!$M$2:$M$242,'辅助-汇总损益长表'!$A$2:$A$242,"主营业务收入",'辅助-汇总损益长表'!$B$2:$B$242,N$6) -> 791.84389 | O7: =SUMIFS('辅助-汇总损益长表'!$C$2:$C$242,'辅助-汇总损益长表'!$A$2:$A$242,"主营业务收入",'辅助-汇总损益长表'!$B$2:$B$242,O$6)-SUMIFS('辅助-汇总损益长表'!$M$2:$M$242,'辅助-汇总损益长表'!$A$2:$A$242,"主营业务收入",'辅助-汇总损益长表'!$B$2:$B$242,O$6) -> 1045.5994 | ... S7: =SUMIFS('辅助-汇总损益长表'!$C$2:$C$242,'辅助-汇总损益长表'!$A$2:$A$242,"主营业务收入",'辅助-汇总损益长表'!$B$2:$B$242,S$6)-SUMIFS('辅助-汇总损益长表'!$M$2:$M$242,'辅助-汇总损益长表'!$A$2:$A$242,"主营业务收入",'辅助-汇总损益长表'!$B$2:$B$242,S$6) -> 1463.1062 | U7: =SUM(H7:S7) -> 13949.584 | V7: =SUM(N7:S7) -> 7739.2455
B8: 主营业务成本 | F8: 来自各渠道测算表 | H8: =SUMIFS('辅助-汇总损益长表'!$C$2:$C$242,'辅助-汇总损益长表'!$A$2:$A$242,"主营业务成本",'辅助-汇总损益长表'!$B$2:$B$242,H$6) -> 413.97462 | I8: =SUMIFS('辅助-汇总损益长表'!$C$2:$C$242,'辅助-汇总损益长表'!$A$2:$A$242,"主营业务成本",'辅助-汇总损益长表'!$B$2:$B$242,I$6) -> 245.01229 | J8: =SUMIFS('辅助-汇总损益长表'!$C$2:$C$242,'辅助-汇总损益长表'!$A$2:$A$242,"主营业务成本",'辅助-汇总损益长表'!$B$2:$B$242,J$6) -> 437.01891 | K8: =SUMIFS('辅助-汇总损益长表'!$C$2:$C$242,'辅助-汇总损益长表'!$A$2:$A$242,"主营业务成本",'辅助-汇总损益长表'!$B$2:$B$242,K$6) -> 367.20972 | L8: =SUMIFS('辅助-汇总损益长表'!$C$2:$C$242,'辅助-汇总损益长表'!$A$2:$A$242,"主营业务成本",'辅助-汇总损益长表'!$B$2:$B$242,L$6) -> 463.40024 | M8: =SUMIFS('辅助-汇总损益长表'!$C$2:$C$242,'辅助-汇总损益长表'!$A$2:$A$242,"主营业务成本",'辅助-汇总损益长表'!$B$2:$B$242,M$6) -> 451.4047 | N8: =SUMIFS('辅助-汇总损益长表'!$C$2:$C$242,'辅助-汇总损益长表'!$A$2:$A$242,"主营业务成本",'辅助-汇总损益长表'!$B$2:$B$242,N$6) -> 284.77935 | O8: =SUMIFS('辅助-汇总损益长表'!$C$2:$C$242,'辅助-汇总损益长表'!$A$2:$A$242,"主营业务成本",'辅助-汇总损益长表'!$B$2:$B$242,O$6) -> 375.49932 | ... S8: =SUMIFS('辅助-汇总损益长表'!$C$2:$C$242,'辅助-汇总损益长表'!$A$2:$A$242,"主营业务成本",'辅助-汇总损益长表'!$B$2:$B$242,S$6) -> 524.78257 | U8: =SUM(H8:S8) -> 5155.1438 | V8: =SUM(N8:S8) -> 2777.1234
B9: 毛利 | F9: 公式计算 | H9: =H7-H8 -> 682.56571 | I9: =I7-I8 -> 419.94732 | J9: =J7-J8 -> 575.27586 | K9: =K7-K8 -> 610.64003 | L9: =L7-L8 -> 754.70294 | M9: =M7-M8 -> 789.18587 | N9: =N7-N8 -> 507.06454 | O9: =O7-O8 -> 670.10008 | ... S9: =S7-S8 -> 938.3236 | U9: =SUM(H9:S9) -> 8794.4399 | V9: =SUM(N9:S9) -> 4962.1222
B10: 毛利率 | F10: 公式计算 | H10: =IFERROR(H9/H7,0) -> 0.62247205 | I10: =IFERROR(I9/I7,0) -> 0.63153809 | J10: =IFERROR(J9/J7,0) -> 0.56828888 | K10: =IFERROR(K9/K7,0) -> 0.62447224 | L10: =IFERROR(L9/L7,0) -> 0.61957226 | M10: =IFERROR(M9/M7,0) -> 0.63613725 | N10: =IFERROR(N9/N7,0) -> 0.64035922 | O10: =IFERROR(O9/O7,0) -> 0.6408765 | ... S10: =IFERROR(S9/S7,0) -> 0.64132297 | U10: =IFERROR(U9/U7,0) -> 0.63044461 | V10: =IFERROR(V9/V7,0) -> 0.64116356
B11: 内部供货价差调整 | E11: 主体公司内部供货价差（管理口径） | F11: 测算-整体经营 | H11: ='测算-整体经营'!I$13 -> 43.350696 | I11: ='测算-整体经营'!J$13 -> 41.379724 | J11: ='测算-整体经营'!K$13 -> 58.838005 | K11: ='测算-整体经营'!L$13 -> 65.415322 | L11: ='测算-整体经营'!M$13 -> 76.059854 | M11: ='测算-整体经营'!N$13 -> 52.183939 | N11: ='测算-整体经营'!O$13 -> 25.488839 | O11: ='测算-整体经营'!P$13 -> 34.09001 | ... S11: ='测算-整体经营'!T$13 -> 48.250476 | U11: =SUM(H11:S11) -> 591.43413 | V11: =SUM(N11:S11) -> 254.20659
B12: 调整后毛利 | E12: 渠道毛利+内部供货价差 | F12: 公式计算 | H12: =H9+H11 -> 725.9164 | I12: =I9+I11 -> 461.32704 | J12: =J9+J11 -> 634.11387 | K12: =K9+K11 -> 676.05535 | L12: =L9+L11 -> 830.7628 | M12: =M9+M11 -> 841.36981 | N12: =N9+N11 -> 532.55338 | O12: =O9+O11 -> 704.19009 | ... S12: =S9+S11 -> 986.57408 | U12: =SUM(H12:S12) -> 9385.874 | V12: =SUM(N12:S12) -> 5216.3288
B13: 调整后毛利率 | E13: 调整后毛利/渠道主营业务收入 | F13: 公式计算 | H13: =IFERROR(H12/H7,0) -> 0.66200612 | I13: =IFERROR(I12/I7,0) -> 0.69376702 | J13: =IFERROR(J12/J7,0) -> 0.62641227 | K13: =IFERROR(K12/K7,0) -> 0.69136935 | L13: =IFERROR(L12/L7,0) -> 0.68201348 | M13: =IFERROR(M12/M7,0) -> 0.67820103 | N13: =IFERROR(N12/N7,0) -> 0.67254844 | O13: =IFERROR(O12/O7,0) -> 0.67347981 | ... S13: =IFERROR(S12/S7,0) -> 0.67430108 | U13: =IFERROR(U12/U7,0) -> 0.67284259 | V13: =IFERROR(V12/V7,0) -> 0.67400998
B14: 其他业务收入 | E14: 供应商达成返利及推广费支持 | F14: 测算-整体经营 | H14: =SUM(H15:H17) -> 0 | I14: =SUM(I15:I17) -> 38.32731 | J14: =SUM(J15:J17) -> 36.58473 | K14: =SUM(K15:K17) -> 57.214246 | L14: =SUM(L15:L17) -> 63.029398 | M14: =SUM(M15:M17) -> 72.440464 | N14: =SUM(N15:N17) -> 53.143506 | O14: =SUM(O15:O17) -> 29.541777 | ... S14: =SUM(S15:S17) -> 120.37413 | U14: =SUM(H14:S14) -> 587.13888 | V14: =SUM(N14:S14) -> 319.54273
C15: 达成返利 | D15: 季度达成返利（回款） | E15: 季度结算、下季度分月到账 | F15: 测算-整体经营 | H15: ='测算-整体经营'!I$17 -> 0 | I15: ='测算-整体经营'!J$17 -> 0 | J15: ='测算-整体经营'!K$17 -> 0 | K15: ='测算-整体经营'!L$17 -> 5.1942638 | L15: ='测算-整体经营'!M$17 -> 5.1942638 | M15: ='测算-整体经营'!N$17 -> 5.1942638 | N15: ='测算-整体经营'!O$17 -> 7.0065303 | O15: ='测算-整体经营'!P$17 -> 7.0065303 | ... S15: ='测算-整体经营'!T$17 -> 0 | U15: =SUM(H15:S15) -> 36.602382 | V15: =SUM(N15:S15) -> 21.019591
C16: 达成返利 | D16: 年度达成返利 | E16: 年度目标达成后确认 | F16: 测算-整体经营 | H16: ='测算-整体经营'!I$18 -> 0 | I16: ='测算-整体经营'!J$18 -> 0 | J16: ='测算-整体经营'!K$18 -> 0 | K16: ='测算-整体经营'!L$18 -> 0 | L16: ='测算-整体经营'!M$18 -> 0 | M16: ='测算-整体经营'!N$18 -> 0 | N16: ='测算-整体经营'!O$18 -> 0 | O16: ='测算-整体经营'!P$18 -> 0 | ... S16: ='测算-整体经营'!T$18 -> 70.29581 | U16: =SUM(H16:S16) -> 70.29581 | V16: =SUM(N16:S16) -> 70.29581
C17: 达成返利 | D17: 推广费支持（回款） | E17: 季度结算、下季度分月到账 | F17: 测算-整体经营 | H17: ='测算-整体经营'!I$19 -> 0 | I17: ='测算-整体经营'!J$19 -> 38.32731 | J17: ='测算-整体经营'!K$19 -> 36.58473 | K17: ='测算-整体经营'!L$19 -> 52.019982 | L17: ='测算-整体经营'!M$19 -> 57.835134 | M17: ='测算-整体经营'!N$19 -> 67.2462 | N17: ='测算-整体经营'!O$19 -> 46.136975 | O17: ='测算-整体经营'!P$19 -> 22.535246 | ... S17: ='测算-整体经营'!T$19 -> 50.078325 | U17: =SUM(H17:S17) -> 480.24069 | V17: =SUM(N17:S17) -> 228.22733
B18: 销售费用 | F18: 下列明细汇总 | H18: =SUM(H20,H29,H34,H38,H43) -> 490.21725 | I18: =SUM(I20,I29,I34,I38,I43) -> 308.16564 | J18: =SUM(J20,J29,J34,J38,J43) -> 661.62352 | K18: =SUM(K20,K29,K34,K38,K43) -> 432.60885 | L18: =SUM(L20,L29,L34,L38,L43) -> 566.72381 | M18: =SUM(M20,M29,M34,M38,M43) -> 657.77219 | N18: =SUM(N20,N29,N34,N38,N43) -> 460.36615 | O18: =SUM(O20,O29,O34,O38,O43) -> 598.93023 | ... S18: =SUM(S20,S29,S34,S38,S43) -> 822.274 | U18: =SUM(U20,U29,U34,U38,U43) -> 7519.8614 | V18: =SUM(V20,V29,V34,V38,V43) -> 4374.6607
B19: 销售费用率 | E19: 销售费用/收入 | F19: 公式计算 | H19: =IFERROR(H18/H7,0) -> 0.44705811 | I19: =IFERROR(I18/I7,0) -> 0.46343512 | J19: =IFERROR(J18/J7,0) -> 0.65358781 | K19: =IFERROR(K18/K7,0) -> 0.44240831 | L19: =IFERROR(L18/L7,0) -> 0.46525107 | M19: =IFERROR(M18/M7,0) -> 0.53020893 | N19: =IFERROR(N18/N7,0) -> 0.58138498 | O19: =IFERROR(O18/O7,0) -> 0.57281042 | ... S19: =IFERROR(S18/S7,0) -> 0.56200569 | U19: =IFERROR(U18/U7,0) -> 0.53907425 | V19: =IFERROR(V18/V7,0) -> 0.56525674
C20: 渠道投入 | H20: =SUM(H21:H28) -> 412.18124 | I20: =SUM(I21:I28) -> 249.59394 | J20: =SUM(J21:J28) -> 566.78644 | K20: =SUM(K21:K28) -> 353.13792 | L20: =SUM(L21:L28) -> 472.97887 | M20: =SUM(M21:M28) -> 545.4595 | N20: =SUM(N21:N28) -> 343.93451 | O20: =SUM(O21:O28) -> 460.4476 | ... S20: =SUM(S21:S28) -> 648.12293 | U20: =SUM(U21:U28) -> 6019.0674 | V20: =SUM(V21:V28) -> 3418.9295
D21: 广告投流费 | E21: 渠道测算费用明细 | F21: 各渠道测算表汇总 | H21: =SUM('测算-高个子抖音'!I$22)+SUM('测算-高个子视频号'!I$22)+SUM('测算-天猫淘宝'!I$21)+SUM('测算-拼多多'!I$22)+SUM('测算-京东POP'!I$22)+SUM('测算-达播'!I$23)+SUM('测算-私域'!I$22)+SUM('测算-外部分销'!I$22)++SUM('测算-京东自营'!I$21) -> 334.9911 | I21: =SUM('测算-高个子抖音'!J$22)+SUM('测算-高个子视频号'!J$22)+SUM('测算-天猫淘宝'!J$21)+SUM('测算-拼多多'!J$22)+SUM('测算-京东POP'!J$22)+SUM('测算-达播'!J$23)+SUM('测算-私域'!J$22)+SUM('测算-外部分销'!J$22)++SUM('测算-京东自营'!J$21) -> 214.39622 | J21: =SUM('测算-高个子抖音'!K$22)+SUM('测算-高个子视频号'!K$22)+SUM('测算-天猫淘宝'!K$21)+SUM('测算-拼多多'!K$22)+SUM('测算-京东POP'!K$22)+SUM('测算-达播'!K$23)+SUM('测算-私域'!K$22)+SUM('测算-外部分销'!K$22)++SUM('测算-京东自营'!K$21) -> 437.40128 | K21: =SUM('测算-高个子抖音'!L$22)+SUM('测算-高个子视频号'!L$22)+SUM('测算-天猫淘宝'!L$21)+SUM('测算-拼多多'!L$22)+SUM('测算-京东POP'!L$22)+SUM('测算-达播'!L$23)+SUM('测算-私域'!L$22)+SUM('测算-外部分销'!L$22)++SUM('测算-京东自营'!L$21) -> 301.87089 | L21: =SUM('测算-高个子抖音'!M$22)+SUM('测算-高个子视频号'!M$22)+SUM('测算-天猫淘宝'!M$21)+SUM('测算-拼多多'!M$22)+SUM('测算-京东POP'!M$22)+SUM('测算-达播'!M$23)+SUM('测算-私域'!M$22)+SUM('测算-外部分销'!M$22)++SUM('测算-京东自营'!M$21) -> 396.08316 | M21: =SUM('测算-高个子抖音'!N$22)+SUM('测算-高个子视频号'!N$22)+SUM('测算-天猫淘宝'!N$21)+SUM('测算-拼多多'!N$22)+SUM('测算-京东POP'!N$22)+SUM('测算-达播'!N$23)+SUM('测算-私域'!N$22)+SUM('测算-外部分销'!N$22)++SUM('测算-京东自营'!N$21) -> 440.42027 | N21: =SUM('测算-高个子抖音'!O$22)+SUM('测算-高个子视频号'!O$22)+SUM('测算-天猫淘宝'!O$21)+SUM('测算-拼多多'!O$22)+SUM('测算-京东POP'!O$22)+SUM('测算-达播'!O$23)+SUM('测算-私域'!O$22)+SUM('测算-外部分销'!O$22)++SUM('测算-京东自营'!O$21) -> 290.9505 | O21: =SUM('测算-高个子抖音'!P$22)+SUM('测算-高个子视频号'!P$22)+SUM('测算-天猫淘宝'!P$21)+SUM('测算-拼多多'!P$22)+SUM('测算-京东POP'!P$22)+SUM('测算-达播'!P$23)+SUM('测算-私域'!P$22)+SUM('测算-外部分销'!P$22)++SUM('测算-京东自营'!P$21) -> 389.58422 | ... S21: =SUM('测算-高个子抖音'!T$22)+SUM('测算-高个子视频号'!T$22)+SUM('测算-天猫淘宝'!T$21)+SUM('测算-拼多多'!T$22)+SUM('测算-京东POP'!T$22)+SUM('测算-达播'!T$23)+SUM('测算-私域'!T$22)+SUM('测算-外部分销'!T$22)++SUM('测算-京东自营'!T$21) -> 547.82399 | U21: =SUM('测算-高个子抖音'!V$22)+SUM('测算-高个子视频号'!V$22)+SUM('测算-天猫淘宝'!V$21)+SUM('测算-拼多多'!V$22)+SUM('测算-京东POP'!V$22)+SUM('测算-达播'!V$23)+SUM('测算-私域'!V$22)+SUM('测算-外部分销'!V$22)++SUM('测算-京东自营'!V$21) -> 5015.6696 | V21: =SUM('测算-高个子抖音'!W$22)+SUM('测算-高个子视频号'!W$22)+SUM('测算-天猫淘宝'!W$21)+SUM('测算-拼多多'!W$22)+SUM('测算-京东POP'!W$22)+SUM('测算-达播'!W$23)+SUM('测算-私域'!W$22)+SUM('测算-外部分销'!W$22)++SUM('测算-京东自营'!W$21) -> 2890.5067
D22: 媒介种草 | E22: 渠道测算费用明细 | F22: 各渠道测算表汇总 | H22: =SUM('测算-高个子抖音'!I$23)+SUM('测算-高个子视频号'!I$23)+SUM('测算-天猫淘宝'!I$22)+SUM('测算-拼多多'!I$23)+SUM('测算-京东POP'!I$23)+SUM('测算-达播'!I$24)+SUM('测算-私域'!I$23)+SUM('测算-外部分销'!I$23) -> 0 | I22: =SUM('测算-高个子抖音'!J$23)+SUM('测算-高个子视频号'!J$23)+SUM('测算-天猫淘宝'!J$22)+SUM('测算-拼多多'!J$23)+SUM('测算-京东POP'!J$23)+SUM('测算-达播'!J$24)+SUM('测算-私域'!J$23)+SUM('测算-外部分销'!J$23) -> 0 | J22: =SUM('测算-高个子抖音'!K$23)+SUM('测算-高个子视频号'!K$23)+SUM('测算-天猫淘宝'!K$22)+SUM('测算-拼多多'!K$23)+SUM('测算-京东POP'!K$23)+SUM('测算-达播'!K$24)+SUM('测算-私域'!K$23)+SUM('测算-外部分销'!K$23) -> 0 | K22: =SUM('测算-高个子抖音'!L$23)+SUM('测算-高个子视频号'!L$23)+SUM('测算-天猫淘宝'!L$22)+SUM('测算-拼多多'!L$23)+SUM('测算-京东POP'!L$23)+SUM('测算-达播'!L$24)+SUM('测算-私域'!L$23)+SUM('测算-外部分销'!L$23) -> 0 | L22: =SUM('测算-高个子抖音'!M$23)+SUM('测算-高个子视频号'!M$23)+SUM('测算-天猫淘宝'!M$22)+SUM('测算-拼多多'!M$23)+SUM('测算-京东POP'!M$23)+SUM('测算-达播'!M$24)+SUM('测算-私域'!M$23)+SUM('测算-外部分销'!M$23) -> 0 | M22: =SUM('测算-高个子抖音'!N$23)+SUM('测算-高个子视频号'!N$23)+SUM('测算-天猫淘宝'!N$22)+SUM('测算-拼多多'!N$23)+SUM('测算-京东POP'!N$23)+SUM('测算-达播'!N$24)+SUM('测算-私域'!N$23)+SUM('测算-外部分销'!N$23) -> 0 | N22: =SUM('测算-高个子抖音'!O$23)+SUM('测算-高个子视频号'!O$23)+SUM('测算-天猫淘宝'!O$22)+SUM('测算-拼多多'!O$23)+SUM('测算-京东POP'!O$23)+SUM('测算-达播'!O$24)+SUM('测算-私域'!O$23)+SUM('测算-外部分销'!O$23) -> 0 | O22: =SUM('测算-高个子抖音'!P$23)+SUM('测算-高个子视频号'!P$23)+SUM('测算-天猫淘宝'!P$22)+SUM('测算-拼多多'!P$23)+SUM('测算-京东POP'!P$23)+SUM('测算-达播'!P$24)+SUM('测算-私域'!P$23)+SUM('测算-外部分销'!P$23) -> 0 | ... S22: =SUM('测算-高个子抖音'!T$23)+SUM('测算-高个子视频号'!T$23)+SUM('测算-天猫淘宝'!T$22)+SUM('测算-拼多多'!T$23)+SUM('测算-京东POP'!T$23)+SUM('测算-达播'!T$24)+SUM('测算-私域'!T$23)+SUM('测算-外部分销'!T$23) -> 0 | U22: =SUM('测算-高个子抖音'!V$23)+SUM('测算-高个子视频号'!V$23)+SUM('测算-天猫淘宝'!V$22)+SUM('测算-拼多多'!V$23)+SUM('测算-京东POP'!V$23)+SUM('测算-达播'!V$24)+SUM('测算-私域'!V$23)+SUM('测算-外部分销'!V$23) -> 0 | V22: =SUM('测算-高个子抖音'!W$23)+SUM('测算-高个子视频号'!W$23)+SUM('测算-天猫淘宝'!W$22)+SUM('测算-拼多多'!W$23)+SUM('测算-京东POP'!W$23)+SUM('测算-达播'!W$24)+SUM('测算-私域'!W$23)+SUM('测算-外部分销'!W$23) -> 0
D23: 分销返佣 | E23: 渠道测算费用明细 | F23: 各渠道测算表汇总 | H23: =SUM('测算-高个子抖音'!I$24)+SUM('测算-高个子视频号'!I$24)+SUM('测算-天猫淘宝'!I$23)+SUM('测算-拼多多'!I$24)+SUM('测算-京东POP'!I$24)+SUM('测算-京东自营'!I$24)+SUM('测算-达播'!I$25)+SUM('测算-私域'!I$24)+SUM('测算-外部分销'!I$24) -> 0 | I23: =SUM('测算-高个子抖音'!J$24)+SUM('测算-高个子视频号'!J$24)+SUM('测算-天猫淘宝'!J$23)+SUM('测算-拼多多'!J$24)+SUM('测算-京东POP'!J$24)+SUM('测算-京东自营'!J$24)+SUM('测算-达播'!J$25)+SUM('测算-私域'!J$24)+SUM('测算-外部分销'!J$24) -> 0 | J23: =SUM('测算-高个子抖音'!K$24)+SUM('测算-高个子视频号'!K$24)+SUM('测算-天猫淘宝'!K$23)+SUM('测算-拼多多'!K$24)+SUM('测算-京东POP'!K$24)+SUM('测算-京东自营'!K$24)+SUM('测算-达播'!K$25)+SUM('测算-私域'!K$24)+SUM('测算-外部分销'!K$24) -> 0 | K23: =SUM('测算-高个子抖音'!L$24)+SUM('测算-高个子视频号'!L$24)+SUM('测算-天猫淘宝'!L$23)+SUM('测算-拼多多'!L$24)+SUM('测算-京东POP'!L$24)+SUM('测算-京东自营'!L$24)+SUM('测算-达播'!L$25)+SUM('测算-私域'!L$24)+SUM('测算-外部分销'!L$24) -> 0 | L23: =SUM('测算-高个子抖音'!M$24)+SUM('测算-高个子视频号'!M$24)+SUM('测算-天猫淘宝'!M$23)+SUM('测算-拼多多'!M$24)+SUM('测算-京东POP'!M$24)+SUM('测算-京东自营'!M$24)+SUM('测算-达播'!M$25)+SUM('测算-私域'!M$24)+SUM('测算-外部分销'!M$24) -> 0 | M23: =SUM('测算-高个子抖音'!N$24)+SUM('测算-高个子视频号'!N$24)+SUM('测算-天猫淘宝'!N$23)+SUM('测算-拼多多'!N$24)+SUM('测算-京东POP'!N$24)+SUM('测算-京东自营'!N$24)+SUM('测算-达播'!N$25)+SUM('测算-私域'!N$24)+SUM('测算-外部分销'!N$24) -> 0 | N23: =SUM('测算-高个子抖音'!O$24)+SUM('测算-高个子视频号'!O$24)+SUM('测算-天猫淘宝'!O$23)+SUM('测算-拼多多'!O$24)+SUM('测算-京东POP'!O$24)+SUM('测算-京东自营'!O$24)+SUM('测算-达播'!O$25)+SUM('测算-私域'!O$24)+SUM('测算-外部分销'!O$24) -> 0 | O23: =SUM('测算-高个子抖音'!P$24)+SUM('测算-高个子视频号'!P$24)+SUM('测算-天猫淘宝'!P$23)+SUM('测算-拼多多'!P$24)+SUM('测算-京东POP'!P$24)+SUM('测算-京东自营'!P$24)+SUM('测算-达播'!P$25)+SUM('测算-私域'!P$24)+SUM('测算-外部分销'!P$24) -> 0 | ... S23: =SUM('测算-高个子抖音'!T$24)+SUM('测算-高个子视频号'!T$24)+SUM('测算-天猫淘宝'!T$23)+SUM('测算-拼多多'!T$24)+SUM('测算-京东POP'!T$24)+SUM('测算-京东自营'!T$24)+SUM('测算-达播'!T$25)+SUM('测算-私域'!T$24)+SUM('测算-外部分销'!T$24) -> 0 | U23: =SUM('测算-高个子抖音'!V$24)+SUM('测算-高个子视频号'!V$24)+SUM('测算-天猫淘宝'!V$23)+SUM('测算-拼多多'!V$24)+SUM('测算-京东POP'!V$24)+SUM('测算-京东自营'!V$24)+SUM('测算-达播'!V$25)+SUM('测算-私域'!V$24)+SUM('测算-外部分销'!V$24) -> 0 | V23: =SUM('测算-高个子抖音'!W$24)+SUM('测算-高个子视频号'!W$24)+SUM('测算-天猫淘宝'!W$23)+SUM('测算-拼多多'!W$24)+SUM('测算-京东POP'!W$24)+SUM('测算-京东自营'!W$24)+SUM('测算-达播'!W$25)+SUM('测算-私域'!W$24)+SUM('测算-外部分销'!W$24) -> 0
D24: 平台毛利补贴 | E24: 渠道测算费用明细 | F24: 各渠道测算表汇总 | H24: =SUM('测算-高个子抖音'!I$25)+SUM('测算-高个子视频号'!I$25)+SUM('测算-天猫淘宝'!I$24)+SUM('测算-拼多多'!I$25)+SUM('测算-京东POP'!I$25)+SUM('测算-京东自营'!I$25)+SUM('测算-达播'!I$26)+SUM('测算-私域'!I$25)+SUM('测算-外部分销'!I$25) -> 37.598827 | I24: =SUM('测算-高个子抖音'!J$25)+SUM('测算-高个子视频号'!J$25)+SUM('测算-天猫淘宝'!J$24)+SUM('测算-拼多多'!J$25)+SUM('测算-京东POP'!J$25)+SUM('测算-京东自营'!J$25)+SUM('测算-达播'!J$26)+SUM('测算-私域'!J$25)+SUM('测算-外部分销'!J$25) -> 19.697303 | J24: =SUM('测算-高个子抖音'!K$25)+SUM('测算-高个子视频号'!K$25)+SUM('测算-天猫淘宝'!K$24)+SUM('测算-拼多多'!K$25)+SUM('测算-京东POP'!K$25)+SUM('测算-京东自营'!K$25)+SUM('测算-达播'!K$26)+SUM('测算-私域'!K$25)+SUM('测算-外部分销'!K$25) -> 33.311613 | K24: =SUM('测算-高个子抖音'!L$25)+SUM('测算-高个子视频号'!L$25)+SUM('测算-天猫淘宝'!L$24)+SUM('测算-拼多多'!L$25)+SUM('测算-京东POP'!L$25)+SUM('测算-京东自营'!L$25)+SUM('测算-达播'!L$26)+SUM('测算-私域'!L$25)+SUM('测算-外部分销'!L$25) -> 20.577461 | L24: =SUM('测算-高个子抖音'!M$25)+SUM('测算-高个子视频号'!M$25)+SUM('测算-天猫淘宝'!M$24)+SUM('测算-拼多多'!M$25)+SUM('测算-京东POP'!M$25)+SUM('测算-京东自营'!M$25)+SUM('测算-达播'!M$26)+SUM('测算-私域'!M$25)+SUM('测算-外部分销'!M$25) -> 16.509449 | M24: =SUM('测算-高个子抖音'!N$25)+SUM('测算-高个子视频号'!N$25)+SUM('测算-天猫淘宝'!N$24)+SUM('测算-拼多多'!N$25)+SUM('测算-京东POP'!N$25)+SUM('测算-京东自营'!N$25)+SUM('测算-达播'!N$26)+SUM('测算-私域'!N$25)+SUM('测算-外部分销'!N$25) -> 51.805845 | N24: =SUM('测算-高个子抖音'!O$25)+SUM('测算-高个子视频号'!O$25)+SUM('测算-天猫淘宝'!O$24)+SUM('测算-拼多多'!O$25)+SUM('测算-京东POP'!O$25)+SUM('测算-京东自营'!O$25)+SUM('测算-达播'!O$26)+SUM('测算-私域'!O$25)+SUM('测算-外部分销'!O$25) -> 25.304162 | O24: =SUM('测算-高个子抖音'!P$25)+SUM('测算-高个子视频号'!P$25)+SUM('测算-天猫淘宝'!P$24)+SUM('测算-拼多多'!P$25)+SUM('测算-京东POP'!P$25)+SUM('测算-京东自营'!P$25)+SUM('测算-达播'!P$26)+SUM('测算-私域'!P$25)+SUM('测算-外部分销'!P$25) -> 33.843015 | ... S24: =SUM('测算-高个子抖音'!T$25)+SUM('测算-高个子视频号'!T$25)+SUM('测算-天猫淘宝'!T$24)+SUM('测算-拼多多'!T$25)+SUM('测算-京东POP'!T$25)+SUM('测算-京东自营'!T$25)+SUM('测算-达播'!T$26)+SUM('测算-私域'!T$25)+SUM('测算-外部分销'!T$25) -> 47.900882 | U24: =SUM('测算-高个子抖音'!V$25)+SUM('测算-高个子视频号'!V$25)+SUM('测算-天猫淘宝'!V$24)+SUM('测算-拼多多'!V$25)+SUM('测算-京东POP'!V$25)+SUM('测算-京东自营'!V$25)+SUM('测算-达播'!V$26)+SUM('测算-私域'!V$25)+SUM('测算-外部分销'!V$25) -> 431.86525 | V24: =SUM('测算-高个子抖音'!W$25)+SUM('测算-高个子视频号'!W$25)+SUM('测算-天猫淘宝'!W$24)+SUM('测算-拼多多'!W$25)+SUM('测算-京东POP'!W$25)+SUM('测算-京东自营'!W$25)+SUM('测算-达播'!W$26)+SUM('测算-私域'!W$25)+SUM('测算-外部分销'!W$25) -> 252.36476
D25: 平台提现手续费 | E25: 渠道测算费用明细 | F25: 各渠道测算表汇总 | H25: =SUM('测算-高个子抖音'!I$26)+SUM('测算-高个子视频号'!I$26)+SUM('测算-天猫淘宝'!I$25)+SUM('测算-拼多多'!I$26)+SUM('测算-京东POP'!I$26)+SUM('测算-京东自营'!I$26)+SUM('测算-达播'!I$27)+SUM('测算-私域'!I$26)+SUM('测算-外部分销'!I$26) -> 30.256177 | I25: =SUM('测算-高个子抖音'!J$26)+SUM('测算-高个子视频号'!J$26)+SUM('测算-天猫淘宝'!J$25)+SUM('测算-拼多多'!J$26)+SUM('测算-京东POP'!J$26)+SUM('测算-京东自营'!J$26)+SUM('测算-达播'!J$27)+SUM('测算-私域'!J$26)+SUM('测算-外部分销'!J$26) -> 8.9596448 | J25: =SUM('测算-高个子抖音'!K$26)+SUM('测算-高个子视频号'!K$26)+SUM('测算-天猫淘宝'!K$25)+SUM('测算-拼多多'!K$26)+SUM('测算-京东POP'!K$26)+SUM('测算-京东自营'!K$26)+SUM('测算-达播'!K$27)+SUM('测算-私域'!K$26)+SUM('测算-外部分销'!K$26) -> 67.951923 | K25: =SUM('测算-高个子抖音'!L$26)+SUM('测算-高个子视频号'!L$26)+SUM('测算-天猫淘宝'!L$25)+SUM('测算-拼多多'!L$26)+SUM('测算-京东POP'!L$26)+SUM('测算-京东自营'!L$26)+SUM('测算-达播'!L$27)+SUM('测算-私域'!L$26)+SUM('测算-外部分销'!L$26) -> 20.928625 | L25: =SUM('测算-高个子抖音'!M$26)+SUM('测算-高个子视频号'!M$26)+SUM('测算-天猫淘宝'!M$25)+SUM('测算-拼多多'!M$26)+SUM('测算-京东POP'!M$26)+SUM('测算-京东自营'!M$26)+SUM('测算-达播'!M$27)+SUM('测算-私域'!M$26)+SUM('测算-外部分销'!M$26) -> 30.271928 | M25: =SUM('测算-高个子抖音'!N$26)+SUM('测算-高个子视频号'!N$26)+SUM('测算-天猫淘宝'!N$25)+SUM('测算-拼多多'!N$26)+SUM('测算-京东POP'!N$26)+SUM('测算-京东自营'!N$26)+SUM('测算-达播'!N$27)+SUM('测算-私域'!N$26)+SUM('测算-外部分销'!N$26) -> 19.206113 | N25: =SUM('测算-高个子抖音'!O$26)+SUM('测算-高个子视频号'!O$26)+SUM('测算-天猫淘宝'!O$25)+SUM('测算-拼多多'!O$26)+SUM('测算-京东POP'!O$26)+SUM('测算-京东自营'!O$26)+SUM('测算-达播'!O$27)+SUM('测算-私域'!O$26)+SUM('测算-外部分销'!O$26) -> 11.059486 | O25: =SUM('测算-高个子抖音'!P$26)+SUM('测算-高个子视频号'!P$26)+SUM('测算-天猫淘宝'!P$25)+SUM('测算-拼多多'!P$26)+SUM('测算-京东POP'!P$26)+SUM('测算-京东自营'!P$26)+SUM('测算-达播'!P$27)+SUM('测算-私域'!P$26)+SUM('测算-外部分销'!P$26) -> 14.791494 | ... S25: =SUM('测算-高个子抖音'!T$26)+SUM('测算-高个子视频号'!T$26)+SUM('测算-天猫淘宝'!T$25)+SUM('测算-拼多多'!T$26)+SUM('测算-京东POP'!T$26)+SUM('测算-京东自营'!T$26)+SUM('测算-达播'!T$27)+SUM('测算-私域'!T$26)+SUM('测算-外部分销'!T$26) -> 20.935653 | U25: =SUM('测算-高个子抖音'!V$26)+SUM('测算-高个子视频号'!V$26)+SUM('测算-天猫淘宝'!V$25)+SUM('测算-拼多多'!V$26)+SUM('测算-京东POP'!V$26)+SUM('测算-京东自营'!V$26)+SUM('测算-达播'!V$27)+SUM('测算-私域'!V$26)+SUM('测算-外部分销'!V$26) -> 287.87344 | V25: =SUM('测算-高个子抖音'!W$26)+SUM('测算-高个子视频号'!W$26)+SUM('测算-天猫淘宝'!W$25)+SUM('测算-拼多多'!W$26)+SUM('测算-京东POP'!W$26)+SUM('测算-京东自营'!W$26)+SUM('测算-达播'!W$27)+SUM('测算-私域'!W$26)+SUM('测算-外部分销'!W$26) -> 110.29903
D26: 自营渠道推广费 | E26: 渠道测算费用明细 | F26: 各渠道测算表汇总 | H26: =SUM('测算-京东自营'!I$22) -> 0.160283 | I26: =SUM('测算-京东自营'!J$22) -> 0.157019 | J26: =SUM('测算-京东自营'!K$22) -> 0.504767 | K26: =SUM('测算-京东自营'!L$22) -> 0.367181 | L26: =SUM('测算-京东自营'!M$22) -> 4.232029 | M26: =SUM('测算-京东自营'!N$22) -> 2.1994182 | N26: =SUM('测算-京东自营'!O$22) -> 1.0742887 | O26: =SUM('测算-京东自营'!P$22) -> 1.4368058 | ... S26: =SUM('测算-京东自营'!T$22) -> 2.0336329 | U26: =SUM('测算-京东自营'!V$22) -> 18.334848 | V26: =SUM('测算-京东自营'!W$22) -> 10.714151
D27: 商务政策费用 | E27: 渠道测算费用明细 | F27: 各渠道测算表汇总 | H27: =SUM('测算-京东自营'!I$23) -> 2.78929 | I27: =SUM('测算-京东自营'!J$23) -> 2.923083 | J27: =SUM('测算-京东自营'!K$23) -> 16.47138 | K27: =SUM('测算-京东自营'!L$23) -> 3.142293 | L27: =SUM('测算-京东自营'!M$23) -> 7.224989 | M27: =SUM('测算-京东自营'!N$23) -> 13.205987 | N27: =SUM('测算-京东自营'!O$23) -> 6.4503613 | O27: =SUM('测算-京东自营'!P$23) -> 8.6270265 | ... S27: =SUM('测算-京东自营'!T$23) -> 12.210561 | U27: =SUM('测算-京东自营'!V$23) -> 110.08809 | V27: =SUM('测算-京东自营'!W$23) -> 64.331073
D28: 退货成本 | E28: 渠道测算费用明细 | F28: 各渠道测算表汇总 | H28: =SUM('测算-京东自营'!I$27) -> 6.38556 | I28: =SUM('测算-京东自营'!J$27) -> 3.46067 | J28: =SUM('测算-京东自营'!K$27) -> 11.14547 | K28: =SUM('测算-京东自营'!L$27) -> 6.25147 | L28: =SUM('测算-京东自营'!M$27) -> 18.65732 | M28: =SUM('测算-京东自营'!N$27) -> 18.621874 | N28: =SUM('测算-京东自营'!O$27) -> 9.0957091 | O28: =SUM('测算-京东自营'!P$27) -> 12.165043 | ... S28: =SUM('测算-京东自营'!T$27) -> 17.218215 | U28: =SUM('测算-京东自营'!V$27) -> 155.23615 | V28: =SUM('测算-京东自营'!W$27) -> 90.71379
C29: 达人费用 | H29: =SUM(H30:H33) -> 0 | I29: =SUM(I30:I33) -> 0 | J29: =SUM(J30:J33) -> 0 | K29: =SUM(K30:K33) -> 0 | L29: =SUM(L30:L33) -> 0 | M29: =SUM(M30:M33) -> 0 | N29: =SUM(N30:N33) -> 22.751163 | O29: =SUM(O30:O33) -> 30.42851 | ... S29: =SUM(S30:S33) -> 43.068044 | U29: =SUM(U30:U33) -> 226.90306 | V29: =SUM(V30:V33) -> 226.90306
D30: 达人视频采买 | E30: 渠道测算费用明细 | F30: 各渠道测算表汇总 | H30: =SUM('测算-高个子抖音'!I$28)+SUM('测算-高个子视频号'!I$28)+SUM('测算-天猫淘宝'!I$27)+SUM('测算-拼多多'!I$28)+SUM('测算-京东POP'!I$28)+SUM('测算-京东自营'!I$29)+SUM('测算-达播'!I$29)+SUM('测算-私域'!I$28)+SUM('测算-外部分销'!I$28) -> 0 | I30: =SUM('测算-高个子抖音'!J$28)+SUM('测算-高个子视频号'!J$28)+SUM('测算-天猫淘宝'!J$27)+SUM('测算-拼多多'!J$28)+SUM('测算-京东POP'!J$28)+SUM('测算-京东自营'!J$29)+SUM('测算-达播'!J$29)+SUM('测算-私域'!J$28)+SUM('测算-外部分销'!J$28) -> 0 | J30: =SUM('测算-高个子抖音'!K$28)+SUM('测算-高个子视频号'!K$28)+SUM('测算-天猫淘宝'!K$27)+SUM('测算-拼多多'!K$28)+SUM('测算-京东POP'!K$28)+SUM('测算-京东自营'!K$29)+SUM('测算-达播'!K$29)+SUM('测算-私域'!K$28)+SUM('测算-外部分销'!K$28) -> 0 | K30: =SUM('测算-高个子抖音'!L$28)+SUM('测算-高个子视频号'!L$28)+SUM('测算-天猫淘宝'!L$27)+SUM('测算-拼多多'!L$28)+SUM('测算-京东POP'!L$28)+SUM('测算-京东自营'!L$29)+SUM('测算-达播'!L$29)+SUM('测算-私域'!L$28)+SUM('测算-外部分销'!L$28) -> 0 | L30: =SUM('测算-高个子抖音'!M$28)+SUM('测算-高个子视频号'!M$28)+SUM('测算-天猫淘宝'!M$27)+SUM('测算-拼多多'!M$28)+SUM('测算-京东POP'!M$28)+SUM('测算-京东自营'!M$29)+SUM('测算-达播'!M$29)+SUM('测算-私域'!M$28)+SUM('测算-外部分销'!M$28) -> 0 | M30: =SUM('测算-高个子抖音'!N$28)+SUM('测算-高个子视频号'!N$28)+SUM('测算-天猫淘宝'!N$27)+SUM('测算-拼多多'!N$28)+SUM('测算-京东POP'!N$28)+SUM('测算-京东自营'!N$29)+SUM('测算-达播'!N$29)+SUM('测算-私域'!N$28)+SUM('测算-外部分销'!N$28) -> 0 | N30: =SUM('测算-高个子抖音'!O$28)+SUM('测算-高个子视频号'!O$28)+SUM('测算-天猫淘宝'!O$27)+SUM('测算-拼多多'!O$28)+SUM('测算-京东POP'!O$28)+SUM('测算-京东自营'!O$29)+SUM('测算-达播'!O$29)+SUM('测算-私域'!O$28)+SUM('测算-外部分销'!O$28) -> 3.4668438 | O30: =SUM('测算-高个子抖音'!P$28)+SUM('测算-高个子视频号'!P$28)+SUM('测算-天猫淘宝'!P$27)+SUM('测算-拼多多'!P$28)+SUM('测算-京东POP'!P$28)+SUM('测算-京东自营'!P$29)+SUM('测算-达播'!P$29)+SUM('测算-私域'!P$28)+SUM('测算-外部分销'!P$28) -> 4.6367253 | ... S30: =SUM('测算-高个子抖音'!T$28)+SUM('测算-高个子视频号'!T$28)+SUM('测算-天猫淘宝'!T$27)+SUM('测算-拼多多'!T$28)+SUM('测算-京东POP'!T$28)+SUM('测算-京东自营'!T$29)+SUM('测算-达播'!T$29)+SUM('测算-私域'!T$28)+SUM('测算-外部分销'!T$28) -> 6.5627496 | U30: =SUM('测算-高个子抖音'!V$28)+SUM('测算-高个子视频号'!V$28)+SUM('测算-天猫淘宝'!V$27)+SUM('测算-拼多多'!V$28)+SUM('测算-京东POP'!V$28)+SUM('测算-京东自营'!V$29)+SUM('测算-达播'!V$29)+SUM('测算-私域'!V$28)+SUM('测算-外部分销'!V$28) -> 34.575704 | V30: =SUM('测算-高个子抖音'!W$28)+SUM('测算-高个子视频号'!W$28)+SUM('测算-天猫淘宝'!W$27)+SUM('测算-拼多多'!W$28)+SUM('测算-京东POP'!W$28)+SUM('测算-京东自营'!W$29)+SUM('测算-达播'!W$29)+SUM('测算-私域'!W$28)+SUM('测算-外部分销'!W$28) -> 34.575704
D31: 达人视频带货佣金 | E31: 渠道测算费用明细 | F31: 各渠道测算表汇总 | H31: =SUM('测算-高个子抖音'!I$29)+SUM('测算-高个子视频号'!I$29)+SUM('测算-天猫淘宝'!I$28)+SUM('测算-拼多多'!I$29)+SUM('测算-京东POP'!I$29)+SUM('测算-京东自营'!I$30)+SUM('测算-达播'!I$30)+SUM('测算-私域'!I$29)+SUM('测算-外部分销'!I$29) -> 0 | I31: =SUM('测算-高个子抖音'!J$29)+SUM('测算-高个子视频号'!J$29)+SUM('测算-天猫淘宝'!J$28)+SUM('测算-拼多多'!J$29)+SUM('测算-京东POP'!J$29)+SUM('测算-京东自营'!J$30)+SUM('测算-达播'!J$30)+SUM('测算-私域'!J$29)+SUM('测算-外部分销'!J$29) -> 0 | J31: =SUM('测算-高个子抖音'!K$29)+SUM('测算-高个子视频号'!K$29)+SUM('测算-天猫淘宝'!K$28)+SUM('测算-拼多多'!K$29)+SUM('测算-京东POP'!K$29)+SUM('测算-京东自营'!K$30)+SUM('测算-达播'!K$30)+SUM('测算-私域'!K$29)+SUM('测算-外部分销'!K$29) -> 0 | K31: =SUM('测算-高个子抖音'!L$29)+SUM('测算-高个子视频号'!L$29)+SUM('测算-天猫淘宝'!L$28)+SUM('测算-拼多多'!L$29)+SUM('测算-京东POP'!L$29)+SUM('测算-京东自营'!L$30)+SUM('测算-达播'!L$30)+SUM('测算-私域'!L$29)+SUM('测算-外部分销'!L$29) -> 0 | L31: =SUM('测算-高个子抖音'!M$29)+SUM('测算-高个子视频号'!M$29)+SUM('测算-天猫淘宝'!M$28)+SUM('测算-拼多多'!M$29)+SUM('测算-京东POP'!M$29)+SUM('测算-京东自营'!M$30)+SUM('测算-达播'!M$30)+SUM('测算-私域'!M$29)+SUM('测算-外部分销'!M$29) -> 0 | M31: =SUM('测算-高个子抖音'!N$29)+SUM('测算-高个子视频号'!N$29)+SUM('测算-天猫淘宝'!N$28)+SUM('测算-拼多多'!N$29)+SUM('测算-京东POP'!N$29)+SUM('测算-京东自营'!N$30)+SUM('测算-达播'!N$30)+SUM('测算-私域'!N$29)+SUM('测算-外部分销'!N$29) -> 0 | N31: =SUM('测算-高个子抖音'!O$29)+SUM('测算-高个子视频号'!O$29)+SUM('测算-天猫淘宝'!O$28)+SUM('测算-拼多多'!O$29)+SUM('测算-京东POP'!O$29)+SUM('测算-京东自营'!O$30)+SUM('测算-达播'!O$30)+SUM('测算-私域'!O$29)+SUM('测算-外部分销'!O$29) -> 5.2002657 | O31: =SUM('测算-高个子抖音'!P$29)+SUM('测算-高个子视频号'!P$29)+SUM('测算-天猫淘宝'!P$28)+SUM('测算-拼多多'!P$29)+SUM('测算-京东POP'!P$29)+SUM('测算-京东自营'!P$30)+SUM('测算-达播'!P$30)+SUM('测算-私域'!P$29)+SUM('测算-外部分销'!P$29) -> 6.9550879 | ... S31: =SUM('测算-高个子抖音'!T$29)+SUM('测算-高个子视频号'!T$29)+SUM('测算-天猫淘宝'!T$28)+SUM('测算-拼多多'!T$29)+SUM('测算-京东POP'!T$29)+SUM('测算-京东自营'!T$30)+SUM('测算-达播'!T$30)+SUM('测算-私域'!T$29)+SUM('测算-外部分销'!T$29) -> 9.8441244 | U31: =SUM('测算-高个子抖音'!V$29)+SUM('测算-高个子视频号'!V$29)+SUM('测算-天猫淘宝'!V$28)+SUM('测算-拼多多'!V$29)+SUM('测算-京东POP'!V$29)+SUM('测算-京东自营'!V$30)+SUM('测算-达播'!V$30)+SUM('测算-私域'!V$29)+SUM('测算-外部分销'!V$29) -> 51.863555 | V31: =SUM('测算-高个子抖音'!W$29)+SUM('测算-高个子视频号'!W$29)+SUM('测算-天猫淘宝'!W$28)+SUM('测算-拼多多'!W$29)+SUM('测算-京东POP'!W$29)+SUM('测算-京东自营'!W$30)+SUM('测算-达播'!W$30)+SUM('测算-私域'!W$29)+SUM('测算-外部分销'!W$29) -> 51.863555
D32: 达人直播带货佣金 | E32: 渠道测算费用明细 | F32: 各渠道测算表汇总 | H32: =SUM('测算-高个子抖音'!I$30)+SUM('测算-高个子视频号'!I$30)+SUM('测算-天猫淘宝'!I$29)+SUM('测算-拼多多'!I$30)+SUM('测算-京东POP'!I$30)+SUM('测算-京东自营'!I$31)+SUM('测算-达播'!I$31)+SUM('测算-私域'!I$30)+SUM('测算-外部分销'!I$30) -> 0 | I32: =SUM('测算-高个子抖音'!J$30)+SUM('测算-高个子视频号'!J$30)+SUM('测算-天猫淘宝'!J$29)+SUM('测算-拼多多'!J$30)+SUM('测算-京东POP'!J$30)+SUM('测算-京东自营'!J$31)+SUM('测算-达播'!J$31)+SUM('测算-私域'!J$30)+SUM('测算-外部分销'!J$30) -> 0 | J32: =SUM('测算-高个子抖音'!K$30)+SUM('测算-高个子视频号'!K$30)+SUM('测算-天猫淘宝'!K$29)+SUM('测算-拼多多'!K$30)+SUM('测算-京东POP'!K$30)+SUM('测算-京东自营'!K$31)+SUM('测算-达播'!K$31)+SUM('测算-私域'!K$30)+SUM('测算-外部分销'!K$30) -> 0 | K32: =SUM('测算-高个子抖音'!L$30)+SUM('测算-高个子视频号'!L$30)+SUM('测算-天猫淘宝'!L$29)+SUM('测算-拼多多'!L$30)+SUM('测算-京东POP'!L$30)+SUM('测算-京东自营'!L$31)+SUM('测算-达播'!L$31)+SUM('测算-私域'!L$30)+SUM('测算-外部分销'!L$30) -> 0 | L32: =SUM('测算-高个子抖音'!M$30)+SUM('测算-高个子视频号'!M$30)+SUM('测算-天猫淘宝'!M$29)+SUM('测算-拼多多'!M$30)+SUM('测算-京东POP'!M$30)+SUM('测算-京东自营'!M$31)+SUM('测算-达播'!M$31)+SUM('测算-私域'!M$30)+SUM('测算-外部分销'!M$30) -> 0 | M32: =SUM('测算-高个子抖音'!N$30)+SUM('测算-高个子视频号'!N$30)+SUM('测算-天猫淘宝'!N$29)+SUM('测算-拼多多'!N$30)+SUM('测算-京东POP'!N$30)+SUM('测算-京东自营'!N$31)+SUM('测算-达播'!N$31)+SUM('测算-私域'!N$30)+SUM('测算-外部分销'!N$30) -> 0 | N32: =SUM('测算-高个子抖音'!O$30)+SUM('测算-高个子视频号'!O$30)+SUM('测算-天猫淘宝'!O$29)+SUM('测算-拼多多'!O$30)+SUM('测算-京东POP'!O$30)+SUM('测算-京东自营'!O$31)+SUM('测算-达播'!O$31)+SUM('测算-私域'!O$30)+SUM('测算-外部分销'!O$30) -> 6.2836544 | O32: =SUM('测算-高个子抖音'!P$30)+SUM('测算-高个子视频号'!P$30)+SUM('测算-天猫淘宝'!P$29)+SUM('测算-拼多多'!P$30)+SUM('测算-京东POP'!P$30)+SUM('测算-京东自营'!P$31)+SUM('测算-达播'!P$31)+SUM('测算-私域'!P$30)+SUM('测算-外部分销'!P$30) -> 8.4040646 | ... S32: =SUM('测算-高个子抖音'!T$30)+SUM('测算-高个子视频号'!T$30)+SUM('测算-天猫淘宝'!T$29)+SUM('测算-拼多多'!T$30)+SUM('测算-京东POP'!T$30)+SUM('测算-京东自营'!T$31)+SUM('测算-达播'!T$31)+SUM('测算-私域'!T$30)+SUM('测算-外部分销'!T$30) -> 11.894984 | U32: =SUM('测算-高个子抖音'!V$30)+SUM('测算-高个子视频号'!V$30)+SUM('测算-天猫淘宝'!V$29)+SUM('测算-拼多多'!V$30)+SUM('测算-京东POP'!V$30)+SUM('测算-京东自营'!V$31)+SUM('测算-达播'!V$31)+SUM('测算-私域'!V$30)+SUM('测算-外部分销'!V$30) -> 62.668463 | V32: =SUM('测算-高个子抖音'!W$30)+SUM('测算-高个子视频号'!W$30)+SUM('测算-天猫淘宝'!W$29)+SUM('测算-拼多多'!W$30)+SUM('测算-京东POP'!W$30)+SUM('测算-京东自营'!W$31)+SUM('测算-达播'!W$31)+SUM('测算-私域'!W$30)+SUM('测算-外部分销'!W$30) -> 62.668463
D33: 达人直播坑位费 | E33: 渠道测算费用明细 | F33: 各渠道测算表汇总 | H33: =SUM('测算-高个子抖音'!I$31)+SUM('测算-高个子视频号'!I$31)+SUM('测算-天猫淘宝'!I$30)+SUM('测算-拼多多'!I$31)+SUM('测算-京东POP'!I$31)+SUM('测算-京东自营'!I$32)+SUM('测算-达播'!I$32)+SUM('测算-私域'!I$31)+SUM('测算-外部分销'!I$31) -> 0 | I33: =SUM('测算-高个子抖音'!J$31)+SUM('测算-高个子视频号'!J$31)+SUM('测算-天猫淘宝'!J$30)+SUM('测算-拼多多'!J$31)+SUM('测算-京东POP'!J$31)+SUM('测算-京东自营'!J$32)+SUM('测算-达播'!J$32)+SUM('测算-私域'!J$31)+SUM('测算-外部分销'!J$31) -> 0 | J33: =SUM('测算-高个子抖音'!K$31)+SUM('测算-高个子视频号'!K$31)+SUM('测算-天猫淘宝'!K$30)+SUM('测算-拼多多'!K$31)+SUM('测算-京东POP'!K$31)+SUM('测算-京东自营'!K$32)+SUM('测算-达播'!K$32)+SUM('测算-私域'!K$31)+SUM('测算-外部分销'!K$31) -> 0 | K33: =SUM('测算-高个子抖音'!L$31)+SUM('测算-高个子视频号'!L$31)+SUM('测算-天猫淘宝'!L$30)+SUM('测算-拼多多'!L$31)+SUM('测算-京东POP'!L$31)+SUM('测算-京东自营'!L$32)+SUM('测算-达播'!L$32)+SUM('测算-私域'!L$31)+SUM('测算-外部分销'!L$31) -> 0 | L33: =SUM('测算-高个子抖音'!M$31)+SUM('测算-高个子视频号'!M$31)+SUM('测算-天猫淘宝'!M$30)+SUM('测算-拼多多'!M$31)+SUM('测算-京东POP'!M$31)+SUM('测算-京东自营'!M$32)+SUM('测算-达播'!M$32)+SUM('测算-私域'!M$31)+SUM('测算-外部分销'!M$31) -> 0 | M33: =SUM('测算-高个子抖音'!N$31)+SUM('测算-高个子视频号'!N$31)+SUM('测算-天猫淘宝'!N$30)+SUM('测算-拼多多'!N$31)+SUM('测算-京东POP'!N$31)+SUM('测算-京东自营'!N$32)+SUM('测算-达播'!N$32)+SUM('测算-私域'!N$31)+SUM('测算-外部分销'!N$31) -> 0 | N33: =SUM('测算-高个子抖音'!O$31)+SUM('测算-高个子视频号'!O$31)+SUM('测算-天猫淘宝'!O$30)+SUM('测算-拼多多'!O$31)+SUM('测算-京东POP'!O$31)+SUM('测算-京东自营'!O$32)+SUM('测算-达播'!O$32)+SUM('测算-私域'!O$31)+SUM('测算-外部分销'!O$31) -> 7.8003986 | O33: =SUM('测算-高个子抖音'!P$31)+SUM('测算-高个子视频号'!P$31)+SUM('测算-天猫淘宝'!P$30)+SUM('测算-拼多多'!P$31)+SUM('测算-京东POP'!P$31)+SUM('测算-京东自营'!P$32)+SUM('测算-达播'!P$32)+SUM('测算-私域'!P$31)+SUM('测算-外部分销'!P$31) -> 10.432632 | ... S33: =SUM('测算-高个子抖音'!T$31)+SUM('测算-高个子视频号'!T$31)+SUM('测算-天猫淘宝'!T$30)+SUM('测算-拼多多'!T$31)+SUM('测算-京东POP'!T$31)+SUM('测算-京东自营'!T$32)+SUM('测算-达播'!T$32)+SUM('测算-私域'!T$31)+SUM('测算-外部分销'!T$31) -> 14.766187 | U33: =SUM('测算-高个子抖音'!V$31)+SUM('测算-高个子视频号'!V$31)+SUM('测算-天猫淘宝'!V$30)+SUM('测算-拼多多'!V$31)+SUM('测算-京东POP'!V$31)+SUM('测算-京东自营'!V$32)+SUM('测算-达播'!V$32)+SUM('测算-私域'!V$31)+SUM('测算-外部分销'!V$31) -> 77.795333 | V33: =SUM('测算-高个子抖音'!W$31)+SUM('测算-高个子视频号'!W$31)+SUM('测算-天猫淘宝'!W$30)+SUM('测算-拼多多'!W$31)+SUM('测算-京东POP'!W$31)+SUM('测算-京东自营'!W$32)+SUM('测算-达播'!W$32)+SUM('测算-私域'!W$31)+SUM('测算-外部分销'!W$31) -> 77.795333
C34: 行销支持 | H34: =SUM(H35:H37) -> 7.659842 | I34: =SUM(I35:I37) -> 3.539312 | J34: =SUM(J35:J37) -> 7.686161 | K34: =SUM(K35:K37) -> 4.708707 | L34: =SUM(L35:L37) -> 8.107537 | M34: =SUM(M35:M37) -> 11.194122 | N34: =SUM(N35:N37) -> 7.5643179 | O34: =SUM(O35:O37) -> 9.6528241 | ... S34: =SUM(S35:S37) -> 13.082199 | U34: =SUM(U35:U37) -> 112.8851 | V34: =SUM(V35:V37) -> 69.989414
D35: 促销物料 | E35: 渠道测算费用明细 | F35: 各渠道测算表汇总 | H35: =SUM('测算-高个子抖音'!I$33)+SUM('测算-高个子视频号'!I$33)+SUM('测算-天猫淘宝'!I$32)+SUM('测算-拼多多'!I$33)+SUM('测算-京东POP'!I$33)+SUM('测算-京东自营'!I$34)+SUM('测算-达播'!I$34)+SUM('测算-私域'!I$33)+SUM('测算-外部分销'!I$33) -> 3.887473 | I35: =SUM('测算-高个子抖音'!J$33)+SUM('测算-高个子视频号'!J$33)+SUM('测算-天猫淘宝'!J$32)+SUM('测算-拼多多'!J$33)+SUM('测算-京东POP'!J$33)+SUM('测算-京东自营'!J$34)+SUM('测算-达播'!J$34)+SUM('测算-私域'!J$33)+SUM('测算-外部分销'!J$33) -> 0.870303 | J35: =SUM('测算-高个子抖音'!K$33)+SUM('测算-高个子视频号'!K$33)+SUM('测算-天猫淘宝'!K$32)+SUM('测算-拼多多'!K$33)+SUM('测算-京东POP'!K$33)+SUM('测算-京东自营'!K$34)+SUM('测算-达播'!K$34)+SUM('测算-私域'!K$33)+SUM('测算-外部分销'!K$33) -> 2.244855 | K35: =SUM('测算-高个子抖音'!L$33)+SUM('测算-高个子视频号'!L$33)+SUM('测算-天猫淘宝'!L$32)+SUM('测算-拼多多'!L$33)+SUM('测算-京东POP'!L$33)+SUM('测算-京东自营'!L$34)+SUM('测算-达播'!L$34)+SUM('测算-私域'!L$33)+SUM('测算-外部分销'!L$33) -> 0.384608 | L35: =SUM('测算-高个子抖音'!M$33)+SUM('测算-高个子视频号'!M$33)+SUM('测算-天猫淘宝'!M$32)+SUM('测算-拼多多'!M$33)+SUM('测算-京东POP'!M$33)+SUM('测算-京东自营'!M$34)+SUM('测算-达播'!M$34)+SUM('测算-私域'!M$33)+SUM('测算-外部分销'!M$33) -> 3.535826 | M35: =SUM('测算-高个子抖音'!N$33)+SUM('测算-高个子视频号'!N$33)+SUM('测算-天猫淘宝'!N$32)+SUM('测算-拼多多'!N$33)+SUM('测算-京东POP'!N$33)+SUM('测算-京东自营'!N$34)+SUM('测算-达播'!N$34)+SUM('测算-私域'!N$33)+SUM('测算-外部分销'!N$33) -> 6.3484551 | N35: =SUM('测算-高个子抖音'!O$33)+SUM('测算-高个子视频号'!O$33)+SUM('测算-天猫淘宝'!O$32)+SUM('测算-拼多多'!O$33)+SUM('测算-京东POP'!O$33)+SUM('测算-京东自营'!O$34)+SUM('测算-达播'!O$34)+SUM('测算-私域'!O$33)+SUM('测算-外部分销'!O$33) -> 4.7589797 | O35: =SUM('测算-高个子抖音'!P$33)+SUM('测算-高个子视频号'!P$33)+SUM('测算-天猫淘宝'!P$32)+SUM('测算-拼多多'!P$33)+SUM('测算-京东POP'!P$33)+SUM('测算-京东自营'!P$34)+SUM('测算-达播'!P$34)+SUM('测算-私域'!P$33)+SUM('测算-外部分销'!P$33) -> 6.3648906 | ... S35: =SUM('测算-高个子抖音'!T$33)+SUM('测算-高个子视频号'!T$33)+SUM('测算-天猫淘宝'!T$32)+SUM('测算-拼多多'!T$33)+SUM('测算-京东POP'!T$33)+SUM('测算-京东自营'!T$34)+SUM('测算-达播'!T$34)+SUM('测算-私域'!T$33)+SUM('测算-外部分销'!T$33) -> 9.0087682 | U35: =SUM('测算-高个子抖音'!V$33)+SUM('测算-高个子视频号'!V$33)+SUM('测算-天猫淘宝'!V$32)+SUM('测算-拼多多'!V$33)+SUM('测算-京东POP'!V$33)+SUM('测算-京东自营'!V$34)+SUM('测算-达播'!V$34)+SUM('测算-私域'!V$33)+SUM('测算-外部分销'!V$33) -> 64.73402 | V35: =SUM('测算-高个子抖音'!W$33)+SUM('测算-高个子视频号'!W$33)+SUM('测算-天猫淘宝'!W$32)+SUM('测算-拼多多'!W$33)+SUM('测算-京东POP'!W$33)+SUM('测算-京东自营'!W$34)+SUM('测算-达播'!W$34)+SUM('测算-私域'!W$33)+SUM('测算-外部分销'!W$33) -> 47.4625
D36: 赠饮样品费 | E36: 渠道测算费用明细 | F36: 各渠道测算表汇总 | H36: =SUM('测算-高个子抖音'!I$34)+SUM('测算-高个子视频号'!I$34)+SUM('测算-天猫淘宝'!I$33)+SUM('测算-拼多多'!I$34)+SUM('测算-京东POP'!I$34)+SUM('测算-京东自营'!I$35)+SUM('测算-达播'!I$35)+SUM('测算-私域'!I$34)+SUM('测算-外部分销'!I$34) -> 0 | I36: =SUM('测算-高个子抖音'!J$34)+SUM('测算-高个子视频号'!J$34)+SUM('测算-天猫淘宝'!J$33)+SUM('测算-拼多多'!J$34)+SUM('测算-京东POP'!J$34)+SUM('测算-京东自营'!J$35)+SUM('测算-达播'!J$35)+SUM('测算-私域'!J$34)+SUM('测算-外部分销'!J$34) -> 0 | J36: =SUM('测算-高个子抖音'!K$34)+SUM('测算-高个子视频号'!K$34)+SUM('测算-天猫淘宝'!K$33)+SUM('测算-拼多多'!K$34)+SUM('测算-京东POP'!K$34)+SUM('测算-京东自营'!K$35)+SUM('测算-达播'!K$35)+SUM('测算-私域'!K$34)+SUM('测算-外部分销'!K$34) -> 0 | K36: =SUM('测算-高个子抖音'!L$34)+SUM('测算-高个子视频号'!L$34)+SUM('测算-天猫淘宝'!L$33)+SUM('测算-拼多多'!L$34)+SUM('测算-京东POP'!L$34)+SUM('测算-京东自营'!L$35)+SUM('测算-达播'!L$35)+SUM('测算-私域'!L$34)+SUM('测算-外部分销'!L$34) -> 0 | L36: =SUM('测算-高个子抖音'!M$34)+SUM('测算-高个子视频号'!M$34)+SUM('测算-天猫淘宝'!M$33)+SUM('测算-拼多多'!M$34)+SUM('测算-京东POP'!M$34)+SUM('测算-京东自营'!M$35)+SUM('测算-达播'!M$35)+SUM('测算-私域'!M$34)+SUM('测算-外部分销'!M$34) -> 0 | M36: =SUM('测算-高个子抖音'!N$34)+SUM('测算-高个子视频号'!N$34)+SUM('测算-天猫淘宝'!N$33)+SUM('测算-拼多多'!N$34)+SUM('测算-京东POP'!N$34)+SUM('测算-京东自营'!N$35)+SUM('测算-达播'!N$35)+SUM('测算-私域'!N$34)+SUM('测算-外部分销'!N$34) -> 0 | N36: =SUM('测算-高个子抖音'!O$34)+SUM('测算-高个子视频号'!O$34)+SUM('测算-天猫淘宝'!O$33)+SUM('测算-拼多多'!O$34)+SUM('测算-京东POP'!O$34)+SUM('测算-京东自营'!O$35)+SUM('测算-达播'!O$35)+SUM('测算-私域'!O$34)+SUM('测算-外部分销'!O$34) -> 0 | O36: =SUM('测算-高个子抖音'!P$34)+SUM('测算-高个子视频号'!P$34)+SUM('测算-天猫淘宝'!P$33)+SUM('测算-拼多多'!P$34)+SUM('测算-京东POP'!P$34)+SUM('测算-京东自营'!P$35)+SUM('测算-达播'!P$35)+SUM('测算-私域'!P$34)+SUM('测算-外部分销'!P$34) -> 0 | ... S36: =SUM('测算-高个子抖音'!T$34)+SUM('测算-高个子视频号'!T$34)+SUM('测算-天猫淘宝'!T$33)+SUM('测算-拼多多'!T$34)+SUM('测算-京东POP'!T$34)+SUM('测算-京东自营'!T$35)+SUM('测算-达播'!T$35)+SUM('测算-私域'!T$34)+SUM('测算-外部分销'!T$34) -> 0 | U36: =SUM('测算-高个子抖音'!V$34)+SUM('测算-高个子视频号'!V$34)+SUM('测算-天猫淘宝'!V$33)+SUM('测算-拼多多'!V$34)+SUM('测算-京东POP'!V$34)+SUM('测算-京东自营'!V$35)+SUM('测算-达播'!V$35)+SUM('测算-私域'!V$34)+SUM('测算-外部分销'!V$34) -> 0 | V36: =SUM('测算-高个子抖音'!W$34)+SUM('测算-高个子视频号'!W$34)+SUM('测算-天猫淘宝'!W$33)+SUM('测算-拼多多'!W$34)+SUM('测算-京东POP'!W$34)+SUM('测算-京东自营'!W$35)+SUM('测算-达播'!W$35)+SUM('测算-私域'!W$34)+SUM('测算-外部分销'!W$34) -> 0
D37: 赠品成本 | E37: 渠道测算费用明细 | F37: 各渠道测算表汇总 | H37: =SUM('测算-高个子抖音'!I$35)+SUM('测算-高个子视频号'!I$35)+SUM('测算-天猫淘宝'!I$34)+SUM('测算-拼多多'!I$35)+SUM('测算-京东POP'!I$35)+SUM('测算-京东自营'!I$36)+SUM('测算-达播'!I$36)+SUM('测算-私域'!I$35)+SUM('测算-外部分销'!I$35) -> 3.772369 | I37: =SUM('测算-高个子抖音'!J$35)+SUM('测算-高个子视频号'!J$35)+SUM('测算-天猫淘宝'!J$34)+SUM('测算-拼多多'!J$35)+SUM('测算-京东POP'!J$35)+SUM('测算-京东自营'!J$36)+SUM('测算-达播'!J$36)+SUM('测算-私域'!J$35)+SUM('测算-外部分销'!J$35) -> 2.669009 | J37: =SUM('测算-高个子抖音'!K$35)+SUM('测算-高个子视频号'!K$35)+SUM('测算-天猫淘宝'!K$34)+SUM('测算-拼多多'!K$35)+SUM('测算-京东POP'!K$35)+SUM('测算-京东自营'!K$36)+SUM('测算-达播'!K$36)+SUM('测算-私域'!K$35)+SUM('测算-外部分销'!K$35) -> 5.441306 | K37: =SUM('测算-高个子抖音'!L$35)+SUM('测算-高个子视频号'!L$35)+SUM('测算-天猫淘宝'!L$34)+SUM('测算-拼多多'!L$35)+SUM('测算-京东POP'!L$35)+SUM('测算-京东自营'!L$36)+SUM('测算-达播'!L$36)+SUM('测算-私域'!L$35)+SUM('测算-外部分销'!L$35) -> 4.324099 | L37: =SUM('测算-高个子抖音'!M$35)+SUM('测算-高个子视频号'!M$35)+SUM('测算-天猫淘宝'!M$34)+SUM('测算-拼多多'!M$35)+SUM('测算-京东POP'!M$35)+SUM('测算-京东自营'!M$36)+SUM('测算-达播'!M$36)+SUM('测算-私域'!M$35)+SUM('测算-外部分销'!M$35) -> 4.571711 | M37: =SUM('测算-高个子抖音'!N$35)+SUM('测算-高个子视频号'!N$35)+SUM('测算-天猫淘宝'!N$34)+SUM('测算-拼多多'!N$35)+SUM('测算-京东POP'!N$35)+SUM('测算-京东自营'!N$36)+SUM('测算-达播'!N$36)+SUM('测算-私域'!N$35)+SUM('测算-外部分销'!N$35) -> 4.845667 | N37: =SUM('测算-高个子抖音'!O$35)+SUM('测算-高个子视频号'!O$35)+SUM('测算-天猫淘宝'!O$34)+SUM('测算-拼多多'!O$35)+SUM('测算-京东POP'!O$35)+SUM('测算-京东自营'!O$36)+SUM('测算-达播'!O$36)+SUM('测算-私域'!O$35)+SUM('测算-外部分销'!O$35) -> 2.8053382 | O37: =SUM('测算-高个子抖音'!P$35)+SUM('测算-高个子视频号'!P$35)+SUM('测算-天猫淘宝'!P$34)+SUM('测算-拼多多'!P$35)+SUM('测算-京东POP'!P$35)+SUM('测算-京东自营'!P$36)+SUM('测算-达播'!P$36)+SUM('测算-私域'!P$35)+SUM('测算-外部分销'!P$35) -> 3.2879335 | ... S37: =SUM('测算-高个子抖音'!T$35)+SUM('测算-高个子视频号'!T$35)+SUM('测算-天猫淘宝'!T$34)+SUM('测算-拼多多'!T$35)+SUM('测算-京东POP'!T$35)+SUM('测算-京东自营'!T$36)+SUM('测算-达播'!T$36)+SUM('测算-私域'!T$35)+SUM('测算-外部分销'!T$35) -> 4.0734305 | U37: =SUM('测算-高个子抖音'!V$35)+SUM('测算-高个子视频号'!V$35)+SUM('测算-天猫淘宝'!V$34)+SUM('测算-拼多多'!V$35)+SUM('测算-京东POP'!V$35)+SUM('测算-京东自营'!V$36)+SUM('测算-达播'!V$36)+SUM('测算-私域'!V$35)+SUM('测算-外部分销'!V$35) -> 48.151076 | V37: =SUM('测算-高个子抖音'!W$35)+SUM('测算-高个子视频号'!W$35)+SUM('测算-天猫淘宝'!W$34)+SUM('测算-拼多多'!W$35)+SUM('测算-京东POP'!W$35)+SUM('测算-京东自营'!W$36)+SUM('测算-达播'!W$36)+SUM('测算-私域'!W$35)+SUM('测算-外部分销'!W$35) -> 22.526915
C38: 仓储物流 | H38: =SUM(H39:H42) -> 28.549916 | I38: =SUM(I39:I42) -> 21.185805 | J38: =SUM(J39:J42) -> 40.113545 | K38: =SUM(K39:K42) -> 29.593612 | L38: =SUM(L39:L42) -> 35.070613 | M38: =SUM(M39:M42) -> 48.212656 | N38: =SUM(N39:N42) -> 30.707836 | O38: =SUM(O39:O42) -> 40.606089 | ... S38: =SUM(S39:S42) -> 56.892974 | U38: =SUM(U39:U42) -> 531.62114 | V38: =SUM(V39:V42) -> 300.80553
D39: 快递费用 | E39: 渠道测算费用明细 | F39: 各渠道测算表汇总 | H39: =SUM('测算-高个子抖音'!I$37)+SUM('测算-高个子视频号'!I$37)+SUM('测算-天猫淘宝'!I$36)+SUM('测算-拼多多'!I$37)+SUM('测算-京东POP'!I$37)+SUM('测算-京东自营'!I$38)+SUM('测算-达播'!I$38)+SUM('测算-私域'!I$37)+SUM('测算-外部分销'!I$37) -> 12.31197 | I39: =SUM('测算-高个子抖音'!J$37)+SUM('测算-高个子视频号'!J$37)+SUM('测算-天猫淘宝'!J$36)+SUM('测算-拼多多'!J$37)+SUM('测算-京东POP'!J$37)+SUM('测算-京东自营'!J$38)+SUM('测算-达播'!J$38)+SUM('测算-私域'!J$37)+SUM('测算-外部分销'!J$37) -> 8.740675 | J39: =SUM('测算-高个子抖音'!K$37)+SUM('测算-高个子视频号'!K$37)+SUM('测算-天猫淘宝'!K$36)+SUM('测算-拼多多'!K$37)+SUM('测算-京东POP'!K$37)+SUM('测算-京东自营'!K$38)+SUM('测算-达播'!K$38)+SUM('测算-私域'!K$37)+SUM('测算-外部分销'!K$37) -> 19.75802 | K39: =SUM('测算-高个子抖音'!L$37)+SUM('测算-高个子视频号'!L$37)+SUM('测算-天猫淘宝'!L$36)+SUM('测算-拼多多'!L$37)+SUM('测算-京东POP'!L$37)+SUM('测算-京东自营'!L$38)+SUM('测算-达播'!L$38)+SUM('测算-私域'!L$37)+SUM('测算-外部分销'!L$37) -> 10.679434 | L39: =SUM('测算-高个子抖音'!M$37)+SUM('测算-高个子视频号'!M$37)+SUM('测算-天猫淘宝'!M$36)+SUM('测算-拼多多'!M$37)+SUM('测算-京东POP'!M$37)+SUM('测算-京东自营'!M$38)+SUM('测算-达播'!M$38)+SUM('测算-私域'!M$37)+SUM('测算-外部分销'!M$37) -> 13.419053 | M39: =SUM('测算-高个子抖音'!N$37)+SUM('测算-高个子视频号'!N$37)+SUM('测算-天猫淘宝'!N$36)+SUM('测算-拼多多'!N$37)+SUM('测算-京东POP'!N$37)+SUM('测算-京东自营'!N$38)+SUM('测算-达播'!N$38)+SUM('测算-私域'!N$37)+SUM('测算-外部分销'!N$37) -> 12.024452 | N39: =SUM('测算-高个子抖音'!O$37)+SUM('测算-高个子视频号'!O$37)+SUM('测算-天猫淘宝'!O$36)+SUM('测算-拼多多'!O$37)+SUM('测算-京东POP'!O$37)+SUM('测算-京东自营'!O$38)+SUM('测算-达播'!O$38)+SUM('测算-私域'!O$37)+SUM('测算-外部分销'!O$37) -> 8.9886617 | O39: =SUM('测算-高个子抖音'!P$37)+SUM('测算-高个子视频号'!P$37)+SUM('测算-天猫淘宝'!P$36)+SUM('测算-拼多多'!P$37)+SUM('测算-京东POP'!P$37)+SUM('测算-京东自营'!P$38)+SUM('测算-达播'!P$38)+SUM('测算-私域'!P$37)+SUM('测算-外部分销'!P$37) -> 12.021873 | ... S39: =SUM('测算-高个子抖音'!T$37)+SUM('测算-高个子视频号'!T$37)+SUM('测算-天猫淘宝'!T$36)+SUM('测算-拼多多'!T$37)+SUM('测算-京东POP'!T$37)+SUM('测算-京东自营'!T$38)+SUM('测算-达播'!T$38)+SUM('测算-私域'!T$37)+SUM('测算-外部分销'!T$37) -> 17.015574 | U39: =SUM('测算-高个子抖音'!V$37)+SUM('测算-高个子视频号'!V$37)+SUM('测算-天猫淘宝'!V$36)+SUM('测算-拼多多'!V$37)+SUM('测算-京东POP'!V$37)+SUM('测算-京东自营'!V$38)+SUM('测算-达播'!V$38)+SUM('测算-私域'!V$37)+SUM('测算-外部分销'!V$37) -> 166.57978 | V39: =SUM('测算-高个子抖音'!W$37)+SUM('测算-高个子视频号'!W$37)+SUM('测算-天猫淘宝'!W$36)+SUM('测算-拼多多'!W$37)+SUM('测算-京东POP'!W$37)+SUM('测算-京东自营'!W$38)+SUM('测算-达播'!W$38)+SUM('测算-私域'!W$37)+SUM('测算-外部分销'!W$37) -> 89.64618
D40: 打包包装 | E40: 渠道测算费用明细 | F40: 各渠道测算表汇总 | H40: =SUM('测算-高个子抖音'!I$38)+SUM('测算-高个子视频号'!I$38)+SUM('测算-天猫淘宝'!I$37)+SUM('测算-拼多多'!I$38)+SUM('测算-京东POP'!I$38)+SUM('测算-京东自营'!I$39)+SUM('测算-达播'!I$39)+SUM('测算-私域'!I$38)+SUM('测算-外部分销'!I$38) -> 6.7513262 | I40: =SUM('测算-高个子抖音'!J$38)+SUM('测算-高个子视频号'!J$38)+SUM('测算-天猫淘宝'!J$37)+SUM('测算-拼多多'!J$38)+SUM('测算-京东POP'!J$38)+SUM('测算-京东自营'!J$39)+SUM('测算-达播'!J$39)+SUM('测算-私域'!J$38)+SUM('测算-外部分销'!J$38) -> 3.628259 | J40: =SUM('测算-高个子抖音'!K$38)+SUM('测算-高个子视频号'!K$38)+SUM('测算-天猫淘宝'!K$37)+SUM('测算-拼多多'!K$38)+SUM('测算-京东POP'!K$38)+SUM('测算-京东自营'!K$39)+SUM('测算-达播'!K$39)+SUM('测算-私域'!K$38)+SUM('测算-外部分销'!K$38) -> 8.724739 | K40: =SUM('测算-高个子抖音'!L$38)+SUM('测算-高个子视频号'!L$38)+SUM('测算-天猫淘宝'!L$37)+SUM('测算-拼多多'!L$38)+SUM('测算-京东POP'!L$38)+SUM('测算-京东自营'!L$39)+SUM('测算-达播'!L$39)+SUM('测算-私域'!L$38)+SUM('测算-外部分销'!L$38) -> 4.871998 | L40: =SUM('测算-高个子抖音'!M$38)+SUM('测算-高个子视频号'!M$38)+SUM('测算-天猫淘宝'!M$37)+SUM('测算-拼多多'!M$38)+SUM('测算-京东POP'!M$38)+SUM('测算-京东自营'!M$39)+SUM('测算-达播'!M$39)+SUM('测算-私域'!M$38)+SUM('测算-外部分销'!M$38) -> 6.92985 | M40: =SUM('测算-高个子抖音'!N$38)+SUM('测算-高个子视频号'!N$38)+SUM('测算-天猫淘宝'!N$37)+SUM('测算-拼多多'!N$38)+SUM('测算-京东POP'!N$38)+SUM('测算-京东自营'!N$39)+SUM('测算-达播'!N$39)+SUM('测算-私域'!N$38)+SUM('测算-外部分销'!N$38) -> 6.7076752 | N40: =SUM('测算-高个子抖音'!O$38)+SUM('测算-高个子视频号'!O$38)+SUM('测算-天猫淘宝'!O$37)+SUM('测算-拼多多'!O$38)+SUM('测算-京东POP'!O$38)+SUM('测算-京东自营'!O$39)+SUM('测算-达播'!O$39)+SUM('测算-私域'!O$38)+SUM('测算-外部分销'!O$38) -> 4.2279308 | O40: =SUM('测算-高个子抖音'!P$38)+SUM('测算-高个子视频号'!P$38)+SUM('测算-天猫淘宝'!P$37)+SUM('测算-拼多多'!P$38)+SUM('测算-京东POP'!P$38)+SUM('测算-京东自营'!P$39)+SUM('测算-达播'!P$39)+SUM('测算-私域'!P$38)+SUM('测算-外部分销'!P$38) -> 5.6546399 | ... S40: =SUM('测算-高个子抖音'!T$38)+SUM('测算-高个子视频号'!T$38)+SUM('测算-天猫淘宝'!T$37)+SUM('测算-拼多多'!T$38)+SUM('测算-京东POP'!T$38)+SUM('测算-京东自营'!T$39)+SUM('测算-达播'!T$39)+SUM('测算-私域'!T$38)+SUM('测算-外部分销'!T$38) -> 8.0034904 | U40: =SUM('测算-高个子抖音'!V$38)+SUM('测算-高个子视频号'!V$38)+SUM('测算-天猫淘宝'!V$37)+SUM('测算-拼多多'!V$38)+SUM('测算-京东POP'!V$38)+SUM('测算-京东自营'!V$39)+SUM('测算-达播'!V$39)+SUM('测算-私域'!V$38)+SUM('测算-外部分销'!V$38) -> 79.780062 | V40: =SUM('测算-高个子抖音'!W$38)+SUM('测算-高个子视频号'!W$38)+SUM('测算-天猫淘宝'!W$37)+SUM('测算-拼多多'!W$38)+SUM('测算-京东POP'!W$38)+SUM('测算-京东自营'!W$39)+SUM('测算-达播'!W$39)+SUM('测算-私域'!W$38)+SUM('测算-外部分销'!W$38) -> 42.166215
D41: 干线费用 | E41: 渠道测算费用明细 | F41: 各渠道测算表汇总 | H41: =SUM('测算-高个子抖音'!I$39)+SUM('测算-高个子视频号'!I$39)+SUM('测算-天猫淘宝'!I$38)+SUM('测算-拼多多'!I$39)+SUM('测算-京东POP'!I$39)+SUM('测算-京东自营'!I$40)+SUM('测算-达播'!I$40)+SUM('测算-私域'!I$39)+SUM('测算-外部分销'!I$39) -> 2.529556 | I41: =SUM('测算-高个子抖音'!J$39)+SUM('测算-高个子视频号'!J$39)+SUM('测算-天猫淘宝'!J$38)+SUM('测算-拼多多'!J$39)+SUM('测算-京东POP'!J$39)+SUM('测算-京东自营'!J$40)+SUM('测算-达播'!J$40)+SUM('测算-私域'!J$39)+SUM('测算-外部分销'!J$39) -> 1.245344 | J41: =SUM('测算-高个子抖音'!K$39)+SUM('测算-高个子视频号'!K$39)+SUM('测算-天猫淘宝'!K$38)+SUM('测算-拼多多'!K$39)+SUM('测算-京东POP'!K$39)+SUM('测算-京东自营'!K$40)+SUM('测算-达播'!K$40)+SUM('测算-私域'!K$39)+SUM('测算-外部分销'!K$39) -> 3.913159 | K41: =SUM('测算-高个子抖音'!L$39)+SUM('测算-高个子视频号'!L$39)+SUM('测算-天猫淘宝'!L$38)+SUM('测算-拼多多'!L$39)+SUM('测算-京东POP'!L$39)+SUM('测算-京东自营'!L$40)+SUM('测算-达播'!L$40)+SUM('测算-私域'!L$39)+SUM('测算-外部分销'!L$39) -> 4.59771 | L41: =SUM('测算-高个子抖音'!M$39)+SUM('测算-高个子视频号'!M$39)+SUM('测算-天猫淘宝'!M$38)+SUM('测算-拼多多'!M$39)+SUM('测算-京东POP'!M$39)+SUM('测算-京东自营'!M$40)+SUM('测算-达播'!M$40)+SUM('测算-私域'!M$39)+SUM('测算-外部分销'!M$39) -> 4.839552 | M41: =SUM('测算-高个子抖音'!N$39)+SUM('测算-高个子视频号'!N$39)+SUM('测算-天猫淘宝'!N$38)+SUM('测算-拼多多'!N$39)+SUM('测算-京东POP'!N$39)+SUM('测算-京东自营'!N$40)+SUM('测算-达播'!N$40)+SUM('测算-私域'!N$39)+SUM('测算-外部分销'!N$39) -> 6.9477594 | N41: =SUM('测算-高个子抖音'!O$39)+SUM('测算-高个子视频号'!O$39)+SUM('测算-天猫淘宝'!O$38)+SUM('测算-拼多多'!O$39)+SUM('测算-京东POP'!O$39)+SUM('测算-京东自营'!O$40)+SUM('测算-达播'!O$40)+SUM('测算-私域'!O$39)+SUM('测算-外部分销'!O$39) -> 5.1706365 | O41: =SUM('测算-高个子抖音'!P$39)+SUM('测算-高个子视频号'!P$39)+SUM('测算-天猫淘宝'!P$38)+SUM('测算-拼多多'!P$39)+SUM('测算-京东POP'!P$39)+SUM('测算-京东自营'!P$40)+SUM('测算-达播'!P$40)+SUM('测算-私域'!P$39)+SUM('测算-外部分销'!P$39) -> 6.4513983 | ... S41: =SUM('测算-高个子抖音'!T$39)+SUM('测算-高个子视频号'!T$39)+SUM('测算-天猫淘宝'!T$38)+SUM('测算-拼多多'!T$39)+SUM('测算-京东POP'!T$39)+SUM('测算-京东自营'!T$40)+SUM('测算-达播'!T$40)+SUM('测算-私域'!T$39)+SUM('测算-外部分销'!T$39) -> 8.5509499 | U41: =SUM('测算-高个子抖音'!V$39)+SUM('测算-高个子视频号'!V$39)+SUM('测算-天猫淘宝'!V$38)+SUM('测算-拼多多'!V$39)+SUM('测算-京东POP'!V$39)+SUM('测算-京东自营'!V$40)+SUM('测算-达播'!V$40)+SUM('测算-私域'!V$39)+SUM('测算-外部分销'!V$39) -> 70.189709 | V41: =SUM('测算-高个子抖音'!W$39)+SUM('测算-高个子视频号'!W$39)+SUM('测算-天猫淘宝'!W$38)+SUM('测算-拼多多'!W$39)+SUM('测算-京东POP'!W$39)+SUM('测算-京东自营'!W$40)+SUM('测算-达播'!W$40)+SUM('测算-私域'!W$39)+SUM('测算-外部分销'!W$39) -> 46.116628
D42: 仓储费用 | E42: 渠道测算费用明细 | F42: 各渠道测算表汇总 | H42: =SUM('测算-高个子抖音'!I$40)+SUM('测算-高个子视频号'!I$40)+SUM('测算-天猫淘宝'!I$39)+SUM('测算-拼多多'!I$40)+SUM('测算-京东POP'!I$40)+SUM('测算-达播'!I$41)+SUM('测算-私域'!I$40)+SUM('测算-外部分销'!I$40) -> 6.9570642 | I42: =SUM('测算-高个子抖音'!J$40)+SUM('测算-高个子视频号'!J$40)+SUM('测算-天猫淘宝'!J$39)+SUM('测算-拼多多'!J$40)+SUM('测算-京东POP'!J$40)+SUM('测算-达播'!J$41)+SUM('测算-私域'!J$40)+SUM('测算-外部分销'!J$40) -> 7.5715273 | J42: =SUM('测算-高个子抖音'!K$40)+SUM('测算-高个子视频号'!K$40)+SUM('测算-天猫淘宝'!K$39)+SUM('测算-拼多多'!K$40)+SUM('测算-京东POP'!K$40)+SUM('测算-京东自营'!K$41)+SUM('测算-达播'!K$41)+SUM('测算-私域'!K$40)+SUM('测算-外部分销'!K$40) -> 7.7176273 | K42: =SUM('测算-高个子抖音'!L$40)+SUM('测算-高个子视频号'!L$40)+SUM('测算-天猫淘宝'!L$39)+SUM('测算-拼多多'!L$40)+SUM('测算-京东POP'!L$40)+SUM('测算-京东自营'!L$41)+SUM('测算-达播'!L$41)+SUM('测算-私域'!L$40)+SUM('测算-外部分销'!L$40) -> 9.4444696 | L42: =SUM('测算-高个子抖音'!M$40)+SUM('测算-高个子视频号'!M$40)+SUM('测算-天猫淘宝'!M$39)+SUM('测算-拼多多'!M$40)+SUM('测算-京东POP'!M$40)+SUM('测算-京东自营'!M$41)+SUM('测算-达播'!M$41)+SUM('测算-私域'!M$40)+SUM('测算-外部分销'!M$40) -> 9.8821581 | M42: =SUM('测算-高个子抖音'!N$40)+SUM('测算-高个子视频号'!N$40)+SUM('测算-天猫淘宝'!N$39)+SUM('测算-拼多多'!N$40)+SUM('测算-京东POP'!N$40)+SUM('测算-京东自营'!N$41)+SUM('测算-达播'!N$41)+SUM('测算-私域'!N$40)+SUM('测算-外部分销'!N$40) -> 22.532769 | N42: =SUM('测算-高个子抖音'!O$40)+SUM('测算-高个子视频号'!O$40)+SUM('测算-天猫淘宝'!O$39)+SUM('测算-拼多多'!O$40)+SUM('测算-京东POP'!O$40)+SUM('测算-京东自营'!O$41)+SUM('测算-达播'!O$41)+SUM('测算-私域'!O$40)+SUM('测算-外部分销'!O$40) -> 12.320607 | O42: =SUM('测算-高个子抖音'!P$40)+SUM('测算-高个子视频号'!P$40)+SUM('测算-天猫淘宝'!P$39)+SUM('测算-拼多多'!P$40)+SUM('测算-京东POP'!P$40)+SUM('测算-京东自营'!P$41)+SUM('测算-达播'!P$41)+SUM('测算-私域'!P$40)+SUM('测算-外部分销'!P$40) -> 16.478178 | P42: =SUM('测算-高个子抖音'!Q$40)+SUM('测算-高个子视频号'!Q$40)+SUM('测算-天猫淘宝'!Q$39)+SUM('测算-拼多多'!Q$40)+SUM('测算-京东POP'!Q$40)+SUM('测算-京东自营'!Q$41)+SUM('测算-达播'!Q$41)+SUM('测算-私域'!Q$40)+SUM('测算-外部分销'!Q$40) -> 20.838558 | Q42: =SUM('测算-高个子抖音'!R$40)+SUM('测算-高个子视频号'!R$40)+SUM('测算-天猫淘宝'!R$39)+SUM('测算-拼多多'!R$40)+SUM('测算-京东POP'!R$40)+SUM('测算-京东自营'!R$41)+SUM('测算-达播'!R$41)+SUM('测算-私域'!R$40)+SUM('测算-外部分销'!R$40) -> 22.537078 | ... S42: =SUM('测算-高个子抖音'!T$40)+SUM('测算-高个子视频号'!T$40)+SUM('测算-天猫淘宝'!T$39)+SUM('测算-拼多多'!T$40)+SUM('测算-京东POP'!T$40)+SUM('测算-京东自营'!T$41)+SUM('测算-达播'!T$41)+SUM('测算-私域'!T$40)+SUM('测算-外部分销'!T$40) -> 23.32296 | U42: =SUM('测算-高个子抖音'!V$40)+SUM('测算-高个子视频号'!V$40)+SUM('测算-天猫淘宝'!V$39)+SUM('测算-拼多多'!V$40)+SUM('测算-京东POP'!V$40)+SUM('测算-京东自营'!V$41)+SUM('测算-达播'!V$41)+SUM('测算-私域'!V$40)+SUM('测算-外部分销'!V$40) -> 215.07159 | V42: =SUM('测算-高个子抖音'!W$40)+SUM('测算-高个子视频号'!W$40)+SUM('测算-天猫淘宝'!W$39)+SUM('测算-拼多多'!W$40)+SUM('测算-京东POP'!W$40)+SUM('测算-京东自营'!W$41)+SUM('测算-达播'!W$41)+SUM('测算-私域'!W$40)+SUM('测算-外部分销'!W$40) -> 122.87651
C43: 人工成本 | H43: =SUM(H44:H46) -> 41.826251 | I43: =SUM(I44:I46) -> 33.846583 | J43: =SUM(J44:J46) -> 47.037375 | K43: =SUM(K44:K46) -> 45.168611 | L43: =SUM(L44:L46) -> 50.566793 | M43: =SUM(M44:M46) -> 52.905912 | N43: =SUM(N44:N46) -> 55.408323 | O43: =SUM(O44:O46) -> 57.795207 | ... S43: =SUM(S44:S46) -> 61.107852 | U43: =SUM(U44:U46) -> 629.38475 | V43: =SUM(V44:V46) -> 358.03322
D44: 固定薪资 | E44: 渠道测算费用明细 | F44: 各渠道测算表汇总 | H44: =SUM('测算-高个子抖音'!I$42)+SUM('测算-高个子视频号'!I$42)+SUM('测算-天猫淘宝'!I$41)+SUM('测算-拼多多'!I$42)+SUM('测算-京东POP'!I$42)+SUM('测算-京东自营'!I$43)+SUM('测算-达播'!I$43)+SUM('测算-私域'!I$42)+SUM('测算-外部分销'!I$42) -> 32.677613 | I44: =SUM('测算-高个子抖音'!J$42)+SUM('测算-高个子视频号'!J$42)+SUM('测算-天猫淘宝'!J$41)+SUM('测算-拼多多'!J$42)+SUM('测算-京东POP'!J$42)+SUM('测算-京东自营'!J$43)+SUM('测算-达播'!J$43)+SUM('测算-私域'!J$42)+SUM('测算-外部分销'!J$42) -> 29.437019 | J44: =SUM('测算-高个子抖音'!K$42)+SUM('测算-高个子视频号'!K$42)+SUM('测算-天猫淘宝'!K$41)+SUM('测算-拼多多'!K$42)+SUM('测算-京东POP'!K$42)+SUM('测算-京东自营'!K$43)+SUM('测算-达播'!K$43)+SUM('测算-私域'!K$42)+SUM('测算-外部分销'!K$42) -> 35.846202 | K44: =SUM('测算-高个子抖音'!L$42)+SUM('测算-高个子视频号'!L$42)+SUM('测算-天猫淘宝'!L$41)+SUM('测算-拼多多'!L$42)+SUM('测算-京东POP'!L$42)+SUM('测算-京东自营'!L$43)+SUM('测算-达播'!L$43)+SUM('测算-私域'!L$42)+SUM('测算-外部分销'!L$42) -> 38.322003 | L44: =SUM('测算-高个子抖音'!M$42)+SUM('测算-高个子视频号'!M$42)+SUM('测算-天猫淘宝'!M$41)+SUM('测算-拼多多'!M$42)+SUM('测算-京东POP'!M$42)+SUM('测算-京东自营'!M$43)+SUM('测算-达播'!M$43)+SUM('测算-私域'!M$42)+SUM('测算-外部分销'!M$42) -> 43.272249 | M44: =SUM('测算-高个子抖音'!N$42)+SUM('测算-高个子视频号'!N$42)+SUM('测算-天猫淘宝'!N$41)+SUM('测算-拼多多'!N$42)+SUM('测算-京东POP'!N$42)+SUM('测算-京东自营'!N$43)+SUM('测算-达播'!N$43)+SUM('测算-私域'!N$42)+SUM('测算-外部分销'!N$42) -> 45.506154 | N44: =SUM('测算-高个子抖音'!O$42)+SUM('测算-高个子视频号'!O$42)+SUM('测算-天猫淘宝'!O$41)+SUM('测算-拼多多'!O$42)+SUM('测算-京东POP'!O$42)+SUM('测算-京东自营'!O$43)+SUM('测算-达播'!O$43)+SUM('测算-私域'!O$42)+SUM('测算-外部分销'!O$42) -> 48.672821 | O44: =SUM('测算-高个子抖音'!P$42)+SUM('测算-高个子视频号'!P$42)+SUM('测算-天猫淘宝'!P$41)+SUM('测算-拼多多'!P$42)+SUM('测算-京东POP'!P$42)+SUM('测算-京东自营'!P$43)+SUM('测算-达播'!P$43)+SUM('测算-私域'!P$42)+SUM('测算-外部分销'!P$42) -> 48.906154 | ... S44: =SUM('测算-高个子抖音'!T$42)+SUM('测算-高个子视频号'!T$42)+SUM('测算-天猫淘宝'!T$41)+SUM('测算-拼多多'!T$42)+SUM('测算-京东POP'!T$42)+SUM('测算-京东自营'!T$43)+SUM('测算-达播'!T$43)+SUM('测算-私域'!T$42)+SUM('测算-外部分销'!T$42) -> 48.906154 | U44: =SUM('测算-高个子抖音'!V$42)+SUM('测算-高个子视频号'!V$42)+SUM('测算-天猫淘宝'!V$41)+SUM('测算-拼多多'!V$42)+SUM('测算-京东POP'!V$42)+SUM('测算-京东自营'!V$43)+SUM('测算-达播'!V$43)+SUM('测算-私域'!V$42)+SUM('测算-外部分销'!V$42) -> 518.26483 | V44: =SUM('测算-高个子抖音'!W$42)+SUM('测算-高个子视频号'!W$42)+SUM('测算-天猫淘宝'!W$41)+SUM('测算-拼多多'!W$42)+SUM('测算-京东POP'!W$42)+SUM('测算-京东自营'!W$43)+SUM('测算-达播'!W$43)+SUM('测算-私域'!W$42)+SUM('测算-外部分销'!W$42) -> 293.20359
D45: 奖金 | E45: 渠道测算费用明细 | F45: 各渠道测算表汇总 | H45: =SUM('测算-高个子抖音'!I$43:I$44)+SUM('测算-高个子视频号'!I$43:I$44)+SUM('测算-天猫淘宝'!I$42:I$43)+SUM('测算-拼多多'!I$43:I$44)+SUM('测算-京东POP'!I$43:I$44)+SUM('测算-京东自营'!I$44:I$45)+SUM('测算-达播'!I$44:I$45)+SUM('测算-私域'!I$43:I$44)+SUM('测算-外部分销'!I$43:I$44) -> 9.1486383 | I45: =SUM('测算-高个子抖音'!J$43:J$44)+SUM('测算-高个子视频号'!J$43:J$44)+SUM('测算-天猫淘宝'!J$42:J$43)+SUM('测算-拼多多'!J$43:J$44)+SUM('测算-京东POP'!J$43:J$44)+SUM('测算-京东自营'!J$44:J$45)+SUM('测算-达播'!J$44:J$45)+SUM('测算-私域'!J$43:J$44)+SUM('测算-外部分销'!J$43:J$44) -> 4.4095645 | J45: =SUM('测算-高个子抖音'!K$43:K$44)+SUM('测算-高个子视频号'!K$43:K$44)+SUM('测算-天猫淘宝'!K$42:K$43)+SUM('测算-拼多多'!K$43:K$44)+SUM('测算-京东POP'!K$43:K$44)+SUM('测算-京东自营'!K$44:K$45)+SUM('测算-达播'!K$44:K$45)+SUM('测算-私域'!K$43:K$44)+SUM('测算-外部分销'!K$43:K$44) -> 11.191174 | K45: =SUM('测算-高个子抖音'!L$43:L$44)+SUM('测算-高个子视频号'!L$43:L$44)+SUM('测算-天猫淘宝'!L$42:L$43)+SUM('测算-拼多多'!L$43:L$44)+SUM('测算-京东POP'!L$43:L$44)+SUM('测算-京东自营'!L$44:L$45)+SUM('测算-达播'!L$44:L$45)+SUM('测算-私域'!L$43:L$44)+SUM('测算-外部分销'!L$43:L$44) -> 6.8466085 | L45: =SUM('测算-高个子抖音'!M$43:M$44)+SUM('测算-高个子视频号'!M$43:M$44)+SUM('测算-天猫淘宝'!M$42:M$43)+SUM('测算-拼多多'!M$43:M$44)+SUM('测算-京东POP'!M$43:M$44)+SUM('测算-京东自营'!M$44:M$45)+SUM('测算-达播'!M$44:M$45)+SUM('测算-私域'!M$43:M$44)+SUM('测算-外部分销'!M$43:M$44) -> 7.2945434 | M45: =SUM('测算-高个子抖音'!N$43:N$44)+SUM('测算-高个子视频号'!N$43:N$44)+SUM('测算-天猫淘宝'!N$42:N$43)+SUM('测算-拼多多'!N$43:N$44)+SUM('测算-京东POP'!N$43:N$44)+SUM('测算-京东自营'!N$44:N$45)+SUM('测算-达播'!N$44:N$45)+SUM('测算-私域'!N$43:N$44)+SUM('测算-外部分销'!N$43:N$44) -> 7.3997578 | N45: =SUM('测算-高个子抖音'!O$43:O$44)+SUM('测算-高个子视频号'!O$43:O$44)+SUM('测算-天猫淘宝'!O$42:O$43)+SUM('测算-拼多多'!O$43:O$44)+SUM('测算-京东POP'!O$43:O$44)+SUM('测算-京东自营'!O$44:O$45)+SUM('测算-达播'!O$44:O$45)+SUM('测算-私域'!O$43:O$44)+SUM('测算-外部分销'!O$43:O$44) -> 6.0854689 | O45: =SUM('测算-高个子抖音'!P$43:P$44)+SUM('测算-高个子视频号'!P$43:P$44)+SUM('测算-天猫淘宝'!P$42:P$43)+SUM('测算-拼多多'!P$43:P$44)+SUM('测算-京东POP'!P$43:P$44)+SUM('测算-京东自营'!P$44:P$45)+SUM('测算-达播'!P$44:P$45)+SUM('测算-私域'!P$43:P$44)+SUM('测算-外部分销'!P$43:P$44) -> 8.0196674 | ... S45: =SUM('测算-高个子抖音'!T$43:T$44)+SUM('测算-高个子视频号'!T$43:T$44)+SUM('测算-天猫淘宝'!T$42:T$43)+SUM('测算-拼多多'!T$43:T$44)+SUM('测算-京东POP'!T$43:T$44)+SUM('测算-京东自营'!T$44:T$45)+SUM('测算-达播'!T$44:T$45)+SUM('测算-私域'!T$43:T$44)+SUM('测算-外部分销'!T$43:T$44) -> 10.971183 | U45: =SUM('测算-高个子抖音'!V$43:V$44)+SUM('测算-高个子视频号'!V$43:V$44)+SUM('测算-天猫淘宝'!V$42:V$43)+SUM('测算-拼多多'!V$43:V$44)+SUM('测算-京东POP'!V$43:V$44)+SUM('测算-京东自营'!V$44:V$45)+SUM('测算-达播'!V$44:V$45)+SUM('测算-私域'!V$43:V$44)+SUM('测算-外部分销'!V$43:V$44) -> 104.63697 | V45: =SUM('测算-高个子抖音'!W$43:W$44)+SUM('测算-高个子视频号'!W$43:W$44)+SUM('测算-天猫淘宝'!W$42:W$43)+SUM('测算-拼多多'!W$43:W$44)+SUM('测算-京东POP'!W$43:W$44)+SUM('测算-京东自营'!W$44:W$45)+SUM('测算-达播'!W$44:W$45)+SUM('测算-私域'!W$43:W$44)+SUM('测算-外部分销'!W$43:W$44) -> 58.346688
D46: 日常费用 | E46: 渠道测算费用明细 | F46: 各渠道测算表汇总 | H46: =SUM('测算-高个子抖音'!I$45)+SUM('测算-高个子视频号'!I$45)+SUM('测算-天猫淘宝'!I$44)+SUM('测算-拼多多'!I$45)+SUM('测算-京东POP'!I$45)+SUM('测算-京东自营'!I$46)+SUM('测算-达播'!I$46)+SUM('测算-私域'!I$45)+SUM('测算-外部分销'!I$45) -> 0 | I46: =SUM('测算-高个子抖音'!J$45)+SUM('测算-高个子视频号'!J$45)+SUM('测算-天猫淘宝'!J$44)+SUM('测算-拼多多'!J$45)+SUM('测算-京东POP'!J$45)+SUM('测算-京东自营'!J$46)+SUM('测算-达播'!J$46)+SUM('测算-私域'!J$45)+SUM('测算-外部分销'!J$45) -> 0 | J46: =SUM('测算-高个子抖音'!K$45)+SUM('测算-高个子视频号'!K$45)+SUM('测算-天猫淘宝'!K$44)+SUM('测算-拼多多'!K$45)+SUM('测算-京东POP'!K$45)+SUM('测算-京东自营'!K$46)+SUM('测算-达播'!K$46)+SUM('测算-私域'!K$45)+SUM('测算-外部分销'!K$45) -> 0 | K46: =SUM('测算-高个子抖音'!L$45)+SUM('测算-高个子视频号'!L$45)+SUM('测算-天猫淘宝'!L$44)+SUM('测算-拼多多'!L$45)+SUM('测算-京东POP'!L$45)+SUM('测算-京东自营'!L$46)+SUM('测算-达播'!L$46)+SUM('测算-私域'!L$45)+SUM('测算-外部分销'!L$45) -> 0 | L46: =SUM('测算-高个子抖音'!M$45)+SUM('测算-高个子视频号'!M$45)+SUM('测算-天猫淘宝'!M$44)+SUM('测算-拼多多'!M$45)+SUM('测算-京东POP'!M$45)+SUM('测算-京东自营'!M$46)+SUM('测算-达播'!M$46)+SUM('测算-私域'!M$45)+SUM('测算-外部分销'!M$45) -> 0 | M46: =SUM('测算-高个子抖音'!N$45)+SUM('测算-高个子视频号'!N$45)+SUM('测算-天猫淘宝'!N$44)+SUM('测算-拼多多'!N$45)+SUM('测算-京东POP'!N$45)+SUM('测算-京东自营'!N$46)+SUM('测算-达播'!N$46)+SUM('测算-私域'!N$45)+SUM('测算-外部分销'!N$45) -> 0 | N46: =SUM('测算-高个子抖音'!O$45)+SUM('测算-高个子视频号'!O$45)+SUM('测算-天猫淘宝'!O$44)+SUM('测算-拼多多'!O$45)+SUM('测算-京东POP'!O$45)+SUM('测算-京东自营'!O$46)+SUM('测算-达播'!O$46)+SUM('测算-私域'!O$45)+SUM('测算-外部分销'!O$45) -> 0.65003322 | O46: =SUM('测算-高个子抖音'!P$45)+SUM('测算-高个子视频号'!P$45)+SUM('测算-天猫淘宝'!P$44)+SUM('测算-拼多多'!P$45)+SUM('测算-京东POP'!P$45)+SUM('测算-京东自营'!P$46)+SUM('测算-达播'!P$46)+SUM('测算-私域'!P$45)+SUM('测算-外部分销'!P$45) -> 0.86938599 | ... S46: =SUM('测算-高个子抖音'!T$45)+SUM('测算-高个子视频号'!T$45)+SUM('测算-天猫淘宝'!T$44)+SUM('测算-拼多多'!T$45)+SUM('测算-京东POP'!T$45)+SUM('测算-京东自营'!T$46)+SUM('测算-达播'!T$46)+SUM('测算-私域'!T$45)+SUM('测算-外部分销'!T$45) -> 1.2305156 | U46: =SUM('测算-高个子抖音'!V$45)+SUM('测算-高个子视频号'!V$45)+SUM('测算-天猫淘宝'!V$44)+SUM('测算-拼多多'!V$45)+SUM('测算-京东POP'!V$45)+SUM('测算-京东自营'!V$46)+SUM('测算-达播'!V$46)+SUM('测算-私域'!V$45)+SUM('测算-外部分销'!V$45) -> 6.4829444 | V46: =SUM('测算-高个子抖音'!W$45)+SUM('测算-高个子视频号'!W$45)+SUM('测算-天猫淘宝'!W$44)+SUM('测算-拼多多'!W$45)+SUM('测算-京东POP'!W$45)+SUM('测算-京东自营'!W$46)+SUM('测算-达播'!W$46)+SUM('测算-私域'!W$45)+SUM('测算-外部分销'!W$45) -> 6.4829444
B47: 渠道贡献利润 | E47: 毛利-销售费用 | F47: 公式计算 | H47: =H9-H18 -> 192.34846 | I47: =I9-I18 -> 111.78168 | J47: =J9-J18 -> -86.347656 | K47: =K9-K18 -> 178.03118 | L47: =L9-L18 -> 187.97913 | M47: =M9-M18 -> 131.41367 | N47: =N9-N18 -> 46.698391 | O47: =O9-O18 -> 71.169848 | ... S47: =S9-S18 -> 116.0496 | U47: =SUM(H47:S47) -> 1302.668 | V47: =SUM(N47:S47) -> 587.46149
B48: 管理费用 | E48: 公司公共管理费用合计 | F48: 下列明细汇总 | H48: =SUM(H50:H53) -> 34.59701 | I48: =SUM(I50:I53) -> 29.895113 | J48: =SUM(J50:J53) -> 32.620716 | K48: =SUM(K50:K53) -> 37.711029 | L48: =SUM(L50:L53) -> 40.027496 | M48: =SUM(M50:M53) -> 37.20552 | N48: =SUM(N50:N53) -> 31.889739 | O48: =SUM(O50:O53) -> 34.784908 | ... S48: =SUM(S50:S53) -> 39.548731 | U48: =SUM(H48:S48) -> 437.48783 | V48: =SUM(N48:S48) -> 225.43095
C49: 人工成本
D50: 固定薪资 | E50: 5月职能人员固定薪资 | F50: 预算-经营费用 | H50: ='测算-整体经营'!I$24 -> 21.070904 | I50: ='测算-整体经营'!J$24 -> 21.310779 | J50: ='测算-整体经营'!K$24 -> 22.497768 | K50: ='测算-整体经营'!L$24 -> 24.427648 | L50: ='测算-整体经营'!M$24 -> 24.677212 | M50: ='测算-整体经营'!N$24 -> 23.144495 | N50: ='测算-整体经营'!O$24 -> 23.144495 | O50: ='测算-整体经营'!P$24 -> 23.144495 | ... S50: ='测算-整体经营'!T$24 -> 23.144495 | U50: =SUM(H50:S50) -> 275.99577 | V50: =SUM(N50:S50) -> 138.86697
D51: 分红奖金 | E51: MAX(0,渠道贡献利润)*5% | F51: 预算-经营费用 | H51: ='测算-整体经营'!I$25 -> 2.5607028 | I51: ='测算-整体经营'!J$25 -> 1.9347383 | J51: ='测算-整体经营'!K$25 -> 0 | K51: ='测算-整体经营'!L$25 -> 3.5048835 | L51: ='测算-整体经营'!M$25 -> 3.1692527 | M51: ='测算-整体经营'!N$25 -> 1.6551192 | N51: ='测算-整体经营'!O$25 -> 0.82680495 | O51: ='测算-整体经营'!P$25 -> 1.1844194 | ... S51: ='测算-整体经营'!T$25 -> 1.773175 | U51: =SUM(H51:S51) -> 21.996219 | V51: =SUM(N51:S51) -> 9.1715221
C52: 行政费用
D53: 日常费用 | E53: 总收入*行政管理费用率 | F53: 预算-经营费用 | H53: ='测算-整体经营'!I$26 -> 10.965403 | I53: ='测算-整体经营'!J$26 -> 6.6495961 | J53: ='测算-整体经营'!K$26 -> 10.122948 | K53: ='测算-整体经营'!L$26 -> 9.7784975 | L53: ='测算-整体经营'!M$26 -> 12.181032 | M53: ='测算-整体经营'!N$26 -> 12.405906 | N53: ='测算-整体经营'!O$26 -> 7.9184389 | O53: ='测算-整体经营'!P$26 -> 10.455994 | ... S53: ='测算-整体经营'!T$26 -> 14.631062 | U53: =SUM(H53:S53) -> 139.49584 | V53: =SUM(N53:S53) -> 77.392455
B54: 管理费用率 | E54: 管理费用/收入 | F54: 公式计算 | H54: =IFERROR(H48/H7,0) -> 0.03155106 | I54: =IFERROR(I48/I7,0) -> 0.044957788 | J54: =IFERROR(J48/J7,0) -> 0.032224523 | K54: =IFERROR(K48/K7,0) -> 0.038565259 | L54: =IFERROR(L48/L7,0) -> 0.032860514 | M54: =IFERROR(M48/M7,0) -> 0.029990168 | N54: =IFERROR(N48/N7,0) -> 0.040272759 | O54: =IFERROR(O48/O7,0) -> 0.033267911 | ... S54: =IFERROR(S48/S7,0) -> 0.027030664 | U54: =IFERROR(U48/U7,0) -> 0.031362071 | V54: =IFERROR(V48/V7,0) -> 0.029128285
B55: 财务费用 | E55: 收入费率测算 | F55: 预算-经营费用 | H55: =SUM(H56:H57) -> 10.862404 | I55: =SUM(I56:I57) -> 20.750061 | J55: =SUM(J56:J57) -> 7.1096058 | K55: =SUM(K56:K57) -> 7.1197431 | L55: =SUM(L56:L57) -> 9.4384265 | M55: =SUM(M56:M57) -> 20.875966 | N55: =SUM(N56:N57) -> 10.568477 | O55: =SUM(O56:O57) -> 14.107892 | ... S55: =SUM(S56:S57) -> 19.934455 | U55: =SUM(H55:S55) -> 181.24225 | V55: =SUM(N55:S55) -> 105.08605
D56: 财务费用 | H56: =SUMIFS('辅助-汇总损益长表'!$C$2:$C$242,'辅助-汇总损益长表'!$A$2:$A$242,"财务费用",'辅助-汇总损益长表'!$B$2:$B$242,H$6) -> 2.1930807 | I56: =SUMIFS('辅助-汇总损益长表'!$C$2:$C$242,'辅助-汇总损益长表'!$A$2:$A$242,"财务费用",'辅助-汇总损益长表'!$B$2:$B$242,I$6) -> 1.3299192 | J56: =SUMIFS('辅助-汇总损益长表'!$C$2:$C$242,'辅助-汇总损益长表'!$A$2:$A$242,"财务费用",'辅助-汇总损益长表'!$B$2:$B$242,J$6) -> 2.0245895 | K56: =SUMIFS('辅助-汇总损益长表'!$C$2:$C$242,'辅助-汇总损益长表'!$A$2:$A$242,"财务费用",'辅助-汇总损益长表'!$B$2:$B$242,K$6) -> 1.9556995 | L56: =SUMIFS('辅助-汇总损益长表'!$C$2:$C$242,'辅助-汇总损益长表'!$A$2:$A$242,"财务费用",'辅助-汇总损益长表'!$B$2:$B$242,L$6) -> 2.4362064 | M56: =SUMIFS('辅助-汇总损益长表'!$C$2:$C$242,'辅助-汇总损益长表'!$A$2:$A$242,"财务费用",'辅助-汇总损益长表'!$B$2:$B$242,M$6) -> 2.4811811 | N56: =SUMIFS('辅助-汇总损益长表'!$C$2:$C$242,'辅助-汇总损益长表'!$A$2:$A$242,"财务费用",'辅助-汇总损益长表'!$B$2:$B$242,N$6) -> 1.5836878 | O56: =SUMIFS('辅助-汇总损益长表'!$C$2:$C$242,'辅助-汇总损益长表'!$A$2:$A$242,"财务费用",'辅助-汇总损益长表'!$B$2:$B$242,O$6) -> 2.0911988 | ... S56: =SUMIFS('辅助-汇总损益长表'!$C$2:$C$242,'辅助-汇总损益长表'!$A$2:$A$242,"财务费用",'辅助-汇总损益长表'!$B$2:$B$242,S$6) -> 2.9262123 | U56: =SUM(H56:S56) -> 27.899167 | V56: =SUM(N56:S56) -> 15.478491
D57: 京东贷款利息 | H57: =SUM('测算-京东自营'!I$41) -> 8.6693232 | I57: =SUM('测算-京东自营'!J$41) -> 19.420141 | J57: =SUM('测算-京东自营'!K$41) -> 5.0850163 | K57: =SUM('测算-京东自营'!L$41) -> 5.1640436 | L57: =SUM('测算-京东自营'!M$41) -> 7.0022202 | M57: =SUM('测算-京东自营'!N$41) -> 18.394784 | N57: =SUM('测算-京东自营'!O$41) -> 8.9847892 | O57: =SUM('测算-京东自营'!P$41) -> 12.016693 | ... S57: =SUM('测算-京东自营'!T$41) -> 17.008243 | U57: =SUM(H57:S57) -> 153.34309 | V57: =SUM(N57:S57) -> 89.607558
B58: 税金及附加 | E58: 收入费率测算 | F58: 预算-经营费用 | H58: =SUMIFS('辅助-汇总损益长表'!$C$2:$C$242,'辅助-汇总损益长表'!$A$2:$A$242,"税金及附加",'辅助-汇总损益长表'!$B$2:$B$242,H$6) -> 3.289621 | I58: =SUMIFS('辅助-汇总损益长表'!$C$2:$C$242,'辅助-汇总损益长表'!$A$2:$A$242,"税金及附加",'辅助-汇总损益长表'!$B$2:$B$242,I$6) -> 1.9948788 | J58: =SUMIFS('辅助-汇总损益长表'!$C$2:$C$242,'辅助-汇总损益长表'!$A$2:$A$242,"税金及附加",'辅助-汇总损益长表'!$B$2:$B$242,J$6) -> 3.0368843 | K58: =SUMIFS('辅助-汇总损益长表'!$C$2:$C$242,'辅助-汇总损益长表'!$A$2:$A$242,"税金及附加",'辅助-汇总损益长表'!$B$2:$B$242,K$6) -> 2.9335493 | L58: =SUMIFS('辅助-汇总损益长表'!$C$2:$C$242,'辅助-汇总损益长表'!$A$2:$A$242,"税金及附加",'辅助-汇总损益长表'!$B$2:$B$242,L$6) -> 3.6543095 | M58: =SUMIFS('辅助-汇总损益长表'!$C$2:$C$242,'辅助-汇总损益长表'!$A$2:$A$242,"税金及附加",'辅助-汇总损益长表'!$B$2:$B$242,M$6) -> 3.7217717 | N58: =SUMIFS('辅助-汇总损益长表'!$C$2:$C$242,'辅助-汇总损益长表'!$A$2:$A$242,"税金及附加",'辅助-汇总损益长表'!$B$2:$B$242,N$6) -> 2.3755317 | O58: =SUMIFS('辅助-汇总损益长表'!$C$2:$C$242,'辅助-汇总损益长表'!$A$2:$A$242,"税金及附加",'辅助-汇总损益长表'!$B$2:$B$242,O$6) -> 3.1367982 | ... S58: =SUMIFS('辅助-汇总损益长表'!$C$2:$C$242,'辅助-汇总损益长表'!$A$2:$A$242,"税金及附加",'辅助-汇总损益长表'!$B$2:$B$242,S$6) -> 4.3893185 | U58: =SUM(H58:S58) -> 41.848751 | V58: =SUM(N58:S58) -> 23.217737
B59: 折旧摊销 | E59: 固定额预算 | F59: 预算-经营费用 | H59: =SUMIFS('辅助-汇总损益长表'!$C$2:$C$242,'辅助-汇总损益长表'!$A$2:$A$242,"折旧摊销",'辅助-汇总损益长表'!$B$2:$B$242,H$6) -> 0 | I59: =SUMIFS('辅助-汇总损益长表'!$C$2:$C$242,'辅助-汇总损益长表'!$A$2:$A$242,"折旧摊销",'辅助-汇总损益长表'!$B$2:$B$242,I$6) -> 0 | J59: =SUMIFS('辅助-汇总损益长表'!$C$2:$C$242,'辅助-汇总损益长表'!$A$2:$A$242,"折旧摊销",'辅助-汇总损益长表'!$B$2:$B$242,J$6) -> 0 | K59: =SUMIFS('辅助-汇总损益长表'!$C$2:$C$242,'辅助-汇总损益长表'!$A$2:$A$242,"折旧摊销",'辅助-汇总损益长表'!$B$2:$B$242,K$6) -> 0 | L59: =SUMIFS('辅助-汇总损益长表'!$C$2:$C$242,'辅助-汇总损益长表'!$A$2:$A$242,"折旧摊销",'辅助-汇总损益长表'!$B$2:$B$242,L$6) -> 0 | M59: =SUMIFS('辅助-汇总损益长表'!$C$2:$C$242,'辅助-汇总损益长表'!$A$2:$A$242,"折旧摊销",'辅助-汇总损益长表'!$B$2:$B$242,M$6) -> 0 | N59: =SUMIFS('辅助-汇总损益长表'!$C$2:$C$242,'辅助-汇总损益长表'!$A$2:$A$242,"折旧摊销",'辅助-汇总损益长表'!$B$2:$B$242,N$6) -> 0 | O59: =SUMIFS('辅助-汇总损益长表'!$C$2:$C$242,'辅助-汇总损益长表'!$A$2:$A$242,"折旧摊销",'辅助-汇总损益长表'!$B$2:$B$242,O$6) -> 0 | ... S59: =SUMIFS('辅助-汇总损益长表'!$C$2:$C$242,'辅助-汇总损益长表'!$A$2:$A$242,"折旧摊销",'辅助-汇总损益长表'!$B$2:$B$242,S$6) -> 0 | U59: =SUM(H59:S59) -> 0 | V59: =SUM(N59:S59) -> 0
B60: 营业利润 | E60: 渠道贡献-管理费用-财务费用-税金-折旧 | F60: 公式计算 | H60: =H47+H11+H14-H48-H55-H58-H59 -> 186.95012 | I60: =I47+I11+I14-I48-I55-I58-I59 -> 138.84866 | J60: =J47+J11+J14-J48-J55-J58-J59 -> -33.692127 | K60: =K47+K11+K14-K48-K55-K58-K59 -> 252.89642 | L60: =L47+L11+L14-L48-L55-L58-L59 -> 273.94815 | M60: =M47+M11+M14-M48-M55-M58-M59 -> 194.23482 | N60: =N47+N11+N14-N48-N55-N58-N59 -> 80.496988 | O60: =O47+O11+O14-O48-O55-O58-O59 -> 82.772037 | ... S60: =S47+S11+S14-S48-S55-S58-S59 -> 220.80171 | U60: =SUM(H60:S60) -> 1820.6621 | V60: =SUM(N60:S60) -> 807.47608
B61: 利润总额 | E61: 营业利润 | F61: 公式计算 | H61: =H60 -> 186.95012 | I61: =I60 -> 138.84866 | J61: =J60 -> -33.692127 | K61: =K60 -> 252.89642 | L61: =L60 -> 273.94815 | M61: =M60 -> 194.23482 | N61: =N60 -> 80.496988 | O61: =O60 -> 82.772037 | ... S61: =S60 -> 220.80171 | U61: =SUM(H61:S61) -> 1820.6621 | V61: =SUM(N61:S61) -> 807.47608
B62: 所得税 | E62: 利润总额为正时*所得税率 | F62: 公式计算 | H62: =MAX(0,H61)*'假设-财务口径'!$B$35 -> 46.737531 | I62: =MAX(0,I61)*'假设-财务口径'!$B$35 -> 34.712166 | J62: =MAX(0,J61)*'假设-财务口径'!$B$35 -> 0 | K62: =MAX(0,K61)*'假设-财务口径'!$B$35 -> 63.224105 | L62: =MAX(0,L61)*'假设-财务口径'!$B$35 -> 68.487037 | M62: =MAX(0,M61)*'假设-财务口径'!$B$35 -> 48.558705 | N62: =MAX(0,N61)*'假设-财务口径'!$B$35 -> 20.124247 | O62: =MAX(0,O61)*'假设-财务口径'!$B$35 -> 20.693009 | ... S62: =MAX(0,S61)*'假设-财务口径'!$B$35 -> 55.200426 | U62: =SUM(H62:S62) -> 463.58856 | V62: =SUM(N62:S62) -> 201.86902
B63: 净利润 | E63: 利润总额-所得税 | F63: 公式计算 | H63: =H61-H62 -> 140.21259 | I63: =I61-I62 -> 104.1365 | J63: =J61-J62 -> -33.692127 | K63: =K61-K62 -> 189.67232 | L63: =L61-L62 -> 205.46111 | M63: =M61-M62 -> 145.67612 | N63: =N61-N62 -> 60.372741 | O63: =O61-O62 -> 62.079028 | ... S63: =S61-S62 -> 165.60128 | U63: =SUM(H63:S63) -> 1357.0736 | V63: =SUM(N63:S63) -> 605.60706
B64: 净利率 | E64: 净利润/收入 | F64: 公式计算 | H64: =IFERROR(H63/H7,0) -> 0.12786816 | I64: =IFERROR(I63/I7,0) -> 0.15660575 | J64: =IFERROR(J63/J7,0) -> -0.033282922 | K64: =IFERROR(K63/K7,0) -> 0.19396877 | L64: =IFERROR(L63/L7,0) -> 0.16867299 | M64: =IFERROR(M63/M7,0) -> 0.11742481 | N64: =IFERROR(N63/N7,0) -> 0.076243236 | O64: =IFERROR(O63/O7,0) -> 0.059371713 | ... S64: =IFERROR(S63/S7,0) -> 0.11318473 | U64: =IFERROR(U63/U7,0) -> 0.097284162 | V64: =IFERROR(V63/V7,0) -> 0.078251434

Sheet 总表-渠道二维汇总
A1: 返回目录 | F1: 渠道总贡献（万元） | U1: 抖音（万元） | AJ1: 视频号（万元） | AY1: 天猫淘宝（万元） | BN1: 拼多多（万元） | CC1: 京东POP（万元） | CR1: 京东自营（万元） | DG1: 达播（万元） | DV1: 私域（万元） | EK1: 外部分销（万元）
E2: 费用科目 | F2: 2026-01 | G2: 2026-02 | H2: 2026-03 | I2: 2026-04 | J2: 2026-05 | K2: 2026-06 | L2: 2026-07 | M2: 2026-08 | N2: 2026-09 | O2: 2026-10 | P2: 2026-11 | Q2: 2026-12 | R2: 全年合计 | S2: 中期合计 | U2: 2026-01 | V2: 2026-02 | W2: 2026-03 | X2: 2026-04 | Y2: 2026-05 | Z2: 2026-06 | AA2: 2026-07 | AB2: 2026-08 | AC2: 2026-09 | AD2: 2026-10 | AE2: 2026-11 | AF2: 2026-12 | AG2: 全年合计 | AH2: 中期合计 | AJ2: 2026-01 | AK2: 2026-02 | AL2: 2026-03 | AM2: 2026-04 | AN2: 2026-05 | AO2: 2026-06 | AP2: 2026-07 | AQ2: 2026-08 | AR2: 2026-09 | AS2: 2026-10 | AT2: 2026-11 | AU2: 2026-12 | AV2: 全年合计 | AW2: 中期合计 | AY2: 2026-01 | AZ2: 2026-02 | BA2: 2026-03 | BB2: 2026-04 | BC2: 2026-05 | BD2: 2026-06 | BE2: 2026-07 | BF2: 2026-08 | BG2: 2026-09 | BH2: 2026-10 | BI2: 2026-11 | BJ2: 2026-12 | BK2: 全年合计 | BL2: 中期合计 | BN2: 2026-01 | BO2: 2026-02 | BP2: 2026-03 | BQ2: 2026-04 | BR2: 2026-05 | BS2: 2026-06 | BT2: 2026-07 | BU2: 2026-08 | BV2: 2026-09 | BW2: 2026-10 | BX2: 2026-11 | BY2: 2026-12 | BZ2: 全年合计 | CA2: 中期合计 | CC2: 2026-01 | CD2: 2026-02 | CE2: 2026-03 | CF2: 2026-04 | CG2: 2026-05 | CH2: 2026-06 | CI2: 2026-07 | CJ2: 2026-08 | CK2: 2026-09 | CL2: 2026-10 | CM2: 2026-11 | CN2: 2026-12 | CO2: 全年合计 | CP2: 中期合计 | CR2: 2026-01 | CS2: 2026-02 | CT2: 2026-03 | CU2: 2026-04 | CV2: 2026-05 | CW2: 2026-06 | CX2: 2026-07 | CY2: 2026-08 | CZ2: 2026-09 | DA2: 2026-10 | DB2: 2026-11 | DC2: 2026-12 | DD2: 全年合计 | DE2: 中期合计 | DG2: 2026-01 | DH2: 2026-02 | DI2: 2026-03 | DJ2: 2026-04 | DK2: 2026-05 | DL2: 2026-06 | DM2: 2026-07 | DN2: 2026-08 | DO2: 2026-09 | DP2: 2026-10 | DQ2: 2026-11 | DR2: 2026-12 | DS2: 全年合计 | DT2: 中期合计 | DV2: 2026-01 | DW2: 2026-02 | DX2: 2026-03 | DY2: 2026-04 | DZ2: 2026-05 | EA2: 2026-06 | EB2: 2026-07 | EC2: 2026-08 | ED2: 2026-09 | EE2: 2026-10 | EF2: 2026-11 | EG2: 2026-12 | EH2: 全年合计 | EI2: 中期合计 | EK2: 2026-01 | EL2: 2026-02 | EM2: 2026-03 | EN2: 2026-04 | EO2: 2026-05 | EP2: 2026-06 | EQ2: 2026-07 | ER2: 2026-08 | ES2: 2026-09 | ET2: 2026-10 | EU2: 2026-11 | EV2: 2026-12 | EW2: 全年合计 | EX2: 中期合计
B3: 主营业务收入 | F3: =SUM(U3,AJ3,AY3,BN3,CC3,CR3,DG3,DV3,EK3) -> 1096.5403 | G3: =SUM(V3,AK3,AZ3,BO3,CD3,CS3,DH3,DW3,EL3) -> 664.95961 | H3: =SUM(W3,AL3,BA3,BP3,CE3,CT3,DI3,DX3,EM3) -> 1012.2948 | I3: =SUM(X3,AM3,BB3,BQ3,CF3,CU3,DJ3,DY3,EN3) -> 977.84975 | J3: =SUM(Y3,AN3,BC3,BR3,CG3,CV3,DK3,DZ3,EO3) -> 1218.1032 | K3: =SUM(Z3,AO3,BD3,BS3,CH3,CW3,DL3,EA3,EP3) -> 1240.5906 | L3: =SUM(AA3,AP3,BE3,BT3,CI3,CX3,DM3,EB3,EQ3) -> 791.84389 | M3: =SUM(AB3,AQ3,BF3,BU3,CJ3,CY3,DN3,EC3,ER3) -> 1045.5994 | ... Q3: =SUM(AF3,AU3,BJ3,BY3,CN3,DC3,DR3,EG3,EV3) -> 1463.1062 | R3: =SUM(F3:Q3) -> 13949.584 | S3: =SUM(L3:Q3) -> 7739.2455 | U3: ='测算-高个子抖音'!I$8 -> 412.73609 | V3: ='测算-高个子抖音'!J$8 -> 236.30884 | W3: ='测算-高个子抖音'!K$8 -> 480.96785 | X3: ='测算-高个子抖音'!L$8 -> 290.19738 | Y3: ='测算-高个子抖音'!M$8 -> 383.28089 | Z3: ='测算-高个子抖音'!N$8 -> 271.5265 | AA3: ='测算-高个子抖音'!O$8 -> 187.83606 | AB3: ='测算-高个子抖音'!P$8 -> 251.22106 | ... AF3: ='测算-高个子抖音'!T$8 -> 355.57443 | AG3: ='测算-高个子抖音'!V$8 -> 3948.3537 | AH3: ='测算-高个子抖音'!W$8 -> 1873.3361 | AJ3: ='测算-高个子视频号'!I$8 -> 15.6332 | AK3: ='测算-高个子视频号'!J$8 -> 5.3377 | AL3: ='测算-高个子视频号'!K$8 -> 11.32825 | AM3: ='测算-高个子视频号'!L$8 -> 7.4995 | AN3: ='测算-高个子视频号'!M$8 -> 67.386525 | AO3: ='测算-高个子视频号'!N$8 -> 70.535852 | AP3: ='测算-高个子视频号'!O$8 -> 52.87565 | AQ3: ='测算-高个子视频号'!P$8 -> 70.718462 | ... AU3: ='测算-高个子视频号'!T$8 -> 100.09382 | AV3: ='测算-高个子视频号'!V$8 -> 705.06316 | AW3: ='测算-高个子视频号'!W$8 -> 527.34213 | AY3: ='测算-天猫淘宝'!I$7 -> 27.701168 | AZ3: ='测算-天猫淘宝'!J$7 -> 14.251386 | BA3: ='测算-天猫淘宝'!K$7 -> 32.562117 | BB3: ='测算-天猫淘宝'!L$7 -> 34.249649 | BC3: ='测算-天猫淘宝'!M$7 -> 32.59645 | BD3: ='测算-天猫淘宝'!N$7 -> 26.272108 | BE3: ='测算-天猫淘宝'!O$7 -> 24.189839 | BF3: ='测算-天猫淘宝'!P$7 -> 32.352665 | ... BJ3: ='测算-天猫淘宝'!T$7 -> 45.791464 | BK3: ='测算-天猫淘宝'!V$7 -> 408.88421 | BL3: ='测算-天猫淘宝'!W$7 -> 241.25133 | BN3: ='测算-拼多多'!I$8 -> 0.154536 | BO3: ='测算-拼多多'!J$8 -> 0.276269 | BP3: ='测算-拼多多'!K$8 -> 0.366398 | BQ3: ='测算-拼多多'!L$8 -> 0.117881 | BR3: ='测算-拼多多'!M$8 -> 0.451221 | BS3: ='测算-拼多多'!N$8 -> 4.910275 | BT3: ='测算-拼多多'!O$8 -> 2.9054295 | BU3: ='测算-拼多多'!P$8 -> 3.8858625 | ... BY3: ='测算-拼多多'!T$8 -> 5.49999 | BZ3: ='测算-拼多多'!V$8 -> 35.253158 | CA3: ='测算-拼多多'!W$8 -> 28.976578 | CC3: ='测算-京东POP'!I$8 -> 13.6692 | CD3: ='测算-京东POP'!J$8 -> 8.572073 | CE3: ='测算-京东POP'!K$8 -> 23.263656 | CF3: ='测算-京东POP'!L$8 -> 19.4663 | CG3: ='测算-京东POP'!M$8 -> 19.221455 | CH3: ='测算-京东POP'!N$8 -> 16.670737 | CI3: ='测算-京东POP'!O$8 -> 25.234315 | CJ3: ='测算-京东POP'!P$8 -> 33.749598 | ... CN3: ='测算-京东POP'!T$8 -> 47.768662 | CO3: ='测算-京东POP'!V$8 -> 352.53158 | CP3: ='测算-京东POP'!W$8 -> 251.66816 | CR3: ='测算-京东自营'!I$7 -> 400.66294 | CS3: ='测算-京东自营'!J$7 -> 301.1688 | CT3: ='测算-京东自营'!K$7 -> 40.52241 | CU3: ='测算-京东自营'!L$7 -> 438.91121 | CV3: ='测算-京东自营'!M$7 -> 446.22897 | CW3: ='测算-京东自营'!N$7 -> 660.27604 | CX3: ='测算-京东自营'!O$7 -> 322.50669 | CY3: ='测算-京东自营'!P$7 -> 431.33611 | ... DC3: ='测算-京东自营'!T$7 -> 610.50649 | DD3: ='测算-京东自营'!V$7 -> 5504.2105 | DE3: ='测算-京东自营'!W$7 -> 3216.4402 | DG3: ='测算-达播'!I$8 -> 51.673564 | DH3: ='测算-达播'!J$8 -> 4.2376 | DI3: ='测算-达播'!K$8 -> 190.03228 | DJ3: ='测算-达播'!L$8 -> 37.810497 | DK3: ='测算-达播'!M$8 -> 81.138963 | DL3: ='测算-达播'!N$8 -> 27.381935 | DM3: ='测算-达播'!O$8 -> 86.671095 | DN3: ='测算-达播'!P$8 -> 115.91813 | ... DR3: ='测算-达播'!T$8 -> 164.06874 | DS3: ='测算-达播'!V$8 -> 1256.6674 | DT3: ='测算-达播'!W$8 -> 864.39259 | DV3: ='测算-私域'!I$8 -> 24.7803 | DW3: ='测算-私域'!J$8 -> 7.8601 | DX3: ='测算-私域'!K$8 -> 26.021881 | DY3: ='测算-私域'!L$8 -> 17.22148 | DZ3: ='测算-私域'!M$8 -> 18.57858 | EA3: ='测算-私域'!N$8 -> 20.1019 | EB3: ='测算-私域'!O$8 -> 35.9514 | EC3: ='测算-私域'!P$8 -> 34.632075 | ... EG3: ='测算-私域'!T$8 -> 32.198575 | EH3: ='测算-私域'!V$8 -> 315.10419 | EI3: ='测算-私域'!W$8 -> 200.53995 | EK3: ='测算-外部分销'!I$8 -> 149.52933 | EL3: ='测算-外部分销'!J$8 -> 86.946838 | EM3: ='测算-外部分销'!K$8 -> 207.22994 | EN3: ='测算-外部分销'!L$8 -> 132.37585 | EO3: ='测算-外部分销'!M$8 -> 169.22013 | EP3: ='测算-外部分销'!N$8 -> 142.91523 | EQ3: ='测算-外部分销'!O$8 -> 53.67342 | ER3: ='测算-外部分销'!P$8 -> 71.785438 | ... EV3: ='测算-外部分销'!T$8 -> 101.60401 | EW3: ='测算-外部分销'!V$8 -> 1423.5158 | EX3: ='测算-外部分销'!W$8 -> 535.29849
B4: 主营业务成本 | F4: =SUM(U4,AJ4,AY4,BN4,CC4,CR4,DG4,DV4,EK4) -> 413.97462 | G4: =SUM(V4,AK4,AZ4,BO4,CD4,CS4,DH4,DW4,EL4) -> 245.01229 | H4: =SUM(W4,AL4,BA4,BP4,CE4,CT4,DI4,DX4,EM4) -> 437.01891 | I4: =SUM(X4,AM4,BB4,BQ4,CF4,CU4,DJ4,DY4,EN4) -> 367.20972 | J4: =SUM(Y4,AN4,BC4,BR4,CG4,CV4,DK4,DZ4,EO4) -> 463.40024 | K4: =SUM(Z4,AO4,BD4,BS4,CH4,CW4,DL4,EA4,EP4) -> 451.4047 | L4: =SUM(AA4,AP4,BE4,BT4,CI4,CX4,DM4,EB4,EQ4) -> 284.77935 | M4: =SUM(AB4,AQ4,BF4,BU4,CJ4,CY4,DN4,EC4,ER4) -> 375.49932 | ... Q4: =SUM(AF4,AU4,BJ4,BY4,CN4,DC4,DR4,EG4,EV4) -> 524.78257 | R4: =SUM(F4:Q4) -> 5155.1438 | S4: =SUM(L4:Q4) -> 2777.1234 | U4: ='测算-高个子抖音'!I$19 -> 127.68844 | V4: ='测算-高个子抖音'!J$19 -> 73.107027 | W4: ='测算-高个子抖音'!K$19 -> 148.79735 | X4: ='测算-高个子抖音'!L$19 -> 89.77856 | Y4: ='测算-高个子抖音'!M$19 -> 118.57587 | Z4: ='测算-高个子抖音'!N$19 -> 84.002336 | AA4: ='测算-高个子抖音'!O$19 -> 58.110967 | AB4: ='测算-高个子抖音'!P$19 -> 77.72043 | ... AF4: ='测算-高个子抖音'!T$19 -> 110.0043 | AG4: ='测算-高个子抖音'!V$19 -> 1221.5048 | AH4: ='测算-高个子抖音'!W$19 -> 579.55527 | AJ4: ='测算-高个子视频号'!I$19 -> 4.8364536 | AK4: ='测算-高个子视频号'!J$19 -> 1.6513279 | AL4: ='测算-高个子视频号'!K$19 -> 3.5046283 | AM4: ='测算-高个子视频号'!L$19 -> 2.3201254 | AN4: ='测算-高个子视频号'!M$19 -> 20.847415 | AO4: ='测算-高个子视频号'!N$19 -> 21.821724 | AP4: ='测算-高个子视频号'!O$19 -> 16.358176 | AQ4: ='测算-高个子视频号'!P$19 -> 21.878218 | ... AU4: ='测算-高个子视频号'!T$19 -> 30.966094 | AV4: ='测算-高个子视频号'!V$19 -> 218.12587 | AW4: ='测算-高个子视频号'!W$19 -> 163.14419 | AY4: ='测算-天猫淘宝'!I$18 -> 8.5813401 | AZ4: ='测算-天猫淘宝'!J$18 -> 4.4148315 | BA4: ='测算-天猫淘宝'!K$18 -> 10.087178 | BB4: ='测算-天猫淘宝'!L$18 -> 10.609946 | BC4: ='测算-天猫淘宝'!M$18 -> 10.097813 | BD4: ='测算-天猫淘宝'!N$18 -> 8.1386422 | BE4: ='测算-天猫淘宝'!O$18 -> 7.4935913 | BF4: ='测算-天猫淘宝'!P$18 -> 10.022293 | ... BJ4: ='测算-天猫淘宝'!T$18 -> 14.185399 | BK4: ='测算-天猫淘宝'!V$18 -> 126.66522 | BL4: ='测算-天猫淘宝'!W$18 -> 74.735467 | BN4: ='测算-拼多多'!I$19 -> 0.047808907 | BO4: ='测算-拼多多'!J$19 -> 0.085469527 | BP4: ='测算-拼多多'!K$19 -> 0.1133528 | BQ4: ='测算-拼多多'!L$19 -> 0.036468925 | BR4: ='测算-拼多多'!M$19 -> 0.13959455 | BS4: ='测算-拼多多'!N$19 -> 1.5190951 | BT4: ='测算-拼多多'!O$19 -> 0.89885469 | BU4: ='测算-拼多多'!P$19 -> 1.2021719 | ... BY4: ='测算-拼多多'!T$19 -> 1.7015356 | BZ4: ='测算-拼多多'!V$19 -> 10.906293 | CA4: ='测算-拼多多'!W$19 -> 8.9645035 | CC4: ='测算-京东POP'!I$19 -> 4.2288496 | CD4: ='测算-京东POP'!J$19 -> 2.651948 | CE4: ='测算-京东POP'!K$19 -> 7.197093 | CF4: ='测算-京东POP'!L$19 -> 6.0223024 | CG4: ='测算-京东POP'!M$19 -> 5.9465545 | CH4: ='测算-京东POP'!N$19 -> 5.1574372 | CI4: ='测算-京东POP'!O$19 -> 7.8067571 | CJ4: ='测算-京东POP'!P$19 -> 10.441136 | ... CN4: ='测算-京东POP'!T$19 -> 14.778223 | CO4: ='测算-京东POP'!V$19 -> 109.06293 | CP4: ='测算-京东POP'!W$19 -> 77.858748 | CR4: ='测算-京东自营'!I$18 -> 124.11841 | CS4: ='测算-京东自营'!J$18 -> 93.296857 | CT4: ='测算-京东自营'!K$18 -> 12.553138 | CU4: ='测算-京东自营'!L$18 -> 135.96706 | CV4: ='测算-京东自营'!M$18 -> 138.23397 | CW4: ='测算-京东自营'!N$18 -> 204.54203 | CX4: ='测算-京东自营'!O$18 -> 99.906963 | CY4: ='测算-京东自营'!P$18 -> 133.62042 | ... DC4: ='测算-京东自营'!T$18 -> 189.12429 | DD4: ='测算-京东自营'!V$18 -> 1705.1087 | DE4: ='测算-京东自营'!W$18 -> 996.39722 | DG4: ='测算-达播'!I$20 -> 20.120115 | DH4: ='测算-达播'!J$20 -> 1.6499926 | DI4: ='测算-达播'!K$20 -> 73.992791 | DJ4: ='测算-达播'!L$20 -> 14.722258 | DK4: ='测算-达播'!M$20 -> 31.593045 | DL4: ='测算-达播'!N$20 -> 10.661693 | DM4: ='测算-达播'!O$20 -> 33.747089 | DN4: ='测算-达播'!P$20 -> 45.134996 | ... DR4: ='测算-达播'!T$20 -> 63.883378 | DS4: ='测算-达播'!V$20 -> 489.30808 | DT4: ='测算-达播'!W$20 -> 336.56819 | DV4: ='测算-私域'!I$19 -> 0 | DW4: ='测算-私域'!J$19 -> 0 | DX4: ='测算-私域'!K$19 -> 0 | DY4: ='测算-私域'!L$19 -> 0 | DZ4: ='测算-私域'!M$19 -> 0 | EA4: ='测算-私域'!N$19 -> 0 | EB4: ='测算-私域'!O$19 -> 14.265524 | EC4: ='测算-私域'!P$19 -> 13.700989 | ... EG4: ='测算-私域'!T$19 -> 12.69878 | EH4: ='测算-私域'!V$19 -> 79.221018 | EI4: ='测算-私域'!W$19 -> 79.221018 | EK4: ='测算-外部分销'!I$19 -> 124.3532 | EL4: ='测算-外部分销'!J$19 -> 68.154837 | EM4: ='测算-外部分销'!K$19 -> 180.77338 | EN4: ='测算-外部分销'!L$19 -> 107.753 | EO4: ='测算-外部分销'!M$19 -> 137.96598 | EP4: ='测算-外部分销'!N$19 -> 115.56174 | EQ4: ='测算-外部分销'!O$19 -> 46.191432 | ER4: ='测算-外部分销'!P$19 -> 61.778664 | ... EV4: ='测算-外部分销'!T$19 -> 87.440571 | EW4: ='测算-外部分销'!V$19 -> 1195.2409 | EX4: ='测算-外部分销'!W$19 -> 460.67875
B5: 毛利 | F5: =F3-F4 -> 682.56571 | G5: =G3-G4 -> 419.94732 | H5: =H3-H4 -> 575.27586 | I5: =I3-I4 -> 610.64003 | J5: =J3-J4 -> 754.70294 | K5: =K3-K4 -> 789.18587 | L5: =L3-L4 -> 507.06454 | M5: =M3-M4 -> 670.10008 | ... Q5: =Q3-Q4 -> 938.3236 | R5: =SUM(F5:Q5) -> 8794.4399 | S5: =SUM(L5:Q5) -> 4962.1222 | U5: =U3-U4 -> 285.04765 | V5: =V3-V4 -> 163.20182 | W5: =W3-W4 -> 332.1705 | X5: =X3-X4 -> 200.41882 | Y5: =Y3-Y4 -> 264.70502 | Z5: =Z3-Z4 -> 187.52416 | AA5: =AA3-AA4 -> 129.72509 | AB5: =AB3-AB4 -> 173.50063 | ... AH5: =AH3-AH4 -> 1293.7809 | AJ5: =AJ3-AJ4 -> 10.796746 | AK5: =AK3-AK4 -> 3.6863721 | AL5: =AL3-AL4 -> 7.8236217 | AM5: =AM3-AM4 -> 5.1793746 | AN5: =AN3-AN4 -> 46.53911 | AO5: =AO3-AO4 -> 48.714128 | AP5: =AP3-AP4 -> 36.517474 | AQ5: =AQ3-AQ4 -> 48.840244 | ... AW5: =AW3-AW4 -> 364.19794 | AY5: =AY3-AY4 -> 19.119828 | AZ5: =AZ3-AZ4 -> 9.8365545 | BA5: =BA3-BA4 -> 22.474939 | BB5: =BB3-BB4 -> 23.639703 | BC5: =BC3-BC4 -> 22.498637 | BD5: =BD3-BD4 -> 18.133466 | BE5: =BE3-BE4 -> 16.696247 | BF5: =BF3-BF4 -> 22.330372 | ... BL5: =BL3-BL4 -> 166.51587 | BN5: =BN3-BN4 -> 0.10672709 | BO5: =BO3-BO4 -> 0.19079947 | BP5: =BP3-BP4 -> 0.2530452 | BQ5: =BQ3-BQ4 -> 0.081412075 | BR5: =BR3-BR4 -> 0.31162645 | BS5: =BS3-BS4 -> 3.3911799 | BT5: =BT3-BT4 -> 2.0065748 | BU5: =BU3-BU4 -> 2.6836906 | ... CA5: =CA3-CA4 -> 20.012074 | CC5: =CC3-CC4 -> 9.4403504 | CD5: =CD3-CD4 -> 5.920125 | CE5: =CE3-CE4 -> 16.066563 | CF5: =CF3-CF4 -> 13.443998 | CG5: =CG3-CG4 -> 13.2749 | CH5: =CH3-CH4 -> 11.5133 | CI5: =CI3-CI4 -> 17.427558 | CJ5: =CJ3-CJ4 -> 23.308462 | ... CP5: =CP3-CP4 -> 173.80941 | CR5: =CR3-CR4 -> 276.54453 | CS5: =CS3-CS4 -> 207.87194 | CT5: =CT3-CT4 -> 27.969272 | CU5: =CU3-CU4 -> 302.94415 | CV5: =CV3-CV4 -> 307.995 | CW5: =CW3-CW4 -> 455.734 | CX5: =CX3-CX4 -> 222.59972 | CY5: =CY3-CY4 -> 297.71568 | ... DE5: =DE3-DE4 -> 2220.0429 | DG5: =DG3-DG4 -> 31.553449 | DH5: =DH3-DH4 -> 2.5876074 | DI5: =DI3-DI4 -> 116.03949 | DJ5: =DJ3-DJ4 -> 23.088239 | DK5: =DK3-DK4 -> 49.545918 | DL5: =DL3-DL4 -> 16.720242 | DM5: =DM3-DM4 -> 52.924006 | DN5: =DN3-DN4 -> 70.783136 | ... DT5: =DT3-DT4 -> 527.8244 | DV5: =DV3-DV4 -> 24.7803 | DW5: =DW3-DW4 -> 7.8601 | DX5: =DX3-DX4 -> 26.021881 | DY5: =DY3-DY4 -> 17.22148 | DZ5: =DZ3-DZ4 -> 18.57858 | EA5: =EA3-EA4 -> 20.1019 | EB5: =EB3-EB4 -> 21.685876 | EC5: =EC3-EC4 -> 20.931086 | ... EI5: =EI3-EI4 -> 121.31893 | EK5: =EK3-EK4 -> 25.176132 | EL5: =EL3-EL4 -> 18.792001 | EM5: =EM3-EM4 -> 26.456553 | EN5: =EN3-EN4 -> 24.622848 | EO5: =EO3-EO4 -> 31.254152 | EP5: =EP3-EP4 -> 27.353486 | EQ5: =EQ3-EQ4 -> 7.4819881 | ER5: =ER3-ER4 -> 10.006774 | ... EX5: =EX3-EX4 -> 74.619746
B6: 毛利率 | F6: =IFERROR(F5/F3,0) -> 0.62247205 | G6: =IFERROR(G5/G3,0) -> 0.63153809 | H6: =IFERROR(H5/H3,0) -> 0.56828888 | I6: =IFERROR(I5/I3,0) -> 0.62447224 | J6: =IFERROR(J5/J3,0) -> 0.61957226 | K6: =IFERROR(K5/K3,0) -> 0.63613725 | L6: =IFERROR(L5/L3,0) -> 0.64035922 | M6: =IFERROR(M5/M3,0) -> 0.6408765 | ... S6: =IFERROR(S5/S3,0) -> 0.64116356 | U6: =IFERROR(U5/U3,0) -> 0.69062933 | V6: =IFERROR(V5/V3,0) -> 0.69062933 | W6: =IFERROR(W5/W3,0) -> 0.69062933 | X6: =IFERROR(X5/X3,0) -> 0.69062933 | Y6: =IFERROR(Y5/Y3,0) -> 0.69062933 | Z6: =IFERROR(Z5/Z3,0) -> 0.69062933 | AA6: =IFERROR(AA5/AA3,0) -> 0.69062933 | AB6: =IFERROR(AB5/AB3,0) -> 0.69062933 | ... AH6: =IFERROR(AH5/AH3,0) -> 0.69062933 | AJ6: =IFERROR(AJ5/AJ3,0) -> 0.69062933 | AK6: =IFERROR(AK5/AK3,0) -> 0.69062933 | AL6: =IFERROR(AL5/AL3,0) -> 0.69062933 | AM6: =IFERROR(AM5/AM3,0) -> 0.69062933 | AN6: =IFERROR(AN5/AN3,0) -> 0.69062933 | AO6: =IFERROR(AO5/AO3,0) -> 0.69062933 | AP6: =IFERROR(AP5/AP3,0) -> 0.69062933 | AQ6: =IFERROR(AQ5/AQ3,0) -> 0.69062933 | ... AW6: =IFERROR(AW5/AW3,0) -> 0.69062933 | AY6: =IFERROR(AY5/AY3,0) -> 0.69021739 | AZ6: =IFERROR(AZ5/AZ3,0) -> 0.69021739 | BA6: =IFERROR(BA5/BA3,0) -> 0.69021739 | BB6: =IFERROR(BB5/BB3,0) -> 0.69021739 | BC6: =IFERROR(BC5/BC3,0) -> 0.69021739 | BD6: =IFERROR(BD5/BD3,0) -> 0.69021739 | BE6: =IFERROR(BE5/BE3,0) -> 0.69021739 | BF6: =IFERROR(BF5/BF3,0) -> 0.69021739 | ... BL6: =IFERROR(BL5/BL3,0) -> 0.69021739 | BN6: =IFERROR(BN5/BN3,0) -> 0.69062933 | BO6: =IFERROR(BO5/BO3,0) -> 0.69062933 | BP6: =IFERROR(BP5/BP3,0) -> 0.69062933 | BQ6: =IFERROR(BQ5/BQ3,0) -> 0.69062933 | BR6: =IFERROR(BR5/BR3,0) -> 0.69062933 | BS6: =IFERROR(BS5/BS3,0) -> 0.69062933 | BT6: =IFERROR(BT5/BT3,0) -> 0.69062933 | BU6: =IFERROR(BU5/BU3,0) -> 0.69062933 | ... CA6: =IFERROR(CA5/CA3,0) -> 0.69062933 | CC6: =IFERROR(CC5/CC3,0) -> 0.69062933 | CD6: =IFERROR(CD5/CD3,0) -> 0.69062933 | CE6: =IFERROR(CE5/CE3,0) -> 0.69062933 | CF6: =IFERROR(CF5/CF3,0) -> 0.69062933 | CG6: =IFERROR(CG5/CG3,0) -> 0.69062933 | CH6: =IFERROR(CH5/CH3,0) -> 0.69062933 | CI6: =IFERROR(CI5/CI3,0) -> 0.69062933 | CJ6: =IFERROR(CJ5/CJ3,0) -> 0.69062933 | ... CP6: =IFERROR(CP5/CP3,0) -> 0.69062933 | CR6: =IFERROR(CR5/CR3,0) -> 0.69021739 | CS6: =IFERROR(CS5/CS3,0) -> 0.69021739 | CT6: =IFERROR(CT5/CT3,0) -> 0.69021739 | CU6: =IFERROR(CU5/CU3,0) -> 0.69021739 | CV6: =IFERROR(CV5/CV3,0) -> 0.69021739 | CW6: =IFERROR(CW5/CW3,0) -> 0.69021739 | CX6: =IFERROR(CX5/CX3,0) -> 0.69021739 | CY6: =IFERROR(CY5/CY3,0) -> 0.69021739 | ... DE6: =IFERROR(DE5/DE3,0) -> 0.69021739 | DG6: =IFERROR(DG5/DG3,0) -> 0.61063041 | DH6: =IFERROR(DH5/DH3,0) -> 0.61063041 | DI6: =IFERROR(DI5/DI3,0) -> 0.61063041 | DJ6: =IFERROR(DJ5/DJ3,0) -> 0.61063041 | DK6: =IFERROR(DK5/DK3,0) -> 0.61063041 | DL6: =IFERROR(DL5/DL3,0) -> 0.61063041 | DM6: =IFERROR(DM5/DM3,0) -> 0.61063041 | DN6: =IFERROR(DN5/DN3,0) -> 0.61063041 | ... DT6: =IFERROR(DT5/DT3,0) -> 0.61063041 | DV6: =IFERROR(DV5/DV3,0) -> 1 | DW6: =IFERROR(DW5/DW3,0) -> 1 | DX6: =IFERROR(DX5/DX3,0) -> 1 | DY6: =IFERROR(DY5/DY3,0) -> 1 | DZ6: =IFERROR(DZ5/DZ3,0) -> 1 | EA6: =IFERROR(EA5/EA3,0) -> 1 | EB6: =IFERROR(EB5/EB3,0) -> 0.60319977 | EC6: =IFERROR(EC5/EC3,0) -> 0.60438441 | ... EI6: =IFERROR(EI5/EI3,0) -> 0.60496142 | EK6: =IFERROR(EK5/EK3,0) -> 0.16836919 | EL6: =IFERROR(EL5/EL3,0) -> 0.21613208 | EM6: =IFERROR(EM5/EM3,0) -> 0.12766762 | EN6: =IFERROR(EN5/EN3,0) -> 0.1860071 | EO6: =IFERROR(EO5/EO3,0) -> 0.18469524 | EP6: =IFERROR(EP5/EP3,0) -> 0.19139658 | EQ6: =IFERROR(EQ5/EQ3,0) -> 0.13939839 | ER6: =IFERROR(ER5/ER3,0) -> 0.13939839 | ... EX6: =IFERROR(EX5/EX3,0) -> 0.13939839
B7: 销售费用 | F7: =SUM(U7,AJ7,AY7,BN7,CC7,CR7,DG7,DV7,EK7) -> 498.88657 | G7: =SUM(V7,AK7,AZ7,BO7,CD7,CS7,DH7,DW7,EL7) -> 327.58578 | H7: =SUM(W7,AL7,BA7,BP7,CE7,CT7,DI7,DX7,EM7) -> 661.62352 | I7: =SUM(X7,AM7,BB7,BQ7,CF7,CU7,DJ7,DY7,EN7) -> 432.60885 | J7: =SUM(Y7,AN7,BC7,BR7,CG7,CV7,DK7,DZ7,EO7) -> 566.72381 | K7: =SUM(Z7,AO7,BD7,BS7,CH7,CW7,DL7,EA7,EP7) -> 657.77219 | L7: =SUM(AA7,AP7,BE7,BT7,CI7,CX7,DM7,EB7,EQ7) -> 456.8993 | M7: =SUM(AB7,AQ7,BF7,BU7,CJ7,CY7,DN7,EC7,ER7) -> 594.29351 | ... Q7: =SUM(AF7,AU7,BJ7,BY7,CN7,DC7,DR7,EG7,EV7) -> 815.71125 | R7: =SUM(F7:Q7) -> 7485.2857 | S7: =SUM(L7:Q7) -> 4340.085 | U7: ='测算-高个子抖音'!I$20 -> 237.86509 | V7: ='测算-高个子抖音'!J$20 -> 151.88622 | W7: ='测算-高个子抖音'!K$20 -> 287.1588 | X7: ='测算-高个子抖音'!L$20 -> 177.94864 | Y7: ='测算-高个子抖音'!M$20 -> 225.70137 | Z7: ='测算-高个子抖音'!N$20 -> 143.39233 | AA7: ='测算-高个子抖音'!O$20 -> 105.8577 | AB7: ='测算-高个子抖音'!P$20 -> 137.08182 | ... AF7: ='测算-高个子抖音'!T$20 -> 183.79116 | AG7: ='测算-高个子抖音'!V$20 -> 2207.4195 | AH7: ='测算-高个子抖音'!W$20 -> 983.46707 | AJ7: ='测算-高个子视频号'!I$20 -> 17.620676 | AK7: ='测算-高个子视频号'!J$20 -> 6.2417176 | AL7: ='测算-高个子视频号'!K$20 -> 11.311506 | AM7: ='测算-高个子视频号'!L$20 -> 10.545045 | AN7: ='测算-高个子视频号'!M$20 -> 72.342122 | AO7: ='测算-高个子视频号'!N$20 -> 63.937074 | AP7: ='测算-高个子视频号'!O$20 -> 51.385125 | AQ7: ='测算-高个子视频号'!P$20 -> 64.861735 | ... AU7: ='测算-高个子视频号'!T$20 -> 87.537148 | AV7: ='测算-高个子视频号'!V$20 -> 651.0737 | AW7: ='测算-高个子视频号'!W$20 -> 469.07555 | AY7: ='测算-天猫淘宝'!I$19 -> 10.185268 | AZ7: ='测算-天猫淘宝'!J$19 -> 6.7460173 | BA7: ='测算-天猫淘宝'!K$19 -> 12.697781 | BB7: ='测算-天猫淘宝'!L$19 -> 16.690068 | BC7: ='测算-天猫淘宝'!M$19 -> 13.35027 | BD7: ='测算-天猫淘宝'!N$19 -> 12.591745 | BE7: ='测算-天猫淘宝'!O$19 -> 10.745799 | BF7: ='测算-天猫淘宝'!P$19 -> 13.916033 | ... BJ7: ='测算-天猫淘宝'!T$19 -> 19.135321 | BK7: ='测算-天猫淘宝'!V$19 -> 174.06352 | BL7: ='测算-天猫淘宝'!W$19 -> 101.80237 | BN7: ='测算-拼多多'!I$20 -> 0.062721335 | BO7: ='测算-拼多多'!J$20 -> 0.1590147 | BP7: ='测算-拼多多'!K$20 -> 0.15759852 | BQ7: ='测算-拼多多'!L$20 -> 0.032302404 | BR7: ='测算-拼多多'!M$20 -> 0.29194484 | BS7: ='测算-拼多多'!N$20 -> 1.9239377 | BT7: ='测算-拼多多'!O$20 -> 1.1379731 | BU7: ='测算-拼多多'!P$20 -> 1.5219805 | ... BY7: ='测算-拼多多'!T$20 -> 2.1541878 | BZ7: ='测算-拼多多'!V$20 -> 13.976811 | CA7: ='测算-拼多多'!W$20 -> 11.349292 | CC7: ='测算-京东POP'!I$20 -> 5.6659253 | CD7: ='测算-京东POP'!J$20 -> 4.2449911 | CE7: ='测算-京东POP'!K$20 -> 8.3678422 | CF7: ='测算-京东POP'!L$20 -> 7.0236872 | CG7: ='测算-京东POP'!M$20 -> 7.4856343 | CH7: ='测算-京东POP'!N$20 -> 7.4944361 | CI7: ='测算-京东POP'!O$20 -> 10.868216 | CJ7: ='测算-京东POP'!P$20 -> 14.184123 | ... CN7: ='测算-京东POP'!T$20 -> 19.643237 | CO7: ='测算-京东POP'!V$20 -> 144.53459 | CP7: ='测算-京东POP'!W$20 -> 104.25207 | CR7: ='测算-京东自营'!I$19 -> 200.12233 | CS7: ='测算-京东自营'!J$19 -> 146.4712 | CT7: ='测算-京东自营'!K$19 -> 267.27736 | CU7: ='测算-京东自营'!L$19 -> 193.06433 | CV7: ='测算-京东自营'!M$19 -> 211.50161 | CW7: ='测算-京东自营'!N$19 -> 406.10508 | CX7: ='测算-京东自营'!O$19 -> 201.64004 | CY7: ='测算-京东自营'!P$19 -> 267.51876 | ... DC7: ='测算-京东自营'!T$19 -> 375.97762 | DD7: ='测算-京东自营'!V$19 -> 3410.0639 | DE7: ='测算-京东自营'!W$19 -> 1985.522 | DG7: ='测算-达播'!I$21 -> 19.24395 | DH7: ='测算-达播'!J$21 -> 5.5882433 | DI7: ='测算-达播'!K$21 -> 62.786935 | DJ7: ='测算-达播'!L$21 -> 17.792034 | DK7: ='测算-达播'!M$21 -> 26.062859 | DL7: ='测算-达播'!N$21 -> 12.194093 | DM7: ='测算-达播'!O$21 -> 58.070818 | DN7: ='测算-达播'!P$21 -> 76.294268 | ... DR7: ='测算-达播'!T$21 -> 106.29629 | DS7: ='测算-达播'!V$21 -> 706.66304 | DT7: ='测算-达播'!W$21 -> 562.99492 | DV7: ='测算-私域'!I$20 -> 0 | DW7: ='测算-私域'!J$20 -> 0 | DX7: ='测算-私域'!K$20 -> 0 | DY7: ='测算-私域'!L$20 -> 0 | DZ7: ='测算-私域'!M$20 -> 0 | EA7: ='测算-私域'!N$20 -> 0 | EB7: ='测算-私域'!O$20 -> 13.652883 | EC7: ='测算-私域'!P$20 -> 14.179217 | ... EG7: ='测算-私域'!T$20 -> 14.47363 | EH7: ='测算-私域'!V$20 -> 86.308921 | EI7: ='测算-私域'!W$20 -> 86.308921 | EK7: ='测算-外部分销'!I$20 -> 8.1206105 | EL7: ='测算-外部分销'!J$20 -> 6.2483694 | EM7: ='测算-外部分销'!K$20 -> 11.865694 | EN7: ='测算-外部分销'!L$20 -> 9.512743 | EO7: ='测算-外部分销'!M$20 -> 9.988013 | EP7: ='测算-外部分销'!N$20 -> 10.133491 | EQ7: ='测算-外部分销'!O$20 -> 3.5407512 | ER7: ='测算-外部分销'!P$20 -> 4.7355726 | ... EV7: ='测算-外部分销'!T$20 -> 6.7026566 | EW7: ='测算-外部分销'!V$20 -> 91.181722 | EX7: ='测算-外部分销'!W$20 -> 35.312801
B8: 销售费用率 | F8: =IFERROR(F7/F3,0) -> 0.45496418 | G8: =IFERROR(G7/G3,0) -> 0.49264011 | H8: =IFERROR(H7/H3,0) -> 0.65358781 | I8: =IFERROR(I7/I3,0) -> 0.44240831 | J8: =IFERROR(J7/J3,0) -> 0.46525107 | K8: =IFERROR(K7/K3,0) -> 0.53020893 | L8: =IFERROR(L7/L3,0) -> 0.57700679 | M8: =IFERROR(M7/M3,0) -> 0.56837591 | ... S8: =IFERROR(S7/S3,0) -> 0.56078916 | U8: =IFERROR(U7/U3,0) -> 0.5763128 | V8: =IFERROR(V7/V3,0) -> 0.64274455 | W8: =IFERROR(W7/W3,0) -> 0.59704365 | X8: =IFERROR(X7/X3,0) -> 0.61319863 | Y8: =IFERROR(Y7/Y3,0) -> 0.58886673 | Z8: =IFERROR(Z7/Z3,0) -> 0.52809701 | AA8: =IFERROR(AA7/AA3,0) -> 0.56356431 | AB8: =IFERROR(AB7/AB3,0) -> 0.54566212 | ... AH8: =IFERROR(AH7/AH3,0) -> 0.52498164 | AJ8: =IFERROR(AJ7/AJ3,0) -> 1.1271317 | AK8: =IFERROR(AK7/AK3,0) -> 1.1693646 | AL8: =IFERROR(AL7/AL3,0) -> 0.9985219 | AM8: =IFERROR(AM7/AM3,0) -> 1.4060998 | AN8: =IFERROR(AN7/AN3,0) -> 1.0735399 | AO8: =IFERROR(AO7/AO3,0) -> 0.90644789 | AP8: =IFERROR(AP7/AP3,0) -> 0.97181075 | AQ8: =IFERROR(AQ7/AQ3,0) -> 0.91718249 | ... AW8: =IFERROR(AW7/AW3,0) -> 0.88950897 | AY8: =IFERROR(AY7/AY3,0) -> 0.3676837 | AZ8: =IFERROR(AZ7/AZ3,0) -> 0.47335868 | BA8: =IFERROR(BA7/BA3,0) -> 0.38995564 | BB8: =IFERROR(BB7/BB3,0) -> 0.48730625 | BC8: =IFERROR(BC7/BC3,0) -> 0.40956207 | BD8: =IFERROR(BD7/BD3,0) -> 0.47928187 | BE8: =IFERROR(BE7/BE3,0) -> 0.44422779 | BF8: =IFERROR(BF7/BF3,0) -> 0.4301356 | ... BL8: =IFERROR(BL7/BL3,0) -> 0.4219764 | BN8: =IFERROR(BN7/BN3,0) -> 0.40586876 | BO8: =IFERROR(BO7/BO3,0) -> 0.57557923 | BP8: =IFERROR(BP7/BP3,0) -> 0.4301293 | BQ8: =IFERROR(BQ7/BQ3,0) -> 0.27402553 | BR8: =IFERROR(BR7/BR3,0) -> 0.64701075 | BS8: =IFERROR(BS7/BS3,0) -> 0.39181872 | BT8: =IFERROR(BT7/BT3,0) -> 0.39167122 | BU8: =IFERROR(BU7/BU3,0) -> 0.39167122 | ... CA8: =IFERROR(CA7/CA3,0) -> 0.39167122 | CC8: =IFERROR(CC7/CC3,0) -> 0.41450306 | CD8: =IFERROR(CD7/CD3,0) -> 0.49521173 | CE8: =IFERROR(CE7/CE3,0) -> 0.35969592 | CF8: =IFERROR(CF7/CF3,0) -> 0.36081265 | CG8: =IFERROR(CG7/CG3,0) -> 0.3894416 | CH8: =IFERROR(CH7/CH3,0) -> 0.44955637 | CI8: =IFERROR(CI7/CI3,0) -> 0.43069195 | CJ8: =IFERROR(CJ7/CJ3,0) -> 0.42027531 | ... CP8: =IFERROR(CP7/CP3,0) -> 0.4142442 | CR8: =IFERROR(CR7/CR3,0) -> 0.49947801 | CS8: =IFERROR(CS7/CS3,0) -> 0.48634256 | CT8: =IFERROR(CT7/CT3,0) -> 6.5957914 | CU8: =IFERROR(CU7/CU3,0) -> 0.43987105 | CV8: =IFERROR(CV7/CV3,0) -> 0.47397551 | CW8: =IFERROR(CW7/CW3,0) -> 0.61505349 | CX8: =IFERROR(CX7/CX3,0) -> 0.62522747 | CY8: =IFERROR(CY7/CY3,0) -> 0.62020952 | ... DE8: =IFERROR(DE7/DE3,0) -> 0.61730419 | DG8: =IFERROR(DG7/DG3,0) -> 0.37241384 | DH8: =IFERROR(DH7/DH3,0) -> 1.3187284 | DI8: =IFERROR(DI7/DI3,0) -> 0.33040142 | DJ8: =IFERROR(DJ7/DJ3,0) -> 0.47055806 | DK8: =IFERROR(DK7/DK3,0) -> 0.32121262 | DL8: =IFERROR(DL7/DL3,0) -> 0.44533351 | DM8: =IFERROR(DM7/DM3,0) -> 0.67001366 | DN8: =IFERROR(DN7/DN3,0) -> 0.65817372 | ... DT8: =IFERROR(DT7/DT3,0) -> 0.65131854 | DV8: =IFERROR(DV7/DV3,0) -> 0 | DW8: =IFERROR(DW7/DW3,0) -> 0 | DX8: =IFERROR(DX7/DX3,0) -> 0 | DY8: =IFERROR(DY7/DY3,0) -> 0 | DZ8: =IFERROR(DZ7/DZ3,0) -> 0 | EA8: =IFERROR(EA7/EA3,0) -> 0 | EB8: =IFERROR(EB7/EB3,0) -> 0.37975943 | EC8: =IFERROR(EC7/EC3,0) -> 0.40942441 | ... EI8: =IFERROR(EI7/EI3,0) -> 0.43038268 | EK8: =IFERROR(EK7/EK3,0) -> 0.054307809 | EL8: =IFERROR(EL7/EL3,0) -> 0.071864251 | EM8: =IFERROR(EM7/EM3,0) -> 0.057258591 | EN8: =IFERROR(EN7/EN3,0) -> 0.071861619 | EO8: =IFERROR(EO7/EO3,0) -> 0.059023788 | EP8: =IFERROR(EP7/EP3,0) -> 0.070905607 | EQ8: =IFERROR(EQ7/EQ3,0) -> 0.065968429 | ER8: =IFERROR(ER7/ER3,0) -> 0.065968429 | ... EX8: =IFERROR(EX7/EX3,0) -> 0.065968429
C9: 渠道投入 | F9: =SUM(U9,AJ9,AY9,BN9,CC9,CR9,DG9,DV9,EK9) -> 412.18124 | G9: =SUM(V9,AK9,AZ9,BO9,CD9,CS9,DH9,DW9,EL9) -> 249.59394 | H9: =SUM(W9,AL9,BA9,BP9,CE9,CT9,DI9,DX9,EM9) -> 566.78644 | I9: =SUM(X9,AM9,BB9,BQ9,CF9,CU9,DJ9,DY9,EN9) -> 353.13792 | J9: =SUM(Y9,AN9,BC9,BR9,CG9,CV9,DK9,DZ9,EO9) -> 472.97887 | K9: =SUM(Z9,AO9,BD9,BS9,CH9,CW9,DL9,EA9,EP9) -> 545.4595 | L9: =SUM(AA9,AP9,BE9,BT9,CI9,CX9,DM9,EB9,EQ9) -> 343.93451 | M9: =SUM(AB9,AQ9,BF9,BU9,CJ9,CY9,DN9,EC9,ER9) -> 460.4476 | ... Q9: =SUM(AF9,AU9,BJ9,BY9,CN9,DC9,DR9,EG9,EV9) -> 648.12293 | R9: =SUM(F9:Q9) -> 6019.0674 | S9: =SUM(L9:Q9) -> 3418.9295 | U9: =SUM(U11:U18) -> 198.5858 | V9: =SUM(V11:V18) -> 119.78783 | W9: =SUM(W11:W18) -> 245.56533 | X9: =SUM(X11:X18) -> 141.088 | Y9: =SUM(Y11:Y18) -> 188.31131 | Z9: =SUM(Z11:Z18) -> 106.64524 | AA9: =SUM(AA11:AA18) -> 72.764079 | AB9: =SUM(AB11:AB18) -> 101.12459 | ... AH9: =SUM(AH11:AH18) -> 751.2323 | AJ9: =SUM(AJ11:AJ18) -> 9.1682676 | AK9: =SUM(AK11:AK18) -> 2.4443814 | AL9: =SUM(AL11:AL18) -> 5.7343771 | AM9: =SUM(AM11:AM18) -> 6.4032987 | AN9: =SUM(AN11:AN18) -> 59.579896 | AO9: =SUM(AO11:AO18) -> 45.758906 | AP9: =SUM(AP11:AP18) -> 32.997966 | AQ9: =SUM(AQ11:AQ18) -> 42.97163 | ... AW9: =SUM(AW11:AW18) -> 317.50278 | AY9: =SUM(AY11:AY18) -> 7.8967082 | AZ9: =SUM(AZ11:AZ18) -> 4.9254832 | BA9: =SUM(BA11:BA18) -> 10.243303 | BB9: =SUM(BB11:BB18) -> 14.187198 | BC9: =SUM(BC11:BC18) -> 11.200114 | BD9: =SUM(BD11:BD18) -> 10.372104 | BE9: =SUM(BE11:BE18) -> 8.5255366 | BF9: =SUM(BF11:BF18) -> 11.402467 | ... BL9: =SUM(BL11:BL18) -> 85.027317 | BN9: =SUM(BN11:BN18) -> 0.038202731 | BO9: =SUM(BO11:BO18) -> 0.1152271 | BP9: =SUM(BP11:BP18) -> 0.10377373 | BQ9: =SUM(BQ11:BQ18) -> 0.019899124 | BR9: =SUM(BR11:BR18) -> 0.26045807 | BS9: =SUM(BS11:BS18) -> 1.4925016 | BT9: =SUM(BT11:BT18) -> 0.88311922 | BU9: =SUM(BU11:BU18) -> 1.1811265 | ... CA9: =SUM(CA11:CA18) -> 8.8075697 | CC9: =SUM(CC11:CC18) -> 4.1284941 | CD9: =SUM(CD11:CD18) -> 2.8897998 | CE9: =SUM(CE11:CE18) -> 6.5920523 | CF9: =SUM(CF11:CF18) -> 5.2982317 | CG9: =SUM(CG11:CG18) -> 5.9426699 | CH9: =SUM(CH11:CH18) -> 5.8582645 | CI9: =SUM(CI11:CI18) -> 8.8591812 | CJ9: =SUM(CJ11:CJ18) -> 11.848699 | ... CP9: =SUM(CP11:CP18) -> 88.354838 | CR9: =SUM(CR11:CR18) -> 179.33215 | CS9: =SUM(CS11:CS18) -> 117.67011 | CT9: =SUM(CT11:CT18) -> 248.90643 | CU9: =SUM(CU11:CU18) -> 173.27693 | CV9: =SUM(CV11:CV18) -> 188.87317 | CW9: =SUM(CW11:CW18) -> 368.40034 | CX9: =SUM(CX11:CX18) -> 179.94227 | CY9: =SUM(CY11:CY18) -> 240.66354 | ... DE9: =SUM(DE11:DE18) -> 1794.6095 | DG9: =SUM(DG11:DG18) -> 13.031613 | DH9: =SUM(DH11:DH18) -> 1.761104 | DI9: =SUM(DI11:DI18) -> 49.641174 | DJ9: =SUM(DJ11:DJ18) -> 12.864357 | DK9: =SUM(DK11:DK18) -> 18.811248 | DL9: =SUM(DL11:DL18) -> 6.9321479 | DM9: =SUM(DM11:DM18) -> 32.986352 | DN9: =SUM(DN11:DN18) -> 44.117549 | ... DT9: =SUM(DT11:DT18) -> 328.98117 | DV9: =SUM(DV11:DV18) -> 0 | DW9: =SUM(DW11:DW18) -> 0 | DX9: =SUM(DX11:DX18) -> 0 | DY9: =SUM(DY11:DY18) -> 0 | DZ9: =SUM(DZ11:DZ18) -> 0 | EA9: =SUM(EA11:EA18) -> 0 | EB9: =SUM(EB11:EB18) -> 6.976 | EC9: =SUM(EC11:EC18) -> 7.138 | ... EI9: =SUM(EI11:EI18) -> 44.414 | EK9: =SUM(EK11:EK18) -> 0 | EL9: =SUM(EL11:EL18) -> 0 | EM9: =SUM(EM11:EM18) -> 0 | EN9: =SUM(EN11:EN18) -> 0 | EO9: =SUM(EO11:EO18) -> 0 | EP9: =SUM(EP11:EP18) -> 0 | EQ9: =SUM(EQ11:EQ18) -> 0 | ER9: =SUM(ER11:ER18) -> 0 | ... EX9: =SUM(EX11:EX18) -> 0
C10: Margin | F10: =IFERROR(F9/F3,0) -> 0.37589246 | G10: =IFERROR(G9/G3,0) -> 0.37535203 | H10: =IFERROR(H9/H3,0) -> 0.55990256 | I10: =IFERROR(I9/I3,0) -> 0.3611372 | J10: =IFERROR(J9/J3,0) -> 0.3882913 | K10: =IFERROR(K9/K3,0) -> 0.43967729 | L10: =IFERROR(L9/L3,0) -> 0.43434636 | M10: =IFERROR(M9/M3,0) -> 0.44036712 | ... S10: =IFERROR(S9/S3,0) -> 0.44176521 | U10: =IFERROR(U9/U3,0) -> 0.48114475 | V10: =IFERROR(V9/V3,0) -> 0.50691219 | W10: =IFERROR(W9/W3,0) -> 0.51056495 | X10: =IFERROR(X9/X3,0) -> 0.48617945 | Y10: =IFERROR(Y9/Y3,0) -> 0.49131412 | Z10: =IFERROR(Z9/Z3,0) -> 0.39276183 | AA10: =IFERROR(AA9/AA3,0) -> 0.38738079 | AB10: =IFERROR(AB9/AB3,0) -> 0.4025323 | ... AH10: =IFERROR(AH9/AH3,0) -> 0.40101309 | AJ10: =IFERROR(AJ9/AJ3,0) -> 0.58646135 | AK10: =IFERROR(AK9/AK3,0) -> 0.45794658 | AL10: =IFERROR(AL9/AL3,0) -> 0.5062015 | AM10: =IFERROR(AM9/AM3,0) -> 0.85383008 | AN10: =IFERROR(AN9/AN3,0) -> 0.88415149 | AO10: =IFERROR(AO9/AO3,0) -> 0.64873259 | AP10: =IFERROR(AP9/AP3,0) -> 0.62406733 | AQ10: =IFERROR(AQ9/AQ3,0) -> 0.60764373 | ... AW10: =IFERROR(AW9/AW3,0) -> 0.60208119 | AY10: =IFERROR(AY9/AY3,0) -> 0.2850677 | AZ10: =IFERROR(AZ9/AZ3,0) -> 0.34561433 | BA10: =IFERROR(BA9/BA3,0) -> 0.31457732 | BB10: =IFERROR(BB9/BB3,0) -> 0.41422902 | BC10: =IFERROR(BC9/BC3,0) -> 0.3435992 | BD10: =IFERROR(BD9/BD3,0) -> 0.39479526 | BE10: =IFERROR(BE9/BE3,0) -> 0.35244289 | BF10: =IFERROR(BF9/BF3,0) -> 0.35244289 | ... BL10: =IFERROR(BL9/BL3,0) -> 0.35244289 | BN10: =IFERROR(BN9/BN3,0) -> 0.24720926 | BO10: =IFERROR(BO9/BO3,0) -> 0.417083 | BP10: =IFERROR(BP9/BP3,0) -> 0.2832268 | BQ10: =IFERROR(BQ9/BQ3,0) -> 0.16880688 | BR10: =IFERROR(BR9/BR3,0) -> 0.57722949 | BS10: =IFERROR(BS9/BS3,0) -> 0.30395479 | BT10: =IFERROR(BT9/BT3,0) -> 0.30395479 | BU10: =IFERROR(BU9/BU3,0) -> 0.30395479 | ... CA10: =IFERROR(CA9/CA3,0) -> 0.30395479 | CC10: =IFERROR(CC9/CC3,0) -> 0.30202895 | CD10: =IFERROR(CD9/CD3,0) -> 0.33711796 | CE10: =IFERROR(CE9/CE3,0) -> 0.2833627 | CF10: =IFERROR(CF9/CF3,0) -> 0.27217456 | CG10: =IFERROR(CG9/CG3,0) -> 0.30916858 | CH10: =IFERROR(CH9/CH3,0) -> 0.35141005 | CI10: =IFERROR(CI9/CI3,0) -> 0.35107675 | CJ10: =IFERROR(CJ9/CJ3,0) -> 0.35107675 | ... CP10: =IFERROR(CP9/CP3,0) -> 0.35107675 | CR10: =IFERROR(CR9/CR3,0) -> 0.44758856 | CS10: =IFERROR(CS9/CS3,0) -> 0.39071148 | CT10: =IFERROR(CT9/CT3,0) -> 6.1424389 | CU10: =IFERROR(CU9/CU3,0) -> 0.39478812 | CV10: =IFERROR(CV9/CV3,0) -> 0.42326515 | CW10: =IFERROR(CW9/CW3,0) -> 0.55794897 | CX10: =IFERROR(CX9/CX3,0) -> 0.55794897 | CY10: =IFERROR(CY9/CY3,0) -> 0.55794897 | ... DE10: =IFERROR(DE9/DE3,0) -> 0.55794897 | DG10: =IFERROR(DG9/DG3,0) -> 0.2521911 | DH10: =IFERROR(DH9/DH3,0) -> 0.41558995 | DI10: =IFERROR(DI9/DI3,0) -> 0.26122496 | DJ10: =IFERROR(DJ9/DJ3,0) -> 0.34023242 | DK10: =IFERROR(DK9/DK3,0) -> 0.23183989 | DL10: =IFERROR(DL9/DL3,0) -> 0.25316501 | DM10: =IFERROR(DM9/DM3,0) -> 0.38059231 | DN10: =IFERROR(DN9/DN3,0) -> 0.38059231 | ... DT10: =IFERROR(DT9/DT3,0) -> 0.38059231 | DV10: =IFERROR(DV9/DV3,0) -> 0 | DW10: =IFERROR(DW9/DW3,0) -> 0 | DX10: =IFERROR(DX9/DX3,0) -> 0 | DY10: =IFERROR(DY9/DY3,0) -> 0 | DZ10: =IFERROR(DZ9/DZ3,0) -> 0 | EA10: =IFERROR(EA9/EA3,0) -> 0 | EB10: =IFERROR(EB9/EB3,0) -> 0.19403973 | EC10: =IFERROR(EC9/EC3,0) -> 0.20610951 | ... EI10: =IFERROR(EI9/EI3,0) -> 0.22147208 | EK10: =IFERROR(EK9/EK3,0) -> 0 | EL10: =IFERROR(EL9/EL3,0) -> 0 | EM10: =IFERROR(EM9/EM3,0) -> 0 | EN10: =IFERROR(EN9/EN3,0) -> 0 | EO10: =IFERROR(EO9/EO3,0) -> 0 | EP10: =IFERROR(EP9/EP3,0) -> 0 | EQ10: =IFERROR(EQ9/EQ3,0) -> 0 | ER10: =IFERROR(ER9/ER3,0) -> 0 | ... EX10: =IFERROR(EX9/EX3,0) -> 0
D11: 渠道投入 | E11: 广告投流费 | F11: =SUM(U11,AJ11,AY11,BN11,CC11,CR11,DG11,DV11,EK11) -> 334.9911 | G11: =SUM(V11,AK11,AZ11,BO11,CD11,CS11,DH11,DW11,EL11) -> 214.39622 | H11: =SUM(W11,AL11,BA11,BP11,CE11,CT11,DI11,DX11,EM11) -> 437.40128 | I11: =SUM(X11,AM11,BB11,BQ11,CF11,CU11,DJ11,DY11,EN11) -> 301.87089 | J11: =SUM(Y11,AN11,BC11,BR11,CG11,CV11,DK11,DZ11,EO11) -> 396.08316 | K11: =SUM(Z11,AO11,BD11,BS11,CH11,CW11,DL11,EA11,EP11) -> 440.42027 | L11: =SUM(AA11,AP11,BE11,BT11,CI11,CX11,DM11,EB11,EQ11) -> 290.9505 | M11: =SUM(AB11,AQ11,BF11,BU11,CJ11,CY11,DN11,EC11,ER11) -> 389.58422 | ... Q11: =SUM(AF11,AU11,BJ11,BY11,CN11,DC11,DR11,EG11,EV11) -> 547.82399 | R11: =SUM(F11:Q11) -> 5015.6696 | S11: =SUM(L11:Q11) -> 2890.5067 | U11: ='测算-高个子抖音'!I$22 -> 188.32118 | V11: ='测算-高个子抖音'!J$22 -> 115.30584 | W11: ='测算-高个子抖音'!K$22 -> 232.1286 | X11: ='测算-高个子抖音'!L$22 -> 133.29835 | Y11: ='测算-高个子抖音'!M$22 -> 180.30698 | Z11: ='测算-高个子抖音'!N$22 -> 100.198 | AA11: ='测算-高个子抖音'!O$22 -> 68.30402 | AB11: ='测算-高个子抖音'!P$22 -> 95.159493 | ... AF11: ='测算-高个子抖音'!T$22 -> 134.68728 | AG11: ='测算-高个子抖音'!V$22 -> 1656.31 | AH11: ='测算-高个子抖音'!W$22 -> 706.75102 | AJ11: ='测算-高个子视频号'!I$22 -> 4.63834 | AK11: ='测算-高个子视频号'!J$22 -> 1.37259 | AL11: ='测算-高个子视频号'!K$22 -> 4.507362 | AM11: ='测算-高个子视频号'!L$22 -> 6.453311 | AN11: ='测算-高个子视频号'!M$22 -> 59.403044 | AO11: ='测算-高个子视频号'!N$22 -> 42.749001 | AP11: ='测算-高个子视频号'!O$22 -> 30.741657 | AQ11: ='测算-高个子视频号'!P$22 -> 39.953933 | ... AU11: ='测算-高个子视频号'!T$22 -> 55.607679 | AV11: ='测算-高个子视频号'!V$22 -> 414.12369 | AW11: ='测算-高个子视频号'!W$22 -> 295.00005 | AY11: ='测算-天猫淘宝'!I$21 -> 6.117667 | AZ11: ='测算-天猫淘宝'!J$21 -> 4.027279 | BA11: ='测算-天猫淘宝'!K$21 -> 8.225416 | BB11: ='测算-天猫淘宝'!L$21 -> 12.037204 | BC11: ='测算-天猫淘宝'!M$21 -> 8.9149157 | BD11: ='测算-天猫淘宝'!N$21 -> 8.627313 | BE11: ='测算-天猫淘宝'!O$21 -> 6.9190341 | BF11: ='测算-天猫淘宝'!P$21 -> 9.2538522 | ... BJ11: ='测算-天猫淘宝'!T$21 -> 13.09776 | BK11: ='测算-天猫淘宝'!V$21 -> 116.95506 | BL11: ='测算-天猫淘宝'!W$21 -> 69.005264 | BN11: ='测算-拼多多'!I$22 -> 0.034673144 | BO11: ='测算-拼多多'!J$22 -> 0.11229166 | BP11: ='测算-拼多多'!K$22 -> 0.09678804 | BQ11: ='测算-拼多多'!L$22 -> 0.021318449 | BR11: ='测算-拼多多'!M$22 -> 0.25805389 | BS11: ='测算-拼多多'!N$22 -> 1.4745571 | BT11: ='测算-拼多多'!O$22 -> 0.87250136 | BU11: ='测算-拼多多'!P$22 -> 1.1669257 | ... BY11: ='测算-拼多多'!T$22 -> 1.6516487 | BZ11: ='测算-拼多多'!V$22 -> 10.699357 | CA11: ='测算-拼多多'!W$22 -> 8.701675 | CC11: ='测算-京东POP'!I$22 -> 3.4810526 | CD11: ='测算-京东POP'!J$22 -> 2.1461872 | CE11: ='测算-京东POP'!K$22 -> 4.9012572 | CF11: ='测算-京东POP'!L$22 -> 4.0909631 | CG11: ='测算-京东POP'!M$22 -> 4.9457893 | CH11: ='测算-京东POP'!N$22 -> 4.795998 | CI11: ='测算-京东POP'!O$22 -> 7.2512399 | CJ11: ='测算-京东POP'!P$22 -> 9.6981604 | ... CN11: ='测算-京东POP'!T$22 -> 13.726627 | CO11: ='测算-京东POP'!V$22 -> 96.679684 | CP11: ='测算-京东POP'!W$22 -> 72.318436 | CR11: ='测算-京东自营'!I$21 -> 132.39819 | CS11: ='测算-京东自营'!J$21 -> 91.432032 | CT11: ='测算-京东自营'!K$21 -> 187.4732 | CU11: ='测算-京东自营'!L$21 -> 142.93853 | CV11: ='测算-京东自营'!M$21 -> 142.24938 | CW11: ='测算-京东自营'!N$21 -> 282.56721 | CX11: ='测算-京东自营'!O$21 -> 138.01775 | CY11: ='测算-京东自营'!P$21 -> 184.59165 | ... DC11: ='测算-京东自营'!T$21 -> 261.26818 | DD11: ='测算-京东自营'!V$21 -> 2355.5442 | DE11: ='测算-京东自营'!W$21 -> 1376.4857 | DG11: ='测算-达播'!I$23 -> 0 | DH11: ='测算-达播'!J$23 -> 0 | DI11: ='测算-达播'!K$23 -> 0.068665 | DJ11: ='测算-达播'!L$23 -> 3.031222 | DK11: ='测算-达播'!M$23 -> 0.004987 | DL11: ='测算-达播'!N$23 -> 0.008181 | DM11: ='测算-达播'!O$23 -> 31.868295 | DN11: ='测算-达播'!P$23 -> 42.622205 | ... DR11: ='测算-达播'!T$23 -> 60.326814 | DS11: ='测算-达播'!V$23 -> 320.94356 | DT11: ='测算-达播'!W$23 -> 317.83051 | DV11: ='测算-私域'!I$22 -> 0 | DW11: ='测算-私域'!J$22 -> 0 | DX11: ='测算-私域'!K$22 -> 0 | DY11: ='测算-私域'!L$22 -> 0 | DZ11: ='测算-私域'!M$22 -> 0 | EA11: ='测算-私域'!N$22 -> 0 | EB11: ='测算-私域'!O$22 -> 6.976 | EC11: ='测算-私域'!P$22 -> 7.138 | ... EG11: ='测算-私域'!T$22 -> 7.458 | EH11: ='测算-私域'!V$22 -> 44.414 | EI11: ='测算-私域'!W$22 -> 44.414 | EK11: ='测算-外部分销'!I$22 -> 0 | EL11: ='测算-外部分销'!J$22 -> 0 | EM11: ='测算-外部分销'!K$22 -> 0 | EN11: ='测算-外部分销'!L$22 -> 0 | EO11: ='测算-外部分销'!M$22 -> 0 | EP11: ='测算-外部分销'!N$22 -> 0 | EQ11: ='测算-外部分销'!O$22 -> 0 | ER11: ='测算-外部分销'!P$22 -> 0 | ... EV11: ='测算-外部分销'!T$22 -> 0 | EW11: ='测算-外部分销'!V$22 -> 0 | EX11: ='测算-外部分销'!W$22 -> 0
D12: 渠道投入 | E12: 媒介种草 | F12: =SUM(U12,AJ12,AY12,BN12,CC12,CR12,DG12,DV12,EK12) -> 0 | G12: =SUM(V12,AK12,AZ12,BO12,CD12,CS12,DH12,DW12,EL12) -> 0 | H12: =SUM(W12,AL12,BA12,BP12,CE12,CT12,DI12,DX12,EM12) -> 0 | I12: =SUM(X12,AM12,BB12,BQ12,CF12,CU12,DJ12,DY12,EN12) -> 0 | J12: =SUM(Y12,AN12,BC12,BR12,CG12,CV12,DK12,DZ12,EO12) -> 0 | K12: =SUM(Z12,AO12,BD12,BS12,CH12,CW12,DL12,EA12,EP12) -> 0 | L12: =SUM(AA12,AP12,BE12,BT12,CI12,CX12,DM12,EB12,EQ12) -> 0 | M12: =SUM(AB12,AQ12,BF12,BU12,CJ12,CY12,DN12,EC12,ER12) -> 0 | ... Q12: =SUM(AF12,AU12,BJ12,BY12,CN12,DC12,DR12,EG12,EV12) -> 0 | R12: =SUM(F12:Q12) -> 0 | S12: =SUM(L12:Q12) -> 0 | U12: ='测算-高个子抖音'!I$23 -> 0 | V12: ='测算-高个子抖音'!J$23 -> 0 | W12: ='测算-高个子抖音'!K$23 -> 0 | X12: ='测算-高个子抖音'!L$23 -> 0 | Y12: ='测算-高个子抖音'!M$23 -> 0 | Z12: ='测算-高个子抖音'!N$23 -> 0 | AA12: ='测算-高个子抖音'!O$23 -> 0 | AB12: ='测算-高个子抖音'!P$23 -> 0 | ... AF12: ='测算-高个子抖音'!T$23 -> 0 | AG12: ='测算-高个子抖音'!V$23 -> 0 | AH12: ='测算-高个子抖音'!W$23 -> 0 | AJ12: ='测算-高个子视频号'!I$23 -> 0 | AK12: ='测算-高个子视频号'!J$23 -> 0 | AL12: ='测算-高个子视频号'!K$23 -> 0 | AM12: ='测算-高个子视频号'!L$23 -> 0 | AN12: ='测算-高个子视频号'!M$23 -> 0 | AO12: ='测算-高个子视频号'!N$23 -> 0 | AP12: ='测算-高个子视频号'!O$23 -> 0 | AQ12: ='测算-高个子视频号'!P$23 -> 0 | ... AU12: ='测算-高个子视频号'!T$23 -> 0 | AV12: ='测算-高个子视频号'!V$23 -> 0 | AW12: ='测算-高个子视频号'!W$23 -> 0 | AY12: ='测算-天猫淘宝'!I$22 -> 0 | AZ12: ='测算-天猫淘宝'!J$22 -> 0 | BA12: ='测算-天猫淘宝'!K$22 -> 0 | BB12: ='测算-天猫淘宝'!L$22 -> 0 | BC12: ='测算-天猫淘宝'!M$22 -> 0 | BD12: ='测算-天猫淘宝'!N$22 -> 0 | BE12: ='测算-天猫淘宝'!O$22 -> 0 | BF12: ='测算-天猫淘宝'!P$22 -> 0 | ... BJ12: ='测算-天猫淘宝'!T$22 -> 0 | BK12: ='测算-天猫淘宝'!V$22 -> 0 | BL12: ='测算-天猫淘宝'!W$22 -> 0 | BN12: ='测算-拼多多'!I$23 -> 0 | BO12: ='测算-拼多多'!J$23 -> 0 | BP12: ='测算-拼多多'!K$23 -> 0 | BQ12: ='测算-拼多多'!L$23 -> 0 | BR12: ='测算-拼多多'!M$23 -> 0 | BS12: ='测算-拼多多'!N$23 -> 0 | BT12: ='测算-拼多多'!O$23 -> 0 | BU12: ='测算-拼多多'!P$23 -> 0 | ... BY12: ='测算-拼多多'!T$23 -> 0 | BZ12: ='测算-拼多多'!V$23 -> 0 | CA12: ='测算-拼多多'!W$23 -> 0 | CC12: ='测算-京东POP'!I$23 -> 0 | CD12: ='测算-京东POP'!J$23 -> 0 | CE12: ='测算-京东POP'!K$23 -> 0 | CF12: ='测算-京东POP'!L$23 -> 0 | CG12: ='测算-京东POP'!M$23 -> 0 | CH12: ='测算-京东POP'!N$23 -> 0 | CI12: ='测算-京东POP'!O$23 -> 0 | CJ12: ='测算-京东POP'!P$23 -> 0 | ... CN12: ='测算-京东POP'!T$23 -> 0 | CO12: ='测算-京东POP'!V$23 -> 0 | CP12: ='测算-京东POP'!W$23 -> 0 | CR12: ="" | CS12: ="" | CT12: ="" | CU12: ="" | CV12: ="" | CW12: ="" | CX12: ="" | CY12: ="" | ... DE12: ="" | DG12: ='测算-达播'!I$24 -> 0 | DH12: ='测算-达播'!J$24 -> 0 | DI12: ='测算-达播'!K$24 -> 0 | DJ12: ='测算-达播'!L$24 -> 0 | DK12: ='测算-达播'!M$24 -> 0 | DL12: ='测算-达播'!N$24 -> 0 | DM12: ='测算-达播'!O$24 -> 0 | DN12: ='测算-达播'!P$24 -> 0 | ... DR12: ='测算-达播'!T$24 -> 0 | DS12: ='测算-达播'!V$24 -> 0 | DT12: ='测算-达播'!W$24 -> 0 | DV12: ='测算-私域'!I$23 -> 0 | DW12: ='测算-私域'!J$23 -> 0 | DX12: ='测算-私域'!K$23 -> 0 | DY12: ='测算-私域'!L$23 -> 0 | DZ12: ='测算-私域'!M$23 -> 0 | EA12: ='测算-私域'!N$23 -> 0 | EB12: ='测算-私域'!O$23 -> 0 | EC12: ='测算-私域'!P$23 -> 0 | ... EG12: ='测算-私域'!T$23 -> 0 | EH12: ='测算-私域'!V$23 -> 0 | EI12: ='测算-私域'!W$23 -> 0 | EK12: ='测算-外部分销'!I$23 | EL12: ='测算-外部分销'!J$23 | EM12: ='测算-外部分销'!K$23 | EN12: ='测算-外部分销'!L$23 | EO12: ='测算-外部分销'!M$23 | EP12: ='测算-外部分销'!N$23 | EQ12: ='测算-外部分销'!O$23 -> 0 | ER12: ='测算-外部分销'!P$23 -> 0 | ... EV12: ='测算-外部分销'!T$23 -> 0 | EW12: ='测算-外部分销'!V$23 -> 0 | EX12: ='测算-外部分销'!W$23 -> 0
D13: 渠道投入 | E13: 分销返佣 | F13: =SUM(U13,AJ13,AY13,BN13,CC13,CR13,DG13,DV13,EK13) -> 0 | G13: =SUM(V13,AK13,AZ13,BO13,CD13,CS13,DH13,DW13,EL13) -> 0 | H13: =SUM(W13,AL13,BA13,BP13,CE13,CT13,DI13,DX13,EM13) -> 0 | I13: =SUM(X13,AM13,BB13,BQ13,CF13,CU13,DJ13,DY13,EN13) -> 0 | J13: =SUM(Y13,AN13,BC13,BR13,CG13,CV13,DK13,DZ13,EO13) -> 0 | K13: =SUM(Z13,AO13,BD13,BS13,CH13,CW13,DL13,EA13,EP13) -> 0 | L13: =SUM(AA13,AP13,BE13,BT13,CI13,CX13,DM13,EB13,EQ13) -> 0 | M13: =SUM(AB13,AQ13,BF13,BU13,CJ13,CY13,DN13,EC13,ER13) -> 0 | ... Q13: =SUM(AF13,AU13,BJ13,BY13,CN13,DC13,DR13,EG13,EV13) -> 0 | R13: =SUM(F13:Q13) -> 0 | S13: =SUM(L13:Q13) -> 0 | U13: ='测算-高个子抖音'!I$24 -> 0 | V13: ='测算-高个子抖音'!J$24 -> 0 | W13: ='测算-高个子抖音'!K$24 -> 0 | X13: ='测算-高个子抖音'!L$24 -> 0 | Y13: ='测算-高个子抖音'!M$24 -> 0 | Z13: ='测算-高个子抖音'!N$24 -> 0 | AA13: ='测算-高个子抖音'!O$24 -> 0 | AB13: ='测算-高个子抖音'!P$24 -> 0 | ... AF13: ='测算-高个子抖音'!T$24 -> 0 | AG13: ='测算-高个子抖音'!V$24 -> 0 | AH13: ='测算-高个子抖音'!W$24 -> 0 | AJ13: ='测算-高个子视频号'!I$24 -> 0 | AK13: ='测算-高个子视频号'!J$24 -> 0 | AL13: ='测算-高个子视频号'!K$24 -> 0 | AM13: ='测算-高个子视频号'!L$24 -> 0 | AN13: ='测算-高个子视频号'!M$24 -> 0 | AO13: ='测算-高个子视频号'!N$24 -> 0 | AP13: ='测算-高个子视频号'!O$24 -> 0 | AQ13: ='测算-高个子视频号'!P$24 -> 0 | ... AU13: ='测算-高个子视频号'!T$24 -> 0 | AV13: ='测算-高个子视频号'!V$24 -> 0 | AW13: ='测算-高个子视频号'!W$24 -> 0 | AY13: ='测算-天猫淘宝'!I$23 -> 0 | AZ13: ='测算-天猫淘宝'!J$23 -> 0 | BA13: ='测算-天猫淘宝'!K$23 -> 0 | BB13: ='测算-天猫淘宝'!L$23 -> 0 | BC13: ='测算-天猫淘宝'!M$23 -> 0 | BD13: ='测算-天猫淘宝'!N$23 -> 0 | BE13: ='测算-天猫淘宝'!O$23 -> 0 | BF13: ='测算-天猫淘宝'!P$23 -> 0 | ... BJ13: ='测算-天猫淘宝'!T$23 -> 0 | BK13: ='测算-天猫淘宝'!V$23 -> 0 | BL13: ='测算-天猫淘宝'!W$23 -> 0 | BN13: ='测算-拼多多'!I$24 -> 0 | BO13: ='测算-拼多多'!J$24 -> 0 | BP13: ='测算-拼多多'!K$24 -> 0 | BQ13: ='测算-拼多多'!L$24 -> 0 | BR13: ='测算-拼多多'!M$24 -> 0 | BS13: ='测算-拼多多'!N$24 -> 0 | BT13: ='测算-拼多多'!O$24 -> 0 | BU13: ='测算-拼多多'!P$24 -> 0 | ... BY13: ='测算-拼多多'!T$24 -> 0 | BZ13: ='测算-拼多多'!V$24 -> 0 | CA13: ='测算-拼多多'!W$24 -> 0 | CC13: ='测算-京东POP'!I$24 -> 0 | CD13: ='测算-京东POP'!J$24 -> 0 | CE13: ='测算-京东POP'!K$24 -> 0 | CF13: ='测算-京东POP'!L$24 -> 0 | CG13: ='测算-京东POP'!M$24 -> 0 | CH13: ='测算-京东POP'!N$24 -> 0 | CI13: ='测算-京东POP'!O$24 -> 0 | CJ13: ='测算-京东POP'!P$24 -> 0 | ... CN13: ='测算-京东POP'!T$24 -> 0 | CO13: ='测算-京东POP'!V$24 -> 0 | CP13: ='测算-京东POP'!W$24 -> 0 | CR13: ='测算-京东自营'!I$24 -> 0 | CS13: ='测算-京东自营'!J$24 -> 0 | CT13: ='测算-京东自营'!K$24 -> 0 | CU13: ='测算-京东自营'!L$24 -> 0 | CV13: ='测算-京东自营'!M$24 -> 0 | CW13: ='测算-京东自营'!N$24 -> 0 | CX13: ='测算-京东自营'!O$24 -> 0 | CY13: ='测算-京东自营'!P$24 -> 0 | ... DC13: ='测算-京东自营'!T$24 -> 0 | DD13: ='测算-京东自营'!V$24 -> 0 | DE13: ='测算-京东自营'!W$24 -> 0 | DG13: ='测算-达播'!I$25 -> 0 | DH13: ='测算-达播'!J$25 -> 0 | DI13: ='测算-达播'!K$25 -> 0 | DJ13: ='测算-达播'!L$25 -> 0 | DK13: ='测算-达播'!M$25 -> 0 | DL13: ='测算-达播'!N$25 -> 0 | DM13: ='测算-达播'!O$25 -> 0 | DN13: ='测算-达播'!P$25 -> 0 | ... DR13: ='测算-达播'!T$25 -> 0 | DS13: ='测算-达播'!V$25 -> 0 | DT13: ='测算-达播'!W$25 -> 0 | DV13: ='测算-私域'!I$24 -> 0 | DW13: ='测算-私域'!J$24 -> 0 | DX13: ='测算-私域'!K$24 -> 0 | DY13: ='测算-私域'!L$24 -> 0 | DZ13: ='测算-私域'!M$24 -> 0 | EA13: ='测算-私域'!N$24 -> 0 | EB13: ='测算-私域'!O$24 -> 0 | EC13: ='测算-私域'!P$24 -> 0 | ... EG13: ='测算-私域'!T$24 -> 0 | EH13: ='测算-私域'!V$24 -> 0 | EI13: ='测算-私域'!W$24 -> 0 | EK13: ='测算-外部分销'!I$24 | EL13: ='测算-外部分销'!J$24 | EM13: ='测算-外部分销'!K$24 | EN13: ='测算-外部分销'!L$24 | EO13: ='测算-外部分销'!M$24 | EP13: ='测算-外部分销'!N$24 | EQ13: ='测算-外部分销'!O$24 -> 0 | ER13: ='测算-外部分销'!P$24 -> 0 | ... EV13: ='测算-外部分销'!T$24 -> 0 | EW13: ='测算-外部分销'!V$24 -> 0 | EX13: ='测算-外部分销'!W$24 -> 0
D14: 渠道投入 | E14: 退货成本 | F14: =SUM(U14,AJ14,AY14,BN14,CC14,#REF!,DG14,DV14,CR14) -> #REF! | G14: =SUM(V14,AK14,AZ14,BO14,CD14,#REF!,DH14,DW14,CS14) -> #REF! | H14: =SUM(W14,AL14,BA14,BP14,CE14,#REF!,DI14,DX14,CT14) -> #REF! | I14: =SUM(X14,AM14,BB14,BQ14,CF14,#REF!,DJ14,DY14,CU14) -> #REF! | J14: =SUM(Y14,AN14,BC14,BR14,CG14,#REF!,DK14,DZ14,CV14) -> #REF! | K14: =SUM(Z14,AO14,BD14,BS14,CH14,#REF!,DL14,EA14,CW14) -> #REF! | L14: =SUM(AA14,AP14,BE14,BT14,CI14,#REF!,DM14,EB14,CX14) -> #REF! | M14: =SUM(AB14,AQ14,BF14,BU14,CJ14,#REF!,DN14,EC14,CY14) -> #REF! | ... Q14: =SUM(AF14,AU14,BJ14,BY14,CN14,#REF!,DR14,EG14,DC14) -> #REF! | R14: =SUM(F14:Q14) -> #REF! | S14: =SUM(L14:Q14) -> #REF! | U14: ="" | V14: ="" | W14: ="" | X14: ="" | Y14: ="" | Z14: ="" | AA14: ="" | AB14: ="" | ... AH14: ="" | AJ14: ="" | AK14: ="" | AL14: ="" | AM14: ="" | AN14: ="" | AO14: ="" | AP14: ="" | AQ14: ="" | ... AW14: ="" | AY14: ="" | AZ14: ="" | BA14: ="" | BB14: ="" | BC14: ="" | BD14: ="" | BE14: ="" | BF14: ="" | ... BL14: ="" | BN14: ="" | BO14: ="" | BP14: ="" | BQ14: ="" | BR14: ="" | BS14: ="" | BT14: ="" | BU14: ="" | ... CA14: ="" | CC14: ="" | CD14: ="" | CE14: ="" | CF14: ="" | CG14: ="" | CH14: ="" | CI14: ="" | CJ14: ="" | ... CP14: ="" | CR14: ='测算-京东自营'!I$27 -> 6.38556 | CS14: ='测算-京东自营'!J$27 -> 3.46067 | CT14: ='测算-京东自营'!K$27 -> 11.14547 | CU14: ='测算-京东自营'!L$27 -> 6.25147 | CV14: ='测算-京东自营'!M$27 -> 18.65732 | CW14: ='测算-京东自营'!N$27 -> 18.621874 | CX14: ='测算-京东自营'!O$27 -> 9.0957091 | CY14: ='测算-京东自营'!P$27 -> 12.165043 | ... DC14: ='测算-京东自营'!T$27 -> 17.218215 | DD14: ='测算-京东自营'!V$27 -> 155.23615 | DE14: ='测算-京东自营'!W$27 -> 90.71379 | DG14: ="" | DH14: ="" | DI14: ="" | DJ14: ="" | DK14: ="" | DL14: ="" | DM14: ="" | DN14: ="" | ... DT14: ="" | DV14: ="" | DW14: ="" | DX14: ="" | DY14: ="" | DZ14: ="" | EA14: ="" | EB14: ="" | EC14: ="" | ... EI14: ="" | EW14: ="" | EX14: =""
D15: 渠道投入 | E15: 平台毛利补贴 | F15: =SUM(U15,AJ15,AY15,BN15,CC15,CR15,DG15,DV15,EK15) -> 37.598827 | G15: =SUM(V15,AK15,AZ15,BO15,CD15,CS15,DH15,DW15,EL15) -> 19.697303 | H15: =SUM(W15,AL15,BA15,BP15,CE15,CT15,DI15,DX15,EM15) -> 33.311613 | I15: =SUM(X15,AM15,BB15,BQ15,CF15,CU15,DJ15,DY15,EN15) -> 20.577461 | J15: =SUM(Y15,AN15,BC15,BR15,CG15,CV15,DK15,DZ15,EO15) -> 16.509449 | K15: =SUM(Z15,AO15,BD15,BS15,CH15,CW15,DL15,EA15,EP15) -> 51.805845 | L15: =SUM(AA15,AP15,BE15,BT15,CI15,CX15,DM15,EB15,EQ15) -> 25.304162 | M15: =SUM(AB15,AQ15,BF15,BU15,CJ15,CY15,DN15,EC15,ER15) -> 33.843015 | ... Q15: =SUM(AF15,AU15,BJ15,BY15,CN15,DC15,DR15,EG15,EV15) -> 47.900882 | R15: =SUM(F15:Q15) -> 431.86525 | S15: =SUM(L15:Q15) -> 252.36476 | U15: ='测算-高个子抖音'!I$25 -> 0 | V15: ='测算-高个子抖音'!J$25 -> 0 | W15: ='测算-高个子抖音'!K$25 -> 0 | X15: ='测算-高个子抖音'!L$25 -> 0 | Y15: ='测算-高个子抖音'!M$25 -> 0 | Z15: ='测算-高个子抖音'!N$25 -> 0 | AA15: ='测算-高个子抖音'!O$25 -> 0 | AB15: ='测算-高个子抖音'!P$25 -> 0 | ... AF15: ='测算-高个子抖音'!T$25 -> 0 | AG15: ='测算-高个子抖音'!V$25 -> 0 | AH15: ='测算-高个子抖音'!W$25 -> 0 | AJ15: ='测算-高个子视频号'!I$25 -> 0 | AK15: ='测算-高个子视频号'!J$25 -> 0 | AL15: ='测算-高个子视频号'!K$25 -> 0 | AM15: ='测算-高个子视频号'!L$25 -> 0 | AN15: ='测算-高个子视频号'!M$25 -> 0 | AO15: ='测算-高个子视频号'!N$25 -> 0 | AP15: ='测算-高个子视频号'!O$25 -> 0 | AQ15: ='测算-高个子视频号'!P$25 -> 0 | ... AU15: ='测算-高个子视频号'!T$25 -> 0 | AV15: ='测算-高个子视频号'!V$25 -> 0 | AW15: ='测算-高个子视频号'!W$25 -> 0 | AY15: ='测算-天猫淘宝'!I$24 -> 0 | AZ15: ='测算-天猫淘宝'!J$24 -> 0 | BA15: ='测算-天猫淘宝'!K$24 -> 0 | BB15: ='测算-天猫淘宝'!L$24 -> 0 | BC15: ='测算-天猫淘宝'!M$24 -> 0 | BD15: ='测算-天猫淘宝'!N$24 -> 0 | BE15: ='测算-天猫淘宝'!O$24 -> 0 | BF15: ='测算-天猫淘宝'!P$24 -> 0 | ... BJ15: ='测算-天猫淘宝'!T$24 -> 0 | BK15: ='测算-天猫淘宝'!V$24 -> 0 | BL15: ='测算-天猫淘宝'!W$24 -> 0 | BN15: ='测算-拼多多'!I$25 -> 0 | BO15: ='测算-拼多多'!J$25 -> 0 | BP15: ='测算-拼多多'!K$25 -> 0 | BQ15: ='测算-拼多多'!L$25 -> 0 | BR15: ='测算-拼多多'!M$25 -> 0 | BS15: ='测算-拼多多'!N$25 -> 0 | BT15: ='测算-拼多多'!O$25 -> 0 | BU15: ='测算-拼多多'!P$25 -> 0 | ... BY15: ='测算-拼多多'!T$25 -> 0 | BZ15: ='测算-拼多多'!V$25 -> 0 | CA15: ='测算-拼多多'!W$25 -> 0 | CC15: ='测算-京东POP'!I$25 -> 0 | CD15: ='测算-京东POP'!J$25 -> 0 | CE15: ='测算-京东POP'!K$25 -> 0 | CF15: ='测算-京东POP'!L$25 -> 0 | CG15: ='测算-京东POP'!M$25 -> 0 | CH15: ='测算-京东POP'!N$25 -> 0 | CI15: ='测算-京东POP'!O$25 -> 0 | CJ15: ='测算-京东POP'!P$25 -> 0 | ... CN15: ='测算-京东POP'!T$25 -> 0 | CO15: ='测算-京东POP'!V$25 -> 0 | CP15: ='测算-京东POP'!W$25 -> 0 | CR15: ='测算-京东自营'!I$25 -> 37.598827 | CS15: ='测算-京东自营'!J$25 -> 19.697303 | CT15: ='测算-京东自营'!K$25 -> 33.311613 | CU15: ='测算-京东自营'!L$25 -> 20.577461 | CV15: ='测算-京东自营'!M$25 -> 16.509449 | CW15: ='测算-京东自营'!N$25 -> 51.805845 | CX15: ='测算-京东自营'!O$25 -> 25.304162 | CY15: ='测算-京东自营'!P$25 -> 33.843015 | ... DC15: ='测算-京东自营'!T$25 -> 47.900882 | DD15: ='测算-京东自营'!V$25 -> 431.86525 | DE15: ='测算-京东自营'!W$25 -> 252.36476 | DG15: ='测算-达播'!I$26 -> 0 | DH15: ='测算-达播'!J$26 -> 0 | DI15: ='测算-达播'!K$26 -> 0 | DJ15: ='测算-达播'!L$26 -> 0 | DK15: ='测算-达播'!M$26 -> 0 | DL15: ='测算-达播'!N$26 -> 0 | DM15: ='测算-达播'!O$26 -> 0 | DN15: ='测算-达播'!P$26 -> 0 | ... DR15: ='测算-达播'!T$26 -> 0 | DS15: ='测算-达播'!V$26 -> 0 | DT15: ='测算-达播'!W$26 -> 0 | DV15: ='测算-私域'!I$25 -> 0 | DW15: ='测算-私域'!J$25 -> 0 | DX15: ='测算-私域'!K$25 -> 0 | DY15: ='测算-私域'!L$25 -> 0 | DZ15: ='测算-私域'!M$25 -> 0 | EA15: ='测算-私域'!N$25 -> 0 | EB15: ='测算-私域'!O$25 -> 0 | EC15: ='测算-私域'!P$25 -> 0 | ... EG15: ='测算-私域'!T$25 -> 0 | EH15: ='测算-私域'!V$25 -> 0 | EI15: ='测算-私域'!W$25 -> 0 | EK15: ='测算-外部分销'!I$25 | EL15: ='测算-外部分销'!J$25 | EM15: ='测算-外部分销'!K$25 | EN15: ='测算-外部分销'!L$25 | EO15: ='测算-外部分销'!M$25 | EP15: ='测算-外部分销'!N$25 | EQ15: ='测算-外部分销'!O$25 -> 0 | ER15: ='测算-外部分销'!P$25 -> 0 | ... EV15: ='测算-外部分销'!T$25 -> 0 | EW15: ='测算-外部分销'!V$25 -> 0 | EX15: ='测算-外部分销'!W$25 -> 0
D16: 渠道投入 | E16: 平台提现手续费 | F16: =SUM(U16,AJ16,AY16,BN16,CC16,CR16,DG16,DV16,EK16) -> 30.256177 | G16: =SUM(V16,AK16,AZ16,BO16,CD16,CS16,DH16,DW16,EL16) -> 8.9596448 | H16: =SUM(W16,AL16,BA16,BP16,CE16,CT16,DI16,DX16,EM16) -> 67.951923 | I16: =SUM(X16,AM16,BB16,BQ16,CF16,CU16,DJ16,DY16,EN16) -> 20.928625 | J16: =SUM(Y16,AN16,BC16,BR16,CG16,CV16,DK16,DZ16,EO16) -> 30.271928 | K16: =SUM(Z16,AO16,BD16,BS16,CH16,CW16,DL16,EA16,EP16) -> 19.206113 | L16: =SUM(AA16,AP16,BE16,BT16,CI16,CX16,DM16,EB16,EQ16) -> 11.059486 | M16: =SUM(AB16,AQ16,BF16,BU16,CJ16,CY16,DN16,EC16,ER16) -> 14.791494 | ... Q16: =SUM(AF16,AU16,BJ16,BY16,CN16,DC16,DR16,EG16,EV16) -> 20.935653 | R16: =SUM(F16:Q16) -> 287.87344 | S16: =SUM(L16:Q16) -> 110.29903 | U16: ='测算-高个子抖音'!I$26 -> 10.264625 | V16: ='测算-高个子抖音'!J$26 -> 4.4819971 | W16: ='测算-高个子抖音'!K$26 -> 13.436731 | X16: ='测算-高个子抖音'!L$26 -> 7.7896591 | Y16: ='测算-高个子抖音'!M$26 -> 8.0043313 | Z16: ='测算-高个子抖音'!N$26 -> 6.4472398 | AA16: ='测算-高个子抖音'!O$26 -> 4.4600586 | AB16: ='测算-高个子抖音'!P$26 -> 5.965099 | ... AF16: ='测算-高个子抖音'!T$26 -> 8.4429093 | AG16: ='测算-高个子抖音'!V$26 -> 94.905867 | AH16: ='测算-高个子抖音'!W$26 -> 44.481284 | AJ16: ='测算-高个子视频号'!I$26 -> 4.5299276 | AK16: ='测算-高个子视频号'!J$26 -> 1.0717915 | AL16: ='测算-高个子视频号'!K$26 -> 1.2270151 | AM16: ='测算-高个子视频号'!L$26 -> -0.050012325 | AN16: ='测算-高个子视频号'!M$26 -> 0.17685221 | AO16: ='测算-高个子视频号'!N$26 -> 3.0099046 | AP16: ='测算-高个子视频号'!O$26 -> 2.2563087 | AQ16: ='测算-高个子视频号'!P$26 -> 3.0176969 | ... AU16: ='测算-高个子视频号'!T$26 -> 4.2712017 | AV16: ='测算-高个子视频号'!V$26 -> 32.468212 | AW16: ='测算-高个子视频号'!W$26 -> 22.502734 | AY16: ='测算-天猫淘宝'!I$25 -> 1.7790412 | AZ16: ='测算-天猫淘宝'!J$25 -> 0.89820417 | BA16: ='测算-天猫淘宝'!K$25 -> 2.0178875 | BB16: ='测算-天猫淘宝'!L$25 -> 2.1499941 | BC16: ='测算-天猫淘宝'!M$25 -> 2.2851984 | BD16: ='测算-天猫淘宝'!N$25 -> 1.7447908 | BE16: ='测算-天猫淘宝'!O$25 -> 1.6065025 | BF16: ='测算-天猫淘宝'!P$25 -> 2.1486145 | ... BJ16: ='测算-天猫淘宝'!T$25 -> 3.0411159 | BK16: ='测算-天猫淘宝'!V$25 -> 26.897169 | BL16: ='测算-天猫淘宝'!W$25 -> 16.022053 | BN16: ='测算-拼多多'!I$26 -> 0.003529587 | BO16: ='测算-拼多多'!J$26 -> 0.0029354404 | BP16: ='测算-拼多多'!K$26 -> 0.0069856919 | BQ16: ='测算-拼多多'!L$26 -> -0.0014193255 | BR16: ='测算-拼多多'!M$26 -> 0.0024041816 | BS16: ='测算-拼多多'!N$26 -> 0.017944551 | BT16: ='测算-拼多多'!O$26 -> 0.010617863 | BU16: ='测算-拼多多'!P$26 -> 0.014200846 | ... BY16: ='测算-拼多多'!T$26 -> 0.020099659 | BZ16: ='测算-拼多多'!V$26 -> 0.13827474 | CA16: ='测算-拼多多'!W$26 -> 0.10589462 | CC16: ='测算-京东POP'!I$26 -> 0.64744156 | CD16: ='测算-京东POP'!J$26 -> 0.74361259 | CE16: ='测算-京东POP'!K$26 -> 1.6907951 | CF16: ='测算-京东POP'!L$26 -> 1.2072686 | CG16: ='测算-京东POP'!M$26 -> 0.99688055 | CH16: ='测算-京东POP'!N$26 -> 1.0622665 | CI16: ='测算-京东POP'!O$26 -> 1.6079413 | CJ16: ='测算-京东POP'!P$26 -> 2.1505388 | ... CN16: ='测算-京东POP'!T$26 -> 3.0438395 | CO16: ='测算-京东POP'!V$26 -> 22.384667 | CP16: ='测算-京东POP'!W$26 -> 16.036402 | CR16: ='测算-京东自营'!I$26 -> 0 | CS16: ='测算-京东自营'!J$26 -> 0 | CT16: ='测算-京东自营'!K$26 -> 0 | CU16: ='测算-京东自营'!L$26 -> 0 | CV16: ='测算-京东自营'!M$26 -> 0 | CW16: ='测算-京东自营'!N$26 -> 0 | CX16: ='测算-京东自营'!O$26 -> 0 | CY16: ='测算-京东自营'!P$26 -> 0 | ... DC16: ='测算-京东自营'!T$26 -> 0 | DD16: ='测算-京东自营'!V$26 -> 0 | DE16: ='测算-京东自营'!W$26 -> 0 | DG16: ='测算-达播'!I$27 -> 13.031613 | DH16: ='测算-达播'!J$27 -> 1.761104 | DI16: ='测算-达播'!K$27 -> 49.572509 | DJ16: ='测算-达播'!L$27 -> 9.8331349 | DK16: ='测算-达播'!M$27 -> 18.806261 | DL16: ='测算-达播'!N$27 -> 6.9239669 | DM16: ='测算-达播'!O$27 -> 1.1180571 | DN16: ='测算-达播'!P$27 -> 1.4953439 | ... DR16: ='测算-达播'!T$27 -> 2.1164867 | DS16: ='测算-达播'!V$27 -> 111.07925 | DT16: ='测算-达播'!W$27 -> 11.150664 | DV16: ='测算-私域'!I$26 -> 0 | DW16: ='测算-私域'!J$26 -> 0 | DX16: ='测算-私域'!K$26 -> 0 | DY16: ='测算-私域'!L$26 -> 0 | DZ16: ='测算-私域'!M$26 -> 0 | EA16: ='测算-私域'!N$26 -> 0 | EB16: ='测算-私域'!O$26 -> 0 | EC16: ='测算-私域'!P$26 -> 0 | ... EG16: ='测算-私域'!T$26 -> 0 | EH16: ='测算-私域'!V$26 -> 0 | EI16: ='测算-私域'!W$26 -> 0 | EK16: ='测算-外部分销'!I$26 -> 0 | EL16: ='测算-外部分销'!J$26 -> 0 | EM16: ='测算-外部分销'!K$26 -> 0 | EN16: ='测算-外部分销'!L$26 -> 0 | EO16: ='测算-外部分销'!M$26 -> 0 | EP16: ='测算-外部分销'!N$26 -> 0 | EQ16: ='测算-外部分销'!O$26 -> 0 | ER16: ='测算-外部分销'!P$26 -> 0 | ... EV16: ='测算-外部分销'!T$26 -> 0 | EW16: ='测算-外部分销'!V$26 -> 0 | EX16: ='测算-外部分销'!W$26 -> 0
D17: 渠道投入 | E17: 自营渠道推广费 | F17: =SUM(U17,AJ17,AY17,BN17,CC17,CR17,DG17,DV17,EK17) -> 0.160283 | G17: =SUM(V17,AK17,AZ17,BO17,CD17,CS17,DH17,DW17,EL17) -> 0.157019 | H17: =SUM(W17,AL17,BA17,BP17,CE17,CT17,DI17,DX17,EM17) -> 0.504767 | I17: =SUM(X17,AM17,BB17,BQ17,CF17,CU17,DJ17,DY17,EN17) -> 0.367181 | J17: =SUM(Y17,AN17,BC17,BR17,CG17,CV17,DK17,DZ17,EO17) -> 4.232029 | K17: =SUM(Z17,AO17,BD17,BS17,CH17,CW17,DL17,EA17,EP17) -> 2.1994182 | L17: =SUM(AA17,AP17,BE17,BT17,CI17,CX17,DM17,EB17,EQ17) -> 1.0742887 | M17: =SUM(AB17,AQ17,BF17,BU17,CJ17,CY17,DN17,EC17,ER17) -> 1.4368058 | ... Q17: =SUM(AF17,AU17,BJ17,BY17,CN17,DC17,DR17,EG17,EV17) -> 2.0336329 | R17: =SUM(F17:Q17) -> 18.334848 | S17: =SUM(L17:Q17) -> 10.714151 | U17: ="" | V17: ="" | W17: ="" | X17: ="" | Y17: ="" | Z17: ="" | AA17: ="" | AB17: ="" | ... AH17: ="" | AJ17: ="" | AK17: ="" | AL17: ="" | AM17: ="" | AN17: ="" | AO17: ="" | AP17: ="" | AQ17: ="" | ... AW17: ="" | AY17: ="" | AZ17: ="" | BA17: ="" | BB17: ="" | BC17: ="" | BD17: ="" | BE17: ="" | BF17: ="" | ... BL17: ="" | BN17: ="" | BO17: ="" | BP17: ="" | BQ17: ="" | BR17: ="" | BS17: ="" | BT17: ="" | BU17: ="" | ... CA17: ="" | CC17: ="" | CD17: ="" | CE17: ="" | CF17: ="" | CG17: ="" | CH17: ="" | CI17: ="" | CJ17: ="" | ... CP17: ="" | CR17: ='测算-京东自营'!I$22 -> 0.160283 | CS17: ='测算-京东自营'!J$22 -> 0.157019 | CT17: ='测算-京东自营'!K$22 -> 0.504767 | CU17: ='测算-京东自营'!L$22 -> 0.367181 | CV17: ='测算-京东自营'!M$22 -> 4.232029 | CW17: ='测算-京东自营'!N$22 -> 2.1994182 | CX17: ='测算-京东自营'!O$22 -> 1.0742887 | CY17: ='测算-京东自营'!P$22 -> 1.4368058 | ... DC17: ='测算-京东自营'!T$22 -> 2.0336329 | DD17: ='测算-京东自营'!V$22 -> 18.334848 | DE17: ='测算-京东自营'!W$22 -> 10.714151 | DG17: ="" | DH17: ="" | DI17: ="" | DJ17: ="" | DK17: ="" | DL17: ="" | DM17: ="" | DN17: ="" | ... DT17: ="" | DV17: ="" | DW17: ="" | DX17: ="" | DY17: ="" | DZ17: ="" | EA17: ="" | EB17: ="" | EC17: ="" | ... EI17: ="" | EK17: ="" | EL17: ="" | EM17: ="" | EN17: ="" | EO17: ="" | EP17: ="" | EQ17: ="" | ER17: ="" | ... EX17: =""
D18: 渠道投入 | E18: 商务政策费用 | F18: =SUM(U18,AJ18,AY18,BN18,CC18,CR18,DG18,DV18,EK18) -> 2.78929 | G18: =SUM(V18,AK18,AZ18,BO18,CD18,CS18,DH18,DW18,EL18) -> 2.923083 | H18: =SUM(W18,AL18,BA18,BP18,CE18,CT18,DI18,DX18,EM18) -> 16.47138 | I18: =SUM(X18,AM18,BB18,BQ18,CF18,CU18,DJ18,DY18,EN18) -> 3.142293 | J18: =SUM(Y18,AN18,BC18,BR18,CG18,CV18,DK18,DZ18,EO18) -> 7.224989 | K18: =SUM(Z18,AO18,BD18,BS18,CH18,CW18,DL18,EA18,EP18) -> 13.205987 | L18: =SUM(AA18,AP18,BE18,BT18,CI18,CX18,DM18,EB18,EQ18) -> 6.4503613 | M18: =SUM(AB18,AQ18,BF18,BU18,CJ18,CY18,DN18,EC18,ER18) -> 8.6270265 | ... Q18: =SUM(AF18,AU18,BJ18,BY18,CN18,DC18,DR18,EG18,EV18) -> 12.210561 | R18: =SUM(F18:Q18) -> 110.08809 | S18: =SUM(L18:Q18) -> 64.331073 | U18: ="" | V18: ="" | W18: ="" | X18: ="" | Y18: ="" | Z18: ="" | AA18: ="" | AB18: ="" | ... AH18: ="" | AJ18: ="" | AK18: ="" | AL18: ="" | AM18: ="" | AN18: ="" | AO18: ="" | AP18: ="" | AQ18: ="" | ... AW18: ="" | AY18: ="" | AZ18: ="" | BA18: ="" | BB18: ="" | BC18: ="" | BD18: ="" | BE18: ="" | BF18: ="" | ... BL18: ="" | BN18: ="" | BO18: ="" | BP18: ="" | BQ18: ="" | BR18: ="" | BS18: ="" | BT18: ="" | BU18: ="" | ... CA18: ="" | CC18: ="" | CD18: ="" | CE18: ="" | CF18: ="" | CG18: ="" | CH18: ="" | CI18: ="" | CJ18: ="" | ... CP18: ="" | CR18: ='测算-京东自营'!I$23 -> 2.78929 | CS18: ='测算-京东自营'!J$23 -> 2.923083 | CT18: ='测算-京东自营'!K$23 -> 16.47138 | CU18: ='测算-京东自营'!L$23 -> 3.142293 | CV18: ='测算-京东自营'!M$23 -> 7.224989 | CW18: ='测算-京东自营'!N$23 -> 13.205987 | CX18: ='测算-京东自营'!O$23 -> 6.4503613 | CY18: ='测算-京东自营'!P$23 -> 8.6270265 | ... DC18: ='测算-京东自营'!T$23 -> 12.210561 | DD18: ='测算-京东自营'!V$23 -> 110.08809 | DE18: ='测算-京东自营'!W$23 -> 64.331073 | DG18: ="" | DH18: ="" | DI18: ="" | DJ18: ="" | DK18: ="" | DL18: ="" | DM18: ="" | DN18: ="" | ... DT18: ="" | DV18: ="" | DW18: ="" | DX18: ="" | DY18: ="" | DZ18: ="" | EA18: ="" | EB18: ="" | EC18: ="" | ... EI18: ="" | EK18: ="" | EL18: ="" | EM18: ="" | EN18: ="" | EO18: ="" | EP18: ="" | EQ18: ="" | ER18: ="" | ... EX18: =""
C19: 达人费用 | F19: =SUM(U19,AJ19,AY19,BN19,CC19,CR19,DG19,DV19,EK19) -> 0 | G19: =SUM(V19,AK19,AZ19,BO19,CD19,CS19,DH19,DW19,EL19) -> 0 | H19: =SUM(W19,AL19,BA19,BP19,CE19,CT19,DI19,DX19,EM19) -> 0 | I19: =SUM(X19,AM19,BB19,BQ19,CF19,CU19,DJ19,DY19,EN19) -> 0 | J19: =SUM(Y19,AN19,BC19,BR19,CG19,CV19,DK19,DZ19,EO19) -> 0 | K19: =SUM(Z19,AO19,BD19,BS19,CH19,CW19,DL19,EA19,EP19) -> 0 | L19: =SUM(AA19,AP19,BE19,BT19,CI19,CX19,DM19,EB19,EQ19) -> 22.751163 | M19: =SUM(AB19,AQ19,BF19,BU19,CJ19,CY19,DN19,EC19,ER19) -> 30.42851 | ... Q19: =SUM(AF19,AU19,BJ19,BY19,CN19,DC19,DR19,EG19,EV19) -> 43.068044 | R19: =SUM(F19:Q19) -> 226.90306 | S19: =SUM(L19:Q19) -> 226.90306 | U19: =SUM(U21:U24) -> 0 | V19: =SUM(V21:V24) -> 0 | W19: =SUM(W21:W24) -> 0 | X19: =SUM(X21:X24) -> 0 | Y19: =SUM(Y21:Y24) -> 0 | Z19: =SUM(Z21:Z24) -> 0 | AA19: =SUM(AA21:AA24) -> 3.4668438 | AB19: =SUM(AB21:AB24) -> 4.6367253 | ... AH19: =SUM(AH21:AH24) -> 34.575704 | AJ19: =SUM(AJ21:AJ24) -> 0 | AK19: =SUM(AK21:AK24) -> 0 | AL19: =SUM(AL21:AL24) -> 0 | AM19: =SUM(AM21:AM24) -> 0 | AN19: =SUM(AN21:AN24) -> 0 | AO19: =SUM(AO21:AO24) -> 0 | AP19: =SUM(AP21:AP24) -> 2.8168106 | AQ19: =SUM(AQ21:AQ24) -> 3.7673393 | ... AW19: =SUM(AW21:AW24) -> 28.092759 | AY19: =SUM(AY21:AY24) -> 0 | AZ19: =SUM(AZ21:AZ24) -> 0 | BA19: =SUM(BA21:BA24) -> 0 | BB19: =SUM(BB21:BB24) -> 0 | BC19: =SUM(BC21:BC24) -> 0 | BD19: =SUM(BD21:BD24) -> 0 | BE19: =SUM(BE21:BE24) -> 0 | BF19: =SUM(BF21:BF24) -> 0 | ... BL19: =SUM(BL21:BL24) -> 0 | BN19: =SUM(BN21:BN24) -> 0 | BO19: =SUM(BO21:BO24) -> 0 | BP19: =SUM(BP21:BP24) -> 0 | BQ19: =SUM(BQ21:BQ24) -> 0 | BR19: =SUM(BR21:BR24) -> 0 | BS19: =SUM(BS21:BS24) -> 0 | BT19: =SUM(BT21:BT24) -> 0 | BU19: =SUM(BU21:BU24) -> 0 | ... CA19: =SUM(CA21:CA24) -> 0 | CC19: =SUM(CC21:CC24) -> 0 | CD19: =SUM(CD21:CD24) -> 0 | CE19: =SUM(CE21:CE24) -> 0 | CF19: =SUM(CF21:CF24) -> 0 | CG19: =SUM(CG21:CG24) -> 0 | CH19: =SUM(CH21:CH24) -> 0 | CI19: =SUM(CI21:CI24) -> 0 | CJ19: =SUM(CJ21:CJ24) -> 0 | ... CP19: =SUM(CP21:CP24) -> 0 | CR19: =SUM(CR21:CR24) -> 0 | CS19: =SUM(CS21:CS24) -> 0 | CT19: =SUM(CT21:CT24) -> 0 | CU19: =SUM(CU21:CU24) -> 0 | CV19: =SUM(CV21:CV24) -> 0 | CW19: =SUM(CW21:CW24) -> 0 | CX19: =SUM(CX21:CX24) -> 0 | CY19: =SUM(CY21:CY24) -> 0 | ... DE19: =SUM(DE21:DE24) -> 0 | DG19: =SUM(DG21:DG24) -> 0 | DH19: =SUM(DH21:DH24) -> 0 | DI19: =SUM(DI21:DI24) -> 0 | DJ19: =SUM(DJ21:DJ24) -> 0 | DK19: =SUM(DK21:DK24) -> 0 | DL19: =SUM(DL21:DL24) -> 0 | DM19: =SUM(DM21:DM24) -> 16.467508 | DN19: =SUM(DN21:DN24) -> 22.024445 | ... DT19: =SUM(DT21:DT24) -> 164.23459 | DV19: =SUM(DV21:DV24) -> 0 | DW19: =SUM(DW21:DW24) -> 0 | DX19: =SUM(DX21:DX24) -> 0 | DY19: =SUM(DY21:DY24) -> 0 | DZ19: =SUM(DZ21:DZ24) -> 0 | EA19: =SUM(EA21:EA24) -> 0 | EB19: =SUM(EB21:EB24) -> 0 | EC19: =SUM(EC21:EC24) -> 0 | ... EI19: =SUM(EI21:EI24) -> 0 | EK19: =SUM(EK21:EK24) -> 0 | EL19: =SUM(EL21:EL24) -> 0 | EM19: =SUM(EM21:EM24) -> 0 | EN19: =SUM(EN21:EN24) -> 0 | EO19: =SUM(EO21:EO24) -> 0 | EP19: =SUM(EP21:EP24) -> 0 | EQ19: =SUM(EQ21:EQ24) -> 0 | ER19: =SUM(ER21:ER24) -> 0 | ... EX19: =SUM(EX21:EX24) -> 0
C20: Margin | F20: =IFERROR(F19/F3,0) -> 0 | G20: =IFERROR(G19/G3,0) -> 0 | H20: =IFERROR(H19/H3,0) -> 0 | I20: =IFERROR(I19/I3,0) -> 0 | J20: =IFERROR(J19/J3,0) -> 0 | K20: =IFERROR(K19/K3,0) -> 0 | L20: =IFERROR(L19/L3,0) -> 0.028731879 | M20: =IFERROR(M19/M3,0) -> 0.029101499 | ... S20: =IFERROR(S19/S3,0) -> 0.029318498 | U20: =IFERROR(U19/U3,0) -> 0 | V20: =IFERROR(V19/V3,0) -> 0 | W20: =IFERROR(W19/W3,0) -> 0 | X20: =IFERROR(X19/X3,0) -> 0 | Y20: =IFERROR(Y19/Y3,0) -> 0 | Z20: =IFERROR(Z19/Z3,0) -> 0 | AA20: =IFERROR(AA19/AA3,0) -> 0.018456754 | AB20: =IFERROR(AB19/AB3,0) -> 0.018456754 | ... AH20: =IFERROR(AH19/AH3,0) -> 0.018456754 | AJ20: =IFERROR(AJ19/AJ3,0) -> 0 | AK20: =IFERROR(AK19/AK3,0) -> 0 | AL20: =IFERROR(AL19/AL3,0) -> 0 | AM20: =IFERROR(AM19/AM3,0) -> 0 | AN20: =IFERROR(AN19/AN3,0) -> 0 | AO20: =IFERROR(AO19/AO3,0) -> 0 | AP20: =IFERROR(AP19/AP3,0) -> 0.053272359 | AQ20: =IFERROR(AQ19/AQ3,0) -> 0.053272359 | ... AW20: =IFERROR(AW19/AW3,0) -> 0.053272359 | AY20: =IFERROR(AY19/AY3,0) -> 0 | AZ20: =IFERROR(AZ19/AZ3,0) -> 0 | BA20: =IFERROR(BA19/BA3,0) -> 0 | BB20: =IFERROR(BB19/BB3,0) -> 0 | BC20: =IFERROR(BC19/BC3,0) -> 0 | BD20: =IFERROR(BD19/BD3,0) -> 0 | BE20: =IFERROR(BE19/BE3,0) -> 0 | BF20: =IFERROR(BF19/BF3,0) -> 0 | ... BL20: =IFERROR(BL19/BL3,0) -> 0 | BN20: =IFERROR(BN19/BN3,0) -> 0 | BO20: =IFERROR(BO19/BO3,0) -> 0 | BP20: =IFERROR(BP19/BP3,0) -> 0 | BQ20: =IFERROR(BQ19/BQ3,0) -> 0 | BR20: =IFERROR(BR19/BR3,0) -> 0 | BS20: =IFERROR(BS19/BS3,0) -> 0 | BT20: =IFERROR(BT19/BT3,0) -> 0 | BU20: =IFERROR(BU19/BU3,0) -> 0 | ... CA20: =IFERROR(CA19/CA3,0) -> 0 | CC20: =IFERROR(CC19/CC3,0) -> 0 | CD20: =IFERROR(CD19/CD3,0) -> 0 | CE20: =IFERROR(CE19/CE3,0) -> 0 | CF20: =IFERROR(CF19/CF3,0) -> 0 | CG20: =IFERROR(CG19/CG3,0) -> 0 | CH20: =IFERROR(CH19/CH3,0) -> 0 | CI20: =IFERROR(CI19/CI3,0) -> 0 | CJ20: =IFERROR(CJ19/CJ3,0) -> 0 | ... CP20: =IFERROR(CP19/CP3,0) -> 0 | CR20: =IFERROR(CR19/CR3,0) -> 0 | CS20: =IFERROR(CS19/CS3,0) -> 0 | CT20: =IFERROR(CT19/CT3,0) -> 0 | CU20: =IFERROR(CU19/CU3,0) -> 0 | CV20: =IFERROR(CV19/CV3,0) -> 0 | CW20: =IFERROR(CW19/CW3,0) -> 0 | CX20: =IFERROR(CX19/CX3,0) -> 0 | CY20: =IFERROR(CY19/CY3,0) -> 0 | ... DE20: =IFERROR(DE19/DE3,0) -> 0 | DG20: =IFERROR(DG19/DG3,0) -> 0 | DH20: =IFERROR(DH19/DH3,0) -> 0 | DI20: =IFERROR(DI19/DI3,0) -> 0 | DJ20: =IFERROR(DJ19/DJ3,0) -> 0 | DK20: =IFERROR(DK19/DK3,0) -> 0 | DL20: =IFERROR(DL19/DL3,0) -> 0 | DM20: =IFERROR(DM19/DM3,0) -> 0.19 | DN20: =IFERROR(DN19/DN3,0) -> 0.19 | ... DT20: =IFERROR(DT19/DT3,0) -> 0.19 | DV20: =IFERROR(DV19/DV3,0) -> 0 | DW20: =IFERROR(DW19/DW3,0) -> 0 | DX20: =IFERROR(DX19/DX3,0) -> 0 | DY20: =IFERROR(DY19/DY3,0) -> 0 | DZ20: =IFERROR(DZ19/DZ3,0) -> 0 | EA20: =IFERROR(EA19/EA3,0) -> 0 | EB20: =IFERROR(EB19/EB3,0) -> 0 | EC20: =IFERROR(EC19/EC3,0) -> 0 | ... EI20: =IFERROR(EI19/EI3,0) -> 0 | EK20: =IFERROR(EK19/EK3,0) -> 0 | EL20: =IFERROR(EL19/EL3,0) -> 0 | EM20: =IFERROR(EM19/EM3,0) -> 0 | EN20: =IFERROR(EN19/EN3,0) -> 0 | EO20: =IFERROR(EO19/EO3,0) -> 0 | EP20: =IFERROR(EP19/EP3,0) -> 0 | EQ20: =IFERROR(EQ19/EQ3,0) -> 0 | ER20: =IFERROR(ER19/ER3,0) -> 0 | ... EX20: =IFERROR(EX19/EX3,0) -> 0
D21: 达人费用 | E21: 达人视频采买 | F21: =SUM(U21,AJ21,AY21,BN21,CC21,CR21,DG21,DV21,EK21) -> 0 | G21: =SUM(V21,AK21,AZ21,BO21,CD21,CS21,DH21,DW21,EL21) -> 0 | H21: =SUM(W21,AL21,BA21,BP21,CE21,CT21,DI21,DX21,EM21) -> 0 | I21: =SUM(X21,AM21,BB21,BQ21,CF21,CU21,DJ21,DY21,EN21) -> 0 | J21: =SUM(Y21,AN21,BC21,BR21,CG21,CV21,DK21,DZ21,EO21) -> 0 | K21: =SUM(Z21,AO21,BD21,BS21,CH21,CW21,DL21,EA21,EP21) -> 0 | L21: =SUM(AA21,AP21,BE21,BT21,CI21,CX21,DM21,EB21,EQ21) -> 3.4668438 | M21: =SUM(AB21,AQ21,BF21,BU21,CJ21,CY21,DN21,EC21,ER21) -> 4.6367253 | ... Q21: =SUM(AF21,AU21,BJ21,BY21,CN21,DC21,DR21,EG21,EV21) -> 6.5627496 | R21: =SUM(F21:Q21) -> 34.575704 | S21: =SUM(L21:Q21) -> 34.575704 | U21: ='测算-高个子抖音'!I$28 -> 0 | V21: ='测算-高个子抖音'!J$28 -> 0 | W21: ='测算-高个子抖音'!K$28 -> 0 | X21: ='测算-高个子抖音'!L$28 -> 0 | Y21: ='测算-高个子抖音'!M$28 -> 0 | Z21: ='测算-高个子抖音'!N$28 -> 0 | AA21: ='测算-高个子抖音'!O$28 -> 0.86671095 | AB21: ='测算-高个子抖音'!P$28 -> 1.1591813 | ... AF21: ='测算-高个子抖音'!T$28 -> 1.6406874 | AG21: ='测算-高个子抖音'!V$28 -> 8.6439259 | AH21: ='测算-高个子抖音'!W$28 -> 8.6439259 | AJ21: ='测算-高个子视频号'!I$28 -> 0 | AK21: ='测算-高个子视频号'!J$28 -> 0 | AL21: ='测算-高个子视频号'!K$28 -> 0 | AM21: ='测算-高个子视频号'!L$28 -> 0 | AN21: ='测算-高个子视频号'!M$28 -> 0 | AO21: ='测算-高个子视频号'!N$28 -> 0 | AP21: ='测算-高个子视频号'!O$28 -> 0.86671095 | AQ21: ='测算-高个子视频号'!P$28 -> 1.1591813 | ... AU21: ='测算-高个子视频号'!T$28 -> 1.6406874 | AV21: ='测算-高个子视频号'!V$28 -> 8.6439259 | AW21: ='测算-高个子视频号'!W$28 -> 8.6439259 | AY21: ='测算-天猫淘宝'!I$27 -> 0 | AZ21: ='测算-天猫淘宝'!J$27 -> 0 | BA21: ='测算-天猫淘宝'!K$27 -> 0 | BB21: ='测算-天猫淘宝'!L$27 -> 0 | BC21: ='测算-天猫淘宝'!M$27 -> 0 | BD21: ='测算-天猫淘宝'!N$27 -> 0 | BE21: ='测算-天猫淘宝'!O$27 -> 0 | BF21: ='测算-天猫淘宝'!P$27 -> 0 | ... BJ21: ='测算-天猫淘宝'!T$27 -> 0 | BK21: ='测算-天猫淘宝'!V$27 -> 0 | BL21: ='测算-天猫淘宝'!W$27 -> 0 | BN21: ='测算-拼多多'!I$28 -> 0 | BO21: ='测算-拼多多'!J$28 -> 0 | BP21: ='测算-拼多多'!K$28 -> 0 | BQ21: ='测算-拼多多'!L$28 -> 0 | BR21: ='测算-拼多多'!M$28 -> 0 | BS21: ='测算-拼多多'!N$28 -> 0 | BT21: ='测算-拼多多'!O$28 -> 0 | BU21: ='测算-拼多多'!P$28 -> 0 | ... BY21: ='测算-拼多多'!T$28 -> 0 | BZ21: ='测算-拼多多'!V$28 -> 0 | CA21: ='测算-拼多多'!W$28 -> 0 | CC21: ='测算-京东POP'!I$28 -> 0 | CD21: ='测算-京东POP'!J$28 -> 0 | CE21: ='测算-京东POP'!K$28 -> 0 | CF21: ='测算-京东POP'!L$28 -> 0 | CG21: ='测算-京东POP'!M$28 -> 0 | CH21: ='测算-京东POP'!N$28 -> 0 | CI21: ='测算-京东POP'!O$28 -> 0 | CJ21: ='测算-京东POP'!P$28 -> 0 | ... CN21: ='测算-京东POP'!T$28 -> 0 | CO21: ='测算-京东POP'!V$28 -> 0 | CP21: ='测算-京东POP'!W$28 -> 0 | CR21: ='测算-京东自营'!I$29 -> 0 | CS21: ='测算-京东自营'!J$29 -> 0 | CT21: ='测算-京东自营'!K$29 -> 0 | CU21: ='测算-京东自营'!L$29 -> 0 | CV21: ='测算-京东自营'!M$29 -> 0 | CW21: ='测算-京东自营'!N$29 -> 0 | CX21: ='测算-京东自营'!O$29 -> 0 | CY21: ='测算-京东自营'!P$29 -> 0 | ... DC21: ='测算-京东自营'!T$29 -> 0 | DD21: ='测算-京东自营'!V$29 -> 0 | DE21: ='测算-京东自营'!W$29 -> 0 | DG21: ='测算-达播'!I$29 -> 0 | DH21: ='测算-达播'!J$29 -> 0 | DI21: ='测算-达播'!K$29 -> 0 | DJ21: ='测算-达播'!L$29 -> 0 | DK21: ='测算-达播'!M$29 -> 0 | DL21: ='测算-达播'!N$29 -> 0 | DM21: ='测算-达播'!O$29 -> 1.7334219 | DN21: ='测算-达播'!P$29 -> 2.3183626 | ... DR21: ='测算-达播'!T$29 -> 3.2813748 | DS21: ='测算-达播'!V$29 -> 17.287852 | DT21: ='测算-达播'!W$29 -> 17.287852 | DV21: ='测算-私域'!I$28 -> 0 | DW21: ='测算-私域'!J$28 -> 0 | DX21: ='测算-私域'!K$28 -> 0 | DY21: ='测算-私域'!L$28 -> 0 | DZ21: ='测算-私域'!M$28 -> 0 | EA21: ='测算-私域'!N$28 -> 0 | EB21: ='测算-私域'!O$28 -> 0 | EC21: ='测算-私域'!P$28 -> 0 | ... EG21: ='测算-私域'!T$28 -> 0 | EH21: ='测算-私域'!V$28 -> 0 | EI21: ='测算-私域'!W$28 -> 0 | EK21: ='测算-外部分销'!I$28 | EL21: ='测算-外部分销'!J$28 | EM21: ='测算-外部分销'!K$28 | EN21: ='测算-外部分销'!L$28 | EO21: ='测算-外部分销'!M$28 | EP21: ='测算-外部分销'!N$28 | EQ21: ='测算-外部分销'!O$28 -> 0 | ER21: ='测算-外部分销'!P$28 -> 0 | ... EV21: ='测算-外部分销'!T$28 -> 0 | EW21: ='测算-外部分销'!V$28 -> 0 | EX21: ='测算-外部分销'!W$28 -> 0
D22: 达人费用 | E22: 达人视频带货佣金 | F22: =SUM(U22,AJ22,AY22,BN22,CC22,CR22,DG22,DV22,EK22) -> 0 | G22: =SUM(V22,AK22,AZ22,BO22,CD22,CS22,DH22,DW22,EL22) -> 0 | H22: =SUM(W22,AL22,BA22,BP22,CE22,CT22,DI22,DX22,EM22) -> 0 | I22: =SUM(X22,AM22,BB22,BQ22,CF22,CU22,DJ22,DY22,EN22) -> 0 | J22: =SUM(Y22,AN22,BC22,BR22,CG22,CV22,DK22,DZ22,EO22) -> 0 | K22: =SUM(Z22,AO22,BD22,BS22,CH22,CW22,DL22,EA22,EP22) -> 0 | L22: =SUM(AA22,AP22,BE22,BT22,CI22,CX22,DM22,EB22,EQ22) -> 5.2002657 | M22: =SUM(AB22,AQ22,BF22,BU22,CJ22,CY22,DN22,EC22,ER22) -> 6.9550879 | ... Q22: =SUM(AF22,AU22,BJ22,BY22,CN22,DC22,DR22,EG22,EV22) -> 9.8441244 | R22: =SUM(F22:Q22) -> 51.863555 | S22: =SUM(L22:Q22) -> 51.863555 | U22: ='测算-高个子抖音'!I$29 -> 0 | V22: ='测算-高个子抖音'!J$29 -> 0 | W22: ='测算-高个子抖音'!K$29 -> 0 | X22: ='测算-高个子抖音'!L$29 -> 0 | Y22: ='测算-高个子抖音'!M$29 -> 0 | Z22: ='测算-高个子抖音'!N$29 -> 0 | AA22: ='测算-高个子抖音'!O$29 -> 2.6001329 | AB22: ='测算-高个子抖音'!P$29 -> 3.477544 | ... AF22: ='测算-高个子抖音'!T$29 -> 4.9220622 | AG22: ='测算-高个子抖音'!V$29 -> 25.931778 | AH22: ='测算-高个子抖音'!W$29 -> 25.931778 | AJ22: ='测算-高个子视频号'!I$29 -> 0 | AK22: ='测算-高个子视频号'!J$29 -> 0 | AL22: ='测算-高个子视频号'!K$29 -> 0 | AM22: ='测算-高个子视频号'!L$29 -> 0 | AN22: ='测算-高个子视频号'!M$29 -> 0 | AO22: ='测算-高个子视频号'!N$29 -> 0 | AP22: ='测算-高个子视频号'!O$29 -> 0.86671095 | AQ22: ='测算-高个子视频号'!P$29 -> 1.1591813 | ... AU22: ='测算-高个子视频号'!T$29 -> 1.6406874 | AV22: ='测算-高个子视频号'!V$29 -> 8.6439259 | AW22: ='测算-高个子视频号'!W$29 -> 8.6439259 | AY22: ='测算-天猫淘宝'!I$28 -> 0 | AZ22: ='测算-天猫淘宝'!J$28 -> 0 | BA22: ='测算-天猫淘宝'!K$28 -> 0 | BB22: ='测算-天猫淘宝'!L$28 -> 0 | BC22: ='测算-天猫淘宝'!M$28 -> 0 | BD22: ='测算-天猫淘宝'!N$28 -> 0 | BE22: ='测算-天猫淘宝'!O$28 -> 0 | BF22: ='测算-天猫淘宝'!P$28 -> 0 | ... BJ22: ='测算-天猫淘宝'!T$28 -> 0 | BK22: ='测算-天猫淘宝'!V$28 -> 0 | BL22: ='测算-天猫淘宝'!W$28 -> 0 | BN22: ='测算-拼多多'!I$29 -> 0 | BO22: ='测算-拼多多'!J$29 -> 0 | BP22: ='测算-拼多多'!K$29 -> 0 | BQ22: ='测算-拼多多'!L$29 -> 0 | BR22: ='测算-拼多多'!M$29 -> 0 | BS22: ='测算-拼多多'!N$29 -> 0 | BT22: ='测算-拼多多'!O$29 -> 0 | BU22: ='测算-拼多多'!P$29 -> 0 | ... BY22: ='测算-拼多多'!T$29 -> 0 | BZ22: ='测算-拼多多'!V$29 -> 0 | CA22: ='测算-拼多多'!W$29 -> 0 | CC22: ='测算-京东POP'!I$29 -> 0 | CD22: ='测算-京东POP'!J$29 -> 0 | CE22: ='测算-京东POP'!K$29 -> 0 | CF22: ='测算-京东POP'!L$29 -> 0 | CG22: ='测算-京东POP'!M$29 -> 0 | CH22: ='测算-京东POP'!N$29 -> 0 | CI22: ='测算-京东POP'!O$29 -> 0 | CJ22: ='测算-京东POP'!P$29 -> 0 | ... CN22: ='测算-京东POP'!T$29 -> 0 | CO22: ='测算-京东POP'!V$29 -> 0 | CP22: ='测算-京东POP'!W$29 -> 0 | CR22: ='测算-京东自营'!I$30 -> 0 | CS22: ='测算-京东自营'!J$30 -> 0 | CT22: ='测算-京东自营'!K$30 -> 0 | CU22: ='测算-京东自营'!L$30 -> 0 | CV22: ='测算-京东自营'!M$30 -> 0 | CW22: ='测算-京东自营'!N$30 -> 0 | CX22: ='测算-京东自营'!O$30 -> 0 | CY22: ='测算-京东自营'!P$30 -> 0 | ... DC22: ='测算-京东自营'!T$30 -> 0 | DD22: ='测算-京东自营'!V$30 -> 0 | DE22: ='测算-京东自营'!W$30 -> 0 | DG22: ='测算-达播'!I$30 -> 0 | DH22: ='测算-达播'!J$30 -> 0 | DI22: ='测算-达播'!K$30 -> 0 | DJ22: ='测算-达播'!L$30 -> 0 | DK22: ='测算-达播'!M$30 -> 0 | DL22: ='测算-达播'!N$30 -> 0 | DM22: ='测算-达播'!O$30 -> 1.7334219 | DN22: ='测算-达播'!P$30 -> 2.3183626 | ... DR22: ='测算-达播'!T$30 -> 3.2813748 | DS22: ='测算-达播'!V$30 -> 17.287852 | DT22: ='测算-达播'!W$30 -> 17.287852 | DV22: ='测算-私域'!I$29 -> 0 | DW22: ='测算-私域'!J$29 -> 0 | DX22: ='测算-私域'!K$29 -> 0 | DY22: ='测算-私域'!L$29 -> 0 | DZ22: ='测算-私域'!M$29 -> 0 | EA22: ='测算-私域'!N$29 -> 0 | EB22: ='测算-私域'!O$29 -> 0 | EC22: ='测算-私域'!P$29 -> 0 | ... EG22: ='测算-私域'!T$29 -> 0 | EH22: ='测算-私域'!V$29 -> 0 | EI22: ='测算-私域'!W$29 -> 0 | EK22: ='测算-外部分销'!I$29 | EL22: ='测算-外部分销'!J$29 | EM22: ='测算-外部分销'!K$29 | EN22: ='测算-外部分销'!L$29 | EO22: ='测算-外部分销'!M$29 | EP22: ='测算-外部分销'!N$29 | EQ22: ='测算-外部分销'!O$29 -> 0 | ER22: ='测算-外部分销'!P$29 -> 0 | ... EV22: ='测算-外部分销'!T$29 -> 0 | EW22: ='测算-外部分销'!V$29 -> 0 | EX22: ='测算-外部分销'!W$29 -> 0
D23: 达人费用 | E23: 达人直播带货佣金 | F23: =SUM(U23,AJ23,AY23,BN23,CC23,CR23,DG23,DV23,EK23) -> 0 | G23: =SUM(V23,AK23,AZ23,BO23,CD23,CS23,DH23,DW23,EL23) -> 0 | H23: =SUM(W23,AL23,BA23,BP23,CE23,CT23,DI23,DX23,EM23) -> 0 | I23: =SUM(X23,AM23,BB23,BQ23,CF23,CU23,DJ23,DY23,EN23) -> 0 | J23: =SUM(Y23,AN23,BC23,BR23,CG23,CV23,DK23,DZ23,EO23) -> 0 | K23: =SUM(Z23,AO23,BD23,BS23,CH23,CW23,DL23,EA23,EP23) -> 0 | L23: =SUM(AA23,AP23,BE23,BT23,CI23,CX23,DM23,EB23,EQ23) -> 6.2836544 | M23: =SUM(AB23,AQ23,BF23,BU23,CJ23,CY23,DN23,EC23,ER23) -> 8.4040646 | ... Q23: =SUM(AF23,AU23,BJ23,BY23,CN23,DC23,DR23,EG23,EV23) -> 11.894984 | R23: =SUM(F23:Q23) -> 62.668463 | S23: =SUM(L23:Q23) -> 62.668463 | U23: ='测算-高个子抖音'!I$30 -> 0 | V23: ='测算-高个子抖音'!J$30 -> 0 | W23: ='测算-高个子抖音'!K$30 -> 0 | X23: ='测算-高个子抖音'!L$30 -> 0 | Y23: ='测算-高个子抖音'!M$30 -> 0 | Z23: ='测算-高个子抖音'!N$30 -> 0 | AA23: ='测算-高个子抖音'!O$30 -> 0 | AB23: ='测算-高个子抖音'!P$30 -> 0 | ... AF23: ='测算-高个子抖音'!T$30 -> 0 | AG23: ='测算-高个子抖音'!V$30 -> 0 | AH23: ='测算-高个子抖音'!W$30 -> 0 | AJ23: ='测算-高个子视频号'!I$30 -> 0 | AK23: ='测算-高个子视频号'!J$30 -> 0 | AL23: ='测算-高个子视频号'!K$30 -> 0 | AM23: ='测算-高个子视频号'!L$30 -> 0 | AN23: ='测算-高个子视频号'!M$30 -> 0 | AO23: ='测算-高个子视频号'!N$30 -> 0 | AP23: ='测算-高个子视频号'!O$30 -> 1.0833887 | AQ23: ='测算-高个子视频号'!P$30 -> 1.4489766 | ... AU23: ='测算-高个子视频号'!T$30 -> 2.0508593 | AV23: ='测算-高个子视频号'!V$30 -> 10.804907 | AW23: ='测算-高个子视频号'!W$30 -> 10.804907 | AY23: ='测算-天猫淘宝'!I$29 -> 0 | AZ23: ='测算-天猫淘宝'!J$29 -> 0 | BA23: ='测算-天猫淘宝'!K$29 -> 0 | BB23: ='测算-天猫淘宝'!L$29 -> 0 | BC23: ='测算-天猫淘宝'!M$29 -> 0 | BD23: ='测算-天猫淘宝'!N$29 -> 0 | BE23: ='测算-天猫淘宝'!O$29 -> 0 | BF23: ='测算-天猫淘宝'!P$29 -> 0 | ... BJ23: ='测算-天猫淘宝'!T$29 -> 0 | BK23: ='测算-天猫淘宝'!V$29 -> 0 | BL23: ='测算-天猫淘宝'!W$29 -> 0 | BN23: ='测算-拼多多'!I$30 -> 0 | BO23: ='测算-拼多多'!J$30 -> 0 | BP23: ='测算-拼多多'!K$30 -> 0 | BQ23: ='测算-拼多多'!L$30 -> 0 | BR23: ='测算-拼多多'!M$30 -> 0 | BS23: ='测算-拼多多'!N$30 -> 0 | BT23: ='测算-拼多多'!O$30 -> 0 | BU23: ='测算-拼多多'!P$30 -> 0 | ... BY23: ='测算-拼多多'!T$30 -> 0 | BZ23: ='测算-拼多多'!V$30 -> 0 | CA23: ='测算-拼多多'!W$30 -> 0 | CC23: ='测算-京东POP'!I$30 -> 0 | CD23: ='测算-京东POP'!J$30 -> 0 | CE23: ='测算-京东POP'!K$30 -> 0 | CF23: ='测算-京东POP'!L$30 -> 0 | CG23: ='测算-京东POP'!M$30 -> 0 | CH23: ='测算-京东POP'!N$30 -> 0 | CI23: ='测算-京东POP'!O$30 -> 0 | CJ23: ='测算-京东POP'!P$30 -> 0 | ... CN23: ='测算-京东POP'!T$30 -> 0 | CO23: ='测算-京东POP'!V$30 -> 0 | CP23: ='测算-京东POP'!W$30 -> 0 | CR23: ='测算-京东自营'!I$31 -> 0 | CS23: ='测算-京东自营'!J$31 -> 0 | CT23: ='测算-京东自营'!K$31 -> 0 | CU23: ='测算-京东自营'!L$31 -> 0 | CV23: ='测算-京东自营'!M$31 -> 0 | CW23: ='测算-京东自营'!N$31 -> 0 | CX23: ='测算-京东自营'!O$31 -> 0 | CY23: ='测算-京东自营'!P$31 -> 0 | ... DC23: ='测算-京东自营'!T$31 -> 0 | DD23: ='测算-京东自营'!V$31 -> 0 | DE23: ='测算-京东自营'!W$31 -> 0 | DG23: ='测算-达播'!I$31 -> 0 | DH23: ='测算-达播'!J$31 -> 0 | DI23: ='测算-达播'!K$31 -> 0 | DJ23: ='测算-达播'!L$31 -> 0 | DK23: ='测算-达播'!M$31 -> 0 | DL23: ='测算-达播'!N$31 -> 0 | DM23: ='测算-达播'!O$31 -> 5.2002657 | DN23: ='测算-达播'!P$31 -> 6.9550879 | ... DR23: ='测算-达播'!T$31 -> 9.8441244 | DS23: ='测算-达播'!V$31 -> 51.863555 | DT23: ='测算-达播'!W$31 -> 51.863555 | DV23: ='测算-私域'!I$30 -> 0 | DW23: ='测算-私域'!J$30 -> 0 | DX23: ='测算-私域'!K$30 -> 0 | DY23: ='测算-私域'!L$30 -> 0 | DZ23: ='测算-私域'!M$30 -> 0 | EA23: ='测算-私域'!N$30 -> 0 | EB23: ='测算-私域'!O$30 -> 0 | EC23: ='测算-私域'!P$30 -> 0 | ... EG23: ='测算-私域'!T$30 -> 0 | EH23: ='测算-私域'!V$30 -> 0 | EI23: ='测算-私域'!W$30 -> 0 | EK23: ='测算-外部分销'!I$30 | EL23: ='测算-外部分销'!J$30 | EM23: ='测算-外部分销'!K$30 | EN23: ='测算-外部分销'!L$30 | EO23: ='测算-外部分销'!M$30 | EP23: ='测算-外部分销'!N$30 | EQ23: ='测算-外部分销'!O$30 -> 0 | ER23: ='测算-外部分销'!P$30 -> 0 | ... EV23: ='测算-外部分销'!T$30 -> 0 | EW23: ='测算-外部分销'!V$30 -> 0 | EX23: ='测算-外部分销'!W$30 -> 0
D24: 达人费用 | E24: 达人直播坑位费 | F24: =SUM(U24,AJ24,AY24,BN24,CC24,CR24,DG24,DV24,EK24) -> 0 | G24: =SUM(V24,AK24,AZ24,BO24,CD24,CS24,DH24,DW24,EL24) -> 0 | H24: =SUM(W24,AL24,BA24,BP24,CE24,CT24,DI24,DX24,EM24) -> 0 | I24: =SUM(X24,AM24,BB24,BQ24,CF24,CU24,DJ24,DY24,EN24) -> 0 | J24: =SUM(Y24,AN24,BC24,BR24,CG24,CV24,DK24,DZ24,EO24) -> 0 | K24: =SUM(Z24,AO24,BD24,BS24,CH24,CW24,DL24,EA24,EP24) -> 0 | L24: =SUM(AA24,AP24,BE24,BT24,CI24,CX24,DM24,EB24,EQ24) -> 7.8003986 | M24: =SUM(AB24,AQ24,BF24,BU24,CJ24,CY24,DN24,EC24,ER24) -> 10.432632 | ... Q24: =SUM(AF24,AU24,BJ24,BY24,CN24,DC24,DR24,EG24,EV24) -> 14.766187 | R24: =SUM(F24:Q24) -> 77.795333 | S24: =SUM(L24:Q24) -> 77.795333 | U24: ='测算-高个子抖音'!I$31 -> 0 | V24: ='测算-高个子抖音'!J$31 -> 0 | W24: ='测算-高个子抖音'!K$31 -> 0 | X24: ='测算-高个子抖音'!L$31 -> 0 | Y24: ='测算-高个子抖音'!M$31 -> 0 | Z24: ='测算-高个子抖音'!N$31 -> 0 | AA24: ='测算-高个子抖音'!O$31 -> 0 | AB24: ='测算-高个子抖音'!P$31 -> 0 | ... AF24: ='测算-高个子抖音'!T$31 -> 0 | AG24: ='测算-高个子抖音'!V$31 -> 0 | AH24: ='测算-高个子抖音'!W$31 -> 0 | AJ24: ='测算-高个子视频号'!I$31 -> 0 | AK24: ='测算-高个子视频号'!J$31 -> 0 | AL24: ='测算-高个子视频号'!K$31 -> 0 | AM24: ='测算-高个子视频号'!L$31 -> 0 | AN24: ='测算-高个子视频号'!M$31 -> 0 | AO24: ='测算-高个子视频号'!N$31 -> 0 | AP24: ='测算-高个子视频号'!O$31 -> 0 | AQ24: ='测算-高个子视频号'!P$31 -> 0 | ... AU24: ='测算-高个子视频号'!T$31 -> 0 | AV24: ='测算-高个子视频号'!V$31 -> 0 | AW24: ='测算-高个子视频号'!W$31 -> 0 | AY24: ='测算-天猫淘宝'!I$30 -> 0 | AZ24: ='测算-天猫淘宝'!J$30 -> 0 | BA24: ='测算-天猫淘宝'!K$30 -> 0 | BB24: ='测算-天猫淘宝'!L$30 -> 0 | BC24: ='测算-天猫淘宝'!M$30 -> 0 | BD24: ='测算-天猫淘宝'!N$30 -> 0 | BE24: ='测算-天猫淘宝'!O$30 -> 0 | BF24: ='测算-天猫淘宝'!P$30 -> 0 | ... BJ24: ='测算-天猫淘宝'!T$30 -> 0 | BK24: ='测算-天猫淘宝'!V$30 -> 0 | BL24: ='测算-天猫淘宝'!W$30 -> 0 | BN24: ='测算-拼多多'!I$31 -> 0 | BO24: ='测算-拼多多'!J$31 -> 0 | BP24: ='测算-拼多多'!K$31 -> 0 | BQ24: ='测算-拼多多'!L$31 -> 0 | BR24: ='测算-拼多多'!M$31 -> 0 | BS24: ='测算-拼多多'!N$31 -> 0 | BT24: ='测算-拼多多'!O$31 -> 0 | BU24: ='测算-拼多多'!P$31 -> 0 | ... BY24: ='测算-拼多多'!T$31 -> 0 | BZ24: ='测算-拼多多'!V$31 -> 0 | CA24: ='测算-拼多多'!W$31 -> 0 | CC24: ='测算-京东POP'!I$31 -> 0 | CD24: ='测算-京东POP'!J$31 -> 0 | CE24: ='测算-京东POP'!K$31 -> 0 | CF24: ='测算-京东POP'!L$31 -> 0 | CG24: ='测算-京东POP'!M$31 -> 0 | CH24: ='测算-京东POP'!N$31 -> 0 | CI24: ='测算-京东POP'!O$31 -> 0 | CJ24: ='测算-京东POP'!P$31 -> 0 | ... CN24: ='测算-京东POP'!T$31 -> 0 | CO24: ='测算-京东POP'!V$31 -> 0 | CP24: ='测算-京东POP'!W$31 -> 0 | CR24: ='测算-京东自营'!I$32 -> 0 | CS24: ='测算-京东自营'!J$32 -> 0 | CT24: ='测算-京东自营'!K$32 -> 0 | CU24: ='测算-京东自营'!L$32 -> 0 | CV24: ='测算-京东自营'!M$32 -> 0 | CW24: ='测算-京东自营'!N$32 -> 0 | CX24: ='测算-京东自营'!O$32 -> 0 | CY24: ='测算-京东自营'!P$32 -> 0 | ... DC24: ='测算-京东自营'!T$32 -> 0 | DD24: ='测算-京东自营'!V$32 -> 0 | DE24: ='测算-京东自营'!W$32 -> 0 | DG24: ='测算-达播'!I$32 -> 0 | DH24: ='测算-达播'!J$32 -> 0 | DI24: ='测算-达播'!K$32 -> 0 | DJ24: ='测算-达播'!L$32 -> 0 | DK24: ='测算-达播'!M$32 -> 0 | DL24: ='测算-达播'!N$32 -> 0 | DM24: ='测算-达播'!O$32 -> 7.8003986 | DN24: ='测算-达播'!P$32 -> 10.432632 | ... DR24: ='测算-达播'!T$32 -> 14.766187 | DS24: ='测算-达播'!V$32 -> 77.795333 | DT24: ='测算-达播'!W$32 -> 77.795333 | DV24: ='测算-私域'!I$31 -> 0 | DW24: ='测算-私域'!J$31 -> 0 | DX24: ='测算-私域'!K$31 -> 0 | DY24: ='测算-私域'!L$31 -> 0 | DZ24: ='测算-私域'!M$31 -> 0 | EA24: ='测算-私域'!N$31 -> 0 | EB24: ='测算-私域'!O$31 -> 0 | EC24: ='测算-私域'!P$31 -> 0 | ... EG24: ='测算-私域'!T$31 -> 0 | EH24: ='测算-私域'!V$31 -> 0 | EI24: ='测算-私域'!W$31 -> 0 | EK24: ='测算-外部分销'!I$31 | EL24: ='测算-外部分销'!J$31 | EM24: ='测算-外部分销'!K$31 | EN24: ='测算-外部分销'!L$31 | EO24: ='测算-外部分销'!M$31 | EP24: ='测算-外部分销'!N$31 | EQ24: ='测算-外部分销'!O$31 -> 0 | ER24: ='测算-外部分销'!P$31 -> 0 | ... EV24: ='测算-外部分销'!T$31 -> 0 | EW24: ='测算-外部分销'!V$31 -> 0 | EX24: ='测算-外部分销'!W$31 -> 0
C25: 行销支持 | F25: =SUM(U25,AJ25,AY25,BN25,CC25,CR25,DG25,DV25,EK25) -> 7.659842 | G25: =SUM(V25,AK25,AZ25,BO25,CD25,CS25,DH25,DW25,EL25) -> 3.539312 | H25: =SUM(W25,AL25,BA25,BP25,CE25,CT25,DI25,DX25,EM25) -> 7.686161 | I25: =SUM(X25,AM25,BB25,BQ25,CF25,CU25,DJ25,DY25,EN25) -> 4.708707 | J25: =SUM(Y25,AN25,BC25,BR25,CG25,CV25,DK25,DZ25,EO25) -> 8.107537 | K25: =SUM(Z25,AO25,BD25,BS25,CH25,CW25,DL25,EA25,EP25) -> 11.194122 | L25: =SUM(AA25,AP25,BE25,BT25,CI25,CX25,DM25,EB25,EQ25) -> 7.5643179 | M25: =SUM(AB25,AQ25,BF25,BU25,CJ25,CY25,DN25,EC25,ER25) -> 9.6528241 | ... Q25: =SUM(AF25,AU25,BJ25,BY25,CN25,DC25,DR25,EG25,EV25) -> 13.082199 | R25: =SUM(F25:Q25) -> 112.8851 | S25: =SUM(L25:Q25) -> 69.989414 | U25: =SUM(U27:U29) -> 0 | V25: =SUM(V27:V29) -> 0 | W25: =SUM(W27:W29) -> 0 | X25: =SUM(X27:X29) -> 0 | Y25: =SUM(Y27:Y29) -> 0 | Z25: =SUM(Z27:Z29) -> 0 | AA25: =SUM(AA27:AA29) -> 0 | AB25: =SUM(AB27:AB29) -> 0 | ... AH25: =SUM(AH27:AH29) -> 0 | AJ25: =SUM(AJ27:AJ29) -> 3.887473 | AK25: =SUM(AK27:AK29) -> 0.870303 | AL25: =SUM(AL27:AL29) -> 2.244855 | AM25: =SUM(AM27:AM29) -> 0.384608 | AN25: =SUM(AN27:AN29) -> 3.535826 | AO25: =SUM(AO27:AO29) -> 6.3484551 | AP25: =SUM(AP27:AP29) -> 4.7589797 | AQ25: =SUM(AQ27:AQ29) -> 6.3648906 | ... AW25: =SUM(AW27:AW29) -> 47.4625 | AY25: =SUM(AY27:AY29) -> 0 | AZ25: =SUM(AZ27:AZ29) -> 0 | BA25: =SUM(BA27:BA29) -> 0 | BB25: =SUM(BB27:BB29) -> 0 | BC25: =SUM(BC27:BC29) -> 0 | BD25: =SUM(BD27:BD29) -> 0 | BE25: =SUM(BE27:BE29) -> 0 | BF25: =SUM(BF27:BF29) -> 0 | ... BL25: =SUM(BL27:BL29) -> 0 | BN25: =SUM(BN27:BN29) -> 0 | BO25: =SUM(BO27:BO29) -> 0 | BP25: =SUM(BP27:BP29) -> 0 | BQ25: =SUM(BQ27:BQ29) -> 0 | BR25: =SUM(BR27:BR29) -> 0 | BS25: =SUM(BS27:BS29) -> 0 | BT25: =SUM(BT27:BT29) -> 0 | BU25: =SUM(BU27:BU29) -> 0 | ... CA25: =SUM(CA27:CA29) -> 0 | CC25: =SUM(CC27:CC29) -> 0 | CD25: =SUM(CD27:CD29) -> 0 | CE25: =SUM(CE27:CE29) -> 0 | CF25: =SUM(CF27:CF29) -> 0 | CG25: =SUM(CG27:CG29) -> 0 | CH25: =SUM(CH27:CH29) -> 0 | CI25: =SUM(CI27:CI29) -> 0 | CJ25: =SUM(CJ27:CJ29) -> 0 | ... CP25: =SUM(CP27:CP29) -> 0 | CR25: =SUM(CR27:CR29) -> 0 | CS25: =SUM(CS27:CS29) -> 0 | CT25: =SUM(CT27:CT29) -> 0 | CU25: =SUM(CU27:CU29) -> 0 | CV25: =SUM(CV27:CV29) -> 0 | CW25: =SUM(CW27:CW29) -> 0 | CX25: =SUM(CX27:CX29) -> 0 | CY25: =SUM(CY27:CY29) -> 0 | ... DE25: =SUM(DE27:DE29) -> 0 | DG25: =SUM(DG27:DG29) -> 0 | DH25: =SUM(DH27:DH29) -> 0 | DI25: =SUM(DI27:DI29) -> 0 | DJ25: =SUM(DJ27:DJ29) -> 0 | DK25: =SUM(DK27:DK29) -> 0 | DL25: =SUM(DL27:DL29) -> 0 | DM25: =SUM(DM27:DM29) -> 0 | DN25: =SUM(DN27:DN29) -> 0 | ... DT25: =SUM(DT27:DT29) -> 0 | DV25: =SUM(DV27:DV29) -> 0 | DW25: =SUM(DW27:DW29) -> 0 | DX25: =SUM(DX27:DX29) -> 0 | DY25: =SUM(DY27:DY29) -> 0 | DZ25: =SUM(DZ27:DZ29) -> 0 | EA25: =SUM(EA27:EA29) -> 0 | EB25: =SUM(EB27:EB29) -> 1.2403233 | EC25: =SUM(EC27:EC29) -> 1.1948066 | ... EI25: =SUM(EI27:EI29) -> 6.9186283 | EK25: =SUM(EK27:EK29) -> 3.772369 | EL25: =SUM(EL27:EL29) -> 2.669009 | EM25: =SUM(EM27:EM29) -> 5.441306 | EN25: =SUM(EN27:EN29) -> 4.324099 | EO25: =SUM(EO27:EO29) -> 4.571711 | EP25: =SUM(EP27:EP29) -> 4.845667 | EQ25: =SUM(EQ27:EQ29) -> 1.5650149 | ER25: =SUM(ER27:ER29) -> 2.0931269 | ... EX25: =SUM(EX27:EX29) -> 15.608286
C26: Margin | F26: =IFERROR(F25/F3,0) -> 0.0069854631 | G26: =IFERROR(G25/G3,0) -> 0.005322597 | H26: =IFERROR(H25/H3,0) -> 0.0075928092 | I26: =IFERROR(I25/I3,0) -> 0.0048153686 | J26: =IFERROR(J25/J3,0) -> 0.0066558705 | K26: =IFERROR(K25/K3,0) -> 0.0090232204 | L26: =IFERROR(L25/L3,0) -> 0.0095527894 | M26: =IFERROR(M25/M3,0) -> 0.009231857 | ... S26: =IFERROR(S25/S3,0) -> 0.0090434415 | U26: =IFERROR(U25/U3,0) -> 0 | V26: =IFERROR(V25/V3,0) -> 0 | W26: =IFERROR(W25/W3,0) -> 0 | X26: =IFERROR(X25/X3,0) -> 0 | Y26: =IFERROR(Y25/Y3,0) -> 0 | Z26: =IFERROR(Z25/Z3,0) -> 0 | AA26: =IFERROR(AA25/AA3,0) -> 0 | AB26: =IFERROR(AB25/AB3,0) -> 0 | ... AH26: =IFERROR(AH25/AH3,0) -> 0 | AJ26: =IFERROR(AJ25/AJ3,0) -> 0.24866777 | AK26: =IFERROR(AK25/AK3,0) -> 0.16304832 | AL26: =IFERROR(AL25/AL3,0) -> 0.19816432 | AM26: =IFERROR(AM25/AM3,0) -> 0.051284486 | AN26: =IFERROR(AN25/AN3,0) -> 0.052470817 | AO26: =IFERROR(AO25/AO3,0) -> 0.090003239 | AP26: =IFERROR(AP25/AP3,0) -> 0.090003239 | AQ26: =IFERROR(AQ25/AQ3,0) -> 0.090003239 | ... AW26: =IFERROR(AW25/AW3,0) -> 0.090003239 | AY26: =IFERROR(AY25/AY3,0) -> 0 | AZ26: =IFERROR(AZ25/AZ3,0) -> 0 | BA26: =IFERROR(BA25/BA3,0) -> 0 | BB26: =IFERROR(BB25/BB3,0) -> 0 | BC26: =IFERROR(BC25/BC3,0) -> 0 | BD26: =IFERROR(BD25/BD3,0) -> 0 | BE26: =IFERROR(BE25/BE3,0) -> 0 | BF26: =IFERROR(BF25/BF3,0) -> 0 | ... BL26: =IFERROR(BL25/BL3,0) -> 0 | BN26: =IFERROR(BN25/BN3,0) -> 0 | BO26: =IFERROR(BO25/BO3,0) -> 0 | BP26: =IFERROR(BP25/BP3,0) -> 0 | BQ26: =IFERROR(BQ25/BQ3,0) -> 0 | BR26: =IFERROR(BR25/BR3,0) -> 0 | BS26: =IFERROR(BS25/BS3,0) -> 0 | BT26: =IFERROR(BT25/BT3,0) -> 0 | BU26: =IFERROR(BU25/BU3,0) -> 0 | ... CA26: =IFERROR(CA25/CA3,0) -> 0 | CC26: =IFERROR(CC25/CC3,0) -> 0 | CD26: =IFERROR(CD25/CD3,0) -> 0 | CE26: =IFERROR(CE25/CE3,0) -> 0 | CF26: =IFERROR(CF25/CF3,0) -> 0 | CG26: =IFERROR(CG25/CG3,0) -> 0 | CH26: =IFERROR(CH25/CH3,0) -> 0 | CI26: =IFERROR(CI25/CI3,0) -> 0 | CJ26: =IFERROR(CJ25/CJ3,0) -> 0 | ... CP26: =IFERROR(CP25/CP3,0) -> 0 | CR26: =IFERROR(CR25/CR3,0) -> 0 | CS26: =IFERROR(CS25/CS3,0) -> 0 | CT26: =IFERROR(CT25/CT3,0) -> 0 | CU26: =IFERROR(CU25/CU3,0) -> 0 | CV26: =IFERROR(CV25/CV3,0) -> 0 | CW26: =IFERROR(CW25/CW3,0) -> 0 | CX26: =IFERROR(CX25/CX3,0) -> 0 | CY26: =IFERROR(CY25/CY3,0) -> 0 | ... DE26: =IFERROR(DE25/DE3,0) -> 0 | DG26: =IFERROR(DG25/DG3,0) -> 0 | DH26: =IFERROR(DH25/DH3,0) -> 0 | DI26: =IFERROR(DI25/DI3,0) -> 0 | DJ26: =IFERROR(DJ25/DJ3,0) -> 0 | DK26: =IFERROR(DK25/DK3,0) -> 0 | DL26: =IFERROR(DL25/DL3,0) -> 0 | DM26: =IFERROR(DM25/DM3,0) -> 0 | DN26: =IFERROR(DN25/DN3,0) -> 0 | ... DT26: =IFERROR(DT25/DT3,0) -> 0 | DV26: =IFERROR(DV25/DV3,0) -> 0 | DW26: =IFERROR(DW25/DW3,0) -> 0 | DX26: =IFERROR(DX25/DX3,0) -> 0 | DY26: =IFERROR(DY25/DY3,0) -> 0 | DZ26: =IFERROR(DZ25/DZ3,0) -> 0 | EA26: =IFERROR(EA25/EA3,0) -> 0 | EB26: =IFERROR(EB25/EB3,0) -> 0.0345 | EC26: =IFERROR(EC25/EC3,0) -> 0.0345 | ... EI26: =IFERROR(EI25/EI3,0) -> 0.0345 | EK26: =IFERROR(EK25/EK3,0) -> 0.025228288 | EL26: =IFERROR(EL25/EL3,0) -> 0.030697022 | EM26: =IFERROR(EM25/EM3,0) -> 0.026257336 | EN26: =IFERROR(EN25/EN3,0) -> 0.032665316 | EO26: =IFERROR(EO25/EO3,0) -> 0.027016355 | EP26: =IFERROR(EP25/EP3,0) -> 0.033905883 | EQ26: =IFERROR(EQ25/EQ3,0) -> 0.029158099 | ER26: =IFERROR(ER25/ER3,0) -> 0.029158099 | ... EX26: =IFERROR(EX25/EX3,0) -> 0.029158099
D27: 行销支持 | E27: 赠品成本 | F27: =SUM(U27,AJ27,AY27,BN27,CC27,CR27,DG27,DV27,EK27) -> 3.772369 | G27: =SUM(V27,AK27,AZ27,BO27,CD27,CS27,DH27,DW27,EL27) -> 2.669009 | H27: =SUM(W27,AL27,BA27,BP27,CE27,CT27,DI27,DX27,EM27) -> 5.441306 | I27: =SUM(X27,AM27,BB27,BQ27,CF27,CU27,DJ27,DY27,EN27) -> 4.324099 | J27: =SUM(Y27,AN27,BC27,BR27,CG27,CV27,DK27,DZ27,EO27) -> 4.571711 | K27: =SUM(Z27,AO27,BD27,BS27,CH27,CW27,DL27,EA27,EP27) -> 4.845667 | L27: =SUM(AA27,AP27,BE27,BT27,CI27,CX27,DM27,EB27,EQ27) -> 2.8053382 | M27: =SUM(AB27,AQ27,BF27,BU27,CJ27,CY27,DN27,EC27,ER27) -> 3.2879335 | ... Q27: =SUM(AF27,AU27,BJ27,BY27,CN27,DC27,DR27,EG27,EV27) -> 4.0734305 | R27: =SUM(F27:Q27) -> 48.151076 | S27: =SUM(L27:Q27) -> 22.526915 | U27: ='测算-高个子抖音'!I$35 -> 0 | V27: ='测算-高个子抖音'!J$35 -> 0 | W27: ='测算-高个子抖音'!K$35 -> 0 | X27: ='测算-高个子抖音'!L$35 -> 0 | Y27: ='测算-高个子抖音'!M$35 -> 0 | Z27: ='测算-高个子抖音'!N$35 -> 0 | AA27: ='测算-高个子抖音'!O$35 -> 0 | AB27: ='测算-高个子抖音'!P$35 -> 0 | ... AF27: ='测算-高个子抖音'!T$35 -> 0 | AG27: ='测算-高个子抖音'!V$35 -> 0 | AH27: ='测算-高个子抖音'!W$35 -> 0 | AJ27: ='测算-高个子视频号'!I$35 -> 0 | AK27: ='测算-高个子视频号'!J$35 -> 0 | AL27: ='测算-高个子视频号'!K$35 -> 0 | AM27: ='测算-高个子视频号'!L$35 -> 0 | AN27: ='测算-高个子视频号'!M$35 -> 0 | AO27: ='测算-高个子视频号'!N$35 -> 0 | AP27: ='测算-高个子视频号'!O$35 -> 0 | AQ27: ='测算-高个子视频号'!P$35 -> 0 | ... AU27: ='测算-高个子视频号'!T$35 -> 0 | AV27: ='测算-高个子视频号'!V$35 -> 0 | AW27: ='测算-高个子视频号'!W$35 -> 0 | AY27: ='测算-天猫淘宝'!I$34 -> 0 | AZ27: ='测算-天猫淘宝'!J$34 -> 0 | BA27: ='测算-天猫淘宝'!K$34 -> 0 | BB27: ='测算-天猫淘宝'!L$34 -> 0 | BC27: ='测算-天猫淘宝'!M$34 -> 0 | BD27: ='测算-天猫淘宝'!N$34 -> 0 | BE27: ='测算-天猫淘宝'!O$34 -> 0 | BF27: ='测算-天猫淘宝'!P$34 -> 0 | ... BJ27: ='测算-天猫淘宝'!T$34 -> 0 | BK27: ='测算-天猫淘宝'!V$34 -> 0 | BL27: ='测算-天猫淘宝'!W$34 -> 0 | BN27: ='测算-拼多多'!I$35 -> 0 | BO27: ='测算-拼多多'!J$35 -> 0 | BP27: ='测算-拼多多'!K$35 -> 0 | BQ27: ='测算-拼多多'!L$35 -> 0 | BR27: ='测算-拼多多'!M$35 -> 0 | BS27: ='测算-拼多多'!N$35 -> 0 | BT27: ='测算-拼多多'!O$35 -> 0 | BU27: ='测算-拼多多'!P$35 -> 0 | ... BY27: ='测算-拼多多'!T$35 -> 0 | BZ27: ='测算-拼多多'!V$35 -> 0 | CA27: ='测算-拼多多'!W$35 -> 0 | CC27: ='测算-京东POP'!I$35 -> 0 | CD27: ='测算-京东POP'!J$35 -> 0 | CE27: ='测算-京东POP'!K$35 -> 0 | CF27: ='测算-京东POP'!L$35 -> 0 | CG27: ='测算-京东POP'!M$35 -> 0 | CH27: ='测算-京东POP'!N$35 -> 0 | CI27: ='测算-京东POP'!O$35 -> 0 | CJ27: ='测算-京东POP'!P$35 -> 0 | ... CN27: ='测算-京东POP'!T$35 -> 0 | CO27: ='测算-京东POP'!V$35 -> 0 | CP27: ='测算-京东POP'!W$35 -> 0 | CR27: ='测算-京东自营'!I$36 -> 0 | CS27: ='测算-京东自营'!J$36 -> 0 | CT27: ='测算-京东自营'!K$36 -> 0 | CU27: ='测算-京东自营'!L$36 -> 0 | CV27: ='测算-京东自营'!M$36 -> 0 | CW27: ='测算-京东自营'!N$36 -> 0 | CX27: ='测算-京东自营'!O$36 -> 0 | CY27: ='测算-京东自营'!P$36 -> 0 | ... DC27: ='测算-京东自营'!T$36 -> 0 | DD27: ='测算-京东自营'!V$36 -> 0 | DE27: ='测算-京东自营'!W$36 -> 0 | DG27: ='测算-达播'!I$36 -> 0 | DH27: ='测算-达播'!J$36 -> 0 | DI27: ='测算-达播'!K$36 -> 0 | DJ27: ='测算-达播'!L$36 -> 0 | DK27: ='测算-达播'!M$36 -> 0 | DL27: ='测算-达播'!N$36 -> 0 | DM27: ='测算-达播'!O$36 -> 0 | DN27: ='测算-达播'!P$36 -> 0 | ... DR27: ='测算-达播'!T$36 -> 0 | DS27: ='测算-达播'!V$36 -> 0 | DT27: ='测算-达播'!W$36 -> 0 | DV27: ='测算-私域'!I$35 -> 0 | DW27: ='测算-私域'!J$35 -> 0 | DX27: ='测算-私域'!K$35 -> 0 | DY27: ='测算-私域'!L$35 -> 0 | DZ27: ='测算-私域'!M$35 -> 0 | EA27: ='测算-私域'!N$35 -> 0 | EB27: ='测算-私域'!O$35 -> 1.2403233 | EC27: ='测算-私域'!P$35 -> 1.1948066 | ... EG27: ='测算-私域'!T$35 -> 1.1108508 | EH27: ='测算-私域'!V$35 -> 6.9186283 | EI27: ='测算-私域'!W$35 -> 6.9186283 | EK27: ='测算-外部分销'!I$35 -> 3.772369 | EL27: ='测算-外部分销'!J$35 -> 2.669009 | EM27: ='测算-外部分销'!K$35 -> 5.441306 | EN27: ='测算-外部分销'!L$35 -> 4.324099 | EO27: ='测算-外部分销'!M$35 -> 4.571711 | EP27: ='测算-外部分销'!N$35 -> 4.845667 | EQ27: ='测算-外部分销'!O$35 -> 1.5650149 | ER27: ='测算-外部分销'!P$35 -> 2.0931269 | ... EV27: ='测算-外部分销'!T$35 -> 2.9625796 | EW27: ='测算-外部分销'!V$35 -> 41.232447 | EX27: ='测算-外部分销'!W$35 -> 15.608286
D28: 行销支持 | E28: 促销物料 | F28: =SUM(U28,AJ28,AY28,BN28,CC28,CR28,DG28,DV28,EK28) -> 3.887473 | G28: =SUM(V28,AK28,AZ28,BO28,CD28,CS28,DH28,DW28,EL28) -> 0.870303 | H28: =SUM(W28,AL28,BA28,BP28,CE28,CT28,DI28,DX28,EM28) -> 2.244855 | I28: =SUM(X28,AM28,BB28,BQ28,CF28,CU28,DJ28,DY28,EN28) -> 0.384608 | J28: =SUM(Y28,AN28,BC28,BR28,CG28,CV28,DK28,DZ28,EO28) -> 3.535826 | K28: =SUM(Z28,AO28,BD28,BS28,CH28,CW28,DL28,EA28,EP28) -> 6.3484551 | L28: =SUM(AA28,AP28,BE28,BT28,CI28,CX28,DM28,EB28,EQ28) -> 4.7589797 | M28: =SUM(AB28,AQ28,BF28,BU28,CJ28,CY28,DN28,EC28,ER28) -> 6.3648906 | ... Q28: =SUM(AF28,AU28,BJ28,BY28,CN28,DC28,DR28,EG28,EV28) -> 9.0087682 | R28: =SUM(F28:Q28) -> 64.73402 | S28: =SUM(L28:Q28) -> 47.4625 | U28: ='测算-高个子抖音'!I$33 -> 0 | V28: ='测算-高个子抖音'!J$33 -> 0 | W28: ='测算-高个子抖音'!K$33 -> 0 | X28: ='测算-高个子抖音'!L$33 -> 0 | Y28: ='测算-高个子抖音'!M$33 -> 0 | Z28: ='测算-高个子抖音'!N$33 -> 0 | AA28: ='测算-高个子抖音'!O$33 -> 0 | AB28: ='测算-高个子抖音'!P$33 -> 0 | ... AF28: ='测算-高个子抖音'!T$33 -> 0 | AG28: ='测算-高个子抖音'!V$33 -> 0 | AH28: ='测算-高个子抖音'!W$33 -> 0 | AJ28: ='测算-高个子视频号'!I$33 -> 3.887473 | AK28: ='测算-高个子视频号'!J$33 -> 0.870303 | AL28: ='测算-高个子视频号'!K$33 -> 2.244855 | AM28: ='测算-高个子视频号'!L$33 -> 0.384608 | AN28: ='测算-高个子视频号'!M$33 -> 3.535826 | AO28: ='测算-高个子视频号'!N$33 -> 6.3484551 | AP28: ='测算-高个子视频号'!O$33 -> 4.7589797 | AQ28: ='测算-高个子视频号'!P$33 -> 6.3648906 | ... AU28: ='测算-高个子视频号'!T$33 -> 9.0087682 | AV28: ='测算-高个子视频号'!V$33 -> 64.73402 | AW28: ='测算-高个子视频号'!W$33 -> 47.4625 | AY28: ='测算-天猫淘宝'!I$32 -> 0 | AZ28: ='测算-天猫淘宝'!J$32 -> 0 | BA28: ='测算-天猫淘宝'!K$32 -> 0 | BB28: ='测算-天猫淘宝'!L$32 -> 0 | BC28: ='测算-天猫淘宝'!M$32 -> 0 | BD28: ='测算-天猫淘宝'!N$32 -> 0 | BE28: ='测算-天猫淘宝'!O$32 -> 0 | BF28: ='测算-天猫淘宝'!P$32 -> 0 | ... BJ28: ='测算-天猫淘宝'!T$32 -> 0 | BK28: ='测算-天猫淘宝'!V$32 -> 0 | BL28: ='测算-天猫淘宝'!W$32 -> 0 | BN28: ='测算-拼多多'!I$33 -> 0 | BO28: ='测算-拼多多'!J$33 -> 0 | BP28: ='测算-拼多多'!K$33 -> 0 | BQ28: ='测算-拼多多'!L$33 -> 0 | BR28: ='测算-拼多多'!M$33 -> 0 | BS28: ='测算-拼多多'!N$33 -> 0 | BT28: ='测算-拼多多'!O$33 -> 0 | BU28: ='测算-拼多多'!P$33 -> 0 | ... BY28: ='测算-拼多多'!T$33 -> 0 | BZ28: ='测算-拼多多'!V$33 -> 0 | CA28: ='测算-拼多多'!W$33 -> 0 | CC28: ='测算-京东POP'!I$33 -> 0 | CD28: ='测算-京东POP'!J$33 -> 0 | CE28: ='测算-京东POP'!K$33 -> 0 | CF28: ='测算-京东POP'!L$33 -> 0 | CG28: ='测算-京东POP'!M$33 -> 0 | CH28: ='测算-京东POP'!N$33 -> 0 | CI28: ='测算-京东POP'!O$33 -> 0 | CJ28: ='测算-京东POP'!P$33 -> 0 | ... CN28: ='测算-京东POP'!T$33 -> 0 | CO28: ='测算-京东POP'!V$33 -> 0 | CP28: ='测算-京东POP'!W$33 -> 0 | CR28: ='测算-京东自营'!I$34 -> 0 | CS28: ='测算-京东自营'!J$34 -> 0 | CT28: ='测算-京东自营'!K$34 -> 0 | CU28: ='测算-京东自营'!L$34 -> 0 | CV28: ='测算-京东自营'!M$34 -> 0 | CW28: ='测算-京东自营'!N$34 -> 0 | CX28: ='测算-京东自营'!O$34 -> 0 | CY28: ='测算-京东自营'!P$34 -> 0 | ... DC28: ='测算-京东自营'!T$34 -> 0 | DD28: ='测算-京东自营'!V$34 -> 0 | DE28: ='测算-京东自营'!W$34 -> 0 | DG28: ='测算-达播'!I$34 -> 0 | DH28: ='测算-达播'!J$34 -> 0 | DI28: ='测算-达播'!K$34 -> 0 | DJ28: ='测算-达播'!L$34 -> 0 | DK28: ='测算-达播'!M$34 -> 0 | DL28: ='测算-达播'!N$34 -> 0 | DM28: ='测算-达播'!O$34 -> 0 | DN28: ='测算-达播'!P$34 -> 0 | ... DR28: ='测算-达播'!T$34 -> 0 | DS28: ='测算-达播'!V$34 -> 0 | DT28: ='测算-达播'!W$34 -> 0 | DV28: ='测算-私域'!I$33 -> 0 | DW28: ='测算-私域'!J$33 -> 0 | DX28: ='测算-私域'!K$33 -> 0 | DY28: ='测算-私域'!L$33 -> 0 | DZ28: ='测算-私域'!M$33 -> 0 | EA28: ='测算-私域'!N$33 -> 0 | EB28: ='测算-私域'!O$33 -> 0 | EC28: ='测算-私域'!P$33 -> 0 | ... EG28: ='测算-私域'!T$33 -> 0 | EH28: ='测算-私域'!V$33 -> 0 | EI28: ='测算-私域'!W$33 -> 0 | EK28: ='测算-外部分销'!I$33 | EL28: ='测算-外部分销'!J$33 | EM28: ='测算-外部分销'!K$33 | EN28: ='测算-外部分销'!L$33 | EO28: ='测算-外部分销'!M$33 | EP28: ='测算-外部分销'!N$33 | EQ28: ='测算-外部分销'!O$33 -> 0 | ER28: ='测算-外部分销'!P$33 -> 0 | ... EV28: ='测算-外部分销'!T$33 -> 0 | EW28: ='测算-外部分销'!V$33 -> 0 | EX28: ='测算-外部分销'!W$33 -> 0
D29: 行销支持 | E29: 赠饮样品费 | F29: =SUM(U29,AJ29,AY29,BN29,CC29,CR29,DG29,DV29,EK29) -> 0 | G29: =SUM(V29,AK29,AZ29,BO29,CD29,CS29,DH29,DW29,EL29) -> 0 | H29: =SUM(W29,AL29,BA29,BP29,CE29,CT29,DI29,DX29,EM29) -> 0 | I29: =SUM(X29,AM29,BB29,BQ29,CF29,CU29,DJ29,DY29,EN29) -> 0 | J29: =SUM(Y29,AN29,BC29,BR29,CG29,CV29,DK29,DZ29,EO29) -> 0 | K29: =SUM(Z29,AO29,BD29,BS29,CH29,CW29,DL29,EA29,EP29) -> 0 | L29: =SUM(AA29,AP29,BE29,BT29,CI29,CX29,DM29,EB29,EQ29) -> 0 | M29: =SUM(AB29,AQ29,BF29,BU29,CJ29,CY29,DN29,EC29,ER29) -> 0 | ... Q29: =SUM(AF29,AU29,BJ29,BY29,CN29,DC29,DR29,EG29,EV29) -> 0 | R29: =SUM(F29:Q29) -> 0 | S29: =SUM(L29:Q29) -> 0 | U29: ='测算-高个子抖音'!I$34 -> 0 | V29: ='测算-高个子抖音'!J$34 -> 0 | W29: ='测算-高个子抖音'!K$34 -> 0 | X29: ='测算-高个子抖音'!L$34 -> 0 | Y29: ='测算-高个子抖音'!M$34 -> 0 | Z29: ='测算-高个子抖音'!N$34 -> 0 | AA29: ='测算-高个子抖音'!O$34 -> 0 | AB29: ='测算-高个子抖音'!P$34 -> 0 | ... AF29: ='测算-高个子抖音'!T$34 -> 0 | AG29: ='测算-高个子抖音'!V$34 -> 0 | AH29: ='测算-高个子抖音'!W$34 -> 0 | AJ29: ='测算-高个子视频号'!I$34 -> 0 | AK29: ='测算-高个子视频号'!J$34 -> 0 | AL29: ='测算-高个子视频号'!K$34 -> 0 | AM29: ='测算-高个子视频号'!L$34 -> 0 | AN29: ='测算-高个子视频号'!M$34 -> 0 | AO29: ='测算-高个子视频号'!N$34 -> 0 | AP29: ='测算-高个子视频号'!O$34 -> 0 | AQ29: ='测算-高个子视频号'!P$34 -> 0 | ... AU29: ='测算-高个子视频号'!T$34 -> 0 | AV29: ='测算-高个子视频号'!V$34 -> 0 | AW29: ='测算-高个子视频号'!W$34 -> 0 | AY29: ='测算-天猫淘宝'!I$33 -> 0 | AZ29: ='测算-天猫淘宝'!J$33 -> 0 | BA29: ='测算-天猫淘宝'!K$33 -> 0 | BB29: ='测算-天猫淘宝'!L$33 -> 0 | BC29: ='测算-天猫淘宝'!M$33 -> 0 | BD29: ='测算-天猫淘宝'!N$33 -> 0 | BE29: ='测算-天猫淘宝'!O$33 -> 0 | BF29: ='测算-天猫淘宝'!P$33 -> 0 | ... BJ29: ='测算-天猫淘宝'!T$33 -> 0 | BK29: ='测算-天猫淘宝'!V$33 -> 0 | BL29: ='测算-天猫淘宝'!W$33 -> 0 | BN29: ='测算-拼多多'!I$34 -> 0 | BO29: ='测算-拼多多'!J$34 -> 0 | BP29: ='测算-拼多多'!K$34 -> 0 | BQ29: ='测算-拼多多'!L$34 -> 0 | BR29: ='测算-拼多多'!M$34 -> 0 | BS29: ='测算-拼多多'!N$34 -> 0 | BT29: ='测算-拼多多'!O$34 -> 0 | BU29: ='测算-拼多多'!P$34 -> 0 | ... BY29: ='测算-拼多多'!T$34 -> 0 | BZ29: ='测算-拼多多'!V$34 -> 0 | CA29: ='测算-拼多多'!W$34 -> 0 | CC29: ='测算-京东POP'!I$34 -> 0 | CD29: ='测算-京东POP'!J$34 -> 0 | CE29: ='测算-京东POP'!K$34 -> 0 | CF29: ='测算-京东POP'!L$34 -> 0 | CG29: ='测算-京东POP'!M$34 -> 0 | CH29: ='测算-京东POP'!N$34 -> 0 | CI29: ='测算-京东POP'!O$34 -> 0 | CJ29: ='测算-京东POP'!P$34 -> 0 | ... CN29: ='测算-京东POP'!T$34 -> 0 | CO29: ='测算-京东POP'!V$34 -> 0 | CP29: ='测算-京东POP'!W$34 -> 0 | CR29: ='测算-京东自营'!I$35 -> 0 | CS29: ='测算-京东自营'!J$35 -> 0 | CT29: ='测算-京东自营'!K$35 -> 0 | CU29: ='测算-京东自营'!L$35 -> 0 | CV29: ='测算-京东自营'!M$35 -> 0 | CW29: ='测算-京东自营'!N$35 -> 0 | CX29: ='测算-京东自营'!O$35 -> 0 | CY29: ='测算-京东自营'!P$35 -> 0 | ... DC29: ='测算-京东自营'!T$35 -> 0 | DD29: ='测算-京东自营'!V$35 -> 0 | DE29: ='测算-京东自营'!W$35 -> 0 | DG29: ='测算-达播'!I$35 -> 0 | DH29: ='测算-达播'!J$35 -> 0 | DI29: ='测算-达播'!K$35 -> 0 | DJ29: ='测算-达播'!L$35 -> 0 | DK29: ='测算-达播'!M$35 -> 0 | DL29: ='测算-达播'!N$35 -> 0 | DM29: ='测算-达播'!O$35 -> 0 | DN29: ='测算-达播'!P$35 -> 0 | ... DR29: ='测算-达播'!T$35 -> 0 | DS29: ='测算-达播'!V$35 -> 0 | DT29: ='测算-达播'!W$35 -> 0 | DV29: ='测算-私域'!I$34 -> 0 | DW29: ='测算-私域'!J$34 -> 0 | DX29: ='测算-私域'!K$34 -> 0 | DY29: ='测算-私域'!L$34 -> 0 | DZ29: ='测算-私域'!M$34 -> 0 | EA29: ='测算-私域'!N$34 -> 0 | EB29: ='测算-私域'!O$34 -> 0 | EC29: ='测算-私域'!P$34 -> 0 | ... EG29: ='测算-私域'!T$34 -> 0 | EH29: ='测算-私域'!V$34 -> 0 | EI29: ='测算-私域'!W$34 -> 0 | EK29: ='测算-外部分销'!I$34 | EL29: ='测算-外部分销'!J$34 | EM29: ='测算-外部分销'!K$34 | EN29: ='测算-外部分销'!L$34 | EO29: ='测算-外部分销'!M$34 | EP29: ='测算-外部分销'!N$34 | EQ29: ='测算-外部分销'!O$34 -> 0 | ER29: ='测算-外部分销'!P$34 -> 0 | ... EV29: ='测算-外部分销'!T$34 -> 0 | EW29: ='测算-外部分销'!V$34 -> 0 | EX29: ='测算-外部分销'!W$34 -> 0
C30: 仓储物流 | F30: =SUM(U30,AJ30,AY30,BN30,CC30,CR30,DG30,DV30,EK30) -> 37.21924 | G30: =SUM(V30,AK30,AZ30,BO30,CD30,CS30,DH30,DW30,EL30) -> 40.605947 | H30: =SUM(W30,AL30,BA30,BP30,CE30,CT30,DI30,DX30,EM30) -> 40.113545 | I30: =SUM(X30,AM30,BB30,BQ30,CF30,CU30,DJ30,DY30,EN30) -> 29.593612 | J30: =SUM(Y30,AN30,BC30,BR30,CG30,CV30,DK30,DZ30,EO30) -> 35.070613 | K30: =SUM(Z30,AO30,BD30,BS30,CH30,CW30,DL30,EA30,EP30) -> 48.212656 | L30: =SUM(AA30,AP30,BE30,BT30,CI30,CX30,DM30,EB30,EQ30) -> 30.707836 | M30: =SUM(AB30,AQ30,BF30,BU30,CJ30,CY30,DN30,EC30,ER30) -> 40.606089 | ... Q30: =SUM(AF30,AU30,BJ30,BY30,CN30,DC30,DR30,EG30,EV30) -> 56.892974 | R30: =SUM(F30:Q30) -> 531.62114 | S30: =SUM(L30:Q30) -> 300.80553 | U30: =SUM(U32:U35) -> 15.341834 | V30: =SUM(V32:V35) -> 13.751308 | W30: =SUM(W32:W35) -> 14.375734 | X30: =SUM(X32:X35) -> 11.019812 | Y30: =SUM(Y32:Y35) -> 10.660792 | Z30: =SUM(Z32:Z35) -> 9.8384835 | AA30: =SUM(AA32:AA35) -> 6.8060464 | AB30: =SUM(AB32:AB35) -> 9.1027369 | ... AH30: =SUM(AH32:AH35) -> 67.878409 | AJ30: =SUM(AJ32:AJ35) -> 2.2723218 | AK30: =SUM(AK32:AK35) -> 0.62619706 | AL30: =SUM(AL32:AL35) -> 0.93141624 | AM30: =SUM(AM32:AM35) -> 0.2474142 | AN30: =SUM(AN32:AN35) -> 1.8633687 | AO30: =SUM(AO32:AO35) -> 3.4653381 | AP30: =SUM(AP32:AP35) -> 2.5977145 | AQ30: =SUM(AQ32:AQ35) -> 3.4743095 | ... AW30: =SUM(AW32:AW35) -> 25.907659 | AY30: =SUM(AY32:AY35) -> 0.94911133 | AZ30: =SUM(AZ32:AZ35) -> 0.70270802 | BA30: =SUM(BA32:BA35) -> 0.94589368 | BB30: =SUM(BB32:BB35) -> 1.0456332 | BC30: =SUM(BC32:BC35) -> 0.95081854 | BD30: =SUM(BD32:BD35) -> 0.86273564 | BE30: =SUM(BE32:BE35) -> 0.79435711 | BF30: =SUM(BF32:BF35) -> 1.0624118 | ... BL30: =SUM(BL32:BL35) -> 7.9223229 | BN30: =SUM(BN32:BN35) -> 0.024510935 | BO30: =SUM(BO32:BO35) -> 0.043787597 | BP30: =SUM(BP32:BP35) -> 0.053812519 | BQ30: =SUM(BQ32:BQ35) -> 0.012399512 | BR30: =SUM(BR32:BR35) -> 0.031437704 | BS30: =SUM(BS32:BS35) -> 0.43034714 | BT30: =SUM(BT32:BT35) -> 0.25463814 | BU30: =SUM(BU32:BU35) -> 0.34056541 | ... CA30: =SUM(CA32:CA35) -> 2.5395701 | CC30: =SUM(CC32:CC35) -> 0.59660367 | CD30: =SUM(CD32:CD35) -> 0.43343219 | CE30: =SUM(CE32:CE35) -> 0.66106208 | CF30: =SUM(CF32:CF35) -> 0.67559414 | CG30: =SUM(CG32:CG35) -> 0.60362588 | CH30: =SUM(CH32:CH35) -> 0.59066406 | CI30: =SUM(CI32:CI35) -> 0.89408183 | CJ30: =SUM(CJ32:CJ35) -> 1.1957885 | ... CP30: =SUM(CP32:CP35) -> 8.9169025 | CR30: =SUM(CR32:CR35) -> 11.776415 | CS30: =SUM(CS32:CS35) -> 20.945373 | CT30: =SUM(CT32:CT35) -> 9.7895903 | CU30: =SUM(CU32:CU35) -> 10.308852 | CV30: =SUM(CV32:CV35) -> 13.157244 | CW30: =SUM(CW32:CW35) -> 26.767125 | CX30: =SUM(CX32:CX35) -> 13.074194 | CY30: =SUM(CY32:CY35) -> 17.486062 | ... DE30: =SUM(DE32:DE35) -> 130.39222 | DG30: =SUM(DG32:DG35) -> 1.9102016 | DH30: =SUM(DH32:DH35) -> 0.52378123 | DI30: =SUM(DI32:DI35) -> 6.9316488 | DJ30: =SUM(DJ32:DJ35) -> 1.0952625 | DK30: =SUM(DK32:DK35) -> 2.3870243 | DL30: =SUM(DL32:DL35) -> 0.97013811 | DM30: =SUM(DM32:DM35) -> 3.0707447 | DN30: =SUM(DN32:DN35) -> 4.1069631 | ... DT30: =SUM(DT32:DT35) -> 30.625308 | DV30: =SUM(DV32:DV35) -> 0 | DW30: =SUM(DW32:DW35) -> 0 | DX30: =SUM(DX32:DX35) -> 0 | DY30: =SUM(DY32:DY35) -> 0 | DZ30: =SUM(DZ32:DZ35) -> 0 | EA30: =SUM(EA32:EA35) -> 0 | EB30: =SUM(EB32:EB35) -> 1.2403233 | EC30: =SUM(EC32:EC35) -> 1.1948066 | ... EI30: =SUM(EI32:EI35) -> 6.9186283 | EK30: =SUM(EK32:EK35) -> 4.3482415 | EL30: =SUM(EL32:EL35) -> 3.5793604 | EM30: =SUM(EM32:EM35) -> 6.424388 | EN30: =SUM(EN32:EN35) -> 5.188644 | EO30: =SUM(EO32:EO35) -> 5.416302 | EP30: =SUM(EP32:EP35) -> 5.287824 | EQ30: =SUM(EQ32:EQ35) -> 1.9757363 | ER30: =SUM(ER32:ER35) -> 2.6424457 | ... EX30: =SUM(EX32:EX35) -> 19.704514
C31: Margin | F31: =IFERROR(F30/F3,0) -> 0.033942427 | G31: =IFERROR(G30/G3,0) -> 0.061065283 | H31: =IFERROR(H30/H3,0) -> 0.039626348 | I31: =IFERROR(I30/I3,0) -> 0.030263966 | J31: =IFERROR(J30/J3,0) -> 0.028791168 | K31: =IFERROR(K30/K3,0) -> 0.038862665 | L31: =IFERROR(L30/L3,0) -> 0.038780164 | M31: =IFERROR(M30/M3,0) -> 0.038835226 | ... S31: =IFERROR(S30/S3,0) -> 0.038867552 | U31: =IFERROR(U30/U3,0) -> 0.03717105 | V31: =IFERROR(V30/V3,0) -> 0.058192098 | W31: =IFERROR(W30/W3,0) -> 0.029889178 | X31: =IFERROR(X30/X3,0) -> 0.037973507 | Y31: =IFERROR(Y30/Y3,0) -> 0.027814567 | Z31: =IFERROR(Z30/Z3,0) -> 0.036233972 | AA31: =IFERROR(AA30/AA3,0) -> 0.036233972 | AB31: =IFERROR(AB30/AB3,0) -> 0.036233972 | ... AH31: =IFERROR(AH30/AH3,0) -> 0.036233972 | AJ31: =IFERROR(AJ30/AJ3,0) -> 0.14535232 | AK31: =IFERROR(AK30/AK3,0) -> 0.1173159 | AL31: =IFERROR(AL30/AL3,0) -> 0.082220665 | AM31: =IFERROR(AM30/AM3,0) -> 0.032990759 | AN31: =IFERROR(AN30/AN3,0) -> 0.027651948 | AO31: =IFERROR(AO30/AO3,0) -> 0.049128748 | AP31: =IFERROR(AP30/AP3,0) -> 0.049128748 | AQ31: =IFERROR(AQ30/AQ3,0) -> 0.049128748 | ... AW31: =IFERROR(AW30/AW3,0) -> 0.049128748 | AY31: =IFERROR(AY30/AY3,0) -> 0.034262502 | AZ31: =IFERROR(AZ30/AZ3,0) -> 0.049308048 | BA31: =IFERROR(BA30/BA3,0) -> 0.0290489 | BB31: =IFERROR(BB30/BB3,0) -> 0.030529749 | BC31: =IFERROR(BC30/BC3,0) -> 0.029169389 | BD31: =IFERROR(BD30/BD3,0) -> 0.032838463 | BE31: =IFERROR(BE30/BE3,0) -> 0.032838463 | BF31: =IFERROR(BF30/BF3,0) -> 0.032838463 | ... BL31: =IFERROR(BL30/BL3,0) -> 0.032838463 | BN31: =IFERROR(BN30/BN3,0) -> 0.15860987 | BO31: =IFERROR(BO30/BO3,0) -> 0.15849624 | BP31: =IFERROR(BP30/BP3,0) -> 0.14686903 | BQ31: =IFERROR(BQ30/BQ3,0) -> 0.10518668 | BR31: =IFERROR(BR30/BR3,0) -> 0.06967252 | BS31: =IFERROR(BS30/BS3,0) -> 0.087642166 | BT31: =IFERROR(BT30/BT3,0) -> 0.087642166 | BU31: =IFERROR(BU30/BU3,0) -> 0.087642166 | ... CA31: =IFERROR(CA30/CA3,0) -> 0.087642166 | CC31: =IFERROR(CC30/CC3,0) -> 0.043645836 | CD31: =IFERROR(CD30/CD3,0) -> 0.050563287 | CE31: =IFERROR(CE30/CE3,0) -> 0.028416087 | CF31: =IFERROR(CF30/CF3,0) -> 0.034705832 | CG31: =IFERROR(CG30/CG3,0) -> 0.031403756 | CH31: =IFERROR(CH30/CH3,0) -> 0.035431191 | CI31: =IFERROR(CI30/CI3,0) -> 0.035431191 | CJ31: =IFERROR(CJ30/CJ3,0) -> 0.035431191 | ... CP31: =IFERROR(CP30/CP3,0) -> 0.035431191 | CR31: =IFERROR(CR30/CR3,0) -> 0.029392324 | CS31: =IFERROR(CS30/CS3,0) -> 0.069546954 | CT31: =IFERROR(CT30/CT3,0) -> 0.2415846 | CU31: =IFERROR(CU30/CU3,0) -> 0.023487328 | CV31: =IFERROR(CV30/CV3,0) -> 0.02948541 | CW31: =IFERROR(CW30/CW3,0) -> 0.040539296 | CX31: =IFERROR(CX30/CX3,0) -> 0.040539296 | CY31: =IFERROR(CY30/CY3,0) -> 0.040539296 | ... DE31: =IFERROR(DE30/DE3,0) -> 0.040539296 | DG31: =IFERROR(DG30/DG3,0) -> 0.036966709 | DH31: =IFERROR(DH30/DH3,0) -> 0.12360327 | DI31: =IFERROR(DI30/DI3,0) -> 0.036476165 | DJ31: =IFERROR(DJ30/DJ3,0) -> 0.028967155 | DK31: =IFERROR(DK30/DK3,0) -> 0.029418964 | DL31: =IFERROR(DL30/DL3,0) -> 0.035429859 | DM31: =IFERROR(DM30/DM3,0) -> 0.035429859 | DN31: =IFERROR(DN30/DN3,0) -> 0.035429859 | ... DT31: =IFERROR(DT30/DT3,0) -> 0.035429859 | DV31: =IFERROR(DV30/DV3,0) -> 0 | DW31: =IFERROR(DW30/DW3,0) -> 0 | DX31: =IFERROR(DX30/DX3,0) -> 0 | DY31: =IFERROR(DY30/DY3,0) -> 0 | DZ31: =IFERROR(DZ30/DZ3,0) -> 0 | EA31: =IFERROR(EA30/EA3,0) -> 0 | EB31: =IFERROR(EB30/EB3,0) -> 0.0345 | EC31: =IFERROR(EC30/EC3,0) -> 0.0345 | ... EI31: =IFERROR(EI30/EI3,0) -> 0.0345 | EK31: =IFERROR(EK30/EK3,0) -> 0.029079522 | EL31: =IFERROR(EL30/EL3,0) -> 0.041167229 | EM31: =IFERROR(EM30/EM3,0) -> 0.031001255 | EN31: =IFERROR(EN30/EN3,0) -> 0.039196303 | EO31: =IFERROR(EO30/EO3,0) -> 0.032007433 | EP31: =IFERROR(EP30/EP3,0) -> 0.036999724 | EQ31: =IFERROR(EQ30/EQ3,0) -> 0.036810331 | ER31: =IFERROR(ER30/ER3,0) -> 0.036810331 | ... EX31: =IFERROR(EX30/EX3,0) -> 0.036810331
D32: 仓储物流 | E32: 快递费用 | F32: =SUM(U32,AJ32,AY32,BN32,CC32,CR32,DG32,DV32,EK32) -> 12.31197 | G32: =SUM(V32,AK32,AZ32,BO32,CD32,CS32,DH32,DW32,EL32) -> 8.740675 | H32: =SUM(W32,AL32,BA32,BP32,CE32,CT32,DI32,DX32,EM32) -> 19.75802 | I32: =SUM(X32,AM32,BB32,BQ32,CF32,CU32,DJ32,DY32,EN32) -> 10.679434 | J32: =SUM(Y32,AN32,BC32,BR32,CG32,CV32,DK32,DZ32,EO32) -> 13.419053 | K32: =SUM(Z32,AO32,BD32,BS32,CH32,CW32,DL32,EA32,EP32) -> 12.024452 | L32: =SUM(AA32,AP32,BE32,BT32,CI32,CX32,DM32,EB32,EQ32) -> 8.9886617 | M32: =SUM(AB32,AQ32,BF32,BU32,CJ32,CY32,DN32,EC32,ER32) -> 12.021873 | ... Q32: =SUM(AF32,AU32,BJ32,BY32,CN32,DC32,DR32,EG32,EV32) -> 17.015574 | R32: =SUM(F32:Q32) -> 166.57978 | S32: =SUM(L32:Q32) -> 89.64618 | U32: ='测算-高个子抖音'!I$37 -> 6.51725 | V32: ='测算-高个子抖音'!J$37 -> 5.02626 | W32: ='测算-高个子抖音'!K$37 -> 8.88009 | X32: ='测算-高个子抖音'!L$37 -> 4.9522 | Y32: ='测算-高个子抖音'!M$37 -> 5.670952 | Z32: ='测算-高个子抖音'!N$37 -> 4.6395114 | AA32: ='测算-高个子抖音'!O$37 -> 3.2095119 | AB32: ='测算-高个子抖音'!P$37 -> 4.292557 | ... AF32: ='测算-高个子抖音'!T$37 -> 6.0756192 | AG32: ='测算-高个子抖音'!V$37 -> 67.695531 | AH32: ='测算-高个子抖音'!W$37 -> 32.009268 | AJ32: ='测算-高个子视频号'!I$37 -> 0.89852 | AK32: ='测算-高个子视频号'!J$37 -> 0.25692 | AL32: ='测算-高个子视频号'!K$37 -> 0.50637 | AM32: ='测算-高个子视频号'!L$37 -> 0.15041 | AN32: ='测算-高个子视频号'!M$37 -> 1.26472 | AO32: ='测算-高个子视频号'!N$37 -> 1.8385334 | AP32: ='测算-高个子视频号'!O$37 -> 1.3782161 | AQ32: ='测算-高个子视频号'!P$37 -> 1.8432932 | ... AU32: ='测算-高个子视频号'!T$37 -> 2.6089688 | AV32: ='测算-高个子视频号'!V$37 -> 18.660769 | AW32: ='测算-高个子视频号'!W$37 -> 13.745296 | AY32: ='测算-天猫淘宝'!I$36 -> 0.47173 | AZ32: ='测算-天猫淘宝'!J$36 -> 0.31828 | BA32: ='测算-天猫淘宝'!K$36 -> 0.61031 | BB32: ='测算-天猫淘宝'!L$36 -> 0.61673 | BC32: ='测算-天猫淘宝'!M$36 -> 0.57276 | BD32: ='测算-天猫淘宝'!N$36 -> 0.48468331 | BE32: ='测算-天猫淘宝'!O$36 -> 0.44626838 | BF32: ='测算-天猫淘宝'!P$36 -> 0.596861 | ... BJ32: ='测算-天猫淘宝'!T$36 -> 0.84478788 | BK32: ='测算-天猫淘宝'!V$36 -> 7.5252399 | BL32: ='测算-天猫淘宝'!W$36 -> 4.4507466 | BN32: ='测算-拼多多'!I$37 -> 0.01089 | BO32: ='测算-拼多多'!J$37 -> 0.01867 | BP32: ='测算-拼多多'!K$37 -> 0.03532 | BQ32: ='测算-拼多多'!L$37 -> 0.00668 | BR32: ='测算-拼多多'!M$37 -> 0.02039 | BS32: ='测算-拼多多'!N$37 -> 0.25465982 | BT32: ='测算-拼多多'!O$37 -> 0.15068324 | BU32: ='测算-拼多多'!P$37 -> 0.20153108 | ... BY32: ='测算-拼多多'!T$37 -> 0.28524399 | BZ32: ='测算-拼多多'!V$37 -> 1.8494116 | CA32: ='测算-拼多多'!W$37 -> 1.5028018 | CC32: ='测算-京东POP'!I$37 -> 0.286 | CD32: ='测算-京东POP'!J$37 -> 0.21459 | CE32: ='测算-京东POP'!K$37 -> 0.433295 | CF32: ='测算-京东POP'!L$37 -> 0.391011 | CG32: ='测算-京东POP'!M$37 -> 0.38518 | CH32: ='测算-京东POP'!N$37 -> 0.34135275 | CI32: ='测算-京东POP'!O$37 -> 0.51670198 | CJ32: ='测算-京东POP'!P$37 -> 0.69106233 | ... CN32: ='测算-京东POP'!T$37 -> 0.97811898 | CO32: ='测算-京东POP'!V$37 -> 7.2046274 | CP32: ='测算-京东POP'!W$37 -> 5.1531986 | CR32: ='测算-京东自营'!I$38 -> 0 | CS32: ='测算-京东自营'!J$38 -> 0 | CT32: ='测算-京东自营'!K$38 -> 0 | CU32: ='测算-京东自营'!L$38 -> 0 | CV32: ='测算-京东自营'!M$38 -> 0 | CW32: ='测算-京东自营'!N$38 -> 0 | CX32: ='测算-京东自营'!O$38 -> 0 | CY32: ='测算-京东自营'!P$38 -> 0 | ... DC32: ='测算-京东自营'!T$38 -> 0 | DD32: ='测算-京东自营'!V$38 -> 0 | DE32: ='测算-京东自营'!W$38 -> 0 | DG32: ='测算-达播'!I$38 -> 1.03832 | DH32: ='测算-达播'!J$38 -> 0.23013 | DI32: ='测算-达播'!K$38 -> 4.53804 | DJ32: ='测算-达播'!L$38 -> 0.73168 | DK32: ='测算-达播'!M$38 -> 1.55525 | DL32: ='测算-达播'!N$38 -> 0.61105629 | DM32: ='测算-达播'!O$38 -> 1.9341554 | DN32: ='测算-达播'!P$38 -> 2.5868334 | ... DR32: ='测算-达播'!T$38 -> 3.6613642 | DS32: ='测算-达播'!V$38 -> 27.994294 | DT32: ='测算-达播'!W$38 -> 19.289818 | DV32: ='测算-私域'!I$37 -> 0 | DW32: ='测算-私域'!J$37 -> 0 | DX32: ='测算-私域'!K$37 -> 0 | DY32: ='测算-私域'!L$37 -> 0 | DZ32: ='测算-私域'!M$37 -> 0 | EA32: ='测算-私域'!N$37 -> 0 | EB32: ='测算-私域'!O$37 -> 0 | EC32: ='测算-私域'!P$37 -> 0 | ... EG32: ='测算-私域'!T$37 -> 0 | EH32: ='测算-私域'!V$37 -> 0 | EI32: ='测算-私域'!W$37 -> 0 | EK32: ='测算-外部分销'!I$37 -> 3.08926 | EL32: ='测算-外部分销'!J$37 -> 2.675825 | EM32: ='测算-外部分销'!K$37 -> 4.754595 | EN32: ='测算-外部分销'!L$37 -> 3.830723 | EO32: ='测算-外部分销'!M$37 -> 3.949801 | EP32: ='测算-外部分销'!N$37 -> 3.854655 | EQ32: ='测算-外部分销'!O$37 -> 1.3531247 | ER32: ='测算-外部分销'!P$37 -> 1.8097346 | ... EV32: ='测算-外部分销'!T$37 -> 2.5614706 | EW32: ='测算-外部分销'!V$37 -> 35.649911 | EX32: ='测算-外部分销'!W$37 -> 13.495052
D33: 仓储物流 | E33: 打包包装 | F33: =SUM(U33,AJ33,AY33,BN33,CC33,CR33,DG33,DV33,EK33) -> 6.7513262 | G33: =SUM(V33,AK33,AZ33,BO33,CD33,CS33,DH33,DW33,EL33) -> 3.628259 | H33: =SUM(W33,AL33,BA33,BP33,CE33,CT33,DI33,DX33,EM33) -> 8.724739 | I33: =SUM(X33,AM33,BB33,BQ33,CF33,CU33,DJ33,DY33,EN33) -> 4.871998 | J33: =SUM(Y33,AN33,BC33,BR33,CG33,CV33,DK33,DZ33,EO33) -> 6.92985 | K33: =SUM(Z33,AO33,BD33,BS33,CH33,CW33,DL33,EA33,EP33) -> 6.7076752 | L33: =SUM(AA33,AP33,BE33,BT33,CI33,CX33,DM33,EB33,EQ33) -> 4.2279308 | M33: =SUM(AB33,AQ33,BF33,BU33,CJ33,CY33,DN33,EC33,ER33) -> 5.6546399 | ... Q33: =SUM(AF33,AU33,BJ33,BY33,CN33,DC33,DR33,EG33,EV33) -> 8.0034904 | R33: =SUM(F33:Q33) -> 79.780062 | S33: =SUM(L33:Q33) -> 42.166215 | U33: ='测算-高个子抖音'!I$38 -> 3.2559473 | V33: ='测算-高个子抖音'!J$38 -> 1.9615736 | W33: ='测算-高个子抖音'!K$38 -> 3.688352 | X33: ='测算-高个子抖音'!L$38 -> 2.193535 | Y33: ='测算-高个子抖音'!M$38 -> 2.583076 | Z33: ='测算-高个子抖音'!N$38 -> 2.0393681 | AA33: ='测算-高个子抖音'!O$38 -> 1.41079 | AB33: ='测算-高个子抖音'!P$38 -> 1.8868591 | ... AF33: ='测算-高个子抖音'!T$38 -> 2.6706313 | AG33: ='测算-高个子抖音'!V$38 -> 29.792015 | AH33: ='测算-高个子抖音'!W$38 -> 14.070163 | AJ33: ='测算-高个子视频号'!I$38 -> 0.8270832 | AK33: ='测算-高个子视频号'!J$38 -> 0.18483496 | AL33: ='测算-高个子视频号'!K$38 -> 0.399546 | AM33: ='测算-高个子视频号'!L$38 -> 0.066399 | AN33: ='测算-高个子视频号'!M$38 -> 0.57774 | AO33: ='测算-高个子视频号'!N$38 -> 1.1222653 | AP33: ='测算-高个子视频号'!O$38 -> 0.84128153 | AQ33: ='测算-高个子视频号'!P$38 -> 1.1251708 | ... AU33: ='测算-高个子视频号'!T$38 -> 1.5925494 | AV33: ='测算-高个子视频号'!V$38 -> 11.56818 | AW33: ='测算-高个子视频号'!W$38 -> 8.3903119 | AY33: ='测算-天猫淘宝'!I$37 -> 0.25069929 | AZ33: ='测算-天猫淘宝'!J$37 -> 0.13865445 | BA33: ='测算-天猫淘宝'!K$37 -> 0.266873 | BB33: ='测算-天猫淘宝'!L$37 -> 0.276123 | BC33: ='测算-天猫淘宝'!M$37 -> 0.276958 | BD33: ='测算-天猫淘宝'!N$37 -> 0.22595282 | BE33: ='测算-天猫淘宝'!O$37 -> 0.2080443 | BF33: ='测算-天猫淘宝'!P$37 -> 0.27824855 | ... BJ33: ='测算-天猫淘宝'!T$37 -> 0.39382871 | BK33: ='测算-天猫淘宝'!V$37 -> 3.5101386 | BL33: ='测算-天猫淘宝'!W$37 -> 2.074878 | BN33: ='测算-拼多多'!I$38 -> 0.006031134 | BO33: ='测算-拼多多'!J$38 -> 0.0072105968 | BP33: ='测算-拼多多'!K$38 -> 0.013076 | BQ33: ='测算-拼多多'!L$38 -> 0.00363 | BR33: ='测算-拼多多'!M$38 -> 0.007353 | BS33: ='测算-拼多多'!N$38 -> 0.088711404 | BT33: ='测算-拼多多'!O$38 -> 0.052490895 | BU33: ='测算-拼多多'!P$38 -> 0.070203872 | ... BY33: ='测算-拼多多'!T$38 -> 0.099365481 | BZ33: ='测算-拼多多'!V$38 -> 0.64951701 | CA33: ='测算-拼多多'!W$38 -> 0.52350487 | CC33: ='测算-京东POP'!I$38 -> 0.17727617 | CD33: ='测算-京东POP'!J$38 -> 0.076033862 | CE33: ='测算-京东POP'!K$38 -> 0.176158 | CF33: ='测算-京东POP'!L$38 -> 0.196332 | CG33: ='测算-京东POP'!M$38 -> 0.152529 | CH33: ='测算-京东POP'!N$38 -> 0.15076953 | CI33: ='测算-京东POP'!O$38 -> 0.22821821 | CJ33: ='测算-京东POP'!P$38 -> 0.30523011 | ... CN33: ='测算-京东POP'!T$38 -> 0.43201801 | CO33: ='测算-京东POP'!V$38 -> 3.205176 | CP33: ='测算-京东POP'!W$38 -> 2.2760775 | CR33: ='测算-京东自营'!I$39 -> 0.57753564 | CS33: ='测算-京东自营'!J$39 -> 0.27988727 | CT33: ='测算-京东自营'!K$39 -> 0.791415 | CU33: ='测算-京东自营'!L$39 -> 0.547098 | CV33: ='测算-京东自营'!M$39 -> 1.315472 | CW33: ='测算-京东自营'!N$39 -> 1.4245816 | CX33: ='测算-京东自营'!O$39 -> 0.69582579 | CY33: ='测算-京东自营'!P$39 -> 0.93063121 | ... DC33: ='测算-京东自营'!T$39 -> 1.3172011 | DD33: ='测算-京东自营'!V$39 -> 11.875635 | DE33: ='测算-京东自营'!W$39 -> 6.9396453 | DG33: ='测算-达播'!I$39 -> 0.39777207 | DH33: ='测算-达播'!J$39 -> 0.076528854 | DI33: ='测算-达播'!K$39 -> 1.719526 | DJ33: ='测算-达播'!L$39 -> 0.23096 | DK33: ='测算-达播'!M$39 -> 0.550221 | DL33: ='测算-达播'!N$39 -> 0.22285731 | DM33: ='测算-达播'!O$39 -> 0.70540257 | DN33: ='测算-达播'!P$39 -> 0.94343966 | ... DR33: ='测算-达播'!T$39 -> 1.33533 | DS33: ='测算-达播'!V$39 -> 10.233022 | DT33: ='测算-达播'!W$39 -> 7.035157 | DV33: ='测算-私域'!I$38 -> 0 | DW33: ='测算-私域'!J$38 -> 0 | DX33: ='测算-私域'!K$38 -> 0 | DY33: ='测算-私域'!L$38 -> 0 | DZ33: ='测算-私域'!M$38 -> 0 | EA33: ='测算-私域'!N$38 -> 0 | EB33: ='测算-私域'!O$38 -> 0 | EC33: ='测算-私域'!P$38 -> 0 | ... EG33: ='测算-私域'!T$38 -> 0 | EH33: ='测算-私域'!V$38 -> 0 | EI33: ='测算-私域'!W$38 -> 0 | EK33: ='测算-外部分销'!I$38 -> 1.2589815 | EL33: ='测算-外部分销'!J$38 -> 0.90353536 | EM33: ='测算-外部分销'!K$38 -> 1.669793 | EN33: ='测算-外部分销'!L$38 -> 1.357921 | EO33: ='测算-外部分销'!M$38 -> 1.466501 | EP33: ='测算-外部分销'!N$38 -> 1.433169 | EQ33: ='测算-外部分销'!O$38 -> 0.085877472 | ER33: ='测算-外部分销'!P$38 -> 0.1148567 | ... EV33: ='测算-外部分销'!T$38 -> 0.16256641 | EW33: ='测算-外部分销'!V$38 -> 8.9463784 | EX33: ='测算-外部分销'!W$38 -> 0.85647759
D34: 仓储物流 | E34: 干线费用 | F34: =SUM(U34,AJ34,AY34,BN34,CC34,CR34,DG34,DV34,EK34) -> 2.529556 | G34: =SUM(V34,AK34,AZ34,BO34,CD34,CS34,DH34,DW34,EL34) -> 1.245344 | H34: =SUM(W34,AL34,BA34,BP34,CE34,CT34,DI34,DX34,EM34) -> 3.913159 | I34: =SUM(X34,AM34,BB34,BQ34,CF34,CU34,DJ34,DY34,EN34) -> 4.59771 | J34: =SUM(Y34,AN34,BC34,BR34,CG34,CV34,DK34,DZ34,EO34) -> 4.839552 | K34: =SUM(Z34,AO34,BD34,BS34,CH34,CW34,DL34,EA34,EP34) -> 6.9477594 | L34: =SUM(AA34,AP34,BE34,BT34,CI34,CX34,DM34,EB34,EQ34) -> 5.1706365 | M34: =SUM(AB34,AQ34,BF34,BU34,CJ34,CY34,DN34,EC34,ER34) -> 6.4513983 | ... Q34: =SUM(AF34,AU34,BJ34,BY34,CN34,DC34,DR34,EG34,EV34) -> 8.5509499 | R34: =SUM(F34:Q34) -> 70.189709 | S34: =SUM(L34:Q34) -> 46.116628 | U34: ='测算-高个子抖音'!I$39 -> 0 | V34: ='测算-高个子抖音'!J$39 -> 0 | W34: ='测算-高个子抖音'!K$39 -> 0 | X34: ='测算-高个子抖音'!L$39 -> 0 | Y34: ='测算-高个子抖音'!M$39 -> 0 | Z34: ='测算-高个子抖音'!N$39 -> 0 | AA34: ='测算-高个子抖音'!O$39 -> 0 | AB34: ='测算-高个子抖音'!P$39 -> 0 | ... AF34: ='测算-高个子抖音'!T$39 -> 0 | AG34: ='测算-高个子抖音'!V$39 -> 0 | AH34: ='测算-高个子抖音'!W$39 -> 0 | AJ34: ='测算-高个子视频号'!I$39 -> 0 | AK34: ='测算-高个子视频号'!J$39 -> 0 | AL34: ='测算-高个子视频号'!K$39 -> 0 | AM34: ='测算-高个子视频号'!L$39 -> 0 | AN34: ='测算-高个子视频号'!M$39 -> 0 | AO34: ='测算-高个子视频号'!N$39 -> 0 | AP34: ='测算-高个子视频号'!O$39 -> 0 | AQ34: ='测算-高个子视频号'!P$39 -> 0 | ... AU34: ='测算-高个子视频号'!T$39 -> 0 | AV34: ='测算-高个子视频号'!V$39 -> 0 | AW34: ='测算-高个子视频号'!W$39 -> 0 | AY34: ='测算-天猫淘宝'!I$38 -> 0 | AZ34: ='测算-天猫淘宝'!J$38 -> 0 | BA34: ='测算-天猫淘宝'!K$38 -> 0 | BB34: ='测算-天猫淘宝'!L$38 -> 0 | BC34: ='测算-天猫淘宝'!M$38 -> 0 | BD34: ='测算-天猫淘宝'!N$38 -> 0 | BE34: ='测算-天猫淘宝'!O$38 -> 0 | BF34: ='测算-天猫淘宝'!P$38 -> 0 | ... BJ34: ='测算-天猫淘宝'!T$38 -> 0 | BK34: ='测算-天猫淘宝'!V$38 -> 0 | BL34: ='测算-天猫淘宝'!W$38 -> 0 | BN34: ='测算-拼多多'!I$39 -> 0 | BO34: ='测算-拼多多'!J$39 -> 0 | BP34: ='测算-拼多多'!K$39 -> 0 | BQ34: ='测算-拼多多'!L$39 -> 0 | BR34: ='测算-拼多多'!M$39 -> 0 | BS34: ='测算-拼多多'!N$39 -> 0 | BT34: ='测算-拼多多'!O$39 -> 0 | BU34: ='测算-拼多多'!P$39 -> 0 | ... BY34: ='测算-拼多多'!T$39 -> 0 | BZ34: ='测算-拼多多'!V$39 -> 0 | CA34: ='测算-拼多多'!W$39 -> 0 | CC34: ='测算-京东POP'!I$39 -> 0 | CD34: ='测算-京东POP'!J$39 -> 0 | CE34: ='测算-京东POP'!K$39 -> 0 | CF34: ='测算-京东POP'!L$39 -> 0 | CG34: ='测算-京东POP'!M$39 -> 0 | CH34: ='测算-京东POP'!N$39 -> 0 | CI34: ='测算-京东POP'!O$39 -> 0 | CJ34: ='测算-京东POP'!P$39 -> 0 | ... CN34: ='测算-京东POP'!T$39 -> 0 | CO34: ='测算-京东POP'!V$39 -> 0 | CP34: ='测算-京东POP'!W$39 -> 0 | CR34: ='测算-京东自营'!I$40 -> 2.529556 | CS34: ='测算-京东自营'!J$40 -> 1.245344 | CT34: ='测算-京东自营'!K$40 -> 3.913159 | CU34: ='测算-京东自营'!L$40 -> 4.59771 | CV34: ='测算-京东自营'!M$40 -> 4.839552 | CW34: ='测算-京东自营'!N$40 -> 6.9477594 | CX34: ='测算-京东自营'!O$40 -> 3.393579 | CY34: ='测算-京东自营'!P$40 -> 4.5387373 | ... DC34: ='测算-京东自营'!T$40 -> 6.424059 | DD34: ='测算-京东自营'!V$40 -> 57.918096 | DE34: ='测算-京东自营'!W$40 -> 33.845015 | DG34: ='测算-达播'!I$40 -> 0 | DH34: ='测算-达播'!J$40 -> 0 | DI34: ='测算-达播'!K$40 -> 0 | DJ34: ='测算-达播'!L$40 -> 0 | DK34: ='测算-达播'!M$40 -> 0 | DL34: ='测算-达播'!N$40 -> 0 | DM34: ='测算-达播'!O$40 -> 0 | DN34: ='测算-达播'!P$40 -> 0 | ... DR34: ='测算-达播'!T$40 -> 0 | DS34: ='测算-达播'!V$40 -> 0 | DT34: ='测算-达播'!W$40 -> 0 | DV34: ='测算-私域'!I$39 -> 0 | DW34: ='测算-私域'!J$39 -> 0 | DX34: ='测算-私域'!K$39 -> 0 | DY34: ='测算-私域'!L$39 -> 0 | DZ34: ='测算-私域'!M$39 -> 0 | EA34: ='测算-私域'!N$39 -> 0 | EB34: ='测算-私域'!O$39 -> 1.2403233 | EC34: ='测算-私域'!P$39 -> 1.1948066 | ... EG34: ='测算-私域'!T$39 -> 1.1108508 | EH34: ='测算-私域'!V$39 -> 6.9186283 | EI34: ='测算-私域'!W$39 -> 6.9186283 | EK34: ='测算-外部分销'!I$39 | EL34: ='测算-外部分销'!J$39 | EM34: ='测算-外部分销'!K$39 | EN34: ='测算-外部分销'!L$39 | EO34: ='测算-外部分销'!M$39 | EP34: ='测算-外部分销'!N$39 | EQ34: ='测算-外部分销'!O$39 -> 0.5367342 | ER34: ='测算-外部分销'!P$39 -> 0.71785438 | ... EV34: ='测算-外部分销'!T$39 -> 1.0160401 | EW34: ='测算-外部分销'!V$39 -> 5.3529849 | EX34: ='测算-外部分销'!W$39 -> 5.3529849
D35: 仓储物流 | E35: 仓储费用 | F35: =SUM(U35,AJ35,AY35,BN35,CC35,CR35,DG35,DV35,EK35) -> 15.626387 | G35: =SUM(V35,AK35,AZ35,BO35,CD35,CS35,DH35,DW35,EL35) -> 26.991669 | H35: =SUM(W35,AL35,BA35,BP35,CE35,CT35,DI35,DX35,EM35) -> 7.7176273 | I35: =SUM(X35,AM35,BB35,BQ35,CF35,CU35,DJ35,DY35,EN35) -> 9.4444696 | J35: =SUM(Y35,AN35,BC35,BR35,CG35,CV35,DK35,DZ35,EO35) -> 9.8821581 | K35: =SUM(Z35,AO35,BD35,BS35,CH35,CW35,DL35,EA35,EP35) -> 22.532769 | L35: =SUM(AA35,AP35,BE35,BT35,CI35,CX35,DM35,EB35,EQ35) -> 12.320607 | M35: =SUM(AB35,AQ35,BF35,BU35,CJ35,CY35,DN35,EC35,ER35) -> 16.478178 | ... Q35: =SUM(AF35,AU35,BJ35,BY35,CN35,DC35,DR35,EG35,EV35) -> 23.32296 | R35: =SUM(F35:Q35) -> 215.07159 | S35: =SUM(L35:Q35) -> 122.87651 | U35: ='测算-高个子抖音'!I$40 -> 5.5686367 | V35: ='测算-高个子抖音'!J$40 -> 6.7634739 | W35: ='测算-高个子抖音'!K$40 -> 1.8072917 | X35: ='测算-高个子抖音'!L$40 -> 3.8740774 | Y35: ='测算-高个子抖音'!M$40 -> 2.4067639 | Z35: ='测算-高个子抖音'!N$40 -> 3.1596039 | AA35: ='测算-高个子抖音'!O$40 -> 2.1857445 | AB35: ='测算-高个子抖音'!P$40 -> 2.9233208 | ... AF35: ='测算-高个子抖音'!T$40 -> 4.1376233 | AG35: ='测算-高个子抖音'!V$40 -> 45.378826 | AH35: ='测算-高个子抖音'!W$40 -> 21.798978 | AJ35: ='测算-高个子视频号'!I$40 -> 0.54671863 | AK35: ='测算-高个子视频号'!J$40 -> 0.1844421 | AL35: ='测算-高个子视频号'!K$40 -> 0.025500243 | AM35: ='测算-高个子视频号'!L$40 -> 0.030605199 | AN35: ='测算-高个子视频号'!M$40 -> 0.020908667 | AO35: ='测算-高个子视频号'!N$40 -> 0.50453936 | AP35: ='测算-高个子视频号'!O$40 -> 0.37821683 | AQ35: ='测算-高个子视频号'!P$40 -> 0.50584556 | ... AU35: ='测算-高个子视频号'!T$40 -> 0.71596602 | AV35: ='测算-高个子视频号'!V$40 -> 5.0847656 | AW35: ='测算-高个子视频号'!W$40 -> 3.7720514 | AY35: ='测算-天猫淘宝'!I$39 -> 0.22668204 | AZ35: ='测算-天猫淘宝'!J$39 -> 0.24577357 | BA35: ='测算-天猫淘宝'!K$39 -> 0.068710679 | BB35: ='测算-天猫淘宝'!L$39 -> 0.15278017 | BC35: ='测算-天猫淘宝'!M$39 -> 0.10110054 | BD35: ='测算-天猫淘宝'!N$39 -> 0.1520995 | BE35: ='测算-天猫淘宝'!O$39 -> 0.14004443 | BF35: ='测算-天猫淘宝'!P$39 -> 0.18730223 | ... BJ35: ='测算-天猫淘宝'!T$39 -> 0.26510469 | BK35: ='测算-天猫淘宝'!V$39 -> 2.3438448 | BL35: ='测算-天猫淘宝'!W$39 -> 1.3966983 | BN35: ='测算-拼多多'!I$40 -> 0.0075898005 | BO35: ='测算-拼多多'!J$40 -> 0.017907 | BP35: ='测算-拼多多'!K$40 -> 0.0054165194 | BQ35: ='测算-拼多多'!L$40 -> 0.0020895116 | BR35: ='测算-拼多多'!M$40 -> 0.0036947042 | BS35: ='测算-拼多多'!N$40 -> 0.086975916 | BT35: ='测算-拼多多'!O$40 -> 0.051464 | BU35: ='测算-拼多多'!P$40 -> 0.068830453 | ... BY35: ='测算-拼多多'!T$40 -> 0.097421564 | BZ35: ='测算-拼多多'!V$40 -> 0.63693685 | CA35: ='测算-拼多多'!W$40 -> 0.51326339 | CC35: ='测算-京东POP'!I$40 -> 0.1333275 | CD35: ='测算-京东POP'!J$40 -> 0.14280832 | CE35: ='测算-京东POP'!K$40 -> 0.051609084 | CF35: ='测算-京东POP'!L$40 -> 0.088251137 | CG35: ='测算-京东POP'!M$40 -> 0.065916882 | CH35: ='测算-京东POP'!N$40 -> 0.098541785 | CI35: ='测算-京东POP'!O$40 -> 0.14916164 | CJ35: ='测算-京东POP'!P$40 -> 0.19949602 | ... CN35: ='测算-京东POP'!T$40 -> 0.2823636 | CO35: ='测算-京东POP'!V$40 -> 2.0680812 | CP35: ='测算-京东POP'!W$40 -> 1.4876265 | CR35: ='测算-京东自营'!I$41 -> 8.6693232 | CS35: ='测算-京东自营'!J$41 -> 19.420141 | CT35: ='测算-京东自营'!K$41 -> 5.0850163 | CU35: ='测算-京东自营'!L$41 -> 5.1640436 | CV35: ='测算-京东自营'!M$41 -> 7.0022202 | CW35: ='测算-京东自营'!N$41 -> 18.394784 | CX35: ='测算-京东自营'!O$41 -> 8.9847892 | CY35: ='测算-京东自营'!P$41 -> 12.016693 | ... DC35: ='测算-京东自营'!T$41 -> 17.008243 | DD35: ='测算-京东自营'!V$41 -> 153.34309 | DE35: ='测算-京东自营'!W$41 -> 89.607558 | DG35: ='测算-达播'!I$41 -> 0.47410954 | DH35: ='测算-达播'!J$41 -> 0.21712237 | DI35: ='测算-达播'!K$41 -> 0.6740828 | DJ35: ='测算-达播'!L$41 -> 0.13262253 | DK35: ='测算-达播'!M$41 -> 0.28155325 | DL35: ='测算-达播'!N$41 -> 0.1362245 | DM35: ='测算-达播'!O$41 -> 0.43118673 | DN35: ='测算-达播'!P$41 -> 0.57669007 | ... DR35: ='测算-达播'!T$41 -> 0.81623825 | DS35: ='测算-达播'!V$41 -> 6.2160485 | DT35: ='测算-达播'!W$41 -> 4.3003335 | DV35: ='测算-私域'!I$40 -> 0 | DW35: ='测算-私域'!J$40 -> 0 | DX35: ='测算-私域'!K$40 -> 0 | DY35: ='测算-私域'!L$40 -> 0 | DZ35: ='测算-私域'!M$40 -> 0 | EA35: ='测算-私域'!N$40 -> 0 | EB35: ='测算-私域'!O$40 -> 0 | EC35: ='测算-私域'!P$40 -> 0 | ... EG35: ='测算-私域'!T$40 -> 0 | EH35: ='测算-私域'!V$40 -> 0 | EI35: ='测算-私域'!W$40 -> 0 | EK35: ='测算-外部分销'!I$40 -> 0 | EL35: ='测算-外部分销'!J$40 -> 0 | EM35: ='测算-外部分销'!K$40 -> 0 | EN35: ='测算-外部分销'!L$40 -> 0 | EO35: ='测算-外部分销'!M$40 -> 0 | EP35: ='测算-外部分销'!N$40 -> 0 | EQ35: ='测算-外部分销'!O$40 -> 0 | ER35: ='测算-外部分销'!P$40 -> 0 | ... EV35: ='测算-外部分销'!T$40 -> 0 | EW35: ='测算-外部分销'!V$40 -> 0 | EX35: ='测算-外部分销'!W$40 -> 0
C36: 人工成本 | F36: =SUM(U36,AJ36,AY36,BN36,CC36,CR36,DG36,DV36,EK36) -> 41.826251 | G36: =SUM(V36,AK36,AZ36,BO36,CD36,CS36,DH36,DW36,EL36) -> 33.846583 | H36: =SUM(W36,AL36,BA36,BP36,CE36,CT36,DI36,DX36,EM36) -> 47.037375 | I36: =SUM(X36,AM36,BB36,BQ36,CF36,CU36,DJ36,DY36,EN36) -> 45.168611 | J36: =SUM(Y36,AN36,BC36,BR36,CG36,CV36,DK36,DZ36,EO36) -> 50.566793 | K36: =SUM(Z36,AO36,BD36,BS36,CH36,CW36,DL36,EA36,EP36) -> 52.905912 | L36: =SUM(AA36,AP36,BE36,BT36,CI36,CX36,DM36,EB36,EQ36) -> 55.408323 | M36: =SUM(AB36,AQ36,BF36,BU36,CJ36,CY36,DN36,EC36,ER36) -> 57.795207 | ... Q36: =SUM(AF36,AU36,BJ36,BY36,CN36,DC36,DR36,EG36,EV36) -> 61.107852 | R36: =SUM(F36:Q36) -> 629.38475 | S36: =SUM(L36:Q36) -> 358.03322 | U36: =SUM(U38:U40) -> 23.937452 | V36: =SUM(V38:V40) -> 18.347079 | W36: =SUM(W38:W40) -> 27.217739 | X36: =SUM(X38:X40) -> 25.840821 | Y36: =SUM(Y38:Y40) -> 26.729259 | Z36: =SUM(Z38:Z40) -> 26.908605 | AA36: =SUM(AA38:AA40) -> 26.287572 | AB36: =SUM(AB38:AB40) -> 26.854488 | ... AH36: =SUM(AH38:AH40) -> 164.35636 | AJ36: =SUM(AJ38:AJ40) -> 2.2926135 | AK36: =SUM(AK38:AK40) -> 2.3008361 | AL36: =SUM(AL38:AL40) -> 2.4008573 | AM36: =SUM(AM38:AM40) -> 3.5097245 | AN36: =SUM(AN38:AN40) -> 7.3630312 | AO36: =SUM(AO38:AO40) -> 8.3643754 | AP36: =SUM(AP38:AP40) -> 8.2136543 | AQ36: =SUM(AQ38:AQ40) -> 8.2835658 | ... AW36: =SUM(AW38:AW40) -> 50.109858 | AY36: =SUM(AY38:AY40) -> 1.3394484 | AZ36: =SUM(AZ38:AZ40) -> 1.1178261 | BA36: =SUM(BA38:BA40) -> 1.5085841 | BB36: =SUM(BB38:BB40) -> 1.4572365 | BC36: =SUM(BC38:BC40) -> 1.199337 | BD36: =SUM(BD38:BD40) -> 1.3569056 | BE36: =SUM(BE38:BE40) -> 1.4259048 | BF36: =SUM(BF38:BF40) -> 1.4511545 | ... BL36: =SUM(BL38:BL40) -> 8.8527292 | BN36: =SUM(BN38:BN40) -> 7.6694926e-06 | BO36: =SUM(BO38:BO40) -> 0 | BP36: =SUM(BP38:BP40) -> 1.2264373e-05 | BQ36: =SUM(BQ38:BQ40) -> 3.7684394e-06 | BR36: =SUM(BR38:BR40) -> 4.9068225e-05 | BS36: =SUM(BS38:BS40) -> 0.0010889287 | BT36: =SUM(BT38:BT40) -> 0.00021576732 | BU36: =SUM(BU38:BU40) -> 0.00028857769 | ... CA36: =SUM(CA38:CA40) -> 0.0021519017 | CC36: =SUM(CC38:CC40) -> 0.94082749 | CD36: =SUM(CD38:CD40) -> 0.92175914 | CE36: =SUM(CE38:CE40) -> 1.1147278 | CF36: =SUM(CF38:CF40) -> 1.0498614 | CG36: =SUM(CG38:CG40) -> 0.93933853 | CH36: =SUM(CH38:CH40) -> 1.0455076 | CI36: =SUM(CI38:CI40) -> 1.1149533 | CJ36: =SUM(CJ38:CJ40) -> 1.1396352 | ... CP36: =SUM(CP38:CP40) -> 6.9803339 | CR36: =SUM(CR38:CR40) -> 9.0137658 | CS36: =SUM(CS38:CS40) -> 7.8557242 | CT36: =SUM(CT38:CT40) -> 8.5813426 | CU36: =SUM(CU38:CU40) -> 9.4785494 | CV36: =SUM(CV38:CV40) -> 9.4711914 | CW36: =SUM(CW38:CW40) -> 10.937622 | CX36: =SUM(CX38:CX40) -> 8.6235731 | CY36: =SUM(CY38:CY40) -> 9.3691607 | ... DE36: =SUM(DE38:DE40) -> 60.520278 | DG36: =SUM(DG38:DG40) -> 4.302136 | DH36: =SUM(DH38:DH40) -> 3.3033581 | DI36: =SUM(DI38:DI40) -> 6.2141122 | DJ36: =SUM(DJ38:DJ40) -> 3.8324148 | DK36: =SUM(DK38:DK40) -> 4.8645866 | DL36: =SUM(DL38:DL40) -> 4.2918073 | DM36: =SUM(DM38:DM40) -> 5.5462125 | DN36: =SUM(DN38:DN40) -> 6.0453108 | ... DT36: =SUM(DT38:DT40) -> 39.153853 | DV36: =SUM(DV38:DV40) -> 0 | DW36: =SUM(DW38:DW40) -> 0 | DX36: =SUM(DX38:DX40) -> 0 | DY36: =SUM(DY38:DY40) -> 0 | DZ36: =SUM(DZ38:DZ40) -> 0 | EA36: =SUM(EA38:EA40) -> 0 | EB36: =SUM(EB38:EB40) -> 4.1962367 | EC36: =SUM(EC38:EC40) -> 4.6516037 | ... EI36: =SUM(EI38:EI40) -> 28.057664 | EK36: =SUM(EK38:EK40) -> -5.2386895e-14 | EL36: =SUM(EL38:EL40) -> -1.0477379e-13 | EM36: =SUM(EM38:EM40) -> 0 | EN36: =SUM(EN38:EN40) -> 0 | EO36: =SUM(EO38:EO40) -> 0 | EP36: =SUM(EP38:EP40) -> 0 | EQ36: =SUM(EQ38:EQ40) -> -9.5987069e-15 | ER36: =SUM(ER38:ER40) -> -1.2837777e-14 | ... EX36: =SUM(EX38:EX40) -> -9.5730313e-14
C37: Margin | F37: =IFERROR(F36/F3,0) -> 0.038143833 | G37: =IFERROR(G36/G3,0) -> 0.050900209 | H37: =IFERROR(H36/H3,0) -> 0.046466086 | I37: =IFERROR(I36/I3,0) -> 0.04619177 | J37: =IFERROR(J36/J3,0) -> 0.041512733 | K37: =IFERROR(K36/K3,0) -> 0.042645747 | L37: =IFERROR(L36/L3,0) -> 0.069973796 | M37: =IFERROR(M36/M3,0) -> 0.055274714 | ... S37: =IFERROR(S36/S3,0) -> 0.046262032 | U37: =IFERROR(U36/U3,0) -> 0.057996994 | V37: =IFERROR(V36/V3,0) -> 0.077640257 | W37: =IFERROR(W36/W3,0) -> 0.056589519 | X37: =IFERROR(X36/X3,0) -> 0.089045672 | Y37: =IFERROR(Y36/Y3,0) -> 0.069738042 | Z37: =IFERROR(Z36/Z3,0) -> 0.099101211 | AA37: =IFERROR(AA36/AA3,0) -> 0.13994955 | AB37: =IFERROR(AB36/AB3,0) -> 0.10689585 | ... AH37: =IFERROR(AH36/AH3,0) -> 0.087734578 | AJ37: =IFERROR(AJ36/AJ3,0) -> 0.1466503 | AK37: =IFERROR(AK36/AK3,0) -> 0.43105384 | AL37: =IFERROR(AL36/AL3,0) -> 0.21193541 | AM37: =IFERROR(AM36/AM3,0) -> 0.46799447 | AN37: =IFERROR(AN36/AN3,0) -> 0.10926563 | AO37: =IFERROR(AO36/AO3,0) -> 0.11858332 | AP37: =IFERROR(AP36/AP3,0) -> 0.15533907 | AQ37: =IFERROR(AQ36/AQ3,0) -> 0.11713442 | ... AW37: =IFERROR(AW36/AW3,0) -> 0.09502343 | AY37: =IFERROR(AY36/AY3,0) -> 0.048353498 | AZ37: =IFERROR(AZ36/AZ3,0) -> 0.078436308 | BA37: =IFERROR(BA36/BA3,0) -> 0.046329423 | BB37: =IFERROR(BB36/BB3,0) -> 0.042547488 | BC37: =IFERROR(BC36/BC3,0) -> 0.036793486 | BD37: =IFERROR(BD36/BD3,0) -> 0.051648142 | BE37: =IFERROR(BE36/BE3,0) -> 0.058946437 | BF37: =IFERROR(BF36/BF3,0) -> 0.044854251 | ... BL37: =IFERROR(BL36/BL3,0) -> 0.036695048 | BN37: =IFERROR(BN36/BN3,0) -> 4.9629165e-05 | BO37: =IFERROR(BO36/BO3,0) -> 0 | BP37: =IFERROR(BP36/BP3,0) -> 3.3472818e-05 | BQ37: =IFERROR(BQ36/BQ3,0) -> 3.1968166e-05 | BR37: =IFERROR(BR36/BR3,0) -> 0.00010874544 | BS37: =IFERROR(BS36/BS3,0) -> 0.00022176533 | BT37: =IFERROR(BT36/BT3,0) -> 7.4263485e-05 | BU37: =IFERROR(BU36/BU3,0) -> 7.4263485e-05 | ... CA37: =IFERROR(CA36/CA3,0) -> 7.4263485e-05 | CC37: =IFERROR(CC36/CC3,0) -> 0.068828277 | CD37: =IFERROR(CD36/CD3,0) -> 0.10753048 | CE37: =IFERROR(CE36/CE3,0) -> 0.047917136 | CF37: =IFERROR(CF36/CF3,0) -> 0.053932252 | CG37: =IFERROR(CG36/CG3,0) -> 0.048869273 | CH37: =IFERROR(CH36/CH3,0) -> 0.062715137 | CI37: =IFERROR(CI36/CI3,0) -> 0.044184011 | CJ37: =IFERROR(CJ36/CJ3,0) -> 0.03376737 | ... CP37: =IFERROR(CP36/CP3,0) -> 0.027736262 | CR37: =IFERROR(CR36/CR3,0) -> 0.022497129 | CS37: =IFERROR(CS36/CS3,0) -> 0.026084124 | CT37: =IFERROR(CT36/CT3,0) -> 0.21176782 | CU37: =IFERROR(CU36/CU3,0) -> 0.021595597 | CV37: =IFERROR(CV36/CV3,0) -> 0.021224958 | CW37: =IFERROR(CW36/CW3,0) -> 0.016565227 | CX37: =IFERROR(CX36/CX3,0) -> 0.026739207 | CY37: =IFERROR(CY36/CY3,0) -> 0.021721253 | ... DE37: =IFERROR(DE36/DE3,0) -> 0.018815919 | DG37: =IFERROR(DG36/DG3,0) -> 0.083256034 | DH37: =IFERROR(DH36/DH3,0) -> 0.77953514 | DI37: =IFERROR(DI36/DI3,0) -> 0.032700298 | DJ37: =IFERROR(DJ36/DJ3,0) -> 0.10135849 | DK37: =IFERROR(DK36/DK3,0) -> 0.059953769 | DL37: =IFERROR(DL36/DL3,0) -> 0.15673864 | DM37: =IFERROR(DM36/DM3,0) -> 0.06399149 | DN37: =IFERROR(DN36/DN3,0) -> 0.052151554 | ... DT37: =IFERROR(DT36/DT3,0) -> 0.045296377 | DV37: =IFERROR(DV36/DV3,0) -> 0 | DW37: =IFERROR(DW36/DW3,0) -> 0 | DX37: =IFERROR(DX36/DX3,0) -> 0 | DY37: =IFERROR(DY36/DY3,0) -> 0 | DZ37: =IFERROR(DZ36/DZ3,0) -> 0 | EA37: =IFERROR(EA36/EA3,0) -> 0 | EB37: =IFERROR(EB36/EB3,0) -> 0.1167197 | EC37: =IFERROR(EC36/EC3,0) -> 0.1343149 | ... EI37: =IFERROR(EI36/EI3,0) -> 0.1399106 | EK37: =IFERROR(EK36/EK3,0) -> -3.5034527e-16 | EL37: =IFERROR(EL36/EL3,0) -> -1.2050328e-15 | EM37: =IFERROR(EM36/EM3,0) -> 0 | EN37: =IFERROR(EN36/EN3,0) -> 0 | EO37: =IFERROR(EO36/EO3,0) -> 0 | EP37: =IFERROR(EP36/EP3,0) -> 0 | EQ37: =IFERROR(EQ36/EQ3,0) -> -1.7883539e-16 | ER37: =IFERROR(ER36/ER3,0) -> -1.7883539e-16 | ... EX37: =IFERROR(EX36/EX3,0) -> -1.7883539e-16
D38: 人工成本 | E38: 固定薪资 | F38: =SUM(U38,AJ38,AY38,BN38,CC38,CR38,DG38,DV38,EK38) -> 32.677613 | G38: =SUM(V38,AK38,AZ38,BO38,CD38,CS38,DH38,DW38,EL38) -> 29.437019 | H38: =SUM(W38,AL38,BA38,BP38,CE38,CT38,DI38,DX38,EM38) -> 35.846202 | I38: =SUM(X38,AM38,BB38,BQ38,CF38,CU38,DJ38,DY38,EN38) -> 38.322003 | J38: =SUM(Y38,AN38,BC38,BR38,CG38,CV38,DK38,DZ38,EO38) -> 43.272249 | K38: =SUM(Z38,AO38,BD38,BS38,CH38,CW38,DL38,EA38,EP38) -> 45.506154 | L38: =SUM(AA38,AP38,BE38,BT38,CI38,CX38,DM38,EB38,EQ38) -> 48.672821 | M38: =SUM(AB38,AQ38,BF38,BU38,CJ38,CY38,DN38,EC38,ER38) -> 48.906154 | ... Q38: =SUM(AF38,AU38,BJ38,BY38,CN38,DC38,DR38,EG38,EV38) -> 48.906154 | R38: =SUM(F38:Q38) -> 518.26483 | S38: =SUM(L38:Q38) -> 293.20359 | U38: ='测算-高个子抖音'!I$42 -> 19.478591 | V38: ='测算-高个子抖音'!J$42 -> 16.643369 | W38: ='测算-高个子抖音'!K$42 -> 23.312071 | X38: ='测算-高个子抖音'!L$42 -> 22.607721 | Y38: ='测算-高个子抖音'!M$42 -> 23.509755 | Z38: ='测算-高个子抖音'!N$42 -> 24.633405 | AA38: ='测算-高个子抖音'!O$42 -> 24.633405 | AB38: ='测算-高个子抖音'!P$42 -> 24.633405 | ... AF38: ='测算-高个子抖音'!T$42 -> 24.633405 | AG38: ='测算-高个子抖音'!V$42 -> 277.98535 | AH38: ='测算-高个子抖音'!W$42 -> 147.80043 | AJ38: ='测算-高个子视频号'!I$42 -> 2.2634218 | AK38: ='测算-高个子视频号'!J$42 -> 2.2893172 | AL38: ='测算-高个子视频号'!K$42 -> 2.3586043 | AM38: ='测算-高个子视频号'!L$42 -> 3.4664224 | AN38: ='测算-高个子视频号'!M$42 -> 7.0082157 | AO38: ='测算-高个子视频号'!N$42 -> 7.9985932 | AP38: ='测算-高个子视频号'!O$42 -> 7.9985932 | AQ38: ='测算-高个子视频号'!P$42 -> 7.9985932 | ... AU38: ='测算-高个子视频号'!T$42 -> 7.9985932 | AV38: ='测算-高个子视频号'!V$42 -> 73.376134 | AW38: ='测算-高个子视频号'!W$42 -> 47.991559 | AY38: ='测算-天猫淘宝'!I$41 -> 1.1998273 | AZ38: ='测算-天猫淘宝'!J$41 -> 1.1178261 | BA38: ='测算-天猫淘宝'!K$41 -> 1.2754556 | BB38: ='测算-天猫淘宝'!L$41 -> 1.2507354 | BC38: ='测算-天猫淘宝'!M$41 -> 1.1957923 | BD38: ='测算-天猫淘宝'!N$41 -> 1.3510793 | BE38: ='测算-天猫淘宝'!O$41 -> 1.3510793 | BF38: ='测算-天猫淘宝'!P$41 -> 1.3510793 | ... BJ38: ='测算-天猫淘宝'!T$41 -> 1.3510793 | BK38: ='测算-天猫淘宝'!V$41 -> 15.497192 | BL38: ='测算-天猫淘宝'!W$41 -> 8.1064759 | BN38: ='测算-拼多多'!I$42 -> 0 | BO38: ='测算-拼多多'!J$42 -> 0 | BP38: ='测算-拼多多'!K$42 -> 0 | BQ38: ='测算-拼多多'!L$42 -> 0 | BR38: ='测算-拼多多'!M$42 -> 0 | BS38: ='测算-拼多多'!N$42 -> 0 | BT38: ='测算-拼多多'!O$42 -> 0 | BU38: ='测算-拼多多'!P$42 -> 0 | ... BY38: ='测算-拼多多'!T$42 -> 0 | BZ38: ='测算-拼多多'!V$42 -> 0 | CA38: ='测算-拼多多'!W$42 -> 0 | CC38: ='测算-京东POP'!I$42 -> 0.89054089 | CD38: ='测算-京东POP'!J$42 -> 0.89290109 | CE38: ='测算-京东POP'!K$42 -> 0.98964976 | CF38: ='测算-京东POP'!L$42 -> 0.95956018 | CG38: ='测算-京东POP'!M$42 -> 0.93724828 | CH38: ='测算-京东POP'!N$42 -> 1.0418106 | CI38: ='测算-京东POP'!O$42 -> 1.0418106 | CJ38: ='测算-京东POP'!P$42 -> 1.0418106 | ... CN38: ='测算-京东POP'!T$42 -> 1.0418106 | CO38: ='测算-京东POP'!V$42 -> 11.962574 | CP38: ='测算-京东POP'!W$42 -> 6.2508634 | CR38: ='测算-京东自营'!I$43 -> 5.3207635 | CS38: ='测算-京东自营'!J$43 -> 5.2326235 | CT38: ='测算-京东自营'!K$43 -> 3.2229277 | CU38: ='测算-京东自营'!L$43 -> 6.5076407 | CV38: ='测算-京东自营'!M$43 -> 6.414088 | CW38: ='测算-京东自营'!N$43 -> 6.414088 | CX38: ='测算-京东自营'!O$43 -> 6.414088 | CY38: ='测算-京东自营'!P$43 -> 6.414088 | ... DC38: ='测算-京东自营'!T$43 -> 6.414088 | DD38: ='测算-京东自营'!V$43 -> 71.59666 | DE38: ='测算-京东自营'!W$43 -> 38.484528 | DG38: ='测算-达播'!I$43 -> 3.524468 | DH38: ='测算-达播'!J$43 -> 3.2609821 | DI38: ='测算-达播'!K$43 -> 4.687493 | DJ38: ='测算-达播'!L$43 -> 3.5299228 | DK38: ='测算-达播'!M$43 -> 4.2071494 | DL38: ='测算-达播'!N$43 -> 4.0671775 | DM38: ='测算-达播'!O$43 -> 4.0671775 | DN38: ='测算-达播'!P$43 -> 4.0671775 | ... DR38: ='测算-达播'!T$43 -> 4.0671775 | DS38: ='测算-达播'!V$43 -> 47.680258 | DT38: ='测算-达播'!W$43 -> 24.403065 | DV38: ='测算-私域'!I$42 -> 0 | DW38: ='测算-私域'!J$42 -> 0 | DX38: ='测算-私域'!K$42 -> 0 | DY38: ='测算-私域'!L$42 -> 0 | DZ38: ='测算-私域'!M$42 -> 0 | EA38: ='测算-私域'!N$42 -> 0 | EB38: ='测算-私域'!O$42 -> 3.1666667 | EC38: ='测算-私域'!P$42 -> 3.4 | ... EG38: ='测算-私域'!T$42 -> 3.4 | EH38: ='测算-私域'!V$42 -> 20.166667 | EI38: ='测算-私域'!W$42 -> 20.166667 | EK38: ='测算-外部分销'!I$42 -> -5.2386895e-14 | EL38: ='测算-外部分销'!J$42 -> -1.0477379e-13 | EM38: ='测算-外部分销'!K$42 -> 0 | EN38: ='测算-外部分销'!L$42 -> 0 | EO38: ='测算-外部分销'!M$42 -> 0 | EP38: ='测算-外部分销'!N$42 -> 0 | EQ38: ='测算-外部分销'!O$42 -> -9.5987069e-15 | ER38: ='测算-外部分销'!P$42 -> -1.2837777e-14 | ... EV38: ='测算-外部分销'!T$42 -> -1.8170392e-14 | EW38: ='测算-外部分销'!V$42 -> -2.52891e-13 | EX38: ='测算-外部分销'!W$42 -> -9.5730313e-14
